Workbook

Sheet Anleitung
A1: Art.74 LAI: Dossier dès 2015 pour la saisie des données
A3: Instruction
A5: Ce classeur contient les tableaux suivants (voir marquage des onglets en couleur):
B6: Tableaux obligatoires pour la saisie des coûts et des prestations (à remplir impérativement pour le décompte OFAS)
B7: Modèle pour la CA en tant que sous-traitant UVN et le calcul du substrat du capital ainsi qu'un exemple du programme de travail PROSPREH réalisé (Bsp. Real. Arbeitsprog. LUFEB)
B8: Outils d'évaluation pour cours en bloc et cours d'un jour "Auswertungstool Blockkkurse und Auswertungstool Tageskurse" (utilisation à bien plaire)
A10: Prière de ne pas modifier les tableaux. Merci d'avance
A12: SVP, veuillez prendre note des adaptations de tableaux suivants concernant la saisie des
A13: prestations dès 2015 :
A14: - Données des organisations (Informations de base)
A15: - Comptabilité analytique consolidée
A16: - Statistique consolidée des bénéficiaires et types de cours Pour les champs en fond gris, les données ne sont plus nécessaires.
A17: Nouveaux tableaux pour la saisie des prestations:
A18: - Catégories de cours Ce tableau sera nécessaire au cas où des cours dans diverses catégories seront proposés voir annexe 9.2 CSOAPH
A19: - Programme de travail PROSPREH réalisé avec l'évaluation de l'atteinte des objectifs Relevé d'heures pour les prestations PROSPREH effectuées, voir Ch. 3021 CSOAPH
A20: Rapport sur les PROSPREH : instructions
B21: Les champs en jaune énumèrent les diverses prestations et activités.
B22: Les champs en vert indiquent les heures effectives déclarées.
B23: Les champs en orange sont réservés à l’évaluation de l'atteinte des objectifs et à la description des mesures concrètes/ réorientations prévues pour l’année ou la période contractuelle suivante.
A24: Evaluation de l'atteinte des objectifs
A25: Le mandataire a documenté la planification des activités PROSPREH dans le plan des PROSPREH lors de de la conclusion du contrat. La mise en œuvre des activités PROSPREH prévues a lieu dans l’année sous revue. A la fin de l’année, le mandataire évalue les activités PROSPREH afin d’en contrôler l'atteinte des objectifs/résultats. L’évaluation de l'atteinte des objectifs a pour but de montrer quelles PROSPREH ont été fournies pour atteindre quels objectifs. A cet effet, la référence au plan des PROSPREH est importante.
A26: Il n’est pas nécessaire d’évaluer les résultats obtenus pour toutes les prestations. L’évaluation doit porter à chaque mandataire, sur 5 à 10 prestations de manière consolidée. L’accent est mis sur les prestations qui nécessitent un grand nombre d’heures et effectuées à l’initiative du mandataire. Il s’agit d’activités essentiels, comme les exemples de bonnes pratiques. Les prestations que l'organisation ne peut contrôler, comme les réponses aux médias ou la diffusion d’information, ne vont pas être évaluées. Là où il n’y a pas d’évaluation, il faut l’indiquer en inscrivant « Pas d’évaluation ». Dans ce cas précis, aucune autre justification n’est demandée.
A27: La colonne Mesures/réorientations indique les mesures ou les réorientations adoptées ; autrement dit, elle vise ce qui est prévu pour l’année ou la période contractuelle suivante lorsqu’un objectif n’a pas été atteint, ou atteint partiellement, ou lorsque l’objectif a été redéfini. Cela correspond au cycle de conduite : plan => do => check => act.
A28: Le degré de précision des mesures prévues ou des réorientations peut varier en fonction du degré d'influence de facteurs externes non prises en compte sur une activité ou un projet . Pour chaque mesure, des objectifs partiels doivent également être formulés pour des activités ou projets d’envergure.
A29: La feuille du tableau « Exemple de programme de travail PROSPREH réalisé » contient divers exemples pour l’évaluation des objectifs qui ont été élaborés par le groupe d’échange d’expériences relatif à l’art. 74 LAI.

Sheet Organisationsdaten (Basisinfo)
A1: Données des organisations pour l'année: | D1: 2017 | F1: No de contrat: | H1: 3158 | J1: Perioden ID | K1: 5
B2: Exemple | C2: Cellules jaunes: No OFAS de chaque organisation partie au contrat de prestations. Cellules vertes: Données des organisations
A3: BSV-Nr. | B3: 2388 | C3: 3158 | CE3: Total
A4: Nombre total d'equivalents plein temps (EPT) des collaborateurs engagés dans toute l'organisation | B4: 1.3 | C4: 18.966316 | CE4: =SUM(C4:CD4) -> 18.966316
A5: Nombre d'EPT des collaborateurs engagés dans l'exploitation au sens de l'art. 74 LAI | B5: 1.2 | C5: 12.803316 | CE5: =SUM(C5:CD5) -> 12.803316
A6: Nombre total d'EPT des bénévoles actifs (dans toute l'organisation, ev. estimation) | B6: 1 | C6: 1.2736842 | CE6: =SUM(C6:CD6) -> 1.2736842
A7: Nombre d’EPT des bénévoles actifs dans l’exploitation au sens de l’art. 74 LAI | B7: 0 | C7: 1.2736842 | CE7: =SUM(C7:CD7) -> 1.2736842
A8: Nombre total d’EPT des personnes actives à titre honorifique (dans toute l’organisation, év. estimation) | B8: 0 | C8: 0.80578947 | CE8: =SUM(C8:CD8) -> 0.80578947
A9: Nombre d’EPT des personnes actives à titre honorifique dans l’exploitation au sens de l’art. 74 LAI | B9: 0 | C9: 0.45684211 | CE9: =SUM(C9:CD9) -> 0.45684211
A10: Substrat du capital relatif à l’art. 74 LAI | B10: 250000 | C10: 245798.41 | CE10: =SUM(C10:CD10) -> 245798.41
A11: Total des charges sous l’angle de la comptabilité financière (CF) (CA sous-traitant cellule B11) | B11: 320000 | C11: 995820.89 | CE11: =SUM(C11:CD11) -> 995820.89
A12: Coûts complets de l’exploitation au sens de l’art. 74 LAI après répartition (CA sous-traitant cellule W16) | B12: 340000 | C12: 763338.64 | CE12: =SUM(C12:CD12) -> 763338.64
A13: Subvention AI (CA sous-traitant cellule W18) | B13: 120000 | C13: 220636 | CE13: =SUM(C13:CD13) -> 220636
A14: Contribution de couverture de l’AI (CA sous-traitant cellule W28) | B14: 12000 | C14: -17722.976 | CE14: =SUM(C14:CD14) -> -17722.976
A15: Facteur (B10/B12) | B15: =B10/B12 -> 0.73529412 | C15: =IF(C12=0,0,C10/C12) -> 0.32200441 | D15: =IF(D12=0,0,D10/D12) -> 0 | E15: =IF(E12=0,0,E10/E12) -> 0 | F15: =IF(F12=0,0,F10/F12) -> 0 | G15: =IF(G12=0,0,G10/G12) -> 0 | H15: =IF(H12=0,0,H10/H12) -> 0 | I15: =IF(I12=0,0,I10/I12) -> 0 | J15: =IF(J12=0,0,J10/J12) -> 0 | ... CD15: =IF(CD12=0,0,CD10/CD12) -> 0
A16: Nom de l'organisation (s'affiche avec l'insertion du n° OFAS) | C16: =IF(C3="","",VLOOKUP(C3,$K22:$L671,2,0)) -> Association Cerebral Valais | D16: =IF(D3="","",VLOOKUP(D3,$K22:$L671,2,0)) | E16: =IF(E3="","",VLOOKUP(E3,$K22:$L671,2,0)) | F16: =IF(F3="","",VLOOKUP(F3,$K22:$L671,2,0)) | G16: =IF(G3="","",VLOOKUP(G3,$K22:$L671,2,0)) | H16: =IF(H3="","",VLOOKUP(H3,$K22:$L671,2,0)) | I16: =IF(I3="","",VLOOKUP(I3,$K22:$L671,2,0)) | J16: =IF(J3="","",VLOOKUP(J3,$K22:$L671,2,0)) | ... CD16: =IF(CD3="","",VLOOKUP(CD3,$K22:$L671,2,0))
A17: Attention en cas d'impression: le marquage en vert totalise 10 feuilles. | C17: =IF(AND(SUM(C4:C14)<>0,C3=0),1,"") | D17: =IF(AND(SUM(D4:D14)<>0,D3=0),1,"") | E17: =IF(AND(SUM(E4:E14)<>0,E3=0),1,"") | F17: =IF(AND(SUM(F4:F14)<>0,F3=0),1,"") | G17: =IF(AND(SUM(G4:G14)<>0,G3=0),1,"") | H17: =IF(AND(SUM(H4:H14)<>0,H3=0),1,"") | I17: =IF(AND(SUM(I4:I14)<>0,I3=0),1,"") | J17: =IF(AND(SUM(J4:J14)<>0,J3=0),1,"") | ... CD17: =IF(AND(SUM(CD4:CD14)<>0,CD3=0),1,"")
C18: =IF(AND(SUM(C4:E14)<>0,OR(D1=0,H1=0)),"Bitte geben Sie das Jahr in die Zelle D1 und Ihre Vertrags-Nr. in die Zelle H1 ein","")
C19: =IF(SUM($C17:$CD17)>0,"Bitte BSV-Nr. in rotmarkiete Felder eintragen","") | M19: =C19 | W19: =C19 | AH19: =C19 | AS19: =C19 | BD19: =C19 | BO19: =C19 | BY19: =C19
C20: VERTRAG_NR | D20: PERIODE_ID | E20: JAHR | F20: BSV_NR | G20: TABELLE | H20: FELD | I20: WERT | J20: ADRESSE | Q20: ID | R20: TABELLE | S20: FELD | T20: WERT | U20: ADRESSE
C21: =H$1 -> 3158 | D21: =K$1 -> 5 | E21: =D$1 -> 2017 | F21: =C$3 -> 3158 | G21: ORGANISATIONSDATEN | H21: ANZ_MITARBEITER | I21: =IF(ISBLANK(C4),"",C4) -> 18.966316 | J21: C4 | K21: BSV Nr. | L21: Name | Q21: 1 | R21: VERTRAG | S21: VERTRAG_NR | T21: =H1 -> 3158 | U21: H1 | CE21: =SUM(C19:CD19) -> 0
C22: =H$1 -> 3158 | D22: =K$1 -> 5 | E22: =D$1 -> 2017 | F22: =C$3 -> 3158 | G22: ORGANISATIONSDATEN | H22: ANZ_MITARBEITER_BEHINDERT | I22: =IF(ISBLANK(C5),"",C5) -> 12.803316 | J22: C5 | K22: 2011 | L22: Verein für Hörbehinderte Baden und Umgebung | Q22: 1 | R22: VERTRAG | S22: PERIODE_ID | T22: =K1 -> 5 | U22: K1
C23: =H$1 -> 3158 | D23: =K$1 -> 5 | E23: =D$1 -> 2017 | F23: =C$3 -> 3158 | G23: ORGANISATIONSDATEN | H23: ANZ_MITARBEITER_FREIWILLIG | I23: =IF(ISBLANK(C6),"",C6) -> 1.2736842 | J23: C6 | K23: 2013 | L23: Schwerhörigen-Verein Basel | Q23: 1 | R23: VERTRAG | S23: JAHR | T23: =D1 -> 2017 | U23: D1
C24: =H$1 -> 3158 | D24: =K$1 -> 5 | E24: =D$1 -> 2017 | F24: =C$3 -> 3158 | G24: ORGANISATIONSDATEN | H24: ANZ_MA_FREIWILLIG_BEHINDERT | I24: =IF(ISBLANK(C7),"",C7) -> 1.2736842 | J24: C7 | K24: 2014 | L24: Vereinigung Cerebral Basel | Q24: 1 | R24: ORGANISATION | S24: BSV_NR1 | T24: =C3 -> 3158 | U24: C3
C25: =H$1 -> 3158 | D25: =K$1 -> 5 | E25: =D$1 -> 2017 | F25: =C$3 -> 3158 | G25: ORGANISATIONSDATEN | H25: ANZ_MITARBEITER_EHRENAMTLICH | I25: =IF(ISBLANK(C8),"",C8) -> 0.80578947 | J25: C8 | K25: 2015 | L25: Behinderten Forum Dachorg. der Behinderten-Selbsthilfe Region Basel | Q25: 1 | R25: ORGANISATION | S25: BSV_NR2 | T25: =D3 -> 0 | U25: D3
C26: =H$1 -> 3158 | D26: =K$1 -> 5 | E26: =D$1 -> 2017 | F26: =C$3 -> 3158 | G26: ORGANISATIONSDATEN | H26: ANZ_MA_EHRENAMTLICH_BEHINDERT | I26: =IF(ISBLANK(C9),"",C9) -> 0.45684211 | J26: C9 | K26: 2016 | L26: SBH - Sehbehindertenhilfe Basel, Basel | Q26: 1 | R26: ORGANISATION | S26: BSV_NR3 | T26: =E3 -> 0 | U26: E3
C27: =H$1 -> 3158 | D27: =K$1 -> 5 | E27: =D$1 -> 2017 | F27: =C$3 -> 3158 | G27: ORGANISATIONSDATEN | H27: PERSONALAUFWAND | I27: =IF(ISBLANK(C10),"",C10) -> 245798.41 | J27: C10 | K27: 2018 | L27: BSBS Beratungsstelle für Gehörlose Basel | Q27: 1 | R27: ORGANISATION | S27: BSV_NR4 | T27: =F3 -> 0 | U27: F3
C28: =H$1 -> 3158 | D28: =K$1 -> 5 | E28: =D$1 -> 2017 | F28: =C$3 -> 3158 | G28: ORGANISATIONSDATEN | H28: BETRIEBSAUFWAND | I28: =IF(ISBLANK(C11),"",C11) -> 995820.89 | J28: C11 | K28: 2021 | L28: insieme Solothurn | Q28: 1 | R28: ORGANISATION | S28: BSV_NR5 | T28: =G3 -> 0 | U28: G3
C29: =H$1 -> 3158 | D29: =K$1 -> 5 | E29: =D$1 -> 2017 | F29: =C$3 -> 3158 | G29: ORGANISATIONSDATEN | H29: BETRIEBSERTRAG | I29: =IF(ISBLANK(C12),"",C12) -> 763338.64 | J29: C12 | K29: 2022 | L29: SBH Schweiz. Verein. Zug. V. Pers. Mit… | Q29: 1 | R29: ORGANISATION | S29: BSV_NR6 | T29: =H3 -> 0 | U29: H3
C30: =H$1 -> 3158 | D30: =K$1 -> 5 | E30: =D$1 -> 2017 | F30: =C$3 -> 3158 | G30: ORGANISATIONSDATEN | H30: BEITRAG_IV | I30: =IF(ISBLANK(C13),"",C13) -> 220636 | J30: C13 | K30: 2023 | L30: BSBE Beratungsstelle für Gehörlose Bern | Q30: 1 | R30: ORGANISATION | S30: BSV_NR7 | T30: =I3 -> 0 | U30: I3
C31: =H$1 -> 3158 | D31: =K$1 -> 5 | E31: =D$1 -> 2017 | F31: =C$3 -> 3158 | G31: ORGANISATIONSDATEN | H31: BEITRAG_AHV | I31: =IF(ISBLANK(C14),"",C14) -> -17722.976 | J31: C14 | K31: 2024 | L31: insieme Region Bern | Q31: 1 | R31: ORGANISATION | S31: BSV_NR8 | T31: =J3 -> 0 | U31: J3
C32: =H$1 -> 3158 | D32: =K$1 -> 5 | E32: =D$1 -> 2017 | F32: =D$3 -> 0 | G32: ORGANISATIONSDATEN | H32: ANZ_MITARBEITER | I32: =IF(ISBLANK(D4),"",D4) | J32: D4 | K32: 2026 | L32: ilco Schweiz | Q32: 1 | R32: ORGANISATION | S32: BSV_NR9 | T32: =K3 -> 0 | U32: K3
C33: =H$1 -> 3158 | D33: =K$1 -> 5 | E33: =D$1 -> 2017 | F33: =D$3 -> 0 | G33: ORGANISATIONSDATEN | H33: ANZ_MITARBEITER_BEHINDERT | I33: =IF(ISBLANK(D5),"",D5) | J33: D5 | K33: 2028 | L33: Schwerhörigen-Verein Bern | Q33: 1 | R33: ORGANISATION | S33: BSV_NR10 | T33: =L3 -> 0 | U33: L3
C34: =H$1 -> 3158 | D34: =K$1 -> 5 | E34: =D$1 -> 2017 | F34: =D$3 -> 0 | G34: ORGANISATIONSDATEN | H34: ANZ_MITARBEITER_FREIWILLIG | I34: =IF(ISBLANK(D6),"",D6) | J34: D6 | K34: 2033 | L34: Entlastungsdienst Kanton Bern | Q34: 1 | R34: ORGANISATION | S34: BSV_NR11 | T34: =M3 -> 0 | U34: M3
C35: =H$1 -> 3158 | D35: =K$1 -> 5 | E35: =D$1 -> 2017 | F35: =D$3 -> 0 | G35: ORGANISATIONSDATEN | H35: ANZ_MA_FREIWILLIG_BEHINDERT | I35: =IF(ISBLANK(D7),"",D7) | J35: D7 | K35: 2034 | L35: Team Selbsthilfe Thurgau, Weinfelden | Q35: 1 | R35: ORGANISATION | S35: BSV_NR12 | T35: =N3 -> 0 | U35: N3
C36: =H$1 -> 3158 | D36: =K$1 -> 5 | E36: =D$1 -> 2017 | F36: =D$3 -> 0 | G36: ORGANISATIONSDATEN | H36: ANZ_MITARBEITER_EHRENAMTLICH | I36: =IF(ISBLANK(D8),"",D8) | J36: D8 | K36: 2036 | L36: insieme Freiamt Wohlen | Q36: 1 | R36: ORGANISATION | S36: BSV_NR13 | T36: =O3 -> 0 | U36: O3
C37: =H$1 -> 3158 | D37: =K$1 -> 5 | E37: =D$1 -> 2017 | F37: =D$3 -> 0 | G37: ORGANISATIONSDATEN | H37: ANZ_MA_EHRENAMTLICH_BEHINDERT | I37: =IF(ISBLANK(D9),"",D9) | J37: D9 | K37: 2037 | L37: Schwerhörigen-Verein Oberwallis | Q37: 1 | R37: ORGANISATION | S37: BSV_NR14 | T37: =P3 -> 0 | U37: P3
C38: =H$1 -> 3158 | D38: =K$1 -> 5 | E38: =D$1 -> 2017 | F38: =D$3 -> 0 | G38: ORGANISATIONSDATEN | H38: PERSONALAUFWAND | I38: =IF(ISBLANK(D10),"",D10) | J38: D10 | K38: 2040 | L38: insieme-zwirniträff | Q38: 1 | R38: ORGANISATION | S38: BSV_NR15 | T38: =Q3 -> 0 | U38: Q3
C39: =H$1 -> 3158 | D39: =K$1 -> 5 | E39: =D$1 -> 2017 | F39: =D$3 -> 0 | G39: ORGANISATIONSDATEN | H39: BETRIEBSAUFWAND | I39: =IF(ISBLANK(D11),"",D11) | J39: D11 | K39: 2041 | L39: Freizeitgruppe Burgdorf | Q39: 1 | R39: ORGANISATION | S39: BSV_NR16 | T39: =R3 -> 0 | U39: R3
C40: =H$1 -> 3158 | D40: =K$1 -> 5 | E40: =D$1 -> 2017 | F40: =D$3 -> 0 | G40: ORGANISATIONSDATEN | H40: BETRIEBSERTRAG | I40: =IF(ISBLANK(D12),"",D12) | J40: D12 | K40: 2043 | L40: insieme Graubünden ED | Q40: 1 | R40: ORGANISATION | S40: BSV_NR17 | T40: =S3 -> 0 | U40: S3
C41: =H$1 -> 3158 | D41: =K$1 -> 5 | E41: =D$1 -> 2017 | F41: =D$3 -> 0 | G41: ORGANISATIONSDATEN | H41: BEITRAG_IV | I41: =IF(ISBLANK(D13),"",D13) | J41: D13 | K41: 2045 | L41: Verein für Hörbehinderte Chur und Umgebung | Q41: 1 | R41: ORGANISATION | S41: BSV_NR18 | T41: =T3 -> 0 | U41: T3
C42: =H$1 -> 3158 | D42: =K$1 -> 5 | E42: =D$1 -> 2017 | F42: =D$3 -> 0 | G42: ORGANISATIONSDATEN | H42: BEITRAG_AHV | I42: =IF(ISBLANK(D14),"",D14) | J42: D14 | K42: 2047 | L42: Entlastungsdienst Kanton Zürich | Q42: 1 | R42: ORGANISATION | S42: BSV_NR19 | T42: =U3 -> 0 | U42: U3
C43: =H$1 -> 3158 | D43: =K$1 -> 5 | E43: =D$1 -> 2017 | F43: =E$3 -> 0 | G43: ORGANISATIONSDATEN | H43: ANZ_MITARBEITER | I43: =IF(ISBLANK(E4),"",E4) | J43: E4 | K43: 2048 | L43: insieme Limmattal und Amt | Q43: 1 | R43: ORGANISATION | S43: BSV_NR20 | T43: =V3 -> 0 | U43: V3
C44: =H$1 -> 3158 | D44: =K$1 -> 5 | E44: =D$1 -> 2017 | F44: =E$3 -> 0 | G44: ORGANISATIONSDATEN | H44: ANZ_MITARBEITER_BEHINDERT | I44: =IF(ISBLANK(E5),"",E5) | J44: E5 | K44: 2049 | L44: SVEHK - ASPEDA | Q44: 1 | R44: ORGANISATION | S44: BSV_NR21 | T44: =W3 -> 0 | U44: W3
C45: =H$1 -> 3158 | D45: =K$1 -> 5 | E45: =D$1 -> 2017 | F45: =E$3 -> 0 | G45: ORGANISATIONSDATEN | H45: ANZ_MITARBEITER_FREIWILLIG | I45: =IF(ISBLANK(E6),"",E6) | J45: E6 | K45: 2054 | L45: Kinderkrebshilfe Schweiz | Q45: 1 | R45: ORGANISATION | S45: BSV_NR22 | T45: =X3 -> 0 | U45: X3
C46: =H$1 -> 3158 | D46: =K$1 -> 5 | E46: =D$1 -> 2017 | F46: =E$3 -> 0 | G46: ORGANISATIONSDATEN | H46: ANZ_MA_FREIWILLIG_BEHINDERT | I46: =IF(ISBLANK(E7),"",E7) | J46: E7 | K46: 2057 | L46: Entlastungsdienst Thurgau (Übernahme durch PI per 2016 geplant) | Q46: 1 | R46: ORGANISATION | S46: BSV_NR23 | T46: =Y3 -> 0 | U46: Y3
C47: =H$1 -> 3158 | D47: =K$1 -> 5 | E47: =D$1 -> 2017 | F47: =E$3 -> 0 | G47: ORGANISATIONSDATEN | H47: ANZ_MITARBEITER_EHRENAMTLICH | I47: =IF(ISBLANK(E8),"",E8) | J47: E8 | K47: 2058 | L47: Schwerhörigen-Verein Deutsch-Freiburg | Q47: 1 | R47: ORGANISATION | S47: BSV_NR24 | T47: =Z3 -> 0 | U47: Z3
C48: =H$1 -> 3158 | D48: =K$1 -> 5 | E48: =D$1 -> 2017 | F48: =E$3 -> 0 | G48: ORGANISATIONSDATEN | H48: ANZ_MA_EHRENAMTLICH_BEHINDERT | I48: =IF(ISBLANK(E9),"",E9) | J48: E9 | K48: 2060 | L48: autismus schweiz | Q48: 1 | R48: ORGANISATION | S48: BSV_NR25 | T48: =AA3 -> 0 | U48: AA3
C49: =H$1 -> 3158 | D49: =K$1 -> 5 | E49: =D$1 -> 2017 | F49: =E$3 -> 0 | G49: ORGANISATIONSDATEN | H49: PERSONALAUFWAND | I49: =IF(ISBLANK(E10),"",E10) | J49: E10 | K49: 2066 | L49: insieme Kanton Bern | Q49: 1 | R49: ORGANISATION | S49: BSV_NR26 | T49: =AB3 -> 0 | U49: AB3
C50: =H$1 -> 3158 | D50: =K$1 -> 5 | E50: =D$1 -> 2017 | F50: =E$3 -> 0 | G50: ORGANISATIONSDATEN | H50: BETRIEBSAUFWAND | I50: =IF(ISBLANK(E11),"",E11) | J50: E11 | K50: 2068 | L50: Schwerhörigen-Verein Solothurn u.Umgebung | Q50: 1 | R50: ORGANISATION | S50: BSV_NR27 | T50: =AC3 -> 0 | U50: AC3
C51: =H$1 -> 3158 | D51: =K$1 -> 5 | E51: =D$1 -> 2017 | F51: =E$3 -> 0 | G51: ORGANISATIONSDATEN | H51: BETRIEBSERTRAG | I51: =IF(ISBLANK(E12),"",E12) | J51: E12 | K51: 2073 | L51: Freizeitclub der Region Zofingen* (5190.25) | Q51: 1 | R51: ORGANISATION | S51: BSV_NR28 | T51: =AD3 -> 0 | U51: AD3
C52: =H$1 -> 3158 | D52: =K$1 -> 5 | E52: =D$1 -> 2017 | F52: =E$3 -> 0 | G52: ORGANISATIONSDATEN | H52: BEITRAG_IV | I52: =IF(ISBLANK(E13),"",E13) | J52: E13 | K52: 2075 | L52: Elternvereinigung für das herzkranke Kind | Q52: 1 | R52: ORGANISATION | S52: BSV_NR29 | T52: =AE3 -> 0 | U52: AE3
C53: =H$1 -> 3158 | D53: =K$1 -> 5 | E53: =D$1 -> 2017 | F53: =E$3 -> 0 | G53: ORGANISATIONSDATEN | H53: BEITRAG_AHV | I53: =IF(ISBLANK(E14),"",E14) | J53: E14 | K53: 2077 | L53: Schwerhörigen-Verein Herisau und Umg. | Q53: 1 | R53: ORGANISATION | S53: BSV_NR30 | T53: =AF3 -> 0 | U53: AF3
C54: =H$1 -> 3158 | D54: =K$1 -> 5 | E54: =D$1 -> 2017 | F54: =F$3 -> 0 | G54: ORGANISATIONSDATEN | H54: ANZ_MITARBEITER | I54: =IF(ISBLANK(F4),"",F4) | J54: F4 | K54: 2078 | L54: Verband Entlastungsdienst St.Gallen–Appenzell (VESA) | Q54: 1 | R54: ORGANISATION | S54: BSV_NR31 | T54: =AG3 -> 0 | U54: AG3
C55: =H$1 -> 3158 | D55: =K$1 -> 5 | E55: =D$1 -> 2017 | F55: =F$3 -> 0 | G55: ORGANISATIONSDATEN | H55: ANZ_MITARBEITER_BEHINDERT | I55: =IF(ISBLANK(F5),"",F5) | J55: F5 | K55: 2080 | L55: Schwerhörigen-Verein Horgen-Thalwil | Q55: 1 | R55: ORGANISATION | S55: BSV_NR32 | T55: =AH3 -> 0 | U55: AH3
C56: =H$1 -> 3158 | D56: =K$1 -> 5 | E56: =D$1 -> 2017 | F56: =F$3 -> 0 | G56: ORGANISATIONSDATEN | H56: ANZ_MITARBEITER_FREIWILLIG | I56: =IF(ISBLANK(F6),"",F6) | J56: F6 | K56: 2081 | L56: insieme Bezirk Horgen | Q56: 1 | R56: ORGANISATION | S56: BSV_NR33 | T56: =AI3 -> 0 | U56: AI3
C57: =H$1 -> 3158 | D57: =K$1 -> 5 | E57: =D$1 -> 2017 | F57: =F$3 -> 0 | G57: ORGANISATIONSDATEN | H57: ANZ_MA_FREIWILLIG_BEHINDERT | I57: =IF(ISBLANK(F7),"",F7) | J57: F7 | K57: 2082 | L57: Schweizerische Vereinigung Osteogenesis inperfecta SVOI | Q57: 1 | R57: ORGANISATION | S57: BSV_NR34 | T57: =AJ3 -> 0 | U57: AJ3
C58: =H$1 -> 3158 | D58: =K$1 -> 5 | E58: =D$1 -> 2017 | F58: =F$3 -> 0 | G58: ORGANISATIONSDATEN | H58: ANZ_MITARBEITER_EHRENAMTLICH | I58: =IF(ISBLANK(F8),"",F8) | J58: F8 | K58: 2084 | L58: PTA Pfadibewegung Schweiz PBS | Q58: 1 | R58: ORGANISATION | S58: BSV_NR35 | T58: =AK3 -> 0 | U58: AK3
C59: =H$1 -> 3158 | D59: =K$1 -> 5 | E59: =D$1 -> 2017 | F59: =F$3 -> 0 | G59: ORGANISATIONSDATEN | H59: ANZ_MA_EHRENAMTLICH_BEHINDERT | I59: =IF(ISBLANK(F9),"",F9) | J59: F9 | K59: 2086 | L59: insieme Rapperswil-Jona | Q59: 1 | R59: ORGANISATION | S59: BSV_NR36 | T59: =AL3 -> 0 | U59: AL3
C60: =H$1 -> 3158 | D60: =K$1 -> 5 | E60: =D$1 -> 2017 | F60: =F$3 -> 0 | G60: ORGANISATIONSDATEN | H60: PERSONALAUFWAND | I60: =IF(ISBLANK(F10),"",F10) | J60: F10 | K60: 2088 | L60: insieme Region Zurzach | Q60: 1 | R60: ORGANISATION | S60: BSV_NR37 | T60: =AM3 -> 0 | U60: AM3
C61: =H$1 -> 3158 | D61: =K$1 -> 5 | E61: =D$1 -> 2017 | F61: =F$3 -> 0 | G61: ORGANISATIONSDATEN | H61: BETRIEBSAUFWAND | I61: =IF(ISBLANK(F11),"",F11) | J61: F11 | K61: 2089 | L61: Marfan Stiftung Schweiz | Q61: 1 | R61: ORGANISATION | S61: BSV_NR38 | T61: =AN3 -> 0 | U61: AN3
C62: =H$1 -> 3158 | D62: =K$1 -> 5 | E62: =D$1 -> 2017 | F62: =F$3 -> 0 | G62: ORGANISATIONSDATEN | H62: BETRIEBSERTRAG | I62: =IF(ISBLANK(F12),"",F12) | J62: F12 | K62: 2091 | L62: VERSTA - Vereinigung für Stotternde und Angehörige | Q62: 1 | R62: ORGANISATION | S62: BSV_NR39 | T62: =AO3 -> 0 | U62: AO3
C63: =H$1 -> 3158 | D63: =K$1 -> 5 | E63: =D$1 -> 2017 | F63: =F$3 -> 0 | G63: ORGANISATIONSDATEN | H63: BEITRAG_IV | I63: =IF(ISBLANK(F13),"",F13) | J63: F13 | K63: 2092 | L63: insieme Lenzburg | Q63: 1 | R63: ORGANISATION | S63: BSV_NR40 | T63: =AP3 -> 0 | U63: AP3
C64: =H$1 -> 3158 | D64: =K$1 -> 5 | E64: =D$1 -> 2017 | F64: =F$3 -> 0 | G64: ORGANISATIONSDATEN | H64: BEITRAG_AHV | I64: =IF(ISBLANK(F14),"",F14) | J64: F14 | K64: 2093 | L64: Stiftung Mosaik | Q64: 1 | R64: ORGANISATION | S64: BSV_NR41 | T64: =AQ3 -> 0 | U64: AQ3
C65: =H$1 -> 3158 | D65: =K$1 -> 5 | E65: =D$1 -> 2017 | F65: =G$3 -> 0 | G65: ORGANISATIONSDATEN | H65: ANZ_MITARBEITER | I65: =IF(ISBLANK(G4),"",G4) | J65: G4 | K65: 2095 | L65: insieme Basel-Land | Q65: 1 | R65: ORGANISATION | S65: BSV_NR42 | T65: =AR3 -> 0 | U65: AR3
C66: =H$1 -> 3158 | D66: =K$1 -> 5 | E66: =D$1 -> 2017 | F66: =G$3 -> 0 | G66: ORGANISATIONSDATEN | H66: ANZ_MITARBEITER_BEHINDERT | I66: =IF(ISBLANK(G5),"",G5) | J66: G5 | K66: 2096 | L66: Murg-Stiftung | Q66: 1 | R66: ORGANISATION | S66: BSV_NR43 | T66: =AS3 -> 0 | U66: AS3
C67: =H$1 -> 3158 | D67: =K$1 -> 5 | E67: =D$1 -> 2017 | F67: =G$3 -> 0 | G67: ORGANISATIONSDATEN | H67: ANZ_MITARBEITER_FREIWILLIG | I67: =IF(ISBLANK(G6),"",G6) | J67: G6 | K67: 2097 | L67: Beratungsstelle für Gehörlose Luzern | Q67: 1 | R67: ORGANISATION | S67: BSV_NR44 | T67: =AT3 -> 0 | U67: AT3
C68: =H$1 -> 3158 | D68: =K$1 -> 5 | E68: =D$1 -> 2017 | F68: =G$3 -> 0 | G68: ORGANISATIONSDATEN | H68: ANZ_MA_FREIWILLIG_BEHINDERT | I68: =IF(ISBLANK(G7),"",G7) | J68: G7 | K68: 2098 | L68: Verein Beratungsstellen Hohenrain LGB | Q68: 1 | R68: ORGANISATION | S68: BSV_NR45 | T68: =AU3 -> 0 | U68: AU3
C69: =H$1 -> 3158 | D69: =K$1 -> 5 | E69: =D$1 -> 2017 | F69: =G$3 -> 0 | G69: ORGANISATIONSDATEN | H69: ANZ_MITARBEITER_EHRENAMTLICH | I69: =IF(ISBLANK(G8),"",G8) | J69: G8 | K69: 2102 | L69: traversa | Q69: 1 | R69: ORGANISATION | S69: BSV_NR46 | T69: =AV3 -> 0 | U69: AV3
C70: =H$1 -> 3158 | D70: =K$1 -> 5 | E70: =D$1 -> 2017 | F70: =G$3 -> 0 | G70: ORGANISATIONSDATEN | H70: ANZ_MA_EHRENAMTLICH_BEHINDERT | I70: =IF(ISBLANK(G9),"",G9) | J70: G9 | K70: 2103 | L70: PALU pro audito Luzern | Q70: 1 | R70: ORGANISATION | S70: BSV_NR47 | T70: =AW3 -> 0 | U70: AW3
C71: =H$1 -> 3158 | D71: =K$1 -> 5 | E71: =D$1 -> 2017 | F71: =G$3 -> 0 | G71: ORGANISATIONSDATEN | H71: PERSONALAUFWAND | I71: =IF(ISBLANK(G10),"",G10) | J71: G10 | K71: 2117 | L71: Schwerhörigenverein Aarau & Umgebung | Q71: 1 | R71: ORGANISATION | S71: BSV_NR48 | T71: =AX3 -> 0 | U71: AX3
C72: =H$1 -> 3158 | D72: =K$1 -> 5 | E72: =D$1 -> 2017 | F72: =G$3 -> 0 | G72: ORGANISATIONSDATEN | H72: BETRIEBSAUFWAND | I72: =IF(ISBLANK(G11),"",G11) | J72: G11 | K72: 2119 | L72: Freizeit- und Bildungsklub Thal-Gäu | Q72: 1 | R72: ORGANISATION | S72: BSV_NR49 | T72: =AY3 -> 0 | U72: AY3
C73: =H$1 -> 3158 | D73: =K$1 -> 5 | E73: =D$1 -> 2017 | F73: =G$3 -> 0 | G73: ORGANISATIONSDATEN | H73: BETRIEBSERTRAG | I73: =IF(ISBLANK(G12),"",G12) | J73: G12 | K73: 2120 | L73: Schwerhörigen-Verein Zofingen und Umgebung | Q73: 1 | R73: ORGANISATION | S73: BSV_NR50 | T73: =AZ3 -> 0 | U73: AZ3
C74: =H$1 -> 3158 | D74: =K$1 -> 5 | E74: =D$1 -> 2017 | F74: =G$3 -> 0 | G74: ORGANISATIONSDATEN | H74: BEITRAG_IV | I74: =IF(ISBLANK(G13),"",G13) | J74: G13 | K74: 2122 | L74: Schwerhörigenverein Olten und Umgebung | Q74: 1 | R74: ORGANISATION | S74: BSV_NR51 | T74: =BA3 -> 0 | U74: BA3
C75: =H$1 -> 3158 | D75: =K$1 -> 5 | E75: =D$1 -> 2017 | F75: =G$3 -> 0 | G75: ORGANISATIONSDATEN | H75: BEITRAG_AHV | I75: =IF(ISBLANK(G14),"",G14) | J75: G14 | K75: 2123 | L75: Solothurnische Beratungsstelle für Sehbehinderte, Olten | Q75: 1 | R75: ORGANISATION | S75: BSV_NR52 | T75: =BB3 -> 0 | U75: BB3
C76: =H$1 -> 3158 | D76: =K$1 -> 5 | E76: =D$1 -> 2017 | F76: =H$3 -> 0 | G76: ORGANISATIONSDATEN | H76: ANZ_MITARBEITER | I76: =IF(ISBLANK(H4),"",H4) | J76: H4 | K76: 2124 | L76: Stiftung Arkadis Freizeitclub | Q76: 1 | R76: ORGANISATION | S76: BSV_NR53 | T76: =BC3 -> 0 | U76: BC3
C77: =H$1 -> 3158 | D77: =K$1 -> 5 | E77: =D$1 -> 2017 | F77: =H$3 -> 0 | G77: ORGANISATIONSDATEN | H77: ANZ_MITARBEITER_BEHINDERT | I77: =IF(ISBLANK(H5),"",H5) | J77: H5 | K77: 2125 | L77: insieme Ausserschwyz ED mitenand | Q77: 1 | R77: ORGANISATION | S77: BSV_NR54 | T77: =BD3 -> 0 | U77: BD3
C78: =H$1 -> 3158 | D78: =K$1 -> 5 | E78: =D$1 -> 2017 | F78: =H$3 -> 0 | G78: ORGANISATIONSDATEN | H78: ANZ_MITARBEITER_FREIWILLIG | I78: =IF(ISBLANK(H6),"",H6) | J78: H6 | K78: 2129 | L78: Schwerhörigen-Verein Romanshorn | Q78: 1 | R78: ORGANISATION | S78: BSV_NR55 | T78: =BE3 -> 0 | U78: BE3
C79: =H$1 -> 3158 | D79: =K$1 -> 5 | E79: =D$1 -> 2017 | F79: =H$3 -> 0 | G79: ORGANISATIONSDATEN | H79: ANZ_MA_FREIWILLIG_BEHINDERT | I79: =IF(ISBLANK(H7),"",H7) | J79: H7 | K79: 2134 | L79: Vereinigung Cerebral Schaffhausen | Q79: 1 | R79: ORGANISATION | S79: BSV_NR56 | T79: =BF3 -> 0 | U79: BF3
C80: =H$1 -> 3158 | D80: =K$1 -> 5 | E80: =D$1 -> 2017 | F80: =H$3 -> 0 | G80: ORGANISATIONSDATEN | H80: ANZ_MITARBEITER_EHRENAMTLICH | I80: =IF(ISBLANK(H8),"",H8) | J80: H8 | K80: 2135 | L80: Schwerhörigen-Verein Schaffhausen und Umg. | Q80: 1 | R80: ORGANISATION | S80: BSV_NR57 | T80: =BG3 -> 0 | U80: BG3
C81: =H$1 -> 3158 | D81: =K$1 -> 5 | E81: =D$1 -> 2017 | F81: =H$3 -> 0 | G81: ORGANISATIONSDATEN | H81: ANZ_MA_EHRENAMTLICH_BEHINDERT | I81: =IF(ISBLANK(H9),"",H9) | J81: H9 | K81: 2136 | L81: insieme Schaffhausen | Q81: 1 | R81: ORGANISATION | S81: BSV_NR58 | T81: =BH3 -> 0 | U81: BH3
C82: =H$1 -> 3158 | D82: =K$1 -> 5 | E82: =D$1 -> 2017 | F82: =H$3 -> 0 | G82: ORGANISATIONSDATEN | H82: PERSONALAUFWAND | I82: =IF(ISBLANK(H10),"",H10) | J82: H10 | K82: 2139 | L82: Verein Hörbehinderter Uri Altdorf | Q82: 1 | R82: ORGANISATION | S82: BSV_NR59 | T82: =BI3 -> 0 | U82: BI3
C83: =H$1 -> 3158 | D83: =K$1 -> 5 | E83: =D$1 -> 2017 | F83: =H$3 -> 0 | G83: ORGANISATIONSDATEN | H83: BETRIEBSAUFWAND | I83: =IF(ISBLANK(H11),"",H11) | J83: H11 | K83: 2140 | L83: insieme Innerschwyz ED Zyt ha | Q83: 1 | R83: ORGANISATION | S83: BSV_NR60 | T83: =BJ3 -> 0 | U83: BJ3
C84: =H$1 -> 3158 | D84: =K$1 -> 5 | E84: =D$1 -> 2017 | F84: =H$3 -> 0 | G84: ORGANISATIONSDATEN | H84: BETRIEBSERTRAG | I84: =IF(ISBLANK(H12),"",H12) | J84: H12 | K84: 2141 | L84: insieme Innerschwyz | Q84: 1 | R84: ORGANISATION | S84: BSV_NR61 | T84: =BK3 -> 0 | U84: BK3
C85: =H$1 -> 3158 | D85: =K$1 -> 5 | E85: =D$1 -> 2017 | F85: =H$3 -> 0 | G85: ORGANISATIONSDATEN | H85: BEITRAG_IV | I85: =IF(ISBLANK(H13),"",H13) | J85: H13 | K85: 2144 | L85: Vereinigung Cerebral Solothurn | Q85: 1 | R85: ORGANISATION | S85: BSV_NR62 | T85: =BL3 -> 0 | U85: BL3
C86: =H$1 -> 3158 | D86: =K$1 -> 5 | E86: =D$1 -> 2017 | F86: =H$3 -> 0 | G86: ORGANISATIONSDATEN | H86: BEITRAG_AHV | I86: =IF(ISBLANK(H14),"",H14) | J86: H14 | K86: 2145 | L86: Vereinigung Cerebral Schweiz | Q86: 1 | R86: ORGANISATION | S86: BSV_NR63 | T86: =BM3 -> 0 | U86: BM3
C87: =H$1 -> 3158 | D87: =K$1 -> 5 | E87: =D$1 -> 2017 | F87: =I$3 -> 0 | G87: ORGANISATIONSDATEN | H87: ANZ_MITARBEITER | I87: =IF(ISBLANK(I4),"",I4) | J87: I4 | K87: 2146 | L87: APW - Arbeitsgemeinschaft für Probleme bei Wahrnehmungsstörungen | Q87: 1 | R87: ORGANISATION | S87: BSV_NR64 | T87: =BN3 -> 0 | U87: BN3
C88: =H$1 -> 3158 | D88: =K$1 -> 5 | E88: =D$1 -> 2017 | F88: =I$3 -> 0 | G88: ORGANISATIONSDATEN | H88: ANZ_MITARBEITER_BEHINDERT | I88: =IF(ISBLANK(I5),"",I5) | J88: I5 | K88: 2147 | L88: BSSG Beratungsstelle für Gehörlose St.Gallen | Q88: 1 | R88: ORGANISATION | S88: BSV_NR65 | T88: =BO3 -> 0 | U88: BO3
C89: =H$1 -> 3158 | D89: =K$1 -> 5 | E89: =D$1 -> 2017 | F89: =I$3 -> 0 | G89: ORGANISATIONSDATEN | H89: ANZ_MITARBEITER_FREIWILLIG | I89: =IF(ISBLANK(I6),"",I6) | J89: I6 | K89: 2149 | L89: pro audito, Schwerhörigen-Verein St.Gallen | Q89: 1 | R89: ORGANISATION | S89: BSV_NR66 | T89: =BP3 -> 0 | U89: BP3
C90: =H$1 -> 3158 | D90: =K$1 -> 5 | E90: =D$1 -> 2017 | F90: =I$3 -> 0 | G90: ORGANISATIONSDATEN | H90: ANZ_MA_FREIWILLIG_BEHINDERT | I90: =IF(ISBLANK(I7),"",I7) | J90: I7 | K90: 2151 | L90: Frauenzentrale des Kantons St.Gallen HED | Q90: 1 | R90: ORGANISATION | S90: BSV_NR67 | T90: =BQ3 -> 0 | U90: BQ3
C91: =H$1 -> 3158 | D91: =K$1 -> 5 | E91: =D$1 -> 2017 | F91: =I$3 -> 0 | G91: ORGANISATIONSDATEN | H91: ANZ_MITARBEITER_EHRENAMTLICH | I91: =IF(ISBLANK(I8),"",I8) | J91: I8 | K91: 2155 | L91: OBV - Beratungs - und Sozialdienst für Blinde und Sehbehinderte, St. Gallen | Q91: 1 | R91: ORGANISATION | S91: BSV_NR68 | T91: =BR3 -> 0 | U91: BR3
C92: =H$1 -> 3158 | D92: =K$1 -> 5 | E92: =D$1 -> 2017 | F92: =I$3 -> 0 | G92: ORGANISATIONSDATEN | H92: ANZ_MA_EHRENAMTLICH_BEHINDERT | I92: =IF(ISBLANK(I9),"",I9) | J92: I9 | K92: 2157 | L92: insieme Ostschweiz | Q92: 1 | R92: ORGANISATION | S92: BSV_NR69 | T92: =BS3 -> 0 | U92: BS3
C93: =H$1 -> 3158 | D93: =K$1 -> 5 | E93: =D$1 -> 2017 | F93: =I$3 -> 0 | G93: ORGANISATIONSDATEN | H93: PERSONALAUFWAND | I93: =IF(ISBLANK(I10),"",I10) | J93: I10 | K93: 2158 | L93: insieme Nidwalden | Q93: 1 | R93: ORGANISATION | S93: BSV_NR70 | T93: =BT3 -> 0 | U93: BT3
C94: =H$1 -> 3158 | D94: =K$1 -> 5 | E94: =D$1 -> 2017 | F94: =I$3 -> 0 | G94: ORGANISATIONSDATEN | H94: BETRIEBSAUFWAND | I94: =IF(ISBLANK(I11),"",I11) | J94: I11 | K94: 2161 | L94: Schwerhörigen-Verein Surental und Umg. | Q94: 1 | R94: ORGANISATION | S94: BSV_NR71 | T94: =BU3 -> 0 | U94: BU3
C95: =H$1 -> 3158 | D95: =K$1 -> 5 | E95: =D$1 -> 2017 | F95: =I$3 -> 0 | G95: ORGANISATIONSDATEN | H95: BETRIEBSERTRAG | I95: =IF(ISBLANK(I12),"",I12) | J95: I12 | K95: 2162 | L95: Schwerhörigen-Verein Thun | Q95: 1 | R95: ORGANISATION | S95: BSV_NR72 | T95: =BV3 -> 0 | U95: BV3
C96: =H$1 -> 3158 | D96: =K$1 -> 5 | E96: =D$1 -> 2017 | F96: =I$3 -> 0 | G96: ORGANISATIONSDATEN | H96: BEITRAG_IV | I96: =IF(ISBLANK(I13),"",I13) | J96: I13 | K96: 2163 | L96: Stiftung WOHIN, Thun | Q96: 1 | R96: ORGANISATION | S96: BSV_NR73 | T96: =BW3 -> 0 | U96: BW3
C97: =H$1 -> 3158 | D97: =K$1 -> 5 | E97: =D$1 -> 2017 | F97: =I$3 -> 0 | G97: ORGANISATIONSDATEN | H97: BEITRAG_AHV | I97: =IF(ISBLANK(I14),"",I14) | J97: I14 | K97: 2168 | L97: ABV - Beratungsstelle für Sehbehinderte des Aarg. Blindenfürsorgevereins, Aarau | Q97: 1 | R97: ORGANISATION | S97: BSV_NR74 | T97: =BX3 -> 0 | U97: BX3
C98: =H$1 -> 3158 | D98: =K$1 -> 5 | E98: =D$1 -> 2017 | F98: =J$3 -> 0 | G98: ORGANISATIONSDATEN | H98: ANZ_MITARBEITER | I98: =IF(ISBLANK(J4),"",J4) | J98: J4 | K98: 2169 | L98: Stiftung Kind und Autismus | Q98: 1 | R98: ORGANISATION | S98: BSV_NR75 | T98: =BY3 -> 0 | U98: BY3
C99: =H$1 -> 3158 | D99: =K$1 -> 5 | E99: =D$1 -> 2017 | F99: =J$3 -> 0 | G99: ORGANISATIONSDATEN | H99: ANZ_MITARBEITER_BEHINDERT | I99: =IF(ISBLANK(J5),"",J5) | J99: J5 | K99: 2171 | L99: insieme Zürcher Oberland | Q99: 1 | R99: ORGANISATION | S99: BSV_NR76 | T99: =BZ3 -> 0 | U99: BZ3
C100: =H$1 -> 3158 | D100: =K$1 -> 5 | E100: =D$1 -> 2017 | F100: =J$3 -> 0 | G100: ORGANISATIONSDATEN | H100: ANZ_MITARBEITER_FREIWILLIG | I100: =IF(ISBLANK(J6),"",J6) | J100: J6 | K100: 2175 | L100: Schwerhörigen-Verein Wädenswil-Richters u.Umg. | Q100: 1 | R100: ORGANISATION | S100: BSV_NR77 | T100: =CA3 -> 0 | U100: CA3
...

Sheet Kostenrechnung konsolidiert
B1: CA consolidée au niveau du mandataire (CP) pour l'année: | J1: ='Organisationsdaten (Basisinfo)'!D1 -> 2017 | M1: numéro de contrat | P1: ='Organisationsdaten (Basisinfo)'!H1 -> 3158 | W1: Perioden ID | X1: ='Organisationsdaten (Basisinfo)'!K1 -> 5
B2: A | C2: B | D2: C | E2: D | F2: E | G2: F | H2: G | I2: H | J2: I | K2: J | L2: K | M2: L | N2: M | O2: N | P2: O | Q2: P | U2: T | W2: U | X2: V | Y2: W
A3: 1 | B3: Genre de coûts (indiquer les chiffres de manière complète et non seulement par tranches de mille) | C3: CF-CA | G3: Centre de coûts (coûts indirects/-produits) | J3: Unités d'imputation (Coûts directs/-produits + répartition de coûts indirects/-produits) | Y3: Total
A4: 2 | C4: Charges/Produits selon CF | D4: Délimitations CF-CA | E4: Délimitations des charges propres à la fonction d'organisation faîtière | F4: Charges/Produits selon CA | G4: Personnel | H4: Locaux | I4: Direction, administration et organes | J4: Conseil et aide aux handicapés et aux proches | K4: Aide dans les lieux d'accueil | L4: Conseil en matière de construction | M4: Conseil juridique | N4: Mise en relation avec des services d'aide et d'interprètes | O4: Cours en bloc pour handicapés et proches | P4: Cours d'un jour pour handicapés et proches | Q4: Cours annuels et semestriels pour handicapés et proches | U4: Prestation ayant pour objet de soutenir et de promouvoir la réadaptation des handicapés | W4: Accompagnement à domicile | X4: Récolte de fonds
A5: 3 | B5: Salaires | C5: - | D5: - | E5: 0 | F5: - | G5: - | H5: - | I5: - | J5: 2079.3412 | K5: 0 | L5: 0 | M5: 0 | N5: 0 | O5: 227427.32 | P5: 35858.253 | Q5: 0 | U5: 4050.1469 | W5: 0 | X5: 0 | Y5: =SUM(J5:X5) -> 269415.06 | Z5: Charges directes
A6: 4 | B6: Charges sociales | C6: - | D6: - | E6: 0 | F6: - | G6: - | H6: - | I6: - | J6: 275.33232 | K6: 0 | L6: 0 | M6: 0 | N6: 0 | O6: 30114.39 | P6: 4748.1077 | Q6: 0 | U6: 536.2931 | W6: 0 | X6: 0 | Y6: =SUM(J6:X6) -> 35674.123
A7: 5 | B7: Autres charges de personnel | C7: - | D7: - | E7: 0 | F7: - | G7: - | H7: - | I7: - | J7: 18.913683 | K7: 0 | L7: 0 | M7: 0 | N7: 0 | O7: 2068.6784 | P7: 326.16659 | Q7: 0 | U7: 36.840128 | W7: 0 | X7: 0 | Y7: =SUM(J7:X7) -> 2450.5988
A8: 6 | B8: Honoraires | C8: - | D8: - | E8: 0 | F8: - | G8: - | H8: - | I8: - | J8: 0 | K8: 0 | L8: 0 | M8: 0 | N8: 0 | O8: 0 | P8: 0 | Q8: 0 | U8: 0 | W8: 0 | X8: 0 | Y8: =SUM(J8:X8) -> 0
A9: 7 | B9: Total des charges de personnel/ Coûts | C9: - | D9: - | E9: =SUM(E5:E8) -> 0 | F9: - | G9: - | H9: - | I9: - | J9: =SUM(J5:J8) -> 2373.5872 | K9: =SUM(K5:K8) -> 0 | L9: =SUM(L5:L8) -> 0 | M9: =SUM(M5:M8) -> 0 | N9: =SUM(N5:N8) -> 0 | O9: =SUM(O5:O8) -> 259610.39 | P9: =SUM(P5:P8) -> 40932.528 | Q9: =SUM(Q5:Q8) -> 0 | U9: =SUM(U5:U8) -> 4623.2802 | W9: =SUM(W5:W8) -> 0 | X9: =SUM(X5:X8) -> 0 | Y9: =SUM(J9:X9) -> 307539.79
A10: 8 | B10: Frais de locaux | C10: - | D10: - | E10: 0 | F10: - | G10: - | H10: - | I10: - | J10: 0 | K10: 0 | L10: 0 | M10: 0 | N10: 0 | O10: 0 | P10: 0 | Q10: 0 | U10: 0 | W10: 0 | X10: 0 | Y10: =SUM(J10:X10) -> 0
A11: 9 | B11: Autres frais d'exploitation | C11: - | D11: - | E11: 0 | F11: - | G11: - | H11: - | I11: - | J11: 0 | K11: 0 | L11: 0 | M11: 0 | N11: 0 | O11: 167265.66 | P11: 28497.15 | Q11: 0 | U11: 0 | W11: 0 | X11: 0 | Y11: =SUM(J11:X11) -> 195762.81
A12: 10 | B12: amortissements (immeubles exclus) | C12: - | D12: - | E12: 0.32127082 | F12: - | G12: - | H12: - | I12: - | J12: 0 | K12: 0 | L12: 0 | M12: 0 | N12: 0 | O12: 0 | P12: 0 | Q12: 0 | U12: 0 | W12: 0 | X12: 0 | Y12: =SUM(J12:X12) -> 0
A13: 11 | B13: Total charges/coûts | C13: - | D13: - | E13: =SUM(E9:E12) -> 0.32127082 | F13: - | G13: - | H13: - | I13: - | J13: =SUM(J9:J12) -> 2373.5872 | K13: =SUM(K9:K12) -> 0 | L13: =SUM(L9:L12) -> 0 | M13: =SUM(M9:M12) -> 0 | N13: =SUM(N9:N12) -> 0 | O13: =SUM(O9:O12) -> 426876.05 | P13: =SUM(P9:P12) -> 69429.678 | Q13: =SUM(Q9:Q12) -> 0 | U13: =SUM(U9:U12) -> 4623.2802 | W13: =SUM(W9:W12) -> 0 | X13: =SUM(X9:X12) -> 0 | Y13: =SUM(J13:X13) -> 503302.6
A14: 12 | B14: Répartition charges de personnel | C14: - | D14: - | E14: 0 | F14: - | G14: - | H14: - | I14: - | J14: 0 | K14: 0 | L14: 0 | M14: 0 | N14: 0 | O14: 0 | P14: 0 | Q14: 0 | U14: 0 | W14: 0 | X14: 0 | Y14: =ROUND(SUM(J14:X14),0) -> 0 | Z14: Frais généraux
A15: 13 | B15: Répartition frais de locaux | C15: - | D15: - | E15: 0 | F15: - | G15: - | H15: - | I15: - | J15: 221.47887 | K15: 0 | L15: 0 | M15: 0 | N15: 0 | O15: 39831.704 | P15: 6478.4669 | Q15: 0 | U15: 431.39718 | W15: 0 | X15: 0 | Y15: =ROUND(SUM(J15:X15),0) -> 46963
A16: 14 | B16: Répartition direction/administration/ organes | C16: - | D16: - | E16: 0 | F16: - | G16: - | H16: - | I16: - | J16: 1004.8574 | K16: 0 | L16: 0 | M16: 0 | N16: 0 | O16: 180717.85 | P16: 29393.033 | Q16: 0 | U16: 1957.2642 | W16: 0 | X16: 0 | Y16: =ROUND(SUM(J16:X16),0) -> 213073
A17: 15 | B17: Total des répartitions | C17: - | D17: - | E17: =SUM(E14:E16) -> 0 | F17: - | G17: - | H17: - | I17: - | J17: =SUM(J14:J16) -> 1226.3363 | K17: =SUM(K14:K16) -> 0 | L17: =SUM(L14:L16) -> 0 | M17: =SUM(M14:M16) -> 0 | N17: =SUM(N14:N16) -> 0 | O17: =SUM(O14:O16) -> 220549.55 | P17: =SUM(P14:P16) -> 35871.5 | Q17: =SUM(Q14:Q16) -> 0 | U17: =SUM(U14:U16) -> 2388.6614 | W17: =SUM(W14:W16) -> 0 | X17: =SUM(X14:X16) -> 0 | Y17: =SUM(J17:X17) -> 260036.05
A18: 16 | B18: coûts complets après répartition | C18: - | D18: - | E18: =E17+E13 -> 0.32127082 | F18: - | G18: - | H18: - | I18: - | J18: =J17+J13 -> 3599.9235 | K18: =K17+K13 -> 0 | L18: =L17+L13 -> 0 | M18: =M17+M13 -> 0 | N18: =N17+N13 -> 0 | O18: =O17+O13 -> 647425.6 | P18: =P17+P13 -> 105301.18 | Q18: =Q17+Q13 -> 0 | U18: =U17+U13 -> 7011.9416 | W18: =W17+W13 -> 0 | X18: =X17+X13 -> 0 | Y18: =SUM(J18:X18) -> 763338.64
A19: 17 | B19: Produits des prestations | C19: - | D19: - | E19: - | F19: - | G19: - | H19: - | I19: - | J19: 0 | K19: 0 | L19: 0 | M19: 0 | N19: 0 | O19: 49931.05 | P19: 3929 | Q19: 0 | U19: 0 | W19: 0 | X19: 0 | Y19: =SUM(J19:Q19,U19,W19,X19) -> 53860.05
A20: 18 | B20: Subventions AI (art. 74 LAI et art. 101bis LAVS) | C20: - | D20: - | E20: 0 | F20: - | G20: - | H20: - | I20: - | J20: 12600 | K20: 0 | L20: 0 | M20: 0 | N20: 0 | O20: 200036 | P20: 0 | Q20: 0 | U20: 8000 | W20: 0 | Y20: =SUM(J20:Q20,U20,W20) -> 220636
A21: 19 | B21: Autres subventions de la confédération/ Subventions des cantons/communes | C21: - | D21: - | E21: - | F21: - | G21: - | H21: - | I21: - | J21: 0 | K21: 0 | L21: 0 | M21: 0 | N21: 0 | O21: 148049.22 | P21: 23342.782 | Q21: 0 | U21: 0 | W21: 0 | X21: 0 | Y21: =SUM(J21:Q21,U21,W21,X21) -> 171392
A22: 20 | B22: Donations directes/ Autres produits art. 74 LAI1) | C22: - | D22: - | E22: - | F22: - | G22: - | H22: - | I22: - | J22: 0 | K22: 0 | L22: 0 | M22: 0 | N22: 0 | O22: 26470 | P22: 15000 | Q22: 0 | U22: 0 | W22: 0 | X22: 0 | Y22: =SUM(J22:Q22,U22,W22,X22) -> 41470
A23: 21 | B23: Donations indirectes/ autres produits (clé de répartition) 2) | C23: - | D23: - | E23: - | F23: - | G23: - | H23: - | I23: - | J23: 1217.9492 | K23: 0 | L23: 0 | M23: 0 | N23: 0 | O23: 219041.18 | P23: 35626.169 | Q23: 0 | U23: 2372.325 | W23: 0 | X23: 0 | Y23: =SUM(J23:Q23,U23,W23,X23) -> 258257.62
A24: 22 | B24: Donations directes/ autres produits hors Art. 74 LAI 3) | C24: - | D24: - | E24: - | F24: - | G24: - | H24: - | I24: - | J24: 0 | K24: 0 | L24: 0 | M24: 0 | N24: 0 | O24: 0 | P24: 0 | Q24: 0 | U24: 0 | W24: 0 | X24: 0 | Y24: - | AB24: Plausibilisierung Kostenträger Leistungsstatistik
A25: 23 | B25: Total des produits | C25: - | D25: - | E25: =SUM(E19:E24) -> 0 | F25: - | G25: - | H25: - | I25: - | J25: =SUM(J19:J24) -> 13817.949 | K25: =SUM(K19:K24) -> 0 | L25: =SUM(L19:L24) -> 0 | M25: =SUM(M19:M24) -> 0 | N25: =SUM(N19:N24) -> 0 | O25: =SUM(O19:O24) -> 643527.44 | P25: =SUM(P19:P24) -> 77897.95 | Q25: =SUM(Q19:Q24) -> 0 | U25: =SUM(U19:U24) -> 10372.325 | W25: =SUM(W19:W24) -> 0 | X25: =SUM(X19:X24) -> 0 | Y25: =SUM(Y19:Y24) -> 745615.67 | AB25: Beratung Beh | AC25: Treffpunkte | AD25: Bauberatung | AE25: Rechtsberatung | AF25: Vermittlung Betr | AG25: Blockkurse Beh | AH25: Tageskurse Beh | AI25: Semesterk. Beh | AJ25: Blockkurse F | AK25: Tageskurse F | AL25: Semesterk. F | AM25: LUFEB | AN25: Kontrolle
A26: 24 | AB26: ='Beratung und Betreuung'!F15+'Beratung und Betreuung'!I15 -> 47 | AC26: ='Beratung und Betreuung'!K15 -> 0 | AD26: ='Beratung und Betreuung'!N15 -> 0 | AE26: ='Beratung und Betreuung'!Q15 -> 0 | AF26: ='Beratung und Betreuung'!S15 -> 0 | AG26: =KlientInnenstatistik!B15+KlientInnenstatistik!C15 -> 338 | AI26: =KlientInnenstatistik!F15+KlientInnenstatistik!G15 -> 0 | AJ26: ='Kurse Fachpersonal'!C10 -> 0 | AK26: ='Kurse Fachpersonal'!C11 -> 0 | AL26: ='Kurse Fachpersonal'!C12 -> 0 | AM26: =LUFEB!B14 -> 353
A27: 25 | B27: Contribution de couverture (Cc) I (Produit des prestations - Coûts directs) | J27: =J19-J13 -> -2373.5872 | K27: =K19-K13 -> 0 | L27: =L19-L13 -> 0 | M27: =M19-M13 -> 0 | N27: =N19-N13 -> 0 | O27: =O19-O13 -> -376945 | P27: =P19-P13 -> -65500.678 | Q27: =Q19-Q13 -> 0 | U27: =U19-U13 -> -4623.2802 | W27: =W19-W13 -> 0 | X27: - | Y27: =Y19-Y13 -> -449442.55 | AB27: =J18 -> 3599.9235 | AC27: =K18 -> 0 | AD27: =L18 -> 0 | AE27: =M18 -> 0 | AF27: =N18 -> 0 | AG27: =O18 -> 647425.6 | AH27: =P18 -> 105301.18 | AI27: =Q18 -> 0 | AJ27: =#REF! -> #REF! | AK27: =#REF! -> #REF! | AL27: =#REF! -> #REF! | AM27: =U18 -> 7011.9416
A28: 26 | B28: Contribution de couverture II ( Cc I - coûts indirects + Donations directes/ Autres produits Art.74 LAI + Donations indirectes, Autres produits (clé de répartition)) | C28: - | D28: - | F28: - | G28: - | H28: - | I28: - | J28: =J27-J17+J22+J23 -> -2381.9743 | K28: =K27-K17+K22+K23 -> 0 | L28: =L27-L17+L22+L23 -> 0 | M28: =M27-M17+M22+M23 -> 0 | N28: =N27-N17+N22+N23 -> 0 | O28: =O27-O17+O22+O23 -> -351983.38 | P28: =P27-P17+P22+P23 -> -50746.009 | Q28: =Q27-Q17+Q22+Q23 -> 0 | U28: =U27-U17+U22+U23 -> -4639.6166 | W28: =W27-W17+W22+W23 -> 0 | X28: - | Y28: =Y27-Y17+Y22+Y23 -> -409750.98 | AC28: =COUNTIF(AC26:AC27,">0") -> 0 | AD28: =COUNTIF(AD26:AD27,">0") -> 0 | AE28: =COUNTIF(AE26:AE27,">0") -> 0 | AF28: =COUNTIF(AF26:AF27,">0") -> 0 | AG28: =COUNTIF(AG26:AG27,">0") -> 2 | AH28: 0 | AI28: =COUNTIF(AI26:AI27,">0") -> 0 | AJ28: =COUNTIF(AJ26:AJ27,">0") -> 0 | AK28: =COUNTIF(AK26:AK27,">0") -> 0 | AL28: =COUNTIF(AL26:AL27,">0") -> 0 | AM28: =COUNTIF(AM26:AM27,">0") -> 2 | AN28: =COUNTIF(AB28:AM28,1) -> 0
A29: 27 | B29: Contribution de couverture III ( Cc II + autres subventions Confédération, subventions des cantons et communes) | C29: - | D29: - | F29: - | G29: - | H29: - | I29: - | J29: =J28+J21 -> -2381.9743 | K29: =K28+K21 -> 0 | L29: =L28+L21 -> 0 | M29: =M28+M21 -> 0 | N29: =N28+N21 -> 0 | O29: =O28+O21 -> -203934.16 | P29: =P28+P21 -> -27403.227 | Q29: =Q28+Q21 -> 0 | U29: =U28+U21 -> -4639.6166 | W29: =W28+W21 -> 0 | X29: - | Y29: =Y28+Y21 -> -238358.98
A30: 28 | B30: Contribution de couverture IV (Cc III + Subvention AI) | C30: - | D30: - | F30: - | G30: - | H30: - | I30: - | J30: =J29+J20 -> 10218.026 | K30: =K29+K20 -> 0 | L30: =L29+L20 -> 0 | M30: =M29+M20 -> 0 | N30: =N29+N20 -> 0 | O30: =O29+O20 -> -3898.1581 | P30: =P29+P20 -> -27403.227 | Q30: =Q29+Q20 -> 0 | U30: =U29+U20 -> 3360.3834 | W30: =W29+W20 -> 0 | X30: - | Y30: =Y29+Y20 -> -17722.976 | AB30: Plausibilisierung Direkte- Indirekte Kosten
A31: 1) Donations liées art. 74 LAI, subventions, prestations de services, sponsoring pour l'art.74 LAI | AB31: =J13 -> 2373.5872 | AC31: =K13 -> 0 | AD31: =L13 -> 0 | AE31: =M13 -> 0 | AF31: =N13 -> 0 | AG31: =O13 -> 426876.05 | AH31: =P13 -> 69429.678 | AI31: =Q13 -> 0 | AJ31: =#REF! -> #REF! | AK31: =#REF! -> #REF! | AL31: =#REF! -> #REF! | AM31: =U13 -> 4623.2802 | AN31: =#REF! -> #REF! | AO31: =W13 -> 0 | AP31: =X13 -> 0
A32: 2) Tous autres produits non affectés / donations /héritages, cotisations des membres, résultat financier, produits extraordinaires etc. sont délimités selon clé de répartition et attribués à l'activité Art. 74 LAI. | AB32: =J18 -> 3599.9235 | AC32: =K18 -> 0 | AD32: =L18 -> 0 | AE32: =M18 -> 0 | AF32: =N18 -> 0 | AG32: =O18 -> 647425.6 | AH32: =P18 -> 105301.18 | AI32: =Q18 -> 0 | AJ32: =#REF! -> #REF! | AK32: =#REF! -> #REF! | AL32: =#REF! -> #REF! | AM32: =U18 -> 7011.9416 | AN32: =#REF! -> #REF! | AO32: =W18 -> 0 | AP32: =X18 -> 0
J33: =IF(AN28<>0,"Die blaue Markierung verschwindet, sobald die Angaben für diese Leistung sowohl in der Kostenrechnung als auch in der Leistungstatistik vorhanden sind.","") | AB33: =COUNTIF(AB31:AB32,">0") -> 2 | AC33: =COUNTIF(AC31:AC32,">0") -> 0 | AD33: =COUNTIF(AD31:AD32,">0") -> 0 | AE33: =COUNTIF(AE31:AE32,">0") -> 0 | AF33: =COUNTIF(AF31:AF32,">0") -> 0 | AG33: =COUNTIF(AG31:AG32,">0") -> 2 | AH33: =COUNTIF(AH31:AH32,">0") -> 2 | AI33: =COUNTIF(AI31:AI32,">0") -> 0 | ... AP33: =COUNTIF(AP31:AP32,">0") -> 0 | AQ33: =COUNTIF(AB33:AP33,1) -> 0
A34: 3) Produits affectés hors art. 74 LAI
J35: =IF(AQ33<>0,"Die rote Markierung verschwindet, sobald für diesen Kostenträger auch direkte Kosten erfasst worden sind.","")
C40: VERTRAG_NR | D40: PERIODE_ID | E40: JAHR | F40: KOSTENTRAEGER_ID | G40: TABELLE | H40: FELD | I40: WERT | J40: ADRESSE
C41: =P$1 -> 3158 | D41: =X$1 -> 5 | E41: =J$1 -> 2017 | F41: 1 | G41: KOSTENRECHNUNG_KOSTENTRAEGER | H41: LOHNAUFWAND | I41: =IF(ISBLANK(J5),"",J5) -> 2079.3412 | J41: J5 | K41: Spaltenweise von links nach rechts | L41: Beratung und Betreuung von Behinderten&Angehörigen
C42: =P$1 -> 3158 | D42: =X$1 -> 5 | E42: =J$1 -> 2017 | F42: 1 | G42: KOSTENRECHNUNG_KOSTENTRAEGER | H42: VERSICHERUNGSAUFWAND | I42: =IF(ISBLANK(J6),"",J6) -> 275.33232 | J42: J6
C43: =P$1 -> 3158 | D43: =X$1 -> 5 | E43: =J$1 -> 2017 | F43: 1 | G43: KOSTENRECHNUNG_KOSTENTRAEGER | H43: PERSONALAUFWAND_REST | I43: =IF(ISBLANK(J7),"",J7) -> 18.913683 | J43: J7
C44: =P$1 -> 3158 | D44: =X$1 -> 5 | E44: =J$1 -> 2017 | F44: 1 | G44: KOSTENRECHNUNG_KOSTENTRAEGER | H44: HONORARE | I44: =IF(ISBLANK(J8),"",J8) -> 0 | J44: J8
C45: =P$1 -> 3158 | D45: =X$1 -> 5 | E45: =J$1 -> 2017 | F45: 1 | G45: KOSTENRECHNUNG_KOSTENTRAEGER | H45: PERSONALAUFWAND | I45: =IF(J9=0,"",J9) -> 2373.5872
C46: =P$1 -> 3158 | D46: =X$1 -> 5 | E46: =J$1 -> 2017 | F46: 1 | G46: KOSTENRECHNUNG_KOSTENTRAEGER | H46: RAUMAUFWAND | I46: =IF(ISBLANK(J10),"",J10) -> 0 | J46: J10
C47: =P$1 -> 3158 | D47: =X$1 -> 5 | E47: =J$1 -> 2017 | F47: 1 | G47: KOSTENRECHNUNG_KOSTENTRAEGER | H47: SACHAUFWAND_REST | I47: =IF(ISBLANK(J11),"",J11) -> 0 | J47: J11
C48: =P$1 -> 3158 | D48: =X$1 -> 5 | E48: =J$1 -> 2017 | F48: 1 | G48: KOSTENRECHNUNG_KOSTENTRAEGER | H48: ABSCHREIBUNGEN | I48: =IF(ISBLANK(J12),"",J12) -> 0 | J48: J12
C49: =P$1 -> 3158 | D49: =X$1 -> 5 | E49: =J$1 -> 2017 | F49: 1 | G49: KOSTENRECHNUNG_KOSTENTRAEGER | H49: KOSTEN_DIREKT | I49: =IF(J13=0,"",J13) -> 2373.5872
C50: =P$1 -> 3158 | D50: =X$1 -> 5 | E50: =J$1 -> 2017 | F50: 1 | G50: KOSTENRECHNUNG_KOSTENTRAEGER | H50: PERSONALUMLAGE | I50: =IF(ISBLANK(J14),"",J14) -> 0 | J50: J14
C51: =P$1 -> 3158 | D51: =X$1 -> 5 | E51: =J$1 -> 2017 | F51: 1 | G51: KOSTENRECHNUNG_KOSTENTRAEGER | H51: RAUMUMLAGE | I51: =IF(ISBLANK(J15),"",J15) -> 221.47887 | J51: J15
C52: =P$1 -> 3158 | D52: =X$1 -> 5 | E52: =J$1 -> 2017 | F52: 1 | G52: KOSTENRECHNUNG_KOSTENTRAEGER | H52: VERWALTUNGSUMLAGE | I52: =IF(ISBLANK(J16),"",J16) -> 1004.8574 | J52: J16
C53: =P$1 -> 3158 | D53: =X$1 -> 5 | E53: =J$1 -> 2017 | F53: 1 | G53: KOSTENRECHNUNG_KOSTENTRAEGER | H53: KOSTEN_INDIREKT | I53: =IF(J17=0,"",J17) -> 1226.3363
C54: =P$1 -> 3158 | D54: =X$1 -> 5 | E54: =J$1 -> 2017 | F54: 1 | G54: KOSTENRECHNUNG_KOSTENTRAEGER | H54: LEISTUNGSERTRAG | I54: =IF(ISBLANK(J19),"",J19) -> 0 | J54: J19
C55: =P$1 -> 3158 | D55: =X$1 -> 5 | E55: =J$1 -> 2017 | F55: 1 | G55: KOSTENRECHNUNG_KOSTENTRAEGER | H55: BEITRAG_IV | I55: =IF(ISBLANK(J20),"",J20) -> 12600 | J55: J20
C56: =P$1 -> 3158 | D56: =X$1 -> 5 | E56: =J$1 -> 2017 | F56: 1 | G56: KOSTENRECHNUNG_KOSTENTRAEGER | H56: BEITRAG_AHV | I56: =IF(ISBLANK(J21),"",J21) -> 0 | J56: J21
C57: =P$1 -> 3158 | D57: =X$1 -> 5 | E57: =J$1 -> 2017 | F57: 1 | G57: KOSTENRECHNUNG_KOSTENTRAEGER | H57: BEITRAG_BUND | I57: =IF(ISBLANK(J22),"",J22) -> 0 | J57: J22
C58: =P$1 -> 3158 | D58: =X$1 -> 5 | E58: =J$1 -> 2017 | F58: 1 | G58: KOSTENRECHNUNG_KOSTENTRAEGER | H58: BEITRAG_KANTON | I58: =IF(ISBLANK(J23),"",J23) -> 1217.9492 | J58: J23
C59: =P$1 -> 3158 | D59: =X$1 -> 5 | E59: =J$1 -> 2017 | F59: 1 | G59: KOSTENRECHNUNG_KOSTENTRAEGER | H59: BEITRAG_GEMEINDE | I59: =IF(ISBLANK(J24),"",J24) -> 0 | J59: J24
C60: =P$1 -> 3158 | D60: =X$1 -> 5 | E60: =J$1 -> 2017 | F60: 1 | G60: KOSTENRECHNUNG_KOSTENTRAEGER | H60: ERTRAG | I60: =IF(J25=0,"",J25) -> 13817.949
C61: =P$1 -> 3158 | D61: =X$1 -> 5 | E61: =J$1 -> 2017 | F61: 2 | G61: KOSTENRECHNUNG_KOSTENTRAEGER | H61: LOHNAUFWAND | I61: =IF(ISBLANK(K5),"",K5) -> 0 | J61: K5 | L61: Betreuung in Treffpunkten
C62: =P$1 -> 3158 | D62: =X$1 -> 5 | E62: =J$1 -> 2017 | F62: 2 | G62: KOSTENRECHNUNG_KOSTENTRAEGER | H62: VERSICHERUNGSAUFWAND | I62: =IF(ISBLANK(K6),"",K6) -> 0 | J62: K6
C63: =P$1 -> 3158 | D63: =X$1 -> 5 | E63: =J$1 -> 2017 | F63: 2 | G63: KOSTENRECHNUNG_KOSTENTRAEGER | H63: PERSONALAUFWAND_REST | I63: =IF(ISBLANK(K7),"",K7) -> 0 | J63: K7
C64: =P$1 -> 3158 | D64: =X$1 -> 5 | E64: =J$1 -> 2017 | F64: 2 | G64: KOSTENRECHNUNG_KOSTENTRAEGER | H64: HONORARE | I64: =IF(ISBLANK(K8),"",K8) -> 0 | J64: K8
C65: =P$1 -> 3158 | D65: =X$1 -> 5 | E65: =J$1 -> 2017 | F65: 2 | G65: KOSTENRECHNUNG_KOSTENTRAEGER | H65: PERSONALAUFWAND | I65: =IF(K9=0,"",K9)
C66: =P$1 -> 3158 | D66: =X$1 -> 5 | E66: =J$1 -> 2017 | F66: 2 | G66: KOSTENRECHNUNG_KOSTENTRAEGER | H66: RAUMAUFWAND | I66: =IF(ISBLANK(K10),"",K10) -> 0 | J66: K10
C67: =P$1 -> 3158 | D67: =X$1 -> 5 | E67: =J$1 -> 2017 | F67: 2 | G67: KOSTENRECHNUNG_KOSTENTRAEGER | H67: SACHAUFWAND_REST | I67: =IF(ISBLANK(K11),"",K11) -> 0 | J67: K11
C68: =P$1 -> 3158 | D68: =X$1 -> 5 | E68: =J$1 -> 2017 | F68: 2 | G68: KOSTENRECHNUNG_KOSTENTRAEGER | H68: ABSCHREIBUNGEN | I68: =IF(ISBLANK(K12),"",K12) -> 0 | J68: K12
C69: =P$1 -> 3158 | D69: =X$1 -> 5 | E69: =J$1 -> 2017 | F69: 2 | G69: KOSTENRECHNUNG_KOSTENTRAEGER | H69: KOSTEN_DIREKT | I69: =IF(K13=0,"",K13)
C70: =P$1 -> 3158 | D70: =X$1 -> 5 | E70: =J$1 -> 2017 | F70: 2 | G70: KOSTENRECHNUNG_KOSTENTRAEGER | H70: PERSONALUMLAGE | I70: =IF(ISBLANK(K14),"",K14) -> 0 | J70: K14
C71: =P$1 -> 3158 | D71: =X$1 -> 5 | E71: =J$1 -> 2017 | F71: 2 | G71: KOSTENRECHNUNG_KOSTENTRAEGER | H71: RAUMUMLAGE | I71: =IF(ISBLANK(K15),"",K15) -> 0 | J71: K15
C72: =P$1 -> 3158 | D72: =X$1 -> 5 | E72: =J$1 -> 2017 | F72: 2 | G72: KOSTENRECHNUNG_KOSTENTRAEGER | H72: VERWALTUNGSUMLAGE | I72: =IF(ISBLANK(K16),"",K16) -> 0 | J72: K16
C73: =P$1 -> 3158 | D73: =X$1 -> 5 | E73: =J$1 -> 2017 | F73: 2 | G73: KOSTENRECHNUNG_KOSTENTRAEGER | H73: KOSTEN_INDIREKT | I73: =IF(K17=0,"",K17)
C74: =P$1 -> 3158 | D74: =X$1 -> 5 | E74: =J$1 -> 2017 | F74: 2 | G74: KOSTENRECHNUNG_KOSTENTRAEGER | H74: LEISTUNGSERTRAG | I74: =IF(ISBLANK(K19),"",K19) -> 0 | J74: K19
C75: =P$1 -> 3158 | D75: =X$1 -> 5 | E75: =J$1 -> 2017 | F75: 2 | G75: KOSTENRECHNUNG_KOSTENTRAEGER | H75: BEITRAG_IV | I75: =IF(ISBLANK(K20),"",K20) -> 0 | J75: K20
C76: =P$1 -> 3158 | D76: =X$1 -> 5 | E76: =J$1 -> 2017 | F76: 2 | G76: KOSTENRECHNUNG_KOSTENTRAEGER | H76: BEITRAG_AHV | I76: =IF(ISBLANK(K21),"",K21) -> 0 | J76: K21
C77: =P$1 -> 3158 | D77: =X$1 -> 5 | E77: =J$1 -> 2017 | F77: 2 | G77: KOSTENRECHNUNG_KOSTENTRAEGER | H77: BEITRAG_BUND | I77: =IF(ISBLANK(K22),"",K22) -> 0 | J77: K22
C78: =P$1 -> 3158 | D78: =X$1 -> 5 | E78: =J$1 -> 2017 | F78: 2 | G78: KOSTENRECHNUNG_KOSTENTRAEGER | H78: BEITRAG_KANTON | I78: =IF(ISBLANK(K23),"",K23) -> 0 | J78: K23
C79: =P$1 -> 3158 | D79: =X$1 -> 5 | E79: =J$1 -> 2017 | F79: 2 | G79: KOSTENRECHNUNG_KOSTENTRAEGER | H79: BEITRAG_GEMEINDE | I79: =IF(ISBLANK(K24),"",K24) -> 0 | J79: K24
C80: =P$1 -> 3158 | D80: =X$1 -> 5 | E80: =J$1 -> 2017 | F80: 2 | G80: KOSTENRECHNUNG_KOSTENTRAEGER | H80: ERTRAG | I80: =IF(K25=0,"",K25)
C81: =P$1 -> 3158 | D81: =X$1 -> 5 | E81: =J$1 -> 2017 | F81: 3 | G81: KOSTENRECHNUNG_KOSTENTRAEGER | H81: LOHNAUFWAND | I81: =IF(ISBLANK(L5),"",L5) -> 0 | J81: L5 | L81: Bauberatung
C82: =P$1 -> 3158 | D82: =X$1 -> 5 | E82: =J$1 -> 2017 | F82: 3 | G82: KOSTENRECHNUNG_KOSTENTRAEGER | H82: VERSICHERUNGSAUFWAND | I82: =IF(ISBLANK(L6),"",L6) -> 0 | J82: L6
C83: =P$1 -> 3158 | D83: =X$1 -> 5 | E83: =J$1 -> 2017 | F83: 3 | G83: KOSTENRECHNUNG_KOSTENTRAEGER | H83: PERSONALAUFWAND_REST | I83: =IF(ISBLANK(L7),"",L7) -> 0 | J83: L7
C84: =P$1 -> 3158 | D84: =X$1 -> 5 | E84: =J$1 -> 2017 | F84: 3 | G84: KOSTENRECHNUNG_KOSTENTRAEGER | H84: HONORARE | I84: =IF(ISBLANK(L8),"",L8) -> 0 | J84: L8
C85: =P$1 -> 3158 | D85: =X$1 -> 5 | E85: =J$1 -> 2017 | F85: 3 | G85: KOSTENRECHNUNG_KOSTENTRAEGER | H85: PERSONALAUFWAND | I85: =IF(L9=0,"",L9)
C86: =P$1 -> 3158 | D86: =X$1 -> 5 | E86: =J$1 -> 2017 | F86: 3 | G86: KOSTENRECHNUNG_KOSTENTRAEGER | H86: RAUMAUFWAND | I86: =IF(ISBLANK(L10),"",L10) -> 0 | J86: L10
C87: =P$1 -> 3158 | D87: =X$1 -> 5 | E87: =J$1 -> 2017 | F87: 3 | G87: KOSTENRECHNUNG_KOSTENTRAEGER | H87: SACHAUFWAND_REST | I87: =IF(ISBLANK(L11),"",L11) -> 0 | J87: L11
C88: =P$1 -> 3158 | D88: =X$1 -> 5 | E88: =J$1 -> 2017 | F88: 3 | G88: KOSTENRECHNUNG_KOSTENTRAEGER | H88: ABSCHREIBUNGEN | I88: =IF(ISBLANK(L12),"",L12) -> 0 | J88: L12
C89: =P$1 -> 3158 | D89: =X$1 -> 5 | E89: =J$1 -> 2017 | F89: 3 | G89: KOSTENRECHNUNG_KOSTENTRAEGER | H89: KOSTEN_DIREKT | I89: =IF(L13=0,"",L13)
C90: =P$1 -> 3158 | D90: =X$1 -> 5 | E90: =J$1 -> 2017 | F90: 3 | G90: KOSTENRECHNUNG_KOSTENTRAEGER | H90: PERSONALUMLAGE | I90: =IF(ISBLANK(L14),"",L14) -> 0 | J90: L14
C91: =P$1 -> 3158 | D91: =X$1 -> 5 | E91: =J$1 -> 2017 | F91: 3 | G91: KOSTENRECHNUNG_KOSTENTRAEGER | H91: RAUMUMLAGE | I91: =IF(ISBLANK(L15),"",L15) -> 0 | J91: L15
C92: =P$1 -> 3158 | D92: =X$1 -> 5 | E92: =J$1 -> 2017 | F92: 3 | G92: KOSTENRECHNUNG_KOSTENTRAEGER | H92: VERWALTUNGSUMLAGE | I92: =IF(ISBLANK(L16),"",L16) -> 0 | J92: L16
C93: =P$1 -> 3158 | D93: =X$1 -> 5 | E93: =J$1 -> 2017 | F93: 3 | G93: KOSTENRECHNUNG_KOSTENTRAEGER | H93: KOSTEN_INDIREKT | I93: =IF(L17=0,"",L17)
C94: =P$1 -> 3158 | D94: =X$1 -> 5 | E94: =J$1 -> 2017 | F94: 3 | G94: KOSTENRECHNUNG_KOSTENTRAEGER | H94: LEISTUNGSERTRAG | I94: =IF(ISBLANK(L19),"",L19) -> 0 | J94: L19
C95: =P$1 -> 3158 | D95: =X$1 -> 5 | E95: =J$1 -> 2017 | F95: 3 | G95: KOSTENRECHNUNG_KOSTENTRAEGER | H95: BEITRAG_IV | I95: =IF(ISBLANK(L20),"",L20) -> 0 | J95: L20
C96: =P$1 -> 3158 | D96: =X$1 -> 5 | E96: =J$1 -> 2017 | F96: 3 | G96: KOSTENRECHNUNG_KOSTENTRAEGER | H96: BEITRAG_AHV | I96: =IF(ISBLANK(L21),"",L21) -> 0 | J96: L21
C97: =P$1 -> 3158 | D97: =X$1 -> 5 | E97: =J$1 -> 2017 | F97: 3 | G97: KOSTENRECHNUNG_KOSTENTRAEGER | H97: BEITRAG_BUND | I97: =IF(ISBLANK(L22),"",L22) -> 0 | J97: L22
C98: =P$1 -> 3158 | D98: =X$1 -> 5 | E98: =J$1 -> 2017 | F98: 3 | G98: KOSTENRECHNUNG_KOSTENTRAEGER | H98: BEITRAG_KANTON | I98: =IF(ISBLANK(L23),"",L23) -> 0 | J98: L23
C99: =P$1 -> 3158 | D99: =X$1 -> 5 | E99: =J$1 -> 2017 | F99: 3 | G99: KOSTENRECHNUNG_KOSTENTRAEGER | H99: BEITRAG_GEMEINDE | I99: =IF(ISBLANK(L24),"",L24) -> 0 | J99: L24
C100: =P$1 -> 3158 | D100: =X$1 -> 5 | E100: =J$1 -> 2017 | F100: 3 | G100: KOSTENRECHNUNG_KOSTENTRAEGER | H100: ERTRAG | I100: =IF(L25=0,"",L25)
C101: =P$1 -> 3158 | D101: =X$1 -> 5 | E101: =J$1 -> 2017 | F101: 4 | G101: KOSTENRECHNUNG_KOSTENTRAEGER | H101: LOHNAUFWAND | I101: =IF(ISBLANK(M5),"",M5) -> 0 | J101: M5 | L101: Rechtsberatung
C102: =P$1 -> 3158 | D102: =X$1 -> 5 | E102: =J$1 -> 2017 | F102: 4 | G102: KOSTENRECHNUNG_KOSTENTRAEGER | H102: VERSICHERUNGSAUFWAND | I102: =IF(ISBLANK(M6),"",M6) -> 0 | J102: M6
C103: =P$1 -> 3158 | D103: =X$1 -> 5 | E103: =J$1 -> 2017 | F103: 4 | G103: KOSTENRECHNUNG_KOSTENTRAEGER | H103: PERSONALAUFWAND_REST | I103: =IF(ISBLANK(M7),"",M7) -> 0 | J103: M7
C104: =P$1 -> 3158 | D104: =X$1 -> 5 | E104: =J$1 -> 2017 | F104: 4 | G104: KOSTENRECHNUNG_KOSTENTRAEGER | H104: HONORARE | I104: =IF(ISBLANK(M8),"",M8) -> 0 | J104: M8
...

Sheet Beratung und Betreuung
A1: Conseil et aide pour l'année: | D1: ='Organisationsdaten (Basisinfo)'!D1 -> 2017 | E1: Contrat n° | F1: ='Organisationsdaten (Basisinfo)'!H1 -> 3158 | G1: =D1 -> 2017 | H1: =E1 -> Contrat n° | I1: =F1 -> 3158 | J1: =G1 -> 2017 | K1: =I1 -> 3158 | L1: =G1 -> 2017 | M1: =H1 -> Contrat n° | N1: =I1 -> 3158 | O1: =L1 -> 2017 | P1: =M1 -> Contrat n° | Q1: =N1 -> 3158 | R1: =O1 -> 2017 | S1: =Q1 -> 3158
C3: Conseil social + aide aux handicapés | G3: Conseil aux proches et aux personnes de référence | J3: Aide dans les lieux d'accueil | L3: Conseil en matière de construction | O3: Conseil juridique | R3: Mise en relation avec des services d'aide ou d'interprète
C4: Bref conseil social | D4: Conseil individuel | E4: Conseil en groupe | F4: Total nombre de handicapés | G4: Conseil individuel | H4: Conseil en groupe | I4: Nombre de proches et de pers. de réf. Conseillés. | J4: Nombre d'heures d'aide | K4: Nombre de visites (présences) | L4: Bref conseil | M4: Conseil avec tenue de dossier | O4: Bref conseil | P4: Conseil avec tenue de dossier | R4: Nombre d'heures | S4: Nombre d'interventions
C5: Nombre d'heures | D5: Nombre d'heures | E5: Nombre d'heures | G5: Nombre d'heures | H5: Nombre d'heures | L5: Nombre d'heures | M5: Nombre d'heures | N5: Nombre de handicapés | O5: Nombre d'heures | P5: Nombre d'heures | Q5: Nombre de handicapés
A7: Bénéficiaires reconnus | B7: Handic. mentaux/ayant des difficultés pour apprendre | D7: 16.25 | F7: 1 | G7: 72 | I7: 17
B8: Handicapés de l'ouïe
B9: Handicapés physiques | C9: 13 | D9: 17.25 | F9: 8 | G9: 50.5 | I9: 18
B10: Handicapés par suite de maladie
B11: Handicapés psychiques | D11: 12 | F11: 2 | G11: 17 | I11: 1
B12: Handicapés de la vue
B13: Handicapés du langage | U13: Plausibilisierung der Totale
B14: Handicapés par suite de dépendance | U14: D | V14: E | W14: F | X14: G | Y14: H | Z14: I | AA14: J | AB14: K | AC14: M | AD14: N | AE14: P | AF14: Q | AG14: R | AH14: S | AI14: Kontrolle
B15: Total | C15: =ROUND(SUM(C7:C14),2) -> 13 | D15: =ROUND(SUM(D7:D14),2) -> 45.5 | E15: =ROUND(SUM(E7:E14),2) -> 0 | F15: =SUM(F7:F14) -> 11 | G15: =ROUND(SUM(G7:G14),2) -> 139.5 | H15: =ROUND(SUM(H7:H14),2) -> 0 | I15: =SUM(I7:I14) -> 36 | J15: =ROUND(SUM(J7:J14),2) -> 0 | K15: =SUM(K7:K14) -> 0 | L15: =ROUND(SUM(L7:L14),2) -> 0 | M15: =ROUND(SUM(M7:M14),2) -> 0 | N15: =SUM(N7:N14) -> 0 | O15: =ROUND(SUM(O7:O14),2) -> 0 | P15: =ROUND(SUM(P7:P14),2) -> 0 | Q15: =SUM(Q7:Q14) -> 0 | R15: =ROUND(SUM(R7:R14),2) -> 0 | S15: =SUM(S7:S14) -> 0 | U15: =D15-D19 -> 0 | V15: =E15-E19 -> 0 | W15: =IF(OR(F15-F19<>0,F48-F51<>0,F15-F48<>0),1,0) -> 0 | X15: =G15-G19 -> 0 | Y15: =H15-H19 -> 0 | Z15: =IF(OR(I15-I19<>0,I48-I51<>0,I15-I48<>0),1,0) -> 0 | AA15: 0 | AB15: =IF(K15-K48<>0,1,0) -> 0 | AC15: =M15-M19 -> 0 | AD15: =IF(OR(N15-N19<>0,N48-N51<>0,N15-N48<>0),1,0) -> 0 | AE15: =P15-P19 -> 0 | AF15: =IF(OR(Q15-Q19<>0,Q48-Q51<>0,Q15-Q48<>0),1,0) -> 0 | AG15: =R15-R19 -> 0 | AH15: =IF(OR(S15-S19<>0,S15-S48<>0),1,0) -> 0 | AI15: =SUM(COUNTIF(U15:AH15,"<>0")) -> 0
B16: dont plurihandicapés | D16: 8.25 | F16: 5 | G16: 72.5 | I16: 24
B17: subventionnés selon l'art. 74 LAI | D17: 45.5 | F17: 11 | G17: 139.5 | I17: 36
B18: subventionnés selon l'art. 101bis LAVS | U18: Plausibilisierung Kostenträger Leistungsstatistik
B19: Total | D19: =ROUND(SUM(D17:D18),2) -> 45.5 | E19: =ROUND(SUM(E17:E18),2) -> 0 | F19: =SUM(F17:F18) -> 11 | G19: =ROUND(SUM(G17:G18),2) -> 139.5 | H19: =ROUND(SUM(H17:H18),2) -> 0 | I19: =SUM(I17:I18) -> 36 | M19: =ROUND(SUM(M17:M18),2) -> 0 | N19: =SUM(N17:N18) -> 0 | P19: =ROUND(SUM(P17:P18),2) -> 0 | Q19: =SUM(Q17:Q18) -> 0 | R19: =ROUND(SUM(R17:R18),2) -> 0 | S19: =SUM(S17:S18) -> 0 | U19: Beratung Beh | V19: Treffpunkte | W19: Bauberatung | X19: Rechtsberatung | Y19: Vermittlung | Z19: Kontrolle
A20: Total des bénéficiaires non reconnus | U20: ='Kostenrechnung konsolidiert'!J18 -> 3599.9235 | V20: ='Kostenrechnung konsolidiert'!K18 -> 0 | W20: ='Kostenrechnung konsolidiert'!L18 -> 0 | X20: ='Kostenrechnung konsolidiert'!M18 -> 0 | Y20: ='Kostenrechnung konsolidiert'!N18 -> 0
A21: Bénéficiaires reconnus | B21: AG | I21: 1 | U21: =SUM(C15:I15) -> 245 | V21: =J15+K15 -> 0 | W21: =L15+M15+N15 -> 0 | X21: =O15+P15+Q15 -> 0 | Y21: =R15+S15 -> 0
B22: AI | V22: =COUNTIF(V20:V21,">0") -> 0 | W22: =COUNTIF(W20:W21,">0") -> 0 | X22: =COUNTIF(X20:X21,">0") -> 0 | Y22: =COUNTIF(Y20:Y21,">0") -> 0 | Z22: =COUNTIF(U22:Y22,1) -> 0
B23: AR | C23: =IF(Z22<>0,"Die blaue Markierung verschwindet, sobald die Angaben für diese Leistung sowohl in der Kostenrechnung als auch in der Leistungstatistik vorhanden sind.","")
B24: BE
B25: BL
B26: BS
B27: FR
B28: GE
B29: GL
B30: GR
B31: JU | C31: =IF(AI15<>0,"Die rote Markierung verschwindet, sobald die Totale übereinstimmen","")
B32: LU
B33: NE
B34: NW
B35: OW
B36: SG
B37: SH
B38: SO
B39: SZ
B40: TG
B41: TI
B42: UR
B43: VD
B44: VS | F44: 11 | I44: 35
B45: ZG
B46: ZH
B47: Autre provenance (ayants droit à une subvention)
B48: Total | F48: =SUM(F21:F47) -> 11 | I48: =SUM(I21:I47) -> 36 | K48: =SUM(K21:K47) -> 0 | N48: =SUM(N21:N47) -> 0 | Q48: =SUM(Q21:Q47) -> 0 | R48: - | S48: =SUM(S21:S47) -> 0
B49: nouveaux clients | F49: 2 | I49: 12
B50: repris de l'année précédente | F50: 9 | I50: 24
B51: Total | F51: =SUM(F49:F50) -> 11 | I51: =SUM(I49:I50) -> 36 | N51: =SUM(N49:N50) -> 0 | Q51: =SUM(Q49:Q50) -> 0 | R51: - | S51: -
D53: KS | E53: =SUM(D15:E15,G15:H15,D20:E20,G20:H20)/SUM(C15:E15,G15:H15,D20:E20,G20:H20) -> 0.93434343
D54: KB | E54: =SUM(M15,M20)/SUM(L15,M15,M20) -> #DIV/0!
D55: KR | E55: =SUM(P15,P20)/SUM(O15,P15,P20) -> #DIV/0!
C58: P-ID | D58: ='Organisationsdaten (Basisinfo)'!K1 -> 5
C60: VERTRAG_NR | D60: PERIODE_ID | E60: JAHR | F60: ZIELGRUPPE_ID | G60: LEISTUNGSKATEGORIE_ID | H60: KURSTYP_ID | I60: KANTON_ID | J60: TABELLE | K60: FELD | L60: WERT | M60: ADRESSE
C61: =F$1 -> 3158 | D61: =D$58 -> 5 | E61: =D$1 -> 2017 | F61: 1 | G61: 1 | H61: -1 | J61: LEISTUNG_KATEGORIE_ZIELGRUPPE | K61: STUNDEN_KURZ | L61: =IF(ISBLANK(C7),"",C7) | M61: C7
C62: =F$1 -> 3158 | D62: =D$58 -> 5 | E62: =D$1 -> 2017 | F62: 1 | G62: 1 | H62: -1 | J62: LEISTUNG_KATEGORIE_ZIELGRUPPE | K62: STUNDEN | L62: =IF(ISBLANK(D7),"",D7) -> 16.25 | M62: D7 | N62: nach Zielgruppen: Zeilenweise von oben nach unten (Zeilen 7 bis 14)
C63: =F$1 -> 3158 | D63: =D$58 -> 5 | E63: =D$1 -> 2017 | F63: 1 | G63: 1 | H63: -1 | J63: LEISTUNG_KATEGORIE_ZIELGRUPPE | K63: STUNDEN_GRUPPE | L63: =IF(ISBLANK(E7),"",E7) | M63: E7
C64: =F$1 -> 3158 | D64: =D$58 -> 5 | E64: =D$1 -> 2017 | F64: 1 | G64: 1 | H64: -1 | J64: LEISTUNG_KATEGORIE_ZIELGRUPPE | K64: ANZAHL_BEHINDERTE | L64: =IF(ISBLANK(F7),"",F7) -> 1 | M64: F7
C65: =F$1 -> 3158 | D65: =D$58 -> 5 | E65: =D$1 -> 2017 | F65: 1 | G65: 2 | H65: -1 | J65: LEISTUNG_KATEGORIE_ZIELGRUPPE | K65: STUNDEN | L65: =IF(ISBLANK(G7),"",G7) -> 72 | M65: G7
C66: =F$1 -> 3158 | D66: =D$58 -> 5 | E66: =D$1 -> 2017 | F66: 1 | G66: 2 | H66: -1 | J66: LEISTUNG_KATEGORIE_ZIELGRUPPE | K66: STUNDEN_GRUPPE | L66: =IF(ISBLANK(H7),"",H7) | M66: H7
C67: =F$1 -> 3158 | D67: =D$58 -> 5 | E67: =D$1 -> 2017 | F67: 1 | G67: 2 | H67: -1 | J67: LEISTUNG_KATEGORIE_ZIELGRUPPE | K67: ANZAHL_ANGEHOERIGE | L67: =IF(ISBLANK(I7),"",I7) -> 17 | M67: I7
C68: =F$1 -> 3158 | D68: =D$58 -> 5 | E68: =D$1 -> 2017 | F68: 1 | G68: 3 | H68: -1 | J68: LEISTUNG_KATEGORIE_ZIELGRUPPE | K68: STUNDEN | L68: =IF(ISBLANK(J7),"",J7) | M68: J7
C69: =F$1 -> 3158 | D69: =D$58 -> 5 | E69: =D$1 -> 2017 | F69: 1 | G69: 3 | H69: -1 | J69: LEISTUNG_KATEGORIE_ZIELGRUPPE | K69: ANZAHL_BEHINDERTE | L69: =IF(ISBLANK(K7),"",K7) | M69: K7
C70: =F$1 -> 3158 | D70: =D$58 -> 5 | E70: =D$1 -> 2017 | F70: 1 | G70: 4 | H70: -1 | J70: LEISTUNG_KATEGORIE_ZIELGRUPPE | K70: STUNDEN_KURZ | L70: =IF(ISBLANK(L7),"",L7) | M70: L7
C71: =F$1 -> 3158 | D71: =D$58 -> 5 | E71: =D$1 -> 2017 | F71: 1 | G71: 4 | H71: -1 | J71: LEISTUNG_KATEGORIE_ZIELGRUPPE | K71: STUNDEN | L71: =IF(ISBLANK(M7),"",M7) | M71: M7
C72: =F$1 -> 3158 | D72: =D$58 -> 5 | E72: =D$1 -> 2017 | F72: 1 | G72: 4 | H72: -1 | J72: LEISTUNG_KATEGORIE_ZIELGRUPPE | K72: ANZAHL_BEHINDERTE | L72: =IF(ISBLANK(N7),"",N7) | M72: N7
C73: =F$1 -> 3158 | D73: =D$58 -> 5 | E73: =D$1 -> 2017 | F73: 1 | G73: 5 | H73: -1 | J73: LEISTUNG_KATEGORIE_ZIELGRUPPE | K73: STUNDEN_KURZ | L73: =IF(ISBLANK(O7),"",O7) | M73: O7
C74: =F$1 -> 3158 | D74: =D$58 -> 5 | E74: =D$1 -> 2017 | F74: 1 | G74: 5 | H74: -1 | J74: LEISTUNG_KATEGORIE_ZIELGRUPPE | K74: STUNDEN | L74: =IF(ISBLANK(P7),"",P7) | M74: P7
C75: =F$1 -> 3158 | D75: =D$58 -> 5 | E75: =D$1 -> 2017 | F75: 1 | G75: 5 | H75: -1 | J75: LEISTUNG_KATEGORIE_ZIELGRUPPE | K75: ANZAHL_BEHINDERTE | L75: =IF(ISBLANK(Q7),"",Q7) | M75: Q7
C76: =F$1 -> 3158 | D76: =D$58 -> 5 | E76: =D$1 -> 2017 | F76: 1 | G76: 10 | H76: -1 | J76: LEISTUNG_KATEGORIE_ZIELGRUPPE | K76: STUNDEN | L76: =IF(ISBLANK(R7),"",R7) | M76: R7
C77: =F$1 -> 3158 | D77: =D$58 -> 5 | E77: =D$1 -> 2017 | F77: 1 | G77: 10 | H77: -1 | J77: LEISTUNG_KATEGORIE_ZIELGRUPPE | K77: ANZAHL_BEHINDERTE | L77: =IF(ISBLANK(S7),"",S7) | M77: S7
C78: =F$1 -> 3158 | D78: =D$58 -> 5 | E78: =D$1 -> 2017 | F78: 2 | G78: 1 | H78: -1 | J78: LEISTUNG_KATEGORIE_ZIELGRUPPE | K78: STUNDEN_KURZ | L78: =IF(ISBLANK(C8),"",C8) | M78: C8
C79: =F$1 -> 3158 | D79: =D$58 -> 5 | E79: =D$1 -> 2017 | F79: 2 | G79: 1 | H79: -1 | J79: LEISTUNG_KATEGORIE_ZIELGRUPPE | K79: STUNDEN | L79: =IF(ISBLANK(D8),"",D8) | M79: D8
C80: =F$1 -> 3158 | D80: =D$58 -> 5 | E80: =D$1 -> 2017 | F80: 2 | G80: 1 | H80: -1 | J80: LEISTUNG_KATEGORIE_ZIELGRUPPE | K80: STUNDEN_GRUPPE | L80: =IF(ISBLANK(E8),"",E8) | M80: E8
C81: =F$1 -> 3158 | D81: =D$58 -> 5 | E81: =D$1 -> 2017 | F81: 2 | G81: 1 | H81: -1 | J81: LEISTUNG_KATEGORIE_ZIELGRUPPE | K81: ANZAHL_BEHINDERTE | L81: =IF(ISBLANK(F8),"",F8) | M81: F8
C82: =F$1 -> 3158 | D82: =D$58 -> 5 | E82: =D$1 -> 2017 | F82: 2 | G82: 2 | H82: -1 | J82: LEISTUNG_KATEGORIE_ZIELGRUPPE | K82: STUNDEN | L82: =IF(ISBLANK(G8),"",G8) | M82: G8
C83: =F$1 -> 3158 | D83: =D$58 -> 5 | E83: =D$1 -> 2017 | F83: 2 | G83: 2 | H83: -1 | J83: LEISTUNG_KATEGORIE_ZIELGRUPPE | K83: STUNDEN_GRUPPE | L83: =IF(ISBLANK(H8),"",H8) | M83: H8
C84: =F$1 -> 3158 | D84: =D$58 -> 5 | E84: =D$1 -> 2017 | F84: 2 | G84: 2 | H84: -1 | J84: LEISTUNG_KATEGORIE_ZIELGRUPPE | K84: ANZAHL_ANGEHOERIGE | L84: =IF(ISBLANK(I8),"",I8) | M84: I8
C85: =F$1 -> 3158 | D85: =D$58 -> 5 | E85: =D$1 -> 2017 | F85: 2 | G85: 3 | H85: -1 | J85: LEISTUNG_KATEGORIE_ZIELGRUPPE | K85: STUNDEN | L85: =IF(ISBLANK(J8),"",J8) | M85: J8
C86: =F$1 -> 3158 | D86: =D$58 -> 5 | E86: =D$1 -> 2017 | F86: 2 | G86: 3 | H86: -1 | J86: LEISTUNG_KATEGORIE_ZIELGRUPPE | K86: ANZAHL_BEHINDERTE | L86: =IF(ISBLANK(K8),"",K8) | M86: K8
C87: =F$1 -> 3158 | D87: =D$58 -> 5 | E87: =D$1 -> 2017 | F87: 2 | G87: 4 | H87: -1 | J87: LEISTUNG_KATEGORIE_ZIELGRUPPE | K87: STUNDEN_KURZ | L87: =IF(ISBLANK(L8),"",L8) | M87: L8
C88: =F$1 -> 3158 | D88: =D$58 -> 5 | E88: =D$1 -> 2017 | F88: 2 | G88: 4 | H88: -1 | J88: LEISTUNG_KATEGORIE_ZIELGRUPPE | K88: STUNDEN | L88: =IF(ISBLANK(M8),"",M8) | M88: M8
C89: =F$1 -> 3158 | D89: =D$58 -> 5 | E89: =D$1 -> 2017 | F89: 2 | G89: 4 | H89: -1 | J89: LEISTUNG_KATEGORIE_ZIELGRUPPE | K89: ANZAHL_BEHINDERTE | L89: =IF(ISBLANK(N8),"",N8) | M89: N8
C90: =F$1 -> 3158 | D90: =D$58 -> 5 | E90: =D$1 -> 2017 | F90: 2 | G90: 5 | H90: -1 | J90: LEISTUNG_KATEGORIE_ZIELGRUPPE | K90: STUNDEN_KURZ | L90: =IF(ISBLANK(O8),"",O8) | M90: O8
C91: =F$1 -> 3158 | D91: =D$58 -> 5 | E91: =D$1 -> 2017 | F91: 2 | G91: 5 | H91: -1 | J91: LEISTUNG_KATEGORIE_ZIELGRUPPE | K91: STUNDEN | L91: =IF(ISBLANK(P8),"",P8) | M91: P8
C92: =F$1 -> 3158 | D92: =D$58 -> 5 | E92: =D$1 -> 2017 | F92: 2 | G92: 5 | H92: -1 | J92: LEISTUNG_KATEGORIE_ZIELGRUPPE | K92: ANZAHL_BEHINDERTE | L92: =IF(ISBLANK(Q8),"",Q8) | M92: Q8
C93: =F$1 -> 3158 | D93: =D$58 -> 5 | E93: =D$1 -> 2017 | F93: 2 | G93: 10 | H93: -1 | J93: LEISTUNG_KATEGORIE_ZIELGRUPPE | K93: STUNDEN | L93: =IF(ISBLANK(R8),"",R8) | M93: R8
C94: =F$1 -> 3158 | D94: =D$58 -> 5 | E94: =D$1 -> 2017 | F94: 2 | G94: 10 | H94: -1 | J94: LEISTUNG_KATEGORIE_ZIELGRUPPE | K94: ANZAHL_BEHINDERTE | L94: =IF(ISBLANK(S8),"",S8) | M94: S8
C95: =F$1 -> 3158 | D95: =D$58 -> 5 | E95: =D$1 -> 2017 | F95: 3 | G95: 1 | H95: -1 | J95: LEISTUNG_KATEGORIE_ZIELGRUPPE | K95: STUNDEN_KURZ | L95: =IF(ISBLANK(C9),"",C9) -> 13 | M95: C9
C96: =F$1 -> 3158 | D96: =D$58 -> 5 | E96: =D$1 -> 2017 | F96: 3 | G96: 1 | H96: -1 | J96: LEISTUNG_KATEGORIE_ZIELGRUPPE | K96: STUNDEN | L96: =IF(ISBLANK(D9),"",D9) -> 17.25 | M96: D9
C97: =F$1 -> 3158 | D97: =D$58 -> 5 | E97: =D$1 -> 2017 | F97: 3 | G97: 1 | H97: -1 | J97: LEISTUNG_KATEGORIE_ZIELGRUPPE | K97: STUNDEN_GRUPPE | L97: =IF(ISBLANK(E9),"",E9) | M97: E9
C98: =F$1 -> 3158 | D98: =D$58 -> 5 | E98: =D$1 -> 2017 | F98: 3 | G98: 1 | H98: -1 | J98: LEISTUNG_KATEGORIE_ZIELGRUPPE | K98: ANZAHL_BEHINDERTE | L98: =IF(ISBLANK(F9),"",F9) -> 8 | M98: F9
C99: =F$1 -> 3158 | D99: =D$58 -> 5 | E99: =D$1 -> 2017 | F99: 3 | G99: 2 | H99: -1 | J99: LEISTUNG_KATEGORIE_ZIELGRUPPE | K99: STUNDEN | L99: =IF(ISBLANK(G9),"",G9) -> 50.5 | M99: G9
C100: =F$1 -> 3158 | D100: =D$58 -> 5 | E100: =D$1 -> 2017 | F100: 3 | G100: 2 | H100: -1 | J100: LEISTUNG_KATEGORIE_ZIELGRUPPE | K100: STUNDEN_GRUPPE | L100: =IF(ISBLANK(H9),"",H9) | M100: H9
C101: =F$1 -> 3158 | D101: =D$58 -> 5 | E101: =D$1 -> 2017 | F101: 3 | G101: 2 | H101: -1 | J101: LEISTUNG_KATEGORIE_ZIELGRUPPE | K101: ANZAHL_ANGEHOERIGE | L101: =IF(ISBLANK(I9),"",I9) -> 18 | M101: I9
C102: =F$1 -> 3158 | D102: =D$58 -> 5 | E102: =D$1 -> 2017 | F102: 3 | G102: 3 | H102: -1 | J102: LEISTUNG_KATEGORIE_ZIELGRUPPE | K102: STUNDEN | L102: =IF(ISBLANK(J9),"",J9) | M102: J9
C103: =F$1 -> 3158 | D103: =D$58 -> 5 | E103: =D$1 -> 2017 | F103: 3 | G103: 3 | H103: -1 | J103: LEISTUNG_KATEGORIE_ZIELGRUPPE | K103: ANZAHL_BEHINDERTE | L103: =IF(ISBLANK(K9),"",K9) | M103: K9
C104: =F$1 -> 3158 | D104: =D$58 -> 5 | E104: =D$1 -> 2017 | F104: 3 | G104: 4 | H104: -1 | J104: LEISTUNG_KATEGORIE_ZIELGRUPPE | K104: STUNDEN_KURZ | L104: =IF(ISBLANK(L9),"",L9) | M104: L9
C105: =F$1 -> 3158 | D105: =D$58 -> 5 | E105: =D$1 -> 2017 | F105: 3 | G105: 4 | H105: -1 | J105: LEISTUNG_KATEGORIE_ZIELGRUPPE | K105: STUNDEN | L105: =IF(ISBLANK(M9),"",M9) | M105: M9
C106: =F$1 -> 3158 | D106: =D$58 -> 5 | E106: =D$1 -> 2017 | F106: 3 | G106: 4 | H106: -1 | J106: LEISTUNG_KATEGORIE_ZIELGRUPPE | K106: ANZAHL_BEHINDERTE | L106: =IF(ISBLANK(N9),"",N9) | M106: N9
...

Sheet Kurstypen
A1: Cours pour les handicapés et leurs proches pour l’année | D1: ='Organisationsdaten (Basisinfo)'!D1 -> 2017 | F1: Contrat n°. | G1: ='Organisationsdaten (Basisinfo)'!H1 -> 3158 | K1: P-ID | L1: ='Organisationsdaten (Basisinfo)'!K1 -> 5
A3: Catégories de prestations | B3: Type de cours | C3: Nombre de cours | D3: Nombre de participants (personnes) | F3: Journées ou heures participant effectives
F4: Bénéficiaires reconnus au titre de l'art. 74 LAI | H4: Bénéficiaires reconnus au titre de l'art. 101bis LAVS | J4: Bénéficiaires non reconnus
F6: Handicapés/ personnes valides 1) | G6: Proches | H6: Handicapés | I6: Proches | M6: Plausibilisierung TeilnehmerInnentage/-stunden
B7: Kurstyp | C7: Anzahl Kurse | D7: Anzahl TeilnehmerInnen1) | M7: Behinderte | P7: Angehörige
M8: KlientInnenstatistik | N8: Kurstypen | O8: Kontrolle | P8: KlientInnenstatistik | Q8: Kurstypen | R8: Kontrolle
A9: Cours en bloc (journées participant) | B9: - Réadaptation | M9: =IF(AND($R9>0,C9=0),1,"") | N9: =IF(AND($R9>0,D9=0),1,"") | O9: =IF(AND($R9>0,E9=0),1,"") | P9: =IF(AND($R9>0,F9=0),1,"") | Q9: =IF(AND($R9>0,G9=0),1,"") | R9: =SUM(C9:J9) -> 0
B10: - Formation continue | R10: =SUM(C10:J10) -> 0
B11: - Loisirs et sport | C11: 29 | D11: 338 | F11: 941 | R11: =SUM(C11:J11) -> 1308
B12: Total | C12: =ROUND(SUM(C9:C11),2) -> 29 | D12: =ROUND(SUM(D9:D11),2) -> 338 | F12: =ROUND(SUM(F9:F11),2) -> 941 | G12: =ROUND(SUM(G9:G11),2) -> 0 | H12: =ROUND(SUM(H9:H11),2) -> 0 | I12: =ROUND(SUM(I9:I11),2) -> 0 | J12: =ROUND(SUM(J9:J11),2) -> 0 | L12: Blockkurse | M12: =KlientInnenstatistik!B15 -> 338 | N12: =SUM(F12,H12) -> 941 | O12: =COUNTIF(M12:N12,">0") -> 2 | P12: =KlientInnenstatistik!C15 -> 0 | Q12: =SUM(G12,I12) -> 0 | R12: =COUNTIF(P12:Q12,">0") -> 0
A13: Cours d’un jour (journées participant) | B13: - Réadaptation | R13: 0
B14: - Formation continue | R14: 0
B15: - Loisirs et sport | C15: 19 | D15: 192 | F15: 192 | R15: 0
B16: Total | C16: =ROUND(SUM(C13:C15),2) -> 19 | D16: =ROUND(SUM(D13:D15),2) -> 192 | F16: =ROUND(SUM(F13:F15),2) -> 192 | L16: Tageskurse | M16: 0 | N16: 0 | O16: 0 | P16: 0 | Q16: 0 | R16: 0
A17: Cours semestriels/ annuels (heures participant) | B17: - Réadaptation | R17: =SUM(C17:J17) -> 0
B18: - Formation continue | R18: =SUM(C18:J18) -> 0
B19: - Loisirs et sport | R19: =SUM(C19:J19) -> 0
B20: Total | C20: =ROUND(SUM(C17:C19),2) -> 0 | D20: =ROUND(SUM(D17:D19),2) -> 0 | F20: =ROUND(SUM(F17:F19),2) -> 0 | G20: =ROUND(SUM(G17:G19),2) -> 0 | H20: =ROUND(SUM(H17:H19),2) -> 0 | I20: =ROUND(SUM(I17:I19),2) -> 0 | J20: =ROUND(SUM(J17:J19),2) -> 0 | L20: Semesterkurse | M20: =KlientInnenstatistik!F15 -> 0 | N20: =SUM(F20,H20) -> 0 | O20: =COUNTIF(M20:N20,">0") -> 0 | P20: =KlientInnenstatistik!G15 -> 0 | Q20: =SUM(G20,I20) -> 0 | R20: =COUNTIF(P20:Q20,">0") -> 0
A21: Total global | C21: =SUM(C12,C16,C20) -> 48 | D21: =SUM(D12,D16,D20) -> 530 | F21: - | G21: - | H21: - | I21: - | J21: - | N21: Feld für Text | O21: =IF(OR(O12=1,O16=1,O20=1,R12=1,R16=1,R20=1),1,"") | R21: =SUM(R9:R11,R13:R15,R17:R19) -> 1308
A22: 1) Dans les cours d'un jour, les personnes non-handicapées (proches inclus) peuvent aussi être comptabilisées.
A24: =IF(OR(O21=1),"Die rote Markierung verschwindet, sobald die entsprechenden Angaben in den Tabellen Klientenstatistik und Kurstypen eingetragen sind.","")
A25: =IF(P31<>0,"Das Summentotal der Beitragsberechtigten für die Tageskurse stimmt nicht mit dem Total (Anzahl Behinderte + Anzahl Angehörige) in der Tabelle KlientInnenstatistik überein.","")
M26: Plausibilisierung Anzahl TeilnehmerInnen:
N27: KlientInnenstatistik | O27: Kurstypen | P27: Kontrolle
M28: Blockkurse | N28: =KlientInnenstatistik!B15+KlientInnenstatistik!C15 -> 338 | O28: =D12 -> 338
M29: Tageskurse | N29: 0 | O29: =SUM(F16:I16) -> 192
C30: VERTRAG_NR | D30: PERIODE_ID | E30: JAHR | F30: KURSTYP_ID | G30: KURSFORM_ID | H30: TABELLE | I30: FELD | J30: WERT | K30: ADRESSE | M30: Semesterkurse | N30: =KlientInnenstatistik!F15+KlientInnenstatistik!G15 -> 0 | O30: =D20 -> 0
C31: =G$1 -> 3158 | D31: =L$1 -> 5 | E31: =D$1 -> 2017 | F31: 1 | G31: 1 | H31: LEISTUNG_KURS_BEHINDERTE | I31: ANZAHL_KURSE | J31: =IF(ISBLANK(C9),"",C9) | K31: C9 | L31: Zeilenweise von oben nach unten (jeweils ohne "Total") | O31: Für den Text | P31: =SUM(P28:P30) -> 0
C32: =G$1 -> 3158 | D32: =L$1 -> 5 | E32: =D$1 -> 2017 | F32: 1 | G32: 1 | H32: LEISTUNG_KURS_BEHINDERTE | I32: ANZAHL_TEILNEHMER | J32: =IF(ISBLANK(D9),"",D9) | K32: D9
C33: =G$1 -> 3158 | D33: =L$1 -> 5 | E33: =D$1 -> 2017 | F33: 1 | G33: 1 | H33: LEISTUNG_KURS_BEHINDERTE | I33: PRAESENZ | J33: =IF(ISBLANK(E9),"",E9) | K33: E9
C34: =G$1 -> 3158 | D34: =L$1 -> 5 | E34: =D$1 -> 2017 | F34: 1 | G34: 1 | H34: LEISTUNG_KURS_BEHINDERTE | I34: LEISTUNG_BEH_BERECHTIGT_IVG | J34: =IF(ISBLANK(F9),"",F9) | K34: F9
C35: =G$1 -> 3158 | D35: =L$1 -> 5 | E35: =D$1 -> 2017 | F35: 1 | G35: 1 | H35: LEISTUNG_KURS_BEHINDERTE | I35: LEISTUNG_ANGEH_BERECHTIGT_IVG | J35: =IF(ISBLANK(G9),"",G9) | K35: G9
C36: =G$1 -> 3158 | D36: =L$1 -> 5 | E36: =D$1 -> 2017 | F36: 1 | G36: 1 | H36: LEISTUNG_KURS_BEHINDERTE | I36: LEISTUNG_BEH_BERECHTIGT_AHVG | J36: =IF(ISBLANK(H9),"",H9) | K36: H9
C37: =G$1 -> 3158 | D37: =L$1 -> 5 | E37: =D$1 -> 2017 | F37: 1 | G37: 1 | H37: LEISTUNG_KURS_BEHINDERTE | I37: LEISTUNG_ANGEH_BERECHTIGT_AHVG | J37: =IF(ISBLANK(I9),"",I9) | K37: I9
C38: =G$1 -> 3158 | D38: =L$1 -> 5 | E38: =D$1 -> 2017 | F38: 1 | G38: 1 | H38: LEISTUNG_KURS_BEHINDERTE | I38: LEISTUNG_NICHT_BERECHTIGT | J38: =IF(ISBLANK(J9),"",J9) | K38: J9
C39: =G$1 -> 3158 | D39: =L$1 -> 5 | E39: =D$1 -> 2017 | F39: 1 | G39: 2 | H39: LEISTUNG_KURS_BEHINDERTE | I39: ANZAHL_KURSE | J39: =IF(ISBLANK(C10),"",C10) | K39: C10
C40: =G$1 -> 3158 | D40: =L$1 -> 5 | E40: =D$1 -> 2017 | F40: 1 | G40: 2 | H40: LEISTUNG_KURS_BEHINDERTE | I40: ANZAHL_TEILNEHMER | J40: =IF(ISBLANK(D10),"",D10) | K40: D10
C41: =G$1 -> 3158 | D41: =L$1 -> 5 | E41: =D$1 -> 2017 | F41: 1 | G41: 2 | H41: LEISTUNG_KURS_BEHINDERTE | I41: PRAESENZ | J41: =IF(ISBLANK(E10),"",E10) | K41: E10
C42: =G$1 -> 3158 | D42: =L$1 -> 5 | E42: =D$1 -> 2017 | F42: 1 | G42: 2 | H42: LEISTUNG_KURS_BEHINDERTE | I42: LEISTUNG_BEH_BERECHTIGT_IVG | J42: =IF(ISBLANK(F10),"",F10) | K42: F10
C43: =G$1 -> 3158 | D43: =L$1 -> 5 | E43: =D$1 -> 2017 | F43: 1 | G43: 2 | H43: LEISTUNG_KURS_BEHINDERTE | I43: LEISTUNG_ANGEH_BERECHTIGT_IVG | J43: =IF(ISBLANK(G10),"",G10) | K43: G10
C44: =G$1 -> 3158 | D44: =L$1 -> 5 | E44: =D$1 -> 2017 | F44: 1 | G44: 2 | H44: LEISTUNG_KURS_BEHINDERTE | I44: LEISTUNG_BEH_BERECHTIGT_AHVG | J44: =IF(ISBLANK(H10),"",H10) | K44: H10
C45: =G$1 -> 3158 | D45: =L$1 -> 5 | E45: =D$1 -> 2017 | F45: 1 | G45: 2 | H45: LEISTUNG_KURS_BEHINDERTE | I45: LEISTUNG_ANGEH_BERECHTIGT_AHVG | J45: =IF(ISBLANK(I10),"",I10) | K45: I10
C46: =G$1 -> 3158 | D46: =L$1 -> 5 | E46: =D$1 -> 2017 | F46: 1 | G46: 2 | H46: LEISTUNG_KURS_BEHINDERTE | I46: LEISTUNG_NICHT_BERECHTIGT | J46: =IF(ISBLANK(J10),"",J10) | K46: J10
C47: =G$1 -> 3158 | D47: =L$1 -> 5 | E47: =D$1 -> 2017 | F47: 1 | G47: 3 | H47: LEISTUNG_KURS_BEHINDERTE | I47: ANZAHL_KURSE | J47: =IF(ISBLANK(C11),"",C11) -> 29 | K47: C11
C48: =G$1 -> 3158 | D48: =L$1 -> 5 | E48: =D$1 -> 2017 | F48: 1 | G48: 3 | H48: LEISTUNG_KURS_BEHINDERTE | I48: ANZAHL_TEILNEHMER | J48: =IF(ISBLANK(D11),"",D11) -> 338 | K48: D11
C49: =G$1 -> 3158 | D49: =L$1 -> 5 | E49: =D$1 -> 2017 | F49: 1 | G49: 3 | H49: LEISTUNG_KURS_BEHINDERTE | I49: PRAESENZ | J49: =IF(ISBLANK(E11),"",E11) | K49: E11
C50: =G$1 -> 3158 | D50: =L$1 -> 5 | E50: =D$1 -> 2017 | F50: 1 | G50: 3 | H50: LEISTUNG_KURS_BEHINDERTE | I50: LEISTUNG_BEH_BERECHTIGT_IVG | J50: =IF(ISBLANK(F11),"",F11) -> 941 | K50: F11
C51: =G$1 -> 3158 | D51: =L$1 -> 5 | E51: =D$1 -> 2017 | F51: 1 | G51: 3 | H51: LEISTUNG_KURS_BEHINDERTE | I51: LEISTUNG_ANGEH_BERECHTIGT_IVG | J51: =IF(ISBLANK(G11),"",G11) | K51: G11
C52: =G$1 -> 3158 | D52: =L$1 -> 5 | E52: =D$1 -> 2017 | F52: 1 | G52: 3 | H52: LEISTUNG_KURS_BEHINDERTE | I52: LEISTUNG_BEH_BERECHTIGT_AHVG | J52: =IF(ISBLANK(H11),"",H11) | K52: H11
C53: =G$1 -> 3158 | D53: =L$1 -> 5 | E53: =D$1 -> 2017 | F53: 1 | G53: 3 | H53: LEISTUNG_KURS_BEHINDERTE | I53: LEISTUNG_ANGEH_BERECHTIGT_AHVG | J53: =IF(ISBLANK(I11),"",I11) | K53: I11
C54: =G$1 -> 3158 | D54: =L$1 -> 5 | E54: =D$1 -> 2017 | F54: 1 | G54: 3 | H54: LEISTUNG_KURS_BEHINDERTE | I54: LEISTUNG_NICHT_BERECHTIGT | J54: =IF(ISBLANK(J11),"",J11) | K54: J11
C55: =G$1 -> 3158 | D55: =L$1 -> 5 | E55: =D$1 -> 2017 | F55: 2 | G55: 1 | H55: LEISTUNG_KURS_BEHINDERTE | I55: ANZAHL_KURSE | J55: =IF(ISBLANK(C13),"",C13) | K55: C13
C56: =G$1 -> 3158 | D56: =L$1 -> 5 | E56: =D$1 -> 2017 | F56: 2 | G56: 1 | H56: LEISTUNG_KURS_BEHINDERTE | I56: ANZAHL_TEILNEHMER | J56: =IF(ISBLANK(D13),"",D13) | K56: D13
C57: =G$1 -> 3158 | D57: =L$1 -> 5 | E57: =D$1 -> 2017 | F57: 2 | G57: 1 | H57: LEISTUNG_KURS_BEHINDERTE | I57: PRAESENZ | J57: =IF(ISBLANK(E13),"",E13) | K57: E13
C58: =G$1 -> 3158 | D58: =L$1 -> 5 | E58: =D$1 -> 2017 | F58: 2 | G58: 1 | H58: LEISTUNG_KURS_BEHINDERTE | I58: LEISTUNG_BEH_BERECHTIGT_IVG | J58: =IF(ISBLANK(F13),"",F13) | K58: F13
C59: =G$1 -> 3158 | D59: =L$1 -> 5 | E59: =D$1 -> 2017 | F59: 2 | G59: 1 | H59: LEISTUNG_KURS_BEHINDERTE | I59: LEISTUNG_ANGEH_BERECHTIGT_IVG | J59: =IF(ISBLANK(G13),"",G13) | K59: G13
C60: =G$1 -> 3158 | D60: =L$1 -> 5 | E60: =D$1 -> 2017 | F60: 2 | G60: 1 | H60: LEISTUNG_KURS_BEHINDERTE | I60: LEISTUNG_BEH_BERECHTIGT_AHVG | J60: =IF(ISBLANK(H13),"",H13) | K60: H13
C61: =G$1 -> 3158 | D61: =L$1 -> 5 | E61: =D$1 -> 2017 | F61: 2 | G61: 1 | H61: LEISTUNG_KURS_BEHINDERTE | I61: LEISTUNG_ANGEH_BERECHTIGT_AHVG | J61: =IF(ISBLANK(I13),"",I13) | K61: I13
C62: =G$1 -> 3158 | D62: =L$1 -> 5 | E62: =D$1 -> 2017 | F62: 2 | G62: 1 | H62: LEISTUNG_KURS_BEHINDERTE | I62: LEISTUNG_NICHT_BERECHTIGT | J62: =IF(ISBLANK(J13),"",J13) | K62: J13
C63: =G$1 -> 3158 | D63: =L$1 -> 5 | E63: =D$1 -> 2017 | F63: 2 | G63: 2 | H63: LEISTUNG_KURS_BEHINDERTE | I63: ANZAHL_KURSE | J63: =IF(ISBLANK(C14),"",C14) | K63: C14
C64: =G$1 -> 3158 | D64: =L$1 -> 5 | E64: =D$1 -> 2017 | F64: 2 | G64: 2 | H64: LEISTUNG_KURS_BEHINDERTE | I64: ANZAHL_TEILNEHMER | J64: =IF(ISBLANK(D14),"",D14) | K64: D14
C65: =G$1 -> 3158 | D65: =L$1 -> 5 | E65: =D$1 -> 2017 | F65: 2 | G65: 2 | H65: LEISTUNG_KURS_BEHINDERTE | I65: PRAESENZ | J65: =IF(ISBLANK(E14),"",E14) | K65: E14
C66: =G$1 -> 3158 | D66: =L$1 -> 5 | E66: =D$1 -> 2017 | F66: 2 | G66: 2 | H66: LEISTUNG_KURS_BEHINDERTE | I66: LEISTUNG_BEH_BERECHTIGT_IVG | J66: =IF(ISBLANK(F14),"",F14) | K66: F14
C67: =G$1 -> 3158 | D67: =L$1 -> 5 | E67: =D$1 -> 2017 | F67: 2 | G67: 2 | H67: LEISTUNG_KURS_BEHINDERTE | I67: LEISTUNG_ANGEH_BERECHTIGT_IVG | J67: =IF(ISBLANK(G14),"",G14) | K67: G14
C68: =G$1 -> 3158 | D68: =L$1 -> 5 | E68: =D$1 -> 2017 | F68: 2 | G68: 2 | H68: LEISTUNG_KURS_BEHINDERTE | I68: LEISTUNG_BEH_BERECHTIGT_AHVG | J68: =IF(ISBLANK(H14),"",H14) | K68: H14
C69: =G$1 -> 3158 | D69: =L$1 -> 5 | E69: =D$1 -> 2017 | F69: 2 | G69: 2 | H69: LEISTUNG_KURS_BEHINDERTE | I69: LEISTUNG_ANGEH_BERECHTIGT_AHVG | J69: =IF(ISBLANK(I14),"",I14) | K69: I14
C70: =G$1 -> 3158 | D70: =L$1 -> 5 | E70: =D$1 -> 2017 | F70: 2 | G70: 2 | H70: LEISTUNG_KURS_BEHINDERTE | I70: LEISTUNG_NICHT_BERECHTIGT | J70: =IF(ISBLANK(J14),"",J14) | K70: J14
C71: =G$1 -> 3158 | D71: =L$1 -> 5 | E71: =D$1 -> 2017 | F71: 2 | G71: 3 | H71: LEISTUNG_KURS_BEHINDERTE | I71: ANZAHL_KURSE | J71: =IF(ISBLANK(C15),"",C15) -> 19 | K71: C15
C72: =G$1 -> 3158 | D72: =L$1 -> 5 | E72: =D$1 -> 2017 | F72: 2 | G72: 3 | H72: LEISTUNG_KURS_BEHINDERTE | I72: ANZAHL_TEILNEHMER | J72: =IF(ISBLANK(D15),"",D15) -> 192 | K72: D15
C73: =G$1 -> 3158 | D73: =L$1 -> 5 | E73: =D$1 -> 2017 | F73: 2 | G73: 3 | H73: LEISTUNG_KURS_BEHINDERTE | I73: PRAESENZ | J73: =IF(ISBLANK(E15),"",E15) | K73: E15
C74: =G$1 -> 3158 | D74: =L$1 -> 5 | E74: =D$1 -> 2017 | F74: 2 | G74: 3 | H74: LEISTUNG_KURS_BEHINDERTE | I74: LEISTUNG_BEH_BERECHTIGT_IVG | J74: =IF(ISBLANK(F15),"",F15) -> 192 | K74: F15
C75: =G$1 -> 3158 | D75: =L$1 -> 5 | E75: =D$1 -> 2017 | F75: 2 | G75: 3 | H75: LEISTUNG_KURS_BEHINDERTE | I75: LEISTUNG_ANGEH_BERECHTIGT_IVG | J75: =IF(ISBLANK(G15),"",G15) | K75: G15
C76: =G$1 -> 3158 | D76: =L$1 -> 5 | E76: =D$1 -> 2017 | F76: 2 | G76: 3 | H76: LEISTUNG_KURS_BEHINDERTE | I76: LEISTUNG_BEH_BERECHTIGT_AHVG | J76: =IF(ISBLANK(H15),"",H15) | K76: H15
C77: =G$1 -> 3158 | D77: =L$1 -> 5 | E77: =D$1 -> 2017 | F77: 2 | G77: 3 | H77: LEISTUNG_KURS_BEHINDERTE | I77: LEISTUNG_ANGEH_BERECHTIGT_AHVG | J77: =IF(ISBLANK(I15),"",I15) | K77: I15
C78: =G$1 -> 3158 | D78: =L$1 -> 5 | E78: =D$1 -> 2017 | F78: 2 | G78: 3 | H78: LEISTUNG_KURS_BEHINDERTE | I78: LEISTUNG_NICHT_BERECHTIGT | J78: =IF(ISBLANK(J15),"",J15) | K78: J15
C79: =G$1 -> 3158 | D79: =L$1 -> 5 | E79: =D$1 -> 2017 | F79: 3 | G79: 1 | H79: LEISTUNG_KURS_BEHINDERTE | I79: ANZAHL_KURSE | J79: =IF(ISBLANK(C17),"",C17) | K79: C17
C80: =G$1 -> 3158 | D80: =L$1 -> 5 | E80: =D$1 -> 2017 | F80: 3 | G80: 1 | H80: LEISTUNG_KURS_BEHINDERTE | I80: ANZAHL_TEILNEHMER | J80: =IF(ISBLANK(D17),"",D17) | K80: D17
C81: =G$1 -> 3158 | D81: =L$1 -> 5 | E81: =D$1 -> 2017 | F81: 3 | G81: 1 | H81: LEISTUNG_KURS_BEHINDERTE | I81: PRAESENZ | J81: =IF(ISBLANK(E17),"",E17) | K81: E17
C82: =G$1 -> 3158 | D82: =L$1 -> 5 | E82: =D$1 -> 2017 | F82: 3 | G82: 1 | H82: LEISTUNG_KURS_BEHINDERTE | I82: LEISTUNG_BEH_BERECHTIGT_IVG | J82: =IF(ISBLANK(F17),"",F17) | K82: F17
C83: =G$1 -> 3158 | D83: =L$1 -> 5 | E83: =D$1 -> 2017 | F83: 3 | G83: 1 | H83: LEISTUNG_KURS_BEHINDERTE | I83: LEISTUNG_ANGEH_BERECHTIGT_IVG | J83: =IF(ISBLANK(G17),"",G17) | K83: G17
C84: =G$1 -> 3158 | D84: =L$1 -> 5 | E84: =D$1 -> 2017 | F84: 3 | G84: 1 | H84: LEISTUNG_KURS_BEHINDERTE | I84: LEISTUNG_BEH_BERECHTIGT_AHVG | J84: =IF(ISBLANK(H17),"",H17) | K84: H17
C85: =G$1 -> 3158 | D85: =L$1 -> 5 | E85: =D$1 -> 2017 | F85: 3 | G85: 1 | H85: LEISTUNG_KURS_BEHINDERTE | I85: LEISTUNG_ANGEH_BERECHTIGT_AHVG | J85: =IF(ISBLANK(I17),"",I17) | K85: I17
C86: =G$1 -> 3158 | D86: =L$1 -> 5 | E86: =D$1 -> 2017 | F86: 3 | G86: 1 | H86: LEISTUNG_KURS_BEHINDERTE | I86: LEISTUNG_NICHT_BERECHTIGT | J86: =IF(ISBLANK(J17),"",J17) | K86: J17
C87: =G$1 -> 3158 | D87: =L$1 -> 5 | E87: =D$1 -> 2017 | F87: 3 | G87: 2 | H87: LEISTUNG_KURS_BEHINDERTE | I87: ANZAHL_KURSE | J87: =IF(ISBLANK(C18),"",C18) | K87: C18
C88: =G$1 -> 3158 | D88: =L$1 -> 5 | E88: =D$1 -> 2017 | F88: 3 | G88: 2 | H88: LEISTUNG_KURS_BEHINDERTE | I88: ANZAHL_TEILNEHMER | J88: =IF(ISBLANK(D18),"",D18) | K88: D18
C89: =G$1 -> 3158 | D89: =L$1 -> 5 | E89: =D$1 -> 2017 | F89: 3 | G89: 2 | H89: LEISTUNG_KURS_BEHINDERTE | I89: PRAESENZ | J89: =IF(ISBLANK(E18),"",E18) | K89: E18
C90: =G$1 -> 3158 | D90: =L$1 -> 5 | E90: =D$1 -> 2017 | F90: 3 | G90: 2 | H90: LEISTUNG_KURS_BEHINDERTE | I90: LEISTUNG_BEH_BERECHTIGT_IVG | J90: =IF(ISBLANK(F18),"",F18) | K90: F18
C91: =G$1 -> 3158 | D91: =L$1 -> 5 | E91: =D$1 -> 2017 | F91: 3 | G91: 2 | H91: LEISTUNG_KURS_BEHINDERTE | I91: LEISTUNG_ANGEH_BERECHTIGT_IVG | J91: =IF(ISBLANK(G18),"",G18) | K91: G18
C92: =G$1 -> 3158 | D92: =L$1 -> 5 | E92: =D$1 -> 2017 | F92: 3 | G92: 2 | H92: LEISTUNG_KURS_BEHINDERTE | I92: LEISTUNG_BEH_BERECHTIGT_AHVG | J92: =IF(ISBLANK(H18),"",H18) | K92: H18
C93: =G$1 -> 3158 | D93: =L$1 -> 5 | E93: =D$1 -> 2017 | F93: 3 | G93: 2 | H93: LEISTUNG_KURS_BEHINDERTE | I93: LEISTUNG_ANGEH_BERECHTIGT_AHVG | J93: =IF(ISBLANK(I18),"",I18) | K93: I18
C94: =G$1 -> 3158 | D94: =L$1 -> 5 | E94: =D$1 -> 2017 | F94: 3 | G94: 2 | H94: LEISTUNG_KURS_BEHINDERTE | I94: LEISTUNG_NICHT_BERECHTIGT | J94: =IF(ISBLANK(J18),"",J18) | K94: J18
C95: =G$1 -> 3158 | D95: =L$1 -> 5 | E95: =D$1 -> 2017 | F95: 3 | G95: 3 | H95: LEISTUNG_KURS_BEHINDERTE | I95: ANZAHL_KURSE | J95: =IF(ISBLANK(C19),"",C19) | K95: C19
C96: =G$1 -> 3158 | D96: =L$1 -> 5 | E96: =D$1 -> 2017 | F96: 3 | G96: 3 | H96: LEISTUNG_KURS_BEHINDERTE | I96: ANZAHL_TEILNEHMER | J96: =IF(ISBLANK(D19),"",D19) | K96: D19
C97: =G$1 -> 3158 | D97: =L$1 -> 5 | E97: =D$1 -> 2017 | F97: 3 | G97: 3 | H97: LEISTUNG_KURS_BEHINDERTE | I97: PRAESENZ | J97: =IF(ISBLANK(E19),"",E19) | K97: E19
C98: =G$1 -> 3158 | D98: =L$1 -> 5 | E98: =D$1 -> 2017 | F98: 3 | G98: 3 | H98: LEISTUNG_KURS_BEHINDERTE | I98: LEISTUNG_BEH_BERECHTIGT_IVG | J98: =IF(ISBLANK(F19),"",F19) | K98: F19
C99: =G$1 -> 3158 | D99: =L$1 -> 5 | E99: =D$1 -> 2017 | F99: 3 | G99: 3 | H99: LEISTUNG_KURS_BEHINDERTE | I99: LEISTUNG_ANGEH_BERECHTIGT_IVG | J99: =IF(ISBLANK(G19),"",G19) | K99: G19
C100: =G$1 -> 3158 | D100: =L$1 -> 5 | E100: =D$1 -> 2017 | F100: 3 | G100: 3 | H100: LEISTUNG_KURS_BEHINDERTE | I100: LEISTUNG_BEH_BERECHTIGT_AHVG | J100: =IF(ISBLANK(H19),"",H19) | K100: H19
C101: =G$1 -> 3158 | D101: =L$1 -> 5 | E101: =D$1 -> 2017 | F101: 3 | G101: 3 | H101: LEISTUNG_KURS_BEHINDERTE | I101: LEISTUNG_ANGEH_BERECHTIGT_AHVG | J101: =IF(ISBLANK(I19),"",I19) | K101: I19
C102: =G$1 -> 3158 | D102: =L$1 -> 5 | E102: =D$1 -> 2017 | F102: 3 | G102: 3 | H102: LEISTUNG_KURS_BEHINDERTE | I102: LEISTUNG_NICHT_BERECHTIGT | J102: =IF(ISBLANK(J19),"",J19) | K102: J19

Sheet Kurskategorien
A1: Cours par type de cours pour l'année… | D1: ='Organisationsdaten (Basisinfo)'!D1 -> 2017 | F1: Contrat n° | G1: ='Organisationsdaten (Basisinfo)'!H1 -> 3158
A3: Catégories de prestations | B3: Type de cours | C3: Nombre de cours | D3: Total des coûts complets | E3: Journées ou heures participant effectives | J3: Total
E4: Bénéficaires reconnus selon l'art. 74 LAI | G4: Bénéficiaires reconnus selon l'art. 101bis LAVS | I4: Bénéficaires non reconnus
E6: Handicapés /personnes valides 1) | F6: Proches | G6: Handicapés | H6: Proches
B7: Kurstyp | C7: Anzahl Kurse
A9: Cours en bloc (journées participant) nuitée à l'hôtel obligatoire | B9: Catégorie 1 | J9: =SUM(E9:I9) -> 0
B10: Catégorie 2 | J10: =SUM(E10:I10) -> 0
B11: Catégorie 3 | C11: 29 | D11: 647425.6 | E11: 941 | J11: =SUM(E11:I11) -> 941
B12: Total | C12: =SUM(C9:C11) -> 29 | D12: =SUM(D9:D11) -> 647425.6 | E12: =SUM(E9:E11) -> 941 | F12: =SUM(F9:F11) -> 0 | G12: =SUM(G9:G11) -> 0 | H12: =SUM(H9:H11) -> 0 | I12: =SUM(I9:I11) -> 0 | J12: =SUM(E12:I12) -> 941
A13: Cours d'un jour (journées participant) | B13: Catégorie 1 | J13: =SUM(E13:I13) -> 0
B14: Catégorie 2 | C14: 5 | D14: 27710.836 | E14: 61 | J14: =SUM(E14:I14) -> 61
B15: Catégorie 3 | C15: 14 | D15: 77590.341 | E15: 131 | J15: =SUM(E15:I15) -> 131
B16: Total | C16: =SUM(C13:C15) -> 19 | D16: =SUM(D13:D15) -> 105301.18 | E16: =SUM(E13:E15) -> 192 | F16: =SUM(F13:F15) -> 0 | G16: =SUM(G13:G15) -> 0 | H16: =SUM(H13:H15) -> 0 | I16: =SUM(I13:I15) -> 0 | J16: =SUM(E16:I16) -> 192
A17: Cours semestriels/annuels (heures participant) | B17: Catégorie 1 | J17: =SUM(E17:I17) -> 0
B20: Total | C20: =SUM(C17:C19) -> 0 | D20: =SUM(D17:D19) -> 0 | E20: =SUM(E17:E19) -> 0 | F20: =SUM(F17:F19) -> 0 | G20: =SUM(G17:G19) -> 0 | H20: =SUM(H17:H19) -> 0 | I20: =SUM(I17:I19) -> 0 | J20: =SUM(E20:I20) -> 0
A21: Total global | C21: =SUM(C20,C16,C12) -> 48 | D21: =SUM(D20,D16,D12) -> 752726.78 | E21: - | F21: - | G21: - | H21: - | I21: - | J21: =SUM(E21:I21) -> 0
A22: 1) Dans les cours d'un jour, les personnes non-handicapées (proches inclus) peuvent aussi être comptabilisées.
A24: Reporting:
A25: Le mandataire indique dans le reporting les cours et les unités de prestation selon la catégorie de cours en tenant compte des coûts complets par UP et des critères d’attribution. L’affectation se fait selon les tableaux suivants :
A28: Coûts complets/UP | B28: Critères d'attribution cours en bloc | F28: Coûts complets/UP | H28: Critères d'attribution cours d'un jour
B29: A | C29: B | D29: C | H29: A | I29: B | J29: C
A30: < 442 | B30: Cat 1 | C30: Cat 1 | D30: Cat 1 | F30: < 341 | H30: Cat 1 | I30: Cat 1 | J30: Cat 1
A31: 442 à 642 | B31: Cat 1 | C31: Cat 2 | D31: Cat 2 | F31: 341 à 475 | H31: Cat 1 | I31: Cat 2 | J31: Cat 2
A32: > 643 | B32: Cat 1 | C32: Cat 2 | D32: Cat 3 | F32: > 475 | H32: Cat 1 | I32: Cat 2 | J32: Cat 3

Sheet KlientInnenstatistik
F1: Contrat n° | G1: ='Organisationsdaten (Basisinfo)'!H1 -> 3158 | H1: P-ID | I1: ='Organisationsdaten (Basisinfo)'!K1 -> 5
A2: Statistique des bénéficiaires : cours pour les handicapés et leurs proches pour l’année | G2: ='Organisationsdaten (Basisinfo)'!D1 -> 2017
A3: (N’indiquer que les bénéficiaires reconnus)
B4: Cours en bloc | D4: Cours d’un jour1) | F4: Cours semestriels/annuels
B5: Nombre de handicapés (personnes) | C5: Nombre de proches (personnes) | D5: - | E5: - | F5: Nombre de handicapés (personnes) | G5: Nombre de proches (personnes)
D6: - | E6: -
A7: Handicapés mentaux ou ayant des difficultés d’apprentissage | B7: 10
A8: Handicapés de l’ouïe
A9: Handicapés physiques | B9: 328 | H9: =IF(M23<>0,"Die blaue Markierung verschwindet, sobald die Angaben für diese Leistung sowohl in der Kostenrechnung als auch in der Leistungs-statistik vorhanden sind.","")
A10: Handicapés par suite de maladie
A11: Handicapés psychiques
A12: Handicapés de la vue
A13: Handicapés du langage
A14: Handicapés par suite de dépendance
A15: Total | B15: =SUM(B7:B14) -> 338 | C15: =SUM(C7:C14) -> 0 | D15: - | E15: - | F15: =SUM(F7:F14) -> 0 | G15: =SUM(G7:G14) -> 0 | J15: Plausibilisierung der Totale
A16: dont plurihandicapés | B16: 319 | J16: Blockkurse | L16: Tageskurse | N16: Semesterkurse | P16: Kontrolle
A17: AG | J17: Behinderte | K17: Angehörige | L17: Behinderte | M17: Angehörige | N17: Behinderte | O17: Angehörige
A18: AI | J18: =B15-B44 -> 0 | K18: =C15-C44 -> 0 | L18: 0 | M18: 0 | N18: =F15-F44 -> 0 | O18: =G15-G44 -> 0 | P18: =SUM(COUNTIF(J18:O18,"<>0")) -> 0
A19: AR | J19: Plausibilisierung Kostenträger Leistungsstatistik
A20: BE | H20: =IF(P18<>0,"Die rote Markierung verschwindet, sobald die Totale übereinstimmen.","") | J20: Blockkurse Beh | K20: Tageskurse Beh | L20: Semesterk. Beh | M20: Kontrolle
A21: BL | J21: ='Kostenrechnung konsolidiert'!O18 -> 647425.6 | K21: ='Kostenrechnung konsolidiert'!P18 -> 105301.18 | L21: ='Kostenrechnung konsolidiert'!Q18 -> 0
A22: BS | J22: =B15+C15 -> 338 | K22: 0 | L22: =F15+G15 -> 0
A23: FR | J23: =COUNTIF(J21:J22,">0") -> 2 | K23: 0 | L23: =COUNTIF(L21:L22,">0") -> 0 | M23: =COUNTIF(J23:L23,1) -> 0
A24: GE
A25: GL
A26: GR
A27: JU
A28: LU
A29: NE
A30: NW
A31: OW
A32: SG
A33: SH
A34: SO
A35: SZ
... A39: VD
A40: VS | B40: 338
A41: ZG
A42: ZH
A43: Autre provenance (seulement ayants droit)
A44: Total | B44: =SUM(B17:B43) -> 338 | C44: =SUM(C17:C43) -> 0 | D44: - | E44: - | F44: =SUM(F17:F43) -> 0 | G44: =SUM(G17:G43) -> 0
A45: 1) Les données clients concernant les cours d'un jour ne doivent pas être saisies.
C50: VERTRAG_NR | D50: PERIODE_ID | E50: JAHR | F50: ZIELGRUPPE_ID | G50: LEISTUNGSKATEGORIE_ID | H50: KURSTYP_ID | I50: KANTON_ID | J50: TABELLE | K50: FELD | L50: WERT | M50: ADRESSE
C51: =G$1 -> 3158 | D51: =I$1 -> 5 | E51: =G$2 -> 2017 | F51: 1 | G51: 6 | H51: 1 | J51: LEISTUNG_KATEGORIE_ZIELGRUPPE | K51: ANZAHL_BEHINDERTE | L51: =IF(ISBLANK(B7),"",B7) -> 10 | M51: B7 | N51: nach Zielgruppen: Zeilenweise von oben nach unten (Zeilen 7 bis 14)
C52: =G$1 -> 3158 | D52: =I$1 -> 5 | E52: =G$2 -> 2017 | F52: 1 | G52: 6 | H52: 1 | J52: LEISTUNG_KATEGORIE_ZIELGRUPPE | K52: ANZAHL_ANGEHOERIGE | L52: =IF(ISBLANK(C7),"",C7) | M52: C7
C53: =G$1 -> 3158 | D53: =I$1 -> 5 | E53: =G$2 -> 2017 | F53: 1 | G53: 6 | H53: 2 | J53: LEISTUNG_KATEGORIE_ZIELGRUPPE | K53: ANZAHL_BEHINDERTE | L53: =IF(ISBLANK(D7),"",D7) | M53: D7
C54: =G$1 -> 3158 | D54: =I$1 -> 5 | E54: =G$2 -> 2017 | F54: 1 | G54: 6 | H54: 2 | J54: LEISTUNG_KATEGORIE_ZIELGRUPPE | K54: ANZAHL_ANGEHOERIGE | L54: =IF(ISBLANK(E7),"",E7) | M54: E7
C55: =G$1 -> 3158 | D55: =I$1 -> 5 | E55: =G$2 -> 2017 | F55: 1 | G55: 6 | H55: 3 | J55: LEISTUNG_KATEGORIE_ZIELGRUPPE | K55: ANZAHL_BEHINDERTE | L55: =IF(ISBLANK(F7),"",F7) | M55: F7
C56: =G$1 -> 3158 | D56: =I$1 -> 5 | E56: =G$2 -> 2017 | F56: 1 | G56: 6 | H56: 3 | J56: LEISTUNG_KATEGORIE_ZIELGRUPPE | K56: ANZAHL_ANGEHOERIGE | L56: =IF(ISBLANK(G7),"",G7) | M56: G7
C57: =G$1 -> 3158 | D57: =I$1 -> 5 | E57: =G$2 -> 2017 | F57: 2 | G57: 6 | H57: 1 | J57: LEISTUNG_KATEGORIE_ZIELGRUPPE | K57: ANZAHL_BEHINDERTE | L57: =IF(ISBLANK(B8),"",B8) | M57: B8
C58: =G$1 -> 3158 | D58: =I$1 -> 5 | E58: =G$2 -> 2017 | F58: 2 | G58: 6 | H58: 1 | J58: LEISTUNG_KATEGORIE_ZIELGRUPPE | K58: ANZAHL_ANGEHOERIGE | L58: =IF(ISBLANK(C8),"",C8) | M58: C8
C59: =G$1 -> 3158 | D59: =I$1 -> 5 | E59: =G$2 -> 2017 | F59: 2 | G59: 6 | H59: 2 | J59: LEISTUNG_KATEGORIE_ZIELGRUPPE | K59: ANZAHL_BEHINDERTE | L59: =IF(ISBLANK(D8),"",D8) | M59: D8
C60: =G$1 -> 3158 | D60: =I$1 -> 5 | E60: =G$2 -> 2017 | F60: 2 | G60: 6 | H60: 2 | J60: LEISTUNG_KATEGORIE_ZIELGRUPPE | K60: ANZAHL_ANGEHOERIGE | L60: =IF(ISBLANK(E8),"",E8) | M60: E8
C61: =G$1 -> 3158 | D61: =I$1 -> 5 | E61: =G$2 -> 2017 | F61: 2 | G61: 6 | H61: 3 | J61: LEISTUNG_KATEGORIE_ZIELGRUPPE | K61: ANZAHL_BEHINDERTE | L61: =IF(ISBLANK(F8),"",F8) | M61: F8
C62: =G$1 -> 3158 | D62: =I$1 -> 5 | E62: =G$2 -> 2017 | F62: 2 | G62: 6 | H62: 3 | J62: LEISTUNG_KATEGORIE_ZIELGRUPPE | K62: ANZAHL_ANGEHOERIGE | L62: =IF(ISBLANK(G8),"",G8) | M62: G8
C63: =G$1 -> 3158 | D63: =I$1 -> 5 | E63: =G$2 -> 2017 | F63: 3 | G63: 6 | H63: 1 | J63: LEISTUNG_KATEGORIE_ZIELGRUPPE | K63: ANZAHL_BEHINDERTE | L63: =IF(ISBLANK(B9),"",B9) -> 328 | M63: B9
C64: =G$1 -> 3158 | D64: =I$1 -> 5 | E64: =G$2 -> 2017 | F64: 3 | G64: 6 | H64: 1 | J64: LEISTUNG_KATEGORIE_ZIELGRUPPE | K64: ANZAHL_ANGEHOERIGE | L64: =IF(ISBLANK(C9),"",C9) | M64: C9
C65: =G$1 -> 3158 | D65: =I$1 -> 5 | E65: =G$2 -> 2017 | F65: 3 | G65: 6 | H65: 2 | J65: LEISTUNG_KATEGORIE_ZIELGRUPPE | K65: ANZAHL_BEHINDERTE | L65: =IF(ISBLANK(D9),"",D9) | M65: D9
C66: =G$1 -> 3158 | D66: =I$1 -> 5 | E66: =G$2 -> 2017 | F66: 3 | G66: 6 | H66: 2 | J66: LEISTUNG_KATEGORIE_ZIELGRUPPE | K66: ANZAHL_ANGEHOERIGE | L66: =IF(ISBLANK(E9),"",E9) | M66: E9
C67: =G$1 -> 3158 | D67: =I$1 -> 5 | E67: =G$2 -> 2017 | F67: 3 | G67: 6 | H67: 3 | J67: LEISTUNG_KATEGORIE_ZIELGRUPPE | K67: ANZAHL_BEHINDERTE | L67: =IF(ISBLANK(F9),"",F9) | M67: F9
C68: =G$1 -> 3158 | D68: =I$1 -> 5 | E68: =G$2 -> 2017 | F68: 3 | G68: 6 | H68: 3 | J68: LEISTUNG_KATEGORIE_ZIELGRUPPE | K68: ANZAHL_ANGEHOERIGE | L68: =IF(ISBLANK(G9),"",G9) | M68: G9
C69: =G$1 -> 3158 | D69: =I$1 -> 5 | E69: =G$2 -> 2017 | F69: 4 | G69: 6 | H69: 1 | J69: LEISTUNG_KATEGORIE_ZIELGRUPPE | K69: ANZAHL_BEHINDERTE | L69: =IF(ISBLANK(B10),"",B10) | M69: B10
C70: =G$1 -> 3158 | D70: =I$1 -> 5 | E70: =G$2 -> 2017 | F70: 4 | G70: 6 | H70: 1 | J70: LEISTUNG_KATEGORIE_ZIELGRUPPE | K70: ANZAHL_ANGEHOERIGE | L70: =IF(ISBLANK(C10),"",C10) | M70: C10
C71: =G$1 -> 3158 | D71: =I$1 -> 5 | E71: =G$2 -> 2017 | F71: 4 | G71: 6 | H71: 2 | J71: LEISTUNG_KATEGORIE_ZIELGRUPPE | K71: ANZAHL_BEHINDERTE | L71: =IF(ISBLANK(D10),"",D10) | M71: D10
C72: =G$1 -> 3158 | D72: =I$1 -> 5 | E72: =G$2 -> 2017 | F72: 4 | G72: 6 | H72: 2 | J72: LEISTUNG_KATEGORIE_ZIELGRUPPE | K72: ANZAHL_ANGEHOERIGE | L72: =IF(ISBLANK(E10),"",E10) | M72: E10
C73: =G$1 -> 3158 | D73: =I$1 -> 5 | E73: =G$2 -> 2017 | F73: 4 | G73: 6 | H73: 3 | J73: LEISTUNG_KATEGORIE_ZIELGRUPPE | K73: ANZAHL_BEHINDERTE | L73: =IF(ISBLANK(F10),"",F10) | M73: F10
C74: =G$1 -> 3158 | D74: =I$1 -> 5 | E74: =G$2 -> 2017 | F74: 4 | G74: 6 | H74: 3 | J74: LEISTUNG_KATEGORIE_ZIELGRUPPE | K74: ANZAHL_ANGEHOERIGE | L74: =IF(ISBLANK(G10),"",G10) | M74: G10
C75: =G$1 -> 3158 | D75: =I$1 -> 5 | E75: =G$2 -> 2017 | F75: 5 | G75: 6 | H75: 1 | J75: LEISTUNG_KATEGORIE_ZIELGRUPPE | K75: ANZAHL_BEHINDERTE | L75: =IF(ISBLANK(B11),"",B11) | M75: B11
C76: =G$1 -> 3158 | D76: =I$1 -> 5 | E76: =G$2 -> 2017 | F76: 5 | G76: 6 | H76: 1 | J76: LEISTUNG_KATEGORIE_ZIELGRUPPE | K76: ANZAHL_ANGEHOERIGE | L76: =IF(ISBLANK(C11),"",C11) | M76: C11
C77: =G$1 -> 3158 | D77: =I$1 -> 5 | E77: =G$2 -> 2017 | F77: 5 | G77: 6 | H77: 2 | J77: LEISTUNG_KATEGORIE_ZIELGRUPPE | K77: ANZAHL_BEHINDERTE | L77: =IF(ISBLANK(D11),"",D11) | M77: D11
C78: =G$1 -> 3158 | D78: =I$1 -> 5 | E78: =G$2 -> 2017 | F78: 5 | G78: 6 | H78: 2 | J78: LEISTUNG_KATEGORIE_ZIELGRUPPE | K78: ANZAHL_ANGEHOERIGE | L78: =IF(ISBLANK(E11),"",E11) | M78: E11
C79: =G$1 -> 3158 | D79: =I$1 -> 5 | E79: =G$2 -> 2017 | F79: 5 | G79: 6 | H79: 3 | J79: LEISTUNG_KATEGORIE_ZIELGRUPPE | K79: ANZAHL_BEHINDERTE | L79: =IF(ISBLANK(F11),"",F11) | M79: F11
C80: =G$1 -> 3158 | D80: =I$1 -> 5 | E80: =G$2 -> 2017 | F80: 5 | G80: 6 | H80: 3 | J80: LEISTUNG_KATEGORIE_ZIELGRUPPE | K80: ANZAHL_ANGEHOERIGE | L80: =IF(ISBLANK(G11),"",G11) | M80: G11
C81: =G$1 -> 3158 | D81: =I$1 -> 5 | E81: =G$2 -> 2017 | F81: 6 | G81: 6 | H81: 1 | J81: LEISTUNG_KATEGORIE_ZIELGRUPPE | K81: ANZAHL_BEHINDERTE | L81: =IF(ISBLANK(B12),"",B12) | M81: B12
C82: =G$1 -> 3158 | D82: =I$1 -> 5 | E82: =G$2 -> 2017 | F82: 6 | G82: 6 | H82: 1 | J82: LEISTUNG_KATEGORIE_ZIELGRUPPE | K82: ANZAHL_ANGEHOERIGE | L82: =IF(ISBLANK(C12),"",C12) | M82: C12
C83: =G$1 -> 3158 | D83: =I$1 -> 5 | E83: =G$2 -> 2017 | F83: 6 | G83: 6 | H83: 2 | J83: LEISTUNG_KATEGORIE_ZIELGRUPPE | K83: ANZAHL_BEHINDERTE | L83: =IF(ISBLANK(D12),"",D12) | M83: D12
C84: =G$1 -> 3158 | D84: =I$1 -> 5 | E84: =G$2 -> 2017 | F84: 6 | G84: 6 | H84: 2 | J84: LEISTUNG_KATEGORIE_ZIELGRUPPE | K84: ANZAHL_ANGEHOERIGE | L84: =IF(ISBLANK(E12),"",E12) | M84: E12
C85: =G$1 -> 3158 | D85: =I$1 -> 5 | E85: =G$2 -> 2017 | F85: 6 | G85: 6 | H85: 3 | J85: LEISTUNG_KATEGORIE_ZIELGRUPPE | K85: ANZAHL_BEHINDERTE | L85: =IF(ISBLANK(F12),"",F12) | M85: F12
C86: =G$1 -> 3158 | D86: =I$1 -> 5 | E86: =G$2 -> 2017 | F86: 6 | G86: 6 | H86: 3 | J86: LEISTUNG_KATEGORIE_ZIELGRUPPE | K86: ANZAHL_ANGEHOERIGE | L86: =IF(ISBLANK(G12),"",G12) | M86: G12
C87: =G$1 -> 3158 | D87: =I$1 -> 5 | E87: =G$2 -> 2017 | F87: 7 | G87: 6 | H87: 1 | J87: LEISTUNG_KATEGORIE_ZIELGRUPPE | K87: ANZAHL_BEHINDERTE | L87: =IF(ISBLANK(B13),"",B13) | M87: B13
C88: =G$1 -> 3158 | D88: =I$1 -> 5 | E88: =G$2 -> 2017 | F88: 7 | G88: 6 | H88: 1 | J88: LEISTUNG_KATEGORIE_ZIELGRUPPE | K88: ANZAHL_ANGEHOERIGE | L88: =IF(ISBLANK(C13),"",C13) | M88: C13
C89: =G$1 -> 3158 | D89: =I$1 -> 5 | E89: =G$2 -> 2017 | F89: 7 | G89: 6 | H89: 2 | J89: LEISTUNG_KATEGORIE_ZIELGRUPPE | K89: ANZAHL_BEHINDERTE | L89: =IF(ISBLANK(D13),"",D13) | M89: D13
C90: =G$1 -> 3158 | D90: =I$1 -> 5 | E90: =G$2 -> 2017 | F90: 7 | G90: 6 | H90: 2 | J90: LEISTUNG_KATEGORIE_ZIELGRUPPE | K90: ANZAHL_ANGEHOERIGE | L90: =IF(ISBLANK(E13),"",E13) | M90: E13
C91: =G$1 -> 3158 | D91: =I$1 -> 5 | E91: =G$2 -> 2017 | F91: 7 | G91: 6 | H91: 3 | J91: LEISTUNG_KATEGORIE_ZIELGRUPPE | K91: ANZAHL_BEHINDERTE | L91: =IF(ISBLANK(F13),"",F13) | M91: F13
C92: =G$1 -> 3158 | D92: =I$1 -> 5 | E92: =G$2 -> 2017 | F92: 7 | G92: 6 | H92: 3 | J92: LEISTUNG_KATEGORIE_ZIELGRUPPE | K92: ANZAHL_ANGEHOERIGE | L92: =IF(ISBLANK(G13),"",G13) | M92: G13
C93: =G$1 -> 3158 | D93: =I$1 -> 5 | E93: =G$2 -> 2017 | F93: 8 | G93: 6 | H93: 1 | J93: LEISTUNG_KATEGORIE_ZIELGRUPPE | K93: ANZAHL_BEHINDERTE | L93: =IF(ISBLANK(B14),"",B14) | M93: B14
C94: =G$1 -> 3158 | D94: =I$1 -> 5 | E94: =G$2 -> 2017 | F94: 8 | G94: 6 | H94: 1 | J94: LEISTUNG_KATEGORIE_ZIELGRUPPE | K94: ANZAHL_ANGEHOERIGE | L94: =IF(ISBLANK(C14),"",C14) | M94: C14
C95: =G$1 -> 3158 | D95: =I$1 -> 5 | E95: =G$2 -> 2017 | F95: 8 | G95: 6 | H95: 2 | J95: LEISTUNG_KATEGORIE_ZIELGRUPPE | K95: ANZAHL_BEHINDERTE | L95: =IF(ISBLANK(D14),"",D14) | M95: D14
C96: =G$1 -> 3158 | D96: =I$1 -> 5 | E96: =G$2 -> 2017 | F96: 8 | G96: 6 | H96: 2 | J96: LEISTUNG_KATEGORIE_ZIELGRUPPE | K96: ANZAHL_ANGEHOERIGE | L96: =IF(ISBLANK(E14),"",E14) | M96: E14
C97: =G$1 -> 3158 | D97: =I$1 -> 5 | E97: =G$2 -> 2017 | F97: 8 | G97: 6 | H97: 3 | J97: LEISTUNG_KATEGORIE_ZIELGRUPPE | K97: ANZAHL_BEHINDERTE | L97: =IF(ISBLANK(F14),"",F14) | M97: F14
C98: =G$1 -> 3158 | D98: =I$1 -> 5 | E98: =G$2 -> 2017 | F98: 8 | G98: 6 | H98: 3 | J98: LEISTUNG_KATEGORIE_ZIELGRUPPE | K98: ANZAHL_ANGEHOERIGE | L98: =IF(ISBLANK(G14),"",G14) | M98: G14
C99: =G$1 -> 3158 | D99: =I$1 -> 5 | E99: =G$2 -> 2017 | G99: 6 | H99: 1 | J99: LEISTUNG_KATEGORIE | K99: ANZ_MEHRFACH_BEHINDERT | L99: =IF(ISBLANK(B16),"",B16) -> 319 | M99: B16 | N99: Mehrfachbehinderte: Zeile 16
C100: =G$1 -> 3158 | D100: =I$1 -> 5 | E100: =G$2 -> 2017 | G100: 6 | H100: 1 | J100: LEISTUNG_KATEGORIE | K100: ANZ_ANGEHOERIGE_MEHRFACH_BEH | L100: =IF(ISBLANK(C16),"",C16) | M100: C16
C101: =G$1 -> 3158 | D101: =I$1 -> 5 | E101: =G$2 -> 2017 | G101: 6 | H101: 2 | J101: LEISTUNG_KATEGORIE | K101: ANZ_MEHRFACH_BEHINDERT | L101: =IF(ISBLANK(D16),"",D16) | M101: D16
C102: =G$1 -> 3158 | D102: =I$1 -> 5 | E102: =G$2 -> 2017 | G102: 6 | H102: 2 | J102: LEISTUNG_KATEGORIE | K102: ANZ_ANGEHOERIGE_MEHRFACH_BEH | L102: =IF(ISBLANK(E16),"",E16) | M102: E16
C103: =G$1 -> 3158 | D103: =I$1 -> 5 | E103: =G$2 -> 2017 | G103: 6 | H103: 3 | J103: LEISTUNG_KATEGORIE | K103: ANZ_MEHRFACH_BEHINDERT | L103: =IF(ISBLANK(F16),"",F16) | M103: F16
C104: =G$1 -> 3158 | D104: =I$1 -> 5 | E104: =G$2 -> 2017 | G104: 6 | H104: 3 | J104: LEISTUNG_KATEGORIE | K104: ANZ_ANGEHOERIGE_MEHRFACH_BEH | L104: =IF(ISBLANK(G16),"",G16) | M104: G16
C105: =G$1 -> 3158 | D105: =I$1 -> 5 | E105: =G$2 -> 2017 | G105: 6 | H105: 1 | I105: 19 | J105: LEISTUNG_KATEGORIE_KANTON | K105: ANZAHL_BEHINDERTE | L105: =IF(ISBLANK(B17),"",B17) | M105: B17 | N105: nach Kantonen: Spaltenweise von links nach rechts
C106: =G$1 -> 3158 | D106: =I$1 -> 5 | E106: =G$2 -> 2017 | G106: 6 | H106: 1 | I106: 16 | J106: LEISTUNG_KATEGORIE_KANTON | K106: ANZAHL_BEHINDERTE | L106: =IF(ISBLANK(B18),"",B18) | M106: B18
C107: =G$1 -> 3158 | D107: =I$1 -> 5 | E107: =G$2 -> 2017 | G107: 6 | H107: 1 | I107: 15 | J107: LEISTUNG_KATEGORIE_KANTON | K107: ANZAHL_BEHINDERTE | L107: =IF(ISBLANK(B19),"",B19) | M107: B19
...

Sheet Kurse Fachpersonal
E1: LV-Nr. | F1: ='Organisationsdaten (Basisinfo)'!H1 -> 3158 | G1: P-ID | H1: ='Organisationsdaten (Basisinfo)'!K1 -> 5 | I1: Plausibilisierung Kostenträger Leistungsstatistik
A2: Kurse zur Fortbildung von Fach- und Sekretariatspersonal für das Jahr | F2: ='Organisationsdaten (Basisinfo)'!D1 -> 2017 | I2: Blockkurse F | J2: Tageskurse F | K2: Semesterk. F | L2: Kontrolle
I3: ='Kostenrechnung konsolidiert'!#REF! -> #REF! | J3: ='Kostenrechnung konsolidiert'!#REF! -> #REF! | K3: ='Kostenrechnung konsolidiert'!#REF! -> #REF!
A4: Leistungskategorien | B4: Anzahl Kurse | C4: Anzahl Teilnehmer- Innen (Personen) | E4: Tatsächliche TeilnehmerInnentage resp. -stunden | I4: =C10 -> 0 | J4: =C11 -> 0 | K4: =C12 -> 0
E5: Beitragsberechtigte Art. 74 IVG | F5: Nicht Beitrags- berechtigte | I5: =COUNTIF(I3:I4,">0") -> 0 | J5: =COUNTIF(J3:J4,">0") -> 0 | K5: =COUNTIF(K3:K4,">0") -> 0 | L5: =COUNTIF(I5:K5,1) -> 0
I7: Plausibilisierung
A8: Leistungskategorie | B8: Anzahl Kurse | C8: Anzahl TeilnehmerInnen1) | I8: Kontrolle | J8: Kurse | K8: TeilneherInnen | L8: Präsenz | M8: TeilnehmerInnentate
A10: Blockkurse (TeilnehmerInnentage) | I10: =SUM(B10:F10) -> 0 | J10: =IF(AND($I10>0,B10=0),1,"") | K10: =IF(AND($I10>0,C10=0),1,"") | M10: =IF(AND($I10>0,E10=0),1,"")
A11: Tageskurse (TeilnehmerInnentage) | G11: =IF(C11<E11+F11,"Es gibt mehr TeilnehmerInnentage als TeilnehmerInnen","") | I11: =SUM(E11:F11) -> 0 | J11: =IF(AND($I11>0,B11=0),1,"") | K11: =IF(AND($I11>0,C11=0),1,"") | M11: =IF(AND($I11>0,E11=0),1,"")
A12: Semester- und Jahreskurse (TeilnehmerInnenstunden) | I12: =SUM(B12:F12) -> 0 | J12: =IF(AND($I12>0,B12=0),1,"") | K12: =IF(AND($I12>0,C12=0),1,"") | M12: =IF(AND($I12>0,E12=0),1,"")
A13: Total | B13: =SUM(B10:B12) -> 0 | C13: =SUM(C10:C12) -> 0 | E13: - | F13: -
I14: Feld für Text | J14: =SUM(J10:M12) -> 0
A15: =IF(L5<>0,"Die blaue Markierung verschwindet, sobald die Angaben für diese Leistung sowohl in der Kostenrechnung als auch in der Leistungstatistik vorhanden sind.","") | J15: =IF(AND(I10=1,B10<>0),1,"")
A17: =IF(J14<>0,"Die rote Markierung verschwindet, sobald alle notwendigen Angaben in der entsprechenden Zeile gemacht sind.","")
B20: VERTRAG_NR | C20: PERIODE_ID | D20: JAHR | E20: KURSTYP_ID | F20: TABELLE | G20: FELD | H20: WERT | I20: ADRESSE
B21: =F$1 -> 3158 | C21: =H$1 -> 5 | D21: =F$2 -> 2017 | E21: 1 | F21: LEISTUNG_KURS_FORTBILDUNG | G21: ANZAHL_KURSE | H21: =IF(ISBLANK(B10),"",B10) | I21: B10
B22: =F$1 -> 3158 | C22: =H$1 -> 5 | D22: =F$2 -> 2017 | E22: 1 | F22: LEISTUNG_KURS_FORTBILDUNG | G22: ANZAHL_TEILNEHMER | H22: =IF(ISBLANK(C10),"",C10) | I22: C10
B23: =F$1 -> 3158 | C23: =H$1 -> 5 | D23: =F$2 -> 2017 | E23: 1 | F23: LEISTUNG_KURS_FORTBILDUNG | G23: PRAESENZ | H23: =IF(ISBLANK(D10),"",D10) | I23: D10
B24: =F$1 -> 3158 | C24: =H$1 -> 5 | D24: =F$2 -> 2017 | E24: 1 | F24: LEISTUNG_KURS_FORTBILDUNG | G24: LEISTUNG_IVG_AHVG | H24: =IF(ISBLANK(E10),"",E10) | I24: E10
B25: =F$1 -> 3158 | C25: =H$1 -> 5 | D25: =F$2 -> 2017 | E25: 1 | F25: LEISTUNG_KURS_FORTBILDUNG | G25: LEISTUNG_NICHT_BERECHTIGT | H25: =IF(ISBLANK(F10),"",F10) | I25: F10
B26: =F$1 -> 3158 | C26: =H$1 -> 5 | D26: =F$2 -> 2017 | E26: 2 | F26: LEISTUNG_KURS_FORTBILDUNG | G26: ANZAHL_KURSE | H26: =IF(ISBLANK(B11),"",B11) | I26: B11
B27: =F$1 -> 3158 | C27: =H$1 -> 5 | D27: =F$2 -> 2017 | E27: 2 | F27: LEISTUNG_KURS_FORTBILDUNG | G27: ANZAHL_TEILNEHMER | H27: =IF(ISBLANK(C11),"",C11) | I27: C11
B28: =F$1 -> 3158 | C28: =H$1 -> 5 | D28: =F$2 -> 2017 | E28: 2 | F28: LEISTUNG_KURS_FORTBILDUNG | G28: PRAESENZ | H28: =IF(ISBLANK(D11),"",D11) | I28: D11
B29: =F$1 -> 3158 | C29: =H$1 -> 5 | D29: =F$2 -> 2017 | E29: 2 | F29: LEISTUNG_KURS_FORTBILDUNG | G29: LEISTUNG_IVG_AHVG | H29: =IF(ISBLANK(E11),"",E11) | I29: E11
B30: =F$1 -> 3158 | C30: =H$1 -> 5 | D30: =F$2 -> 2017 | E30: 2 | F30: LEISTUNG_KURS_FORTBILDUNG | G30: LEISTUNG_NICHT_BERECHTIGT | H30: =IF(ISBLANK(F11),"",F11) | I30: F11
B31: =F$1 -> 3158 | C31: =H$1 -> 5 | D31: =F$2 -> 2017 | E31: 3 | F31: LEISTUNG_KURS_FORTBILDUNG | G31: ANZAHL_KURSE | H31: =IF(ISBLANK(B12),"",B12) | I31: B12
B32: =F$1 -> 3158 | C32: =H$1 -> 5 | D32: =F$2 -> 2017 | E32: 3 | F32: LEISTUNG_KURS_FORTBILDUNG | G32: ANZAHL_TEILNEHMER | H32: =IF(ISBLANK(C12),"",C12) | I32: C12
B33: =F$1 -> 3158 | C33: =H$1 -> 5 | D33: =F$2 -> 2017 | E33: 3 | F33: LEISTUNG_KURS_FORTBILDUNG | G33: PRAESENZ | H33: =IF(ISBLANK(D12),"",D12) | I33: D12
B34: =F$1 -> 3158 | C34: =H$1 -> 5 | D34: =F$2 -> 2017 | E34: 3 | F34: LEISTUNG_KURS_FORTBILDUNG | G34: LEISTUNG_IVG_AHVG | H34: =IF(ISBLANK(E12),"",E12) | I34: E12
B35: =F$1 -> 3158 | C35: =H$1 -> 5 | D35: =F$2 -> 2017 | E35: 3 | F35: LEISTUNG_KURS_FORTBILDUNG | G35: LEISTUNG_NICHT_BERECHTIGT | H35: =IF(ISBLANK(F12),"",F12) | I35: F12

Sheet LUFEB
A1: Contrat n° | B1: ='Organisationsdaten (Basisinfo)'!H1 -> 3158 | D1: P-ID | E1: ='Organisationsdaten (Basisinfo)'!K1 -> 5
A2: PROSPREH | B2: ='Organisationsdaten (Basisinfo)'!D1 -> 2017
B3: Total heures 1) | C3: Handicapés mentaux ou ayant des difficultés d’apprentissage | D3: Handicapés de l’ouïe | E3: Handicapés physiques | F3: Handicapés par suite de maladie | G3: Handicapés psychiques | H3: Handicapés de la vue | I3: Handicapés du langage | J3: Handicapés par suite de dépendance | K3: Pluri-handicapés
C4: =SUM(C5:C7) -> 0 | D4: =SUM(D5:D7) -> 0 | E4: =SUM(E5:E7) -> 282.4 | F4: =SUM(F5:F7) -> 0 | G4: =SUM(G5:G7) -> 0 | H4: =SUM(H5:H7) -> 0 | I4: =SUM(I5:I7) -> 0 | J4: =SUM(J5:J7) -> 0 | K4: =SUM(K5:K7) -> 70.6
A5: Tâches générales d’information et de relations publiques (GC B) | B5: 69 | C5: 0 | D5: 0 | E5: 55.2 | F5: 0 | G5: 0 | H5: 0 | I5: 0 | J5: 0 | K5: 13.8 | P5: =SUM(C5:K5)-B5 -> 0
A6: Médias et publications du mandataire accessibles au public (GC C) | B6: 284 | C6: 0 | D6: 0 | E6: 227.2 | F6: 0 | G6: 0 | H6: 0 | I6: 0 | J6: 0 | K6: 56.8 | P6: =SUM(C6:K6)-B6 -> 0
A7: Centre d’information et de documentation (GC C) | P7: =SUM(C7:K7)-B7 -> 0
C8: =C9 -> 0 | D8: =D9 -> 0 | E8: =E9 -> 0 | F8: =F9 -> 0 | G8: =G9 -> 0 | H8: =H9 -> 0 | I8: =I9 -> 0 | J8: =J9 -> 0 | K8: =K9 -> 0
A9: Développement, élaboration et diffusion de matériel d’information destiné aux handicapés sensoriels ou ayant des difficultés d’apprentissage (GC C) | P9: =SUM(C9:K9)-B9 -> 0
A12: Travail de fonds sur des thèmes spécifiques / collaboration dans des projets (GC C) | P12: =SUM(C12:K12)-B12 -> 0
A13: Prestations de base pour l'encouragement de l'entraide / conseil aux organisations et groupes d'entraide (GC C) | P13: =SUM(C13:K13)-B13 -> 0
A14: Total PROSPREH | B14: =SUM(B5,B6,B7,B9,B12,B13) -> 353 | C14: =SUM(C5,C6,C7,C9,C12,C13) -> 0 | D14: =SUM(D5,D6,D7,D9,D12,D13) -> 0 | E14: =SUM(E5,E6,E7,E9,E12,E13) -> 282.4 | F14: =SUM(F5,F6,F7,F9,F12,F13) -> 0 | G14: =SUM(G5,G6,G7,G9,G12,G13) -> 0 | H14: =SUM(H5,H6,H7,H9,H12,H13) -> 0 | I14: =SUM(I5,I6,I7,I9,I12,I13) -> 0 | ... K14: =SUM(K5,K6,K7,K9,K12,K13) -> 70.6 | P14: =SUM(C14:K14)-B14 -> 0
A15: 1) Le total des heures doit être réparti autant que possible sur les différents groupes de personnes handicapés. | P15: =SUM(P5,P6,P7,P9,P12,P13,P14) -> 0
A16: GC=Groupe de compensation
A17: =IF(L39<>0,"Die blaue Markierung verschwindet, sobald die Angaben für diese Leistung sowohl in der Kostenrechnung als auch in der Leistungstatistik vorhanden sind.","")
A20: =IF(P15<>0,"Die Summe der Stunden nach Zielgruppen stimmen nicht mit dem Total überein.","")
C35: VERTRAG_NR | D35: PERIODE_ID | E35: JAHR | F35: ZIELGRUPPE_ID | G35: TABELLE | H35: FELD | I35: WERT | J35: ADRESSE
C36: =B$1 -> 3158 | D36: =E$1 -> 5 | E36: =B$2 -> 2017 | G36: LUFEB | H36: STUNDEN_OEFFENTLICHKEITSARBEIT | I36: =IF(ISBLANK(B4),"",B4) | K36: LUFEB | L36: Kontrolle
C37: =B$1 -> 3158 | D37: =E$1 -> 5 | E37: =B$2 -> 2017 | G37: LUFEB | H37: OEFFENTLICHKEITSARBEIT_ALLG | I37: =IF(ISBLANK(B5),"",B5) -> 69 | J37: B5 | K37: ='Kostenrechnung konsolidiert'!U18 -> 7011.9416
C38: =B$1 -> 3158 | D38: =E$1 -> 5 | E38: =B$2 -> 2017 | G38: LUFEB | H38: PUBLIKATIONEN | I38: =IF(ISBLANK(B6),"",B6) -> 284 | J38: B6 | K38: =B14 -> 353
C39: =B$1 -> 3158 | D39: =E$1 -> 5 | E39: =B$2 -> 2017 | G39: LUFEB | H39: INFORMATIONSSTELLEN | I39: =IF(ISBLANK(B7),"",B7) | J39: B7 | K39: =COUNTIF(K37:K38,">0") -> 2 | L39: =COUNTIF(K39,1) -> 0
C40: =B$1 -> 3158 | D40: =E$1 -> 5 | E40: =B$2 -> 2017 | G40: LUFEB | H40: STUNDEN_DIENSTLEISTUNGEN | I40: =IF(ISBLANK(B8),"",B8)
C41: =B$1 -> 3158 | D41: =E$1 -> 5 | E41: =B$2 -> 2017 | G41: LUFEB | H41: INFORMATIONSMATERIALIEN | I41: =IF(ISBLANK(B9),"",B9) | J41: B9
C42: =B$1 -> 3158 | D42: =E$1 -> 5 | E42: =B$2 -> 2017 | G42: LUFEB | H42: BETREUUNGSDIENSTE | I42: =IF(ISBLANK(B10),"",B10) | J42: B10
C43: =B$1 -> 3158 | D43: =E$1 -> 5 | E43: =B$2 -> 2017 | G43: LUFEB | H43: DOLMETSCHDIENSTE | I43: =IF(ISBLANK(B11),"",B11) | J43: B11
C44: =B$1 -> 3158 | D44: =E$1 -> 5 | E44: =B$2 -> 2017 | G44: LUFEB | H44: STUNDEN_GRUNDLAGENARBEIT | I44: =IF(ISBLANK(B12),"",B12) | J44: B12
C45: =B$1 -> 3158 | D45: =E$1 -> 5 | E45: =B$2 -> 2017 | G45: LUFEB | H45: STUNDEN_FOERDERUNG_SELBSTHILFE | I45: =IF(ISBLANK(B13),"",B13) | J45: B13
C46: =B$1 -> 3158 | D46: =E$1 -> 5 | E46: =B$2 -> 2017 | F46: 1 | G46: LUFEB_ZIELGRUPPE | H46: STUNDEN_OEFFENTLICHKEITSARBEIT | I46: =C4 -> 0 | J46: C4
C47: =B$1 -> 3158 | D47: =E$1 -> 5 | E47: =B$2 -> 2017 | F47: 2 | G47: LUFEB_ZIELGRUPPE | H47: STUNDEN_OEFFENTLICHKEITSARBEIT | I47: =D4 -> 0 | J47: D4
C48: =B$1 -> 3158 | D48: =E$1 -> 5 | E48: =B$2 -> 2017 | F48: 3 | G48: LUFEB_ZIELGRUPPE | H48: STUNDEN_OEFFENTLICHKEITSARBEIT | I48: =E4 -> 282.4 | J48: E4
C49: =B$1 -> 3158 | D49: =E$1 -> 5 | E49: =B$2 -> 2017 | F49: 4 | G49: LUFEB_ZIELGRUPPE | H49: STUNDEN_OEFFENTLICHKEITSARBEIT | I49: =F4 -> 0 | J49: F4
C50: =B$1 -> 3158 | D50: =E$1 -> 5 | E50: =B$2 -> 2017 | F50: 5 | G50: LUFEB_ZIELGRUPPE | H50: STUNDEN_OEFFENTLICHKEITSARBEIT | I50: =G4 -> 0 | J50: G4
C51: =B$1 -> 3158 | D51: =E$1 -> 5 | E51: =B$2 -> 2017 | F51: 6 | G51: LUFEB_ZIELGRUPPE | H51: STUNDEN_OEFFENTLICHKEITSARBEIT | I51: =H4 -> 0 | J51: H4
C52: =B$1 -> 3158 | D52: =E$1 -> 5 | E52: =B$2 -> 2017 | F52: 7 | G52: LUFEB_ZIELGRUPPE | H52: STUNDEN_OEFFENTLICHKEITSARBEIT | I52: =I4 -> 0 | J52: I4
C53: =B$1 -> 3158 | D53: =E$1 -> 5 | E53: =B$2 -> 2017 | F53: 8 | G53: LUFEB_ZIELGRUPPE | H53: STUNDEN_OEFFENTLICHKEITSARBEIT | I53: =J4 -> 0 | J53: J4
C54: =B$1 -> 3158 | D54: =E$1 -> 5 | E54: =B$2 -> 2017 | F54: -2 | G54: LUFEB_ZIELGRUPPE | H54: STUNDEN_OEFFENTLICHKEITSARBEIT | I54: =K4 -> 70.6 | J54: K4
C55: =B$1 -> 3158 | D55: =E$1 -> 5 | E55: =B$2 -> 2017 | F55: 1 | G55: LUFEB_ZIELGRUPPE | H55: STUNDEN_DIENSTLEISTUNGEN | I55: =C8 -> 0 | J55: C8
C56: =B$1 -> 3158 | D56: =E$1 -> 5 | E56: =B$2 -> 2017 | F56: 2 | G56: LUFEB_ZIELGRUPPE | H56: STUNDEN_DIENSTLEISTUNGEN | I56: =D8 -> 0 | J56: D8
C57: =B$1 -> 3158 | D57: =E$1 -> 5 | E57: =B$2 -> 2017 | F57: 3 | G57: LUFEB_ZIELGRUPPE | H57: STUNDEN_DIENSTLEISTUNGEN | I57: =E8 -> 0 | J57: E8
C58: =B$1 -> 3158 | D58: =E$1 -> 5 | E58: =B$2 -> 2017 | F58: 4 | G58: LUFEB_ZIELGRUPPE | H58: STUNDEN_DIENSTLEISTUNGEN | I58: =F8 -> 0 | J58: F8
C59: =B$1 -> 3158 | D59: =E$1 -> 5 | E59: =B$2 -> 2017 | F59: 5 | G59: LUFEB_ZIELGRUPPE | H59: STUNDEN_DIENSTLEISTUNGEN | I59: =G8 -> 0 | J59: G8
C60: =B$1 -> 3158 | D60: =E$1 -> 5 | E60: =B$2 -> 2017 | F60: 6 | G60: LUFEB_ZIELGRUPPE | H60: STUNDEN_DIENSTLEISTUNGEN | I60: =H8 -> 0 | J60: H8
C61: =B$1 -> 3158 | D61: =E$1 -> 5 | E61: =B$2 -> 2017 | F61: 7 | G61: LUFEB_ZIELGRUPPE | H61: STUNDEN_DIENSTLEISTUNGEN | I61: =I8 -> 0 | J61: I8
C62: =B$1 -> 3158 | D62: =E$1 -> 5 | E62: =B$2 -> 2017 | F62: 8 | G62: LUFEB_ZIELGRUPPE | H62: STUNDEN_DIENSTLEISTUNGEN | I62: =J8 -> 0 | J62: J8
C63: =B$1 -> 3158 | D63: =E$1 -> 5 | E63: =B$2 -> 2017 | F63: -2 | G63: LUFEB_ZIELGRUPPE | H63: STUNDEN_DIENSTLEISTUNGEN | I63: =K8 -> 0 | J63: K8
C64: =B$1 -> 3158 | D64: =E$1 -> 5 | E64: =B$2 -> 2017 | F64: 1 | G64: LUFEB_ZIELGRUPPE | H64: STUNDEN_GRUNDLAGENARBEIT | I64: =C12 -> 0 | J64: C12
C65: =B$1 -> 3158 | D65: =E$1 -> 5 | E65: =B$2 -> 2017 | F65: 2 | G65: LUFEB_ZIELGRUPPE | H65: STUNDEN_GRUNDLAGENARBEIT | I65: =D12 -> 0 | J65: D12
C66: =B$1 -> 3158 | D66: =E$1 -> 5 | E66: =B$2 -> 2017 | F66: 3 | G66: LUFEB_ZIELGRUPPE | H66: STUNDEN_GRUNDLAGENARBEIT | I66: =E12 -> 0 | J66: E12
C67: =B$1 -> 3158 | D67: =E$1 -> 5 | E67: =B$2 -> 2017 | F67: 4 | G67: LUFEB_ZIELGRUPPE | H67: STUNDEN_GRUNDLAGENARBEIT | I67: =F12 -> 0 | J67: F12
C68: =B$1 -> 3158 | D68: =E$1 -> 5 | E68: =B$2 -> 2017 | F68: 5 | G68: LUFEB_ZIELGRUPPE | H68: STUNDEN_GRUNDLAGENARBEIT | I68: =G12 -> 0 | J68: G12
C69: =B$1 -> 3158 | D69: =E$1 -> 5 | E69: =B$2 -> 2017 | F69: 6 | G69: LUFEB_ZIELGRUPPE | H69: STUNDEN_GRUNDLAGENARBEIT | I69: =H12 -> 0 | J69: H12
C70: =B$1 -> 3158 | D70: =E$1 -> 5 | E70: =B$2 -> 2017 | F70: 7 | G70: LUFEB_ZIELGRUPPE | H70: STUNDEN_GRUNDLAGENARBEIT | I70: =I12 -> 0 | J70: I12
C71: =B$1 -> 3158 | D71: =E$1 -> 5 | E71: =B$2 -> 2017 | F71: 8 | G71: LUFEB_ZIELGRUPPE | H71: STUNDEN_GRUNDLAGENARBEIT | I71: =J12 -> 0 | J71: J12
C72: =B$1 -> 3158 | D72: =E$1 -> 5 | E72: =B$2 -> 2017 | F72: -2 | G72: LUFEB_ZIELGRUPPE | H72: STUNDEN_GRUNDLAGENARBEIT | I72: =K12 -> 0 | J72: K12
C73: =B$1 -> 3158 | D73: =E$1 -> 5 | E73: =B$2 -> 2017 | F73: 1 | G73: LUFEB_ZIELGRUPPE | H73: STUNDEN_FOERDERUNG_SELBSTHILFE | I73: =C13 -> 0 | J73: C13
C74: =B$1 -> 3158 | D74: =E$1 -> 5 | E74: =B$2 -> 2017 | F74: 2 | G74: LUFEB_ZIELGRUPPE | H74: STUNDEN_FOERDERUNG_SELBSTHILFE | I74: =D13 -> 0 | J74: D13
C75: =B$1 -> 3158 | D75: =E$1 -> 5 | E75: =B$2 -> 2017 | F75: 3 | G75: LUFEB_ZIELGRUPPE | H75: STUNDEN_FOERDERUNG_SELBSTHILFE | I75: =E13 -> 0 | J75: E13
C76: =B$1 -> 3158 | D76: =E$1 -> 5 | E76: =B$2 -> 2017 | F76: 4 | G76: LUFEB_ZIELGRUPPE | H76: STUNDEN_FOERDERUNG_SELBSTHILFE | I76: =F13 -> 0 | J76: F13
C77: =B$1 -> 3158 | D77: =E$1 -> 5 | E77: =B$2 -> 2017 | F77: 5 | G77: LUFEB_ZIELGRUPPE | H77: STUNDEN_FOERDERUNG_SELBSTHILFE | I77: =G13 -> 0 | J77: G13
C78: =B$1 -> 3158 | D78: =E$1 -> 5 | E78: =B$2 -> 2017 | F78: 6 | G78: LUFEB_ZIELGRUPPE | H78: STUNDEN_FOERDERUNG_SELBSTHILFE | I78: =H13 -> 0 | J78: H13
C79: =B$1 -> 3158 | D79: =E$1 -> 5 | E79: =B$2 -> 2017 | F79: 7 | G79: LUFEB_ZIELGRUPPE | H79: STUNDEN_FOERDERUNG_SELBSTHILFE | I79: =I13 -> 0 | J79: I13
C80: =B$1 -> 3158 | D80: =E$1 -> 5 | E80: =B$2 -> 2017 | F80: 8 | G80: LUFEB_ZIELGRUPPE | H80: STUNDEN_FOERDERUNG_SELBSTHILFE | I80: =J13 -> 0 | J80: J13
C81: =B$1 -> 3158 | D81: =E$1 -> 5 | E81: =B$2 -> 2017 | F81: -2 | G81: LUFEB_ZIELGRUPPE | H81: STUNDEN_FOERDERUNG_SELBSTHILFE | I81: =K13 -> 0 | J81: K13

Sheet Begleitetes Wohnen
A1: Accompagnement pour l'année | C1: ='Organisationsdaten (Basisinfo)'!D1 -> 2017 | D1: Contrat n°. | E1: ='Organisationsdaten (Basisinfo)'!H1 -> 3158
C3: Accompagnement à domicile de personnes handicapées
C4: Total d’heures d’accompagnement brutes | D4: Nombre de semaines de présence | E4: Nombre de bénéficiaires
A7: Bénéficiaires reconnus | B7: Handicapés mentaux ou ayant des difficultés d’apprentissage
B8: Handicapés de l’ouïe
B9: Handicapés physiques
B10: Handicapés par suite de maladie
B11: Handicapés psychiques
B12: Handicapés de la vue
B13: Handicapés du langage | T13: Plausibilisierung der Totale
B14: Handicapés par suite de dépendance | V14: F | W14: G | X14: H | Z14: Kontrolle
B15: Total | C15: =SUM(C7:C14) -> 0 | D15: =SUM(D7:D14) -> 0 | E15: =SUM(E7:E14) -> 0 | V15: =IF(OR(C15-C19<>0,C15-C47<>0),1,0) -> 0 | W15: =IF(OR(D15-D19<>0,D15-D47<>0),1,0) -> 0 | X15: =IF(OR(E15-E19<>0,E15-E47<>0),1,0) -> 0 | Z15: =SUM(COUNTIF(V15:X15,"<>0")) -> 0
B16: dont plurihandicapés
B17: reconnus au titre de l'art. 74 LAI
B18: reconnus au titre de l'art.101bis LAVS | T18: Plausibilisierung Kostenträger Leistungsstatistik
B19: Total | C19: =ROUND(SUM(C17:C18),2) -> 0 | D19: =SUM(D17:D18) -> 0 | E19: =SUM(E17:E18) -> 0 | F19: =IF(X20=1,"Die blaue Markierung verschwindet, sobald die Angaben für diese Leistung sowohl in der Kostenrechnung als auch in der Leistungstatistik vorhanden sind.","") | U19: Kore BW | V19: BW
A20: Total des bénéficiaires non reconnus | U20: ='Kostenrechnung konsolidiert'!W18 -> 0 | V20: =E15 -> 0 | X20: =COUNTIF(U20:V20,">0") -> 0
A21: Bénéficiaires reconnus | B21: AG
B22: AI
B23: AR
B24: BE
B25: BL
B26: BS
B27: FR
B28: GE | F28: =IF(Z15<>0,"Die rote Markierung verschwindet, sobald die Totale übereinstimmen","")
B29: GL
B30: GR
B31: JU
B32: LU
B33: NE
B34: NW
B35: OW
B36: SG
B37: SH
B38: SO
B39: SZ
B40: TG
... B46: ZH
B47: Total | C47: =SUM(C21:C46) -> 0 | D47: =SUM(D21:D46) -> 0 | E47: =SUM(E21:E46) -> 0
B48: Nouveaux bénéficiaires
B49: Bénéficiaires repris de l’année précédente
B50: Total | E50: =SUM(E48:E49) -> 0
A51: Nouveaux bénéficiaires sortis des homes 1) | E51: 0
A52: Bénéficiaires vivant de façon indépendante et qui n’ont plus besoin d’accompagnement 2) | E52: 0
A53: 1) Par ex. Clinique, écoles d'autonomie, internats, foyers d'accueil pour adultes
A54: 2) Auto-déclaration des bénéficiaires
C59: P-ID | D59: ='Organisationsdaten (Basisinfo)'!K1 -> 5
C61: VERTRAG_NR | D61: PERIODE_ID | E61: JAHR | F61: ZIELGRUPPE_ID | G61: KANTON_ID | H61: TABELLE | I61: FELD | J61: WERT | K61: ADRESSE
C62: =E$1 -> 3158 | D62: =D$59 -> 5 | E62: =C$1 -> 2017 | F62: 1 | H62: BEGLEITETES_WOHNEN_ZIELGRUPPE | I62: BEGLEITSTUNDEN | J62: =IF(ISBLANK(C7),"",C7) | K62: C7
C63: =E$1 -> 3158 | D63: =D$59 -> 5 | E63: =C$1 -> 2017 | F63: 1 | H63: BEGLEITETES_WOHNEN_ZIELGRUPPE | I63: ANWESENHEITSWOCHEN | J63: =IF(ISBLANK(D7),"",D7) | K63: D7
C64: =E$1 -> 3158 | D64: =D$59 -> 5 | E64: =C$1 -> 2017 | F64: 1 | H64: BEGLEITETES_WOHNEN_ZIELGRUPPE | I64: ANZAHL_KLIENTEN | J64: =IF(ISBLANK(E7),"",E7) | K64: E7
C65: =E$1 -> 3158 | D65: =D$59 -> 5 | E65: =C$1 -> 2017 | F65: 2 | H65: BEGLEITETES_WOHNEN_ZIELGRUPPE | I65: BEGLEITSTUNDEN | J65: =IF(ISBLANK(C8),"",C8) | K65: C8
C66: =E$1 -> 3158 | D66: =D$59 -> 5 | E66: =C$1 -> 2017 | F66: 2 | H66: BEGLEITETES_WOHNEN_ZIELGRUPPE | I66: ANWESENHEITSWOCHEN | J66: =IF(ISBLANK(D8),"",D8) | K66: D8
C67: =E$1 -> 3158 | D67: =D$59 -> 5 | E67: =C$1 -> 2017 | F67: 2 | H67: BEGLEITETES_WOHNEN_ZIELGRUPPE | I67: ANZAHL_KLIENTEN | J67: =IF(ISBLANK(E8),"",E8) | K67: E8
C68: =E$1 -> 3158 | D68: =D$59 -> 5 | E68: =C$1 -> 2017 | F68: 3 | H68: BEGLEITETES_WOHNEN_ZIELGRUPPE | I68: BEGLEITSTUNDEN | J68: =IF(ISBLANK(C9),"",C9) | K68: C9
C69: =E$1 -> 3158 | D69: =D$59 -> 5 | E69: =C$1 -> 2017 | F69: 3 | H69: BEGLEITETES_WOHNEN_ZIELGRUPPE | I69: ANWESENHEITSWOCHEN | J69: =IF(ISBLANK(D9),"",D9) | K69: D9
C70: =E$1 -> 3158 | D70: =D$59 -> 5 | E70: =C$1 -> 2017 | F70: 3 | H70: BEGLEITETES_WOHNEN_ZIELGRUPPE | I70: ANZAHL_KLIENTEN | J70: =IF(ISBLANK(E9),"",E9) | K70: E9
C71: =E$1 -> 3158 | D71: =D$59 -> 5 | E71: =C$1 -> 2017 | F71: 4 | H71: BEGLEITETES_WOHNEN_ZIELGRUPPE | I71: BEGLEITSTUNDEN | J71: =IF(ISBLANK(C10),"",C10) | K71: C10
C72: =E$1 -> 3158 | D72: =D$59 -> 5 | E72: =C$1 -> 2017 | F72: 4 | H72: BEGLEITETES_WOHNEN_ZIELGRUPPE | I72: ANWESENHEITSWOCHEN | J72: =IF(ISBLANK(D10),"",D10) | K72: D10
C73: =E$1 -> 3158 | D73: =D$59 -> 5 | E73: =C$1 -> 2017 | F73: 4 | H73: BEGLEITETES_WOHNEN_ZIELGRUPPE | I73: ANZAHL_KLIENTEN | J73: =IF(ISBLANK(E10),"",E10) | K73: E10
C74: =E$1 -> 3158 | D74: =D$59 -> 5 | E74: =C$1 -> 2017 | F74: 5 | H74: BEGLEITETES_WOHNEN_ZIELGRUPPE | I74: BEGLEITSTUNDEN | J74: =IF(ISBLANK(C11),"",C11) | K74: C11
C75: =E$1 -> 3158 | D75: =D$59 -> 5 | E75: =C$1 -> 2017 | F75: 5 | H75: BEGLEITETES_WOHNEN_ZIELGRUPPE | I75: ANWESENHEITSWOCHEN | J75: =IF(ISBLANK(D11),"",D11) | K75: D11
C76: =E$1 -> 3158 | D76: =D$59 -> 5 | E76: =C$1 -> 2017 | F76: 5 | H76: BEGLEITETES_WOHNEN_ZIELGRUPPE | I76: ANZAHL_KLIENTEN | J76: =IF(ISBLANK(E11),"",E11) | K76: E11
C77: =E$1 -> 3158 | D77: =D$59 -> 5 | E77: =C$1 -> 2017 | F77: 6 | H77: BEGLEITETES_WOHNEN_ZIELGRUPPE | I77: BEGLEITSTUNDEN | J77: =IF(ISBLANK(C12),"",C12) | K77: C12
C78: =E$1 -> 3158 | D78: =D$59 -> 5 | E78: =C$1 -> 2017 | F78: 6 | H78: BEGLEITETES_WOHNEN_ZIELGRUPPE | I78: ANWESENHEITSWOCHEN | J78: =IF(ISBLANK(D12),"",D12) | K78: D12
C79: =E$1 -> 3158 | D79: =D$59 -> 5 | E79: =C$1 -> 2017 | F79: 6 | H79: BEGLEITETES_WOHNEN_ZIELGRUPPE | I79: ANZAHL_KLIENTEN | J79: =IF(ISBLANK(E12),"",E12) | K79: E12
C80: =E$1 -> 3158 | D80: =D$59 -> 5 | E80: =C$1 -> 2017 | F80: 7 | H80: BEGLEITETES_WOHNEN_ZIELGRUPPE | I80: BEGLEITSTUNDEN | J80: =IF(ISBLANK(C13),"",C13) | K80: C13
C81: =E$1 -> 3158 | D81: =D$59 -> 5 | E81: =C$1 -> 2017 | F81: 7 | H81: BEGLEITETES_WOHNEN_ZIELGRUPPE | I81: ANWESENHEITSWOCHEN | J81: =IF(ISBLANK(D13),"",D13) | K81: D13
C82: =E$1 -> 3158 | D82: =D$59 -> 5 | E82: =C$1 -> 2017 | F82: 7 | H82: BEGLEITETES_WOHNEN_ZIELGRUPPE | I82: ANZAHL_KLIENTEN | J82: =IF(ISBLANK(E13),"",E13) | K82: E13
C83: =E$1 -> 3158 | D83: =D$59 -> 5 | E83: =C$1 -> 2017 | F83: 8 | H83: BEGLEITETES_WOHNEN_ZIELGRUPPE | I83: BEGLEITSTUNDEN | J83: =IF(ISBLANK(C14),"",C14) | K83: C14
C84: =E$1 -> 3158 | D84: =D$59 -> 5 | E84: =C$1 -> 2017 | F84: 8 | H84: BEGLEITETES_WOHNEN_ZIELGRUPPE | I84: ANWESENHEITSWOCHEN | J84: =IF(ISBLANK(D14),"",D14) | K84: D14
C85: =E$1 -> 3158 | D85: =D$59 -> 5 | E85: =C$1 -> 2017 | F85: 8 | H85: BEGLEITETES_WOHNEN_ZIELGRUPPE | I85: ANZAHL_KLIENTEN | J85: =IF(ISBLANK(E14),"",E14) | K85: E14
C86: =E$1 -> 3158 | D86: =D$59 -> 5 | E86: =C$1 -> 2017 | H86: BEGLEITETES_WOHNEN | I86: BEGL_STDN_MEHRFACH_BEHINDERT | J86: =IF(ISBLANK(C16),"",C16) | K86: C16
C87: =E$1 -> 3158 | D87: =D$59 -> 5 | E87: =C$1 -> 2017 | H87: BEGLEITETES_WOHNEN | I87: ANW_WOCHEN_MEHRFACH_BEHINDERT | J87: =IF(ISBLANK(D16),"",D16) | K87: D16
C88: =E$1 -> 3158 | D88: =D$59 -> 5 | E88: =C$1 -> 2017 | H88: BEGLEITETES_WOHNEN | I88: ANZ_KLIENTEN_MEHRFACH_BEH | J88: =IF(ISBLANK(E16),"",E16) | K88: E16
C89: =E$1 -> 3158 | D89: =D$59 -> 5 | E89: =C$1 -> 2017 | H89: BEGLEITETES_WOHNEN | I89: BEGL_STDN_BERECHTIGT_IVG | J89: =IF(ISBLANK(C17),"",C17) | K89: C17
C90: =E$1 -> 3158 | D90: =D$59 -> 5 | E90: =C$1 -> 2017 | H90: BEGLEITETES_WOHNEN | I90: ANW_WOCHEN_BERECHTIGT_IVG | J90: =IF(ISBLANK(D17),"",D17) | K90: D17
C91: =E$1 -> 3158 | D91: =D$59 -> 5 | E91: =C$1 -> 2017 | H91: BEGLEITETES_WOHNEN | I91: ANZ_KLIENTEN_BERECHTIGT_IVG | J91: =IF(ISBLANK(E17),"",E17) | K91: E17
C92: =E$1 -> 3158 | D92: =D$59 -> 5 | E92: =C$1 -> 2017 | H92: BEGLEITETES_WOHNEN | I92: BEGL_STDN_BERECHTIGT_AHVG | J92: =IF(ISBLANK(C18),"",C18) | K92: C18
C93: =E$1 -> 3158 | D93: =D$59 -> 5 | E93: =C$1 -> 2017 | H93: BEGLEITETES_WOHNEN | I93: ANW_WOCHEN_BERECHTIGT_AHVG | J93: =IF(ISBLANK(D18),"",D18) | K93: D18
C94: =E$1 -> 3158 | D94: =D$59 -> 5 | E94: =C$1 -> 2017 | H94: BEGLEITETES_WOHNEN | I94: ANZ_KLIENTEN_BERECHTIGT_AHVG | J94: =IF(ISBLANK(E18),"",E18) | K94: E18
C95: =E$1 -> 3158 | D95: =D$59 -> 5 | E95: =C$1 -> 2017 | H95: BEGLEITETES_WOHNEN | I95: BEGL_STDN_NICHT_BERECHTIGT | J95: =IF(ISBLANK(C20),"",C20) | K95: C20
C96: =E$1 -> 3158 | D96: =D$59 -> 5 | E96: =C$1 -> 2017 | H96: BEGLEITETES_WOHNEN | I96: ANW_WOCHEN_NICHT_BERECHTIGT | J96: =IF(ISBLANK(D20),"",D20) | K96: D20
C97: =E$1 -> 3158 | D97: =D$59 -> 5 | E97: =C$1 -> 2017 | H97: BEGLEITETES_WOHNEN | I97: ANZ_KLIENTEN_NICHT_BERECHTIGT | J97: =IF(ISBLANK(E20),"",E20) | K97: E20
C98: =E$1 -> 3158 | D98: =D$59 -> 5 | E98: =C$1 -> 2017 | G98: 19 | H98: BEGLEITETES_WOHNEN_KANTON | I98: BEGLEITSTUNDEN | J98: =IF(ISBLANK(C21),"",C21) | K98: C21
C99: =E$1 -> 3158 | D99: =D$59 -> 5 | E99: =C$1 -> 2017 | G99: 19 | H99: BEGLEITETES_WOHNEN_KANTON | I99: ANWESENHEITSWOCHEN | J99: =IF(ISBLANK(D21),"",D21) | K99: D21
C100: =E$1 -> 3158 | D100: =D$59 -> 5 | E100: =C$1 -> 2017 | G100: 19 | H100: BEGLEITETES_WOHNEN_KANTON | I100: ANZAHL_KLIENTEN | J100: =IF(ISBLANK(E21),"",E21) | K100: E21
C101: =E$1 -> 3158 | D101: =D$59 -> 5 | E101: =C$1 -> 2017 | G101: 16 | H101: BEGLEITETES_WOHNEN_KANTON | I101: BEGLEITSTUNDEN | J101: =IF(ISBLANK(C22),"",C22) | K101: C22
C102: =E$1 -> 3158 | D102: =D$59 -> 5 | E102: =C$1 -> 2017 | G102: 16 | H102: BEGLEITETES_WOHNEN_KANTON | I102: ANWESENHEITSWOCHEN | J102: =IF(ISBLANK(D22),"",D22) | K102: D22
C103: =E$1 -> 3158 | D103: =D$59 -> 5 | E103: =C$1 -> 2017 | G103: 16 | H103: BEGLEITETES_WOHNEN_KANTON | I103: ANZAHL_KLIENTEN | J103: =IF(ISBLANK(E22),"",E22) | K103: E22
C104: =E$1 -> 3158 | D104: =D$59 -> 5 | E104: =C$1 -> 2017 | G104: 15 | H104: BEGLEITETES_WOHNEN_KANTON | I104: BEGLEITSTUNDEN | J104: =IF(ISBLANK(C23),"",C23) | K104: C23
C105: =E$1 -> 3158 | D105: =D$59 -> 5 | E105: =C$1 -> 2017 | G105: 15 | H105: BEGLEITETES_WOHNEN_KANTON | I105: ANWESENHEITSWOCHEN | J105: =IF(ISBLANK(D23),"",D23) | K105: D23
C106: =E$1 -> 3158 | D106: =D$59 -> 5 | E106: =C$1 -> 2017 | G106: 15 | H106: BEGLEITETES_WOHNEN_KANTON | I106: ANZAHL_KLIENTEN | J106: =IF(ISBLANK(E23),"",E23) | K106: E23
C107: =E$1 -> 3158 | D107: =D$59 -> 5 | E107: =C$1 -> 2017 | G107: 2 | H107: BEGLEITETES_WOHNEN_KANTON | I107: BEGLEITSTUNDEN | J107: =IF(ISBLANK(C24),"",C24) | K107: C24
C108: =E$1 -> 3158 | D108: =D$59 -> 5 | E108: =C$1 -> 2017 | G108: 2 | H108: BEGLEITETES_WOHNEN_KANTON | I108: ANWESENHEITSWOCHEN | J108: =IF(ISBLANK(D24),"",D24) | K108: D24
C109: =E$1 -> 3158 | D109: =D$59 -> 5 | E109: =C$1 -> 2017 | G109: 2 | H109: BEGLEITETES_WOHNEN_KANTON | I109: ANZAHL_KLIENTEN | J109: =IF(ISBLANK(E24),"",E24) | K109: E24
C110: =E$1 -> 3158 | D110: =D$59 -> 5 | E110: =C$1 -> 2017 | G110: 13 | H110: BEGLEITETES_WOHNEN_KANTON | I110: BEGLEITSTUNDEN | J110: =IF(ISBLANK(C25),"",C25) | K110: C25
C111: =E$1 -> 3158 | D111: =D$59 -> 5 | E111: =C$1 -> 2017 | G111: 13 | H111: BEGLEITETES_WOHNEN_KANTON | I111: ANWESENHEITSWOCHEN | J111: =IF(ISBLANK(D25),"",D25) | K111: D25
C112: =E$1 -> 3158 | D112: =D$59 -> 5 | E112: =C$1 -> 2017 | G112: 13 | H112: BEGLEITETES_WOHNEN_KANTON | I112: ANZAHL_KLIENTEN | J112: =IF(ISBLANK(E25),"",E25) | K112: E25
C113: =E$1 -> 3158 | D113: =D$59 -> 5 | E113: =C$1 -> 2017 | G113: 12 | H113: BEGLEITETES_WOHNEN_KANTON | I113: BEGLEITSTUNDEN | J113: =IF(ISBLANK(C26),"",C26) | K113: C26
...

Sheet Realisiertes Arbeitsprog. LUFEB
B2: Programme de travail PROSPREH réalisé pour l'année | C2: ='Organisationsdaten (Basisinfo)'!D1 -> 2017 | D2: Contrat n°. | E2: ='Organisationsdaten (Basisinfo)'!H1 -> 3158
A4: Prestations effectives réalisées selon l'annexe 9.3 CSOAPH à décompter pour l'OFAS Liste des différentes activités à introduire dans les champs jaunes. Au besoin, insérez-y des lignes supplémentaires. | E4: Données sur la charge d'heures effectives doivent être insérées dans les champs en vert. | F4: Evaluation de l'atteinte des objectifs Les données suivantes peuvent être résumées pour chaque sous-catégorie de prestations ou présentées en détail pour toutes les activités exercées. Nombre d’évaluations requises : de 5 à 10
F5: Résultat visé selon le plan | G5: Evaluation de l'atteinte des objectifs (par rapport au résultat visé) | H5: Mesures / réorientations (brève description, le reste est à indiquer sous planification, évt délai prévu)
A6: Tâches générales d’information et de relations publiques (groupe de compensation B) | E6: Heures imputées1)
A7: Renseignements généraux (3158 VS) | E7: 69
A10: Total groupe de compensation B | E10: =SUM(E7:E9) -> 69
A11: Prestations spécifiques PROSPREH (groupe de compensation C) | E11: Heures imputées1)
A12: Médias et publications de l’organisation accessibles au public
A13: Bulletion Connaître (3158 VS) | E13: 150 | F13: Les bulletins d'information des associations régionales sont dans la langue locales et abordent les thèmes chers aux membres ciblés | G13: Appréciation des résulats
A14: Site internet et page Facebook (3158 VS) | E14: 134 | F14: Les groupes cibles connaissent les prestations et les produits de l'association Cerebral Suisse, et sont toujours tenus au courant des dernières nouveautés | G14: Appréciation des résulats
A16: Total médias et publications de l’organisation accessibles au public | E16: =SUM(E13:E15) -> 284
A17: Centre d’information et de documentation
A21: Total centre d’information et de documentation | E21: =SUM(E18:E20) -> 0
A22: Développement, élaboration et diffusion de matériel d’information et de supports médiatiques à l’attention des handicapés sensoriels ou mentaux, ou ayant des difficultés d'apprentissage
A26: Total Développement, élaboration et diffusion de matériel d’information et de supports médiatiques à l’attention des handicapés sensoriels ou mentaux, ou ayant des difficultés d'apprentissage | E26: =SUM(E23:E25) -> 0
A27: Travail de fond ou projets ayant pour objet un thème spécifique
A31: Total Travail de fond ou projets ayant pour objet un thème spécifique | E31: =SUM(E28:E30) -> 0
A32: Prestations de base pour l'encouragement de l’entraide / conseil aux organisations et groupes d’entraide ainsi qu’aux particuliers
A36: Total prestations de base pour l'encouragement de l’entraide / conseil aux organisations et groupes d’entraide ainsi qu’aux particuliers | E36: =SUM(E33:E35) -> 0
A37: Total groupe de compensation C | E37: =SUM(E36,E31,E26,E21,E16) -> 284
A38: Total heures PROSPREH | E38: =SUM(E37,E10) -> 353
A39: 1) y compris les heures fournies sur la base des honoraires

Sheet Liste BW
A1: Behinderten Personen im Begleiteten Wohnen für das Jahr | D1: ='Organisationsdaten (Basisinfo)'!D1 -> 2017 | E1: LV-Nr. | F1: ='Organisationsdaten (Basisinfo)'!H1 -> 3158
A4: Nur KlientInnen angeben, die keine Hilflosenentschädigung für lebenspraktische Begleitung erhalten, jedoch gemäss Randziffer 1003 beitragsberechtigt sind
A6: Versichertennummer | B6: Wohnkanton | C6: Behinderungsart | D6: BSV-Nr. ULV-Nehmerin

Sheet Bsp. Real. Arbeitsprog. LUFEB
A1: EXEMPLE de reporting PROSPREH
A2: Programme de travail PROSPREH réalisé (consolidé au niveau du mandataire principal) pour l’année | E2: Numéro de contrat | G2: Evaluation de l'atteinte des objectifs
A3: Prestations fournies conformément à l’annexe 9.3 CSOAPH pour lesquelles vous voulez décompter avec l’OFAS Énumérer les activités dans les champs en jaune. Au besoin, ajouter des lignes supplémentaires. Prestations / activités | F3: Nombre d’heures effectives dans les champs en vert | G3: Les données suivantes peuvent être résumées pour chaque sous-catégorie de prestations ou présentées en détail pour toutes les activités exercées. Nombre d’évaluations requises : de 5 à 10
G4: Résultat visé selon le plan | H4: Evaluation de l'atteinte des objectifs (par rapport au résultat visé) | I4: Mesures / réorientations (brève description, le reste est à indiquer sous planification, évt délai prévu)
A5: Tâches générales d’information et de relations publiques (groupe de compensation B) | F5: Heures effectuées 1)
A6: Diffusion d’informations et tri | F6: 200 | H6: Pas d’évaluation
A7: Campagnes de sensibilisation | F7: 100 | H7: Pas d’évaluation
A8: Relations médias | F8: 300 | H8: Pas d’évaluation
A9: Exposés et conférences | F9: 650 | G9: Les exposés, conférences, débats politiques et autres rencontres permettent d'approfondir l'information envers le public et les professionnels. Les exposés, conférences et autres rencontres portent sur des sujets politiques du handicap actuels. | H9: Bilan de l'évaluation Le mandataire principal est intervenu par le biais des exposés, conférences et autres rencontres dans tous les cantons. Les rencontres suivantes méritent d’être relevées. Ct VD : C’est le première fois qu’un débat a été organisé sur le sujet xxxxx. Ct BE : Colloque sur la convention de l’ONU relative aux droits des personnes handicapées, mis sur pied avec deux autres organisations Ct TG : Rencontre sur le thème xxxxx réunissant quelque 200 personnes La rencontre sur le sujet xxxxx a eu une bonne couverture médiatique. X articles sont parus dans la presse. De notre point de vue, l’objectif est atteint. Les exposés, conférences et autres rencontres ont également eu une certaine efficacité dans l’opinion publique. Pour les grandes occasions, nous collaborons de plus en plus souvent avec d’autres organisations. | I9: En 2016, nous participerons à la délégation suisse de la conférence des Etats parties à la convention de l’ONU relative aux droits des personnes handicapées qui se tiendra à New York. Le sujet principal de la conférence de 2016 est la mise en œuvre de l’agenda 2030 de l’ONU pour un développement durable en faveur de toutes les personnes handicapées.
A10: Total du groupe de compensation B | F10: =SUM(F6:F9) -> 1250
A11: Prestations spécifiques PROSPREH (groupe de compensation C) | F11: Heures effectuées1)
A12: Médias et publications du mandataire accessibles au public
A13: Sites Internet | F13: 650 | G13: Le site Internet est un excellent instrument pour l’entraide. Le site Internet est actualisé en permanence. Objectif: Le nombre de visiteurs et d’informations postées augmente par rapport à l’année précédente. Exploitation des sites suivants : www.xxxxx.ch www.xxxxxx.ch www.xxxxxxxxxxxx.ch www.xxxxxxxxxxxx.ch www.xxxx.ch | H13: Evaluation quantitative Le nombre de visiteurs a été supérieur à l’année précédente. 2015 : xxxxx, 2016 : xxxxx Nous fournissons chaque semaine des informations à nos principaux partenaires sous la forme d’une lettre d’information. Pour répondre à l’intérêt grandissant pour les nouveautés et les tendances en cours, nous avons élargi la palette des sujets et publiés xx informations, ce qui correspond à une augmentation de xx % par rapport à l’année précédente (xx informations). | I13: En 2016, il est prévu d’adresser un questionnaire à nos clients pour connaître le besoin des utilisateurs du site web.
A14: Exemple 1 de journaux appartenant au mandataire : publications périodiques de l’organisation ou collaboration à une revue publiée en commun avec d’autres organisations de l’aide privée aux personnes handicapées | F14: 1250 | G14: Thèmes principaux : participation politique et vie autonome Le magazine xx paraît 4 fois par année en version allemande et en version française et italienne (mélangée). En tant que publication destinée aux membres et consacrée à des sujets spécifiques, il doit répondre au besoin d’information, de conseil et de soutien. Il sensibilise le public à l’actualité politique qui nous concerne. Le magazine s’adresse à quelque 22 000 membres comprenant des personnes handicapées, des leaders d’opinion, des personnes relais et des professionnels qualifiés. | H14: Evaluation qualitative et quantitative Vu les échos nombreux que nous avons enregistrés, nous considérons que l’objectif est atteint. Dossiers principaux en 2015 1/15 : Participation politique 3/15 : Sensibilisation 4/15 : Vivre de manière autonome Les feed-back reçus sur les numéros parus proviennent de certains membres ou d’organisations partenaires. Le magazine est bien considéré par les leaders d’opinions. Le numéro 1/15, qui portait sur la participation politique des personnes handicapées, a donné lieu à une manifestation devant le palais fédéral avec la présence des présidents du national et des états. Objectifs : les personnes handicapées doivent être mises sur un pied d’égalité et pouvoir participer à la vie politique et à la vie publique. Les personnes avec un handicap sont clairement sous-représentées tant au Parlement fédéral que dans les parlements cantonaux. Le magazine en ligne a l’audience suivante : Indications quantitatives Nombre de visites sur le site : 838 Nombre d’exemplaires imprimés : 9267 | I14: En 2016, les sujets suivants sur l’inclusion sont prévus : - Quel est l’accès des personnes handicapées dans le domaine de la santé ? - Mobilité, exemples tirés du domaine de la construction soulignant par ex. les entraves créées dans des grands projets - Recours aux animaux, bénévolat
A15: Exemple 2 de journaux appartenant au mandataire : publications périodiques de l’organisation ou collaboration à une revue publiée en commun avec d’autres organisations de l’aide privée aux personnes handicapées | F15: 850 | G15: Publications Les deux publications, xxxx et yyyy, tentent de couvrir de manière intéressante et instructive autant de sujets pertinents que possible. Les relations publiques sont en outre menées de manière intensive et les mesures de marketing sont produites à l'interne autant de fois que cela paraît utile et nécessaire. La publication de nos revues, feuilles d’information et autres vecteurs se caractérise par sa grande qualité et constance (respect des délais). | H15: Appréciation qualitative et mesures ou réorientations En automne 2015, nous avons demandé à nos membres de répondre à un questionnaire. Les résultats très satisfaisants dans l’ensemble sont pour nous un sujet de fierté car ils montrent que nous sommes sur le bon chemin. Les moyens de communication sont également bien appréciés. Par exemple, la revue Paracontact est très consulté.Les lecteurs y consacrent entre une demi-heure et une heure. La proportion des personnes qui n’y prêtent aucune attention est de seulement xx %. | I15: Notre revue de sport sera publiée en tant que lettre d’information électronique à partir du second semestre 2016. Cela permettra à nos clients de la recevoir plus vite et plus souvent, tout en supprimant les coûts d’impression et d’expédition.
A16: Total Médias et publications du mandataire accessibles au public | F16: =SUM(F13:F15) -> 2750
A17: Service d’information et de documentation
A23: Total Service d’information et de documentation | F23: =SUM(F20:F22) -> 0
A24: Développement, élaboration et diffusion de matériel d’information et de supports médiatiques destinés aux handicapés sensoriels ou mentaux, ou ayant des difficultés d’apprentissage
A30: Total Développement, élaboration et diffusion de matériel d’information et de supports médiatiques destinés aux handicapés sensoriels ou mentaux, ou ayant des difficultés d’apprentissage | F30: =SUM(F27:F29) -> 0
A31: Travail de fond ou projets ayant pour objet un thème spécifique
A32: Eurokey | F32: 150 | H32: Pas d’évaluation
A33: Participation aux procédures de consultation | F33: 220 | H33: Pas d’évaluation
A34: Participation aux groupes, groupes de travail, commissions techniques ou commissions d’experts | F34: 180 | H34: Pas d’évaluation
A35: Représentation | F35: 210 | H35: Pas d’évaluation
A36: Proches aidants (soins ou accompagnement) | F36: 150 | H36: Pas d’évaluation
A37: Absence de barrières/Accessibilité dans l’espace public | F37: 450 | G37: Nous encourageons l’accessibilité dans l’espace public et publions des informations. | H37: Bilan de l'évaluation Des projets ont été lancés dans plusieurs cantons, avec le concours d’autres organisations. On relèvera notamment : Ct XY, parcours de mobilité Il s'agit d’un parcours parsemés de huit obstacles en bois différents. Le but est de suivre ce parcours en fauteuil roulant ou avec les moyens auxiliaires des aveugles et malvoyants pour faire l’expérience des obstacles que rencontrent quotidiennement les personnes handicapées. Ce parcours est destiné à toutes les personnes intéressées à organiser des cours, une formation continue ou une rencontre sur le thème des personnes à mobilité réduite. Ct XY, Projet de tourisme accessible Principaux objectifs : présenter une définition du tourisme accessible, faire connaître les offres touristiques accessibles, mettre en réseau des prestataires institutionnels en vue d’organiser une région de vacances répondant à cette exigence d’accès. Le projet ne vise pas uniquement les hôtels et restaurants, mais aussi les offres de loisirs au sens large. | I37: Parcours de mobilité A partir de 2016, nous analyserons les demandes concernant le parcours de mobilité à l’aide d’un monitoring, afin d’ajuster notre offre à l’évolution. Tourisme accessible Nous prendrons contact avec d’autres régions de vacances, dans le but de les encourager à pratiquer un tourisme accessible.
A38: Habitation accessible | F38: 570 | G38: xxxxx xxx xxx | H38: Bilan de l’appréciation Projets concernant l’habitation accessible menés dans plusieurs cantons et étude sur l’habitat sans obstacle architectonique Brève description de l’étude Présenter l’évolution actuelle de la société en vue de montrer qu’il faudrait désormais construire de plus en plus de bâtiments sans obstacle architectonique. Pro Infirmis a donc demandé à l’Institut d’architecture de la Haute école spécialisée de la Suisse du Nord-Ouest de réaliser une étude qui examine les bâtiments d’habitation du canton de Bâle-Ville sous l’angle de leur potentiel de rénovation. L’étude a été publiée en 2015. Ct Xy, Projet xxxxx Principaux objectifs : xxxxxxxx Projet achevé en 2015. | I38: D’autres mesures a priori nécessaires seront examinées en 2016 : la création d’aides financières incitant à édicter des normes légales obligeant à vérifier, à l’occasion d’une rénovation de bâtiment, que les parties construites non concernées ne présentent pas d’obstacle architectonique, ou incitant à modifier des normes de sorte que les projets de rénovation de moindre importance comprennent systématiquement des adaptations en faveur des personnes à mobilité réduite.
A39: Total Travail de fond ou projets ayant pour objet un thème spécifique | F39: =SUM(F32:F38) -> 1930
A40: Prestations de base pour l’encouragement de l’entraide ou conseil aux organisations et groupes d’entraide ainsi qu’aux particuliers
A41: Soutien, conseil et suivi professionnel en faveur d’organisations et de groupes d’entraide | F41: 350 | G41: Soutien en faveur de clubs de personnes en fauteuils roulants Ces clubs sont animés par des bénévoles. Il est par conséquent important que leurs comités soient soutenus et défrayés autant que possible. Sur demande de ces clubs, l’ASP s'occupe de l’expédition du courrier adressé à leurs membres. | H41: Evaluation de certaines activités En 2015, nous avons pu effectuer l’expédition du courrier adressé aux membres de xx des 27 clubs, soit xx expéditions au total (contre xx l’année précédente).
A42: Planification, organisation et tenue de réunions informelles de personnes handicapées et de proches de telles personnes à des fins d’échange d’opinions et d’expériences | F42: 120 | G42: Les parents d’enfants handicapés se rassemblent pour parler de leurs expériences, de leurs difficultés et des prestations auxquelles ils recourent. | H42: Evaluation de certaines activités Quatre rencontres ont eu lieu en 2015, rassemblant en moyenne 15 à 20 personnes. Sujets abordés : mesures d’économies, décharge, assistance, offres de vacances et pour les week-ends, formes de logement, questions d’ordre médical et échanges. Mise en œuvre sur le terrain des sujets de discussion : Demande faite à une institution quant à la possibilité de louer des locaux le week-end. L'idée est née d'organiser un week-end en dehors du domicile avec l'aide d'assistants. | I42: Le soutien à ce projet se poursuivra en 2016.
G43: .
A44: Prestations de base pour l’encouragement de l’entraide ou conseil aux organisations et groupes d’entraide ainsi qu’aux particuliers | F44: =SUM(F41:F43) -> 470
A45: Total du groupe de compensation C | F45: =SUM(F44,F39,F30,F23,F16) -> 5150
A46: Total des heures PROSPREH | F46: =SUM(F45,F10) -> 6400
A47: 1) y c. heures effectuées sur la base d’honoraires

Sheet Kostenrechnung UVN
B1: CA de toute organisation partie à un contrat en tant que mandataire ou sous-traitant | J1: ='Organisationsdaten (Basisinfo)'!D1 -> 2017 | M1: N° sous-traitant | P1: ='Organisationsdaten (Basisinfo)'!H1 -> 3158
B2: A | C2: B | D2: C | E2: D | F2: E | G2: F | H2: G | I2: H | J2: I | K2: J | L2: K | M2: L | N2: M | O2: N | P2: O | Q2: P | R2: T | S2: U | T2: V | U2: W
A3: 1 | B3: Genre de coûts (indiquer les chiffres de manière complète et non seulement par tranches de mille) | C3: CF-CA | G3: Centre de coûts (coûts indirects) | J3: Unités d'imputation (coûts directs + répartition des coûts indirects) | U3: Total
A4: 2 | C4: Charges/Produits selon CF | D4: Délimitations CF-CA | E4: Délimitations des charges propres à la fonction d'organisation faîtière | F4: Charges/Produits selon CA | G4: Personnel | H4: Locaux | I4: Direction, administration et organes | J4: Conseil et aide aux handicapés et aux proches | K4: Aide dans les lieux d'accueil | L4: Conseil en matière de construction | M4: Conseil juridique | N4: Mise en relation avec des services d'aide et d'interprètes | O4: Cours en bloc pour handicapés et proches | P4: Cours d'un jour pour handicapés et proches | Q4: Cours annuels et semestriels pour handicapés et proches | R4: Prestation ayant pour objet de soutenir et de promouvoir la réadaptation des handicapés | S4: Accompagnement à domicile | T4: Récolte de fonds
A5: 3 | B5: Salaires | C5: 536016.25 | D5: 82581.716 | E5: 0 | F5: =C5-D5-E5 -> 453434.53 | G5: 0 | H5: 5275.0478 | I5: 178744.42 | J5: 2079.3412 | K5: 0 | L5: 0 | M5: 0 | N5: 0 | O5: 227427.32 | P5: 35858.253 | Q5: 0 | R5: 4050.1469 | S5: 0 | T5: 0 | U5: =SUM(J5:T5) -> 269415.06 | V5: Charges directes
A6: 4 | B6: Charges sociales | C6: 69854.6 | D6: 10580.649 | E6: 0 | F6: =C6-D6-E6 -> 59273.951 | G6: 0 | H6: 698.4862 | I6: 22901.341 | J6: 275.33232 | K6: 0 | L6: 0 | M6: 0 | N6: 0 | O6: 30114.39 | P6: 4748.1077 | Q6: 0 | R6: 536.2931 | S6: 0 | T6: 0 | U6: =SUM(J6:T6) -> 35674.123
A7: 5 | B7: Autres charges de personnel | C7: 3652.95 | D7: 364.79244 | E7: 0 | F7: =C7-D7-E7 -> 3288.1576 | G7: 0 | H7: 47.981823 | I7: 789.57689 | J7: 18.913683 | K7: 0 | L7: 0 | M7: 0 | N7: 0 | O7: 2068.6784 | P7: 326.16659 | Q7: 0 | R7: 36.840128 | S7: 0 | T7: 0 | U7: =SUM(J7:T7) -> 2450.5988
A8: 6 | B8: Honoraires | C8: 875 | D8: 875 | E8: 0 | F8: =C8-D8-E8 -> 0 | G8: 0 | H8: 0 | I8: 0 | J8: 0 | K8: 0 | L8: 0 | M8: 0 | N8: 0 | O8: 0 | P8: 0 | Q8: 0 | R8: 0 | S8: 0 | T8: 0 | U8: =SUM(J8:T8) -> 0
A9: 7 | B9: Total des charges de personnel/ Coûts | C9: =SUM(C5:C8) -> 610398.8 | D9: =SUM(D5:D8) -> 94402.158 | E9: =SUM(E5:E8) -> 0 | F9: =SUM(F5:F8) -> 515996.64 | G9: =SUM(G5:G8) -> 0 | H9: =SUM(H5:H8) -> 6021.5158 | I9: =SUM(I5:I8) -> 202435.34 | J9: =SUM(J5:J8) -> 2373.5872 | ... T9: =SUM(T5:T8) -> 0 | U9: =SUM(J9:T9) -> 307539.79
A10: 8 | B10: Frais de locaux | C10: 86526.55 | D10: 27400.338 | E10: 0 | F10: =C10-D10-E10 -> 59126.212 | G10: 0 | H10: 59126.212 | I10: 0 | J10: 0 | K10: 0 | L10: 0 | M10: 0 | N10: 0 | O10: 0 | P10: 0 | Q10: 0 | R10: 0 | S10: 0 | T10: 0 | U10: =SUM(J10:T10) -> 0
A11: 9 | B11: Autres frais d'exploitation | C11: 298895.54 | D11: 110680.07 | E11: 0 | F11: =C11-D11-E11 -> 188215.47 | G11: 0 | H11: 0 | I11: -7547.3419 | J11: 0 | K11: 0 | L11: 0 | M11: 0 | N11: 0 | O11: 167265.66 | P11: 28497.15 | Q11: 0 | R11: 0 | S11: 0 | T11: 0 | U11: =SUM(J11:T11) -> 195762.81
A12: 10 | B12: Amortissements (immeubles exclus) | C12: 0 | D12: 0 | E12: 0 | F12: =C12-D12-E12 -> 0 | G12: 0 | H12: 0 | I12: 0 | J12: 0 | K12: 0 | L12: 0 | M12: 0 | N12: 0 | O12: 0 | P12: 0 | Q12: 0 | R12: 0 | S12: 0 | T12: 0 | U12: =SUM(J12:T12) -> 0
A13: 11 | B13: Total charges/coûts | C13: =SUM(C9:C12) -> 995820.89 | D13: =SUM(D9:D12) -> 232482.57 | E13: =SUM(E9:E12) -> 0 | F13: =SUM(F9:F12) -> 763338.32 | G13: =SUM(G9:G12) -> 0 | H13: =SUM(H9:H12) -> 65147.727 | I13: =SUM(I9:I12) -> 194888 | J13: =SUM(J9:J12) -> 2373.5872 | ... T13: =SUM(T9:T12) -> 0 | U13: =SUM(J13:T13) -> 503302.6
A14: 12 | B14: Répartition charges de personnel | C14: - | D14: - | E14: - | F14: - | G14: =ROUND(-G13,0) -> 0 | H14: 0 | I14: 0 | J14: 0 | K14: 0 | L14: 0 | M14: 0 | N14: 0 | O14: 0 | P14: 0 | Q14: 0 | R14: 0 | S14: 0 | T14: 0 | U14: =ROUND(SUM(J14:T14),0) -> 0 | V14: Frais généraux
A15: 13 | B15: Répartition frais de locaux | C15: - | D15: - | E15: - | F15: - | G15: - | H15: =ROUND(-(H13+H14),0) -> -65148 | I15: 18184.953 | J15: 221.47887 | K15: 0 | L15: 0 | M15: 0 | N15: 0 | O15: 39831.704 | P15: 6478.4669 | Q15: 0 | R15: 431.39718 | S15: 0 | T15: 0 | U15: =ROUND(SUM(J15:T15),0) -> 46963
A16: 14 | B16: Répartition direction/administration/ organes | C16: - | D16: - | E16: - | F16: - | G16: - | H16: - | I16: =ROUND(-(I13+I14+I15),0) -> -213073 | J16: 1004.8574 | K16: 0 | L16: 0 | M16: 0 | N16: 0 | O16: 180717.85 | P16: 29393.033 | Q16: 0 | R16: 1957.2642 | S16: 0 | T16: 0 | U16: =ROUND(SUM(J16:T16),0) -> 213073
A17: 15 | B17: Total des répartitions | C17: - | D17: - | E17: - | F17: - | G17: =SUM(G13:G16) -> 0 | H17: =SUM(H13:H16) -> -0.27255036 | I17: =SUM(I13:I16) -> -0.049091785 | J17: =SUM(J14:J16) -> 1226.3363 | K17: =SUM(K14:K16) -> 0 | L17: =SUM(L14:L16) -> 0 | M17: =SUM(M14:M16) -> 0 | N17: =SUM(N14:N16) -> 0 | O17: =SUM(O14:O16) -> 220549.55 | P17: =SUM(P14:P16) -> 35871.5 | Q17: =SUM(Q14:Q16) -> 0 | ... T17: =SUM(T14:T16) -> 0 | U17: =SUM(J17:T17) -> 260036.05
A18: 16 | B18: coûts complets après répartition | C18: - | D18: - | E18: - | F18: - | G18: - | H18: - | I18: - | J18: =J17+J13 -> 3599.9235 | K18: =K17+K13 -> 0 | L18: =L17+L13 -> 0 | M18: =M17+M13 -> 0 | N18: =N17+N13 -> 0 | O18: =O17+O13 -> 647425.6 | P18: =P17+P13 -> 105301.18 | Q18: =Q17+Q13 -> 0 | ... T18: =T17+T13 -> 0 | U18: =SUM(J18:T18) -> 763338.64
A19: 17 | B19: Produits des prestations | C19: 58660.05 | D19: 4800 | F19: =C19-D19 -> 53860.05 | G19: - | H19: - | I19: - | J19: 0 | K19: 0 | L19: 0 | M19: 0 | N19: 0 | O19: 49931.05 | P19: 3929 | Q19: 0 | R19: 0 | S19: 0 | T19: 0 | U19: =SUM(J19:Q19,R19,S19,T19) -> 53860.05
A20: 18 | B20: Subventions AI (art. 74 LAI et art. 101bis LAVS) | C20: 220636 | E20: 0 | F20: =C20-D20-E20 -> 220636 | G20: - | H20: - | I20: - | J20: 12600 | K20: 0 | L20: 0 | M20: 0 | N20: 0 | O20: 200036 | P20: 0 | Q20: 0 | R20: 8000 | S20: 0 | U20: =SUM(J20:Q20,R20,S20) -> 220636
A21: 19 | B21: Autres subventions de la confédération/ Subventions des cantons/communes | C21: 336441.3 | D21: 165049.3 | F21: =C21-D21 -> 171392 | G21: - | H21: - | I21: - | J21: 0 | K21: 0 | L21: 0 | M21: 0 | N21: 0 | O21: 148049.22 | P21: 23342.782 | Q21: 0 | R21: 0 | S21: 0 | T21: 0 | U21: =SUM(J21:Q21,R21,S21,T21) -> 171392
A22: 20 | B22: Donations directes/ Autres produits art. 74 LAI1) | C22: 41470 | F22: =C22 -> 41470 | G22: - | H22: - | I22: - | J22: 0 | K22: 0 | L22: 0 | M22: 0 | N22: 0 | O22: 26470 | P22: 15000 | Q22: 0 | R22: 0 | S22: 0 | T22: 0 | U22: =SUM(J22:Q22,R22,S22,T22) -> 41470
A23: 21 | B23: Donations indirectes/ autres produits (clé de répartition) 2) | C23: 336912.5 | D23: =C23-F23 -> 78654.882 | F23: =IFERROR(C23*U18/C13,"0") -> 258257.62 | G23: - | H23: - | I23: - | J23: 1217.9492 | K23: 0 | L23: 0 | M23: 0 | N23: 0 | O23: 219041.18 | P23: 35626.169 | Q23: 0 | R23: 2372.325 | S23: 0 | T23: 0 | U23: =SUM(J23:Q23,R23,S23,T23) -> 258257.62 | V23: Résultat d'exploitation:
A24: 22 | B24: Donations directes/ autres produits hors Art. 74 LAI 3) | C24: 2400 | D24: =C24 -> 2400 | E24: - | F24: - | G24: - | H24: - | I24: - | J24: - | K24: - | L24: - | M24: - | N24: - | O24: - | P24: - | Q24: - | R24: - | S24: - | T24: - | U24: -
A25: 23 | B25: Total des produits | C25: =SUM(C19:C24) -> 996519.85 | D25: =SUM(D19:D24) -> 250904.18 | E25: =SUM(E19:E24) -> 0 | F25: =SUM(F19:F24) -> 745615.67 | G25: - | H25: - | I25: - | J25: =SUM(J19:J24) -> 13817.949 | K25: =SUM(K19:K24) -> 0 | L25: =SUM(L19:L24) -> 0 | M25: =SUM(M19:M24) -> 0 | N25: =SUM(N19:N24) -> 0 | O25: =SUM(O19:O24) -> 643527.44 | P25: =SUM(P19:P24) -> 77897.95 | Q25: =SUM(Q19:Q24) -> 0 | ... U25: =SUM(U19:U24) -> 745615.67
A26: 24 | V26: =C25-C13 -> 698.96
A27: 25 | B27: Contribution de couverture (Cc) I (Produit des prestations - Coûts directs) | J27: =J19-J13 -> -2373.5872 | K27: =K19-K13 -> 0 | L27: =L19-L13 -> 0 | M27: =M19-M13 -> 0 | N27: =N19-N13 -> 0 | O27: =O19-O13 -> -376945 | P27: =P19-P13 -> -65500.678 | Q27: =Q19-Q13 -> 0 | ... U27: =U19-U13 -> -449442.55
A28: 26 | B28: Contribution de couverture II ( Cc I - Coûts indirects + Donations directes/ Autres produits Art.74 LAI + Donations indirectes, Autres produits (clé de répartition)) | C28: - | D28: - | F28: - | G28: - | H28: - | I28: - | J28: =J27-J17+J22+J23 -> -2381.9743 | K28: =K27-K17+K22+K23 -> 0 | L28: =L27-L17+L22+L23 -> 0 | M28: =M27-M17+M22+M23 -> 0 | N28: =N27-N17+N22+N23 -> 0 | O28: =O27-O17+O22+O23 -> -351983.38 | P28: =P27-P17+P22+P23 -> -50746.009 | Q28: =Q27-Q17+Q22+Q23 -> 0 | ... U28: =U27-U17+U22+U23 -> -409750.98
A29: 27 | B29: Contribution de couverture III ( Cc II + Autres subventions Confédération, Subventions des cantons et communes) | C29: - | D29: - | F29: - | G29: - | H29: - | I29: - | J29: =J28+J21 -> -2381.9743 | K29: =K28+K21 -> 0 | L29: =L28+L21 -> 0 | M29: =M28+M21 -> 0 | N29: =N28+N21 -> 0 | O29: =O28+O21 -> -203934.16 | P29: =P28+P21 -> -27403.227 | Q29: =Q28+Q21 -> 0 | ... U29: =U28+U21 -> -238358.98
A30: 28 | B30: Contribution de couverture IV (Cc III + Subvention AI) | C30: - | D30: - | F30: - | G30: - | H30: - | I30: - | J30: =J29+J20 -> 10218.026 | K30: =K29+K20 -> 0 | L30: =L29+L20 -> 0 | M30: =M29+M20 -> 0 | N30: =N29+N20 -> 0 | O30: =O29+O20 -> -3898.1581 | P30: =P29+P20 -> -27403.227 | Q30: =Q29+Q20 -> 0 | ... S30: =S29+S20 -> 0 | T30: - | U30: =U29+U20 -> -17722.976
A31: 1) Donations liées Art. 74 LAI, subventions, prestations de services, sponsoring pour l'art.74LAI | J31: =IF(AM33<>0,"Die rote Markierung verschwindet, sobald für diesen Kostenträger auch direkte Kosten erfasst worden sind.","")
A32: 2) Tous autres produits non affectés/donations/héritages, cotisations des membres, résultat financier, produits extraordinaires etc. sont délimités selon clé de répartition et attribués à l'activité Art. 74 LAI.
A33: 3) Produits affectés hors art. 74 LAI

Sheet Vorlage Berechnung Kap.substrat
B1: N° sous-traitant: | C1: 3158
B2: Nom de l'organisation: | C2: Valais
B3: Année: | C3: 2017
B5: Exemple | C5: non-attribuée | D5: attribuée | E5: Remarques
A6: Total des charges selon comptabilité financière (CF) | B6: 5000000 | C6: 995820.89 | D6: -
A7: Total des coûts selon Art. 74 LAI (selon CA) | B7: 3000000 | C7: 763338.64 | D7: -
A8: Clé de répartition | B8: =B7/B6 -> 0.6 | C8: =IFERROR((C7/C6),"") -> 0.76654211 | D8: -
A9: + Capital libéré de l'année précédente | B9: 8000000 | C9: 248312.19 | D9: =IFERROR((C9*C8),"") -> 190341.75
A10: + Capital libre généré (incl. Réserves libres et fonds libres) de l'année précédente | B10: 1100000 | C10: 344533.93 | D10: =IFERROR((C10*C8),"") -> 264099.76
A11: + Fonds lié art. 74 LAI de l'année précédente | B11: 600000 | D11: =C11 -> 0
A12: +/- Résultat annuel de l'année précédente | B12: 200000 | C12: 284.89 | D12: =IFERROR((C12*C8),"") -> 218.38018
A13: + Adaptations nécessaires de l'année précédente | B13: 100000 | D13: =IFERROR((C13*C8),"") -> 0 | E13: p.ex. changement des réserves pour fluctuations
A14: - Capital investi nécessaire au fonctionnement de l'exploitation Art.74 de l'année précédente | B14: 0 | D14: =C14 -> 0
A15: +/- 50% du solde de la contribution de couverture de l'exploitation de l'art. 74 IVG (selon CA) au 31.12 de l'exercice | B15: 100000 | C15: -8861.488 | D15: =C15 -> -8861.488
A16: + Constitution/renflouement de fonds liés par des fonds libres au 31.12. l'année d'exercice, cf. annexe 9.7.4 CSOAPH | B16: 0 | D16: =IFERROR((C16*C8),"") -> 0
A17: - Montant libre (forfait) | B17: -200000 | C17: -200000 | D17: =C17 -> -200000
A18: Substrat du capital art. 74 LAI | B18: =(((B9+B10+B12+B13+B14+B16)*B8)+(B11+B15+B17)) -> 6140000 | C18: =SUM(C9:C17) -> 384269.52 | D18: =SUM(D9:D17) -> 245798.41
A19: Facteur (substrat du capital relatif/Coûts totaux art.74) | B19: =B18/B7 -> 2.0466667 | C19: - | D19: =IFERROR(D18/C7,"") -> 0.32200441
A20: Subvention AI (selon contrat; en rapport avec les quantités fournies) | B20: 3000000 | C20: - | D20: 220636
A21: Réduction de la subvention AI | B21: =IF(B19>2,"oui","non") -> oui | C21: - | D21: =IF(D19>2,"oui","non") -> non
A22: Substrat du capital relatif diminué de 2x les coûts totaux de l'art.74 | B22: =IF(B21="oui",-((2*B7)-B18),"--") -> 140000 | C22: - | D22: =IF(D21="oui",-((2*C7)-D18),"--") -> --
A23: Montant maximal de la réduction (50% Subv. AI) | B23: =IF(B21="oui",B20/2,"--") -> 1500000 | C23: - | D23: =IF(D21="oui",D20/2,"--") -> --
A24: Montant de la réduction | B24: =IF(B21="oui",IF(B22<B23,B22,B23),"--") -> 140000 | C24: - | D24: =IF(D21="oui",IF(D22<D23,D22,D23),"--") -> --
A26: Autres remarques:

Sheet Auswertungstool Blockkurse
A1: Analyse Cours en bloc | D1: Le fait de remplir ce tableau est à bien plaire
B2: Coûts totaux/coûts de mise en oeuvre par cours | E2: Nombre journées participant(e)s (ayants droit et non ayants droit) | F2: Coûts totaux par journée-participant | I2: Affectation à une catégorie
M3: Cacul du supplément frais indirects :
B4: Critères d'attribution | F4: Critères d'attribution | I4: Critères d'attribution | M4: Total des coûts de mise en œuvre | Q4: =SUM(B6:D75) -> 167265.66
A5: Cours | B5: A | C5: B | D5: C | F5: A | G5: B | H5: C | I5: A | J5: B | K5: C | M5: Total coûts indirects
A6: 1 | D6: 4052.7705 | E6: 24 | F6: =IFERROR(($Q$6+1)*B6/$E6,0) -> 0 | G6: =IFERROR(($Q$6+1)*C6/$E6,0) -> 0 | H6: =IFERROR(($Q$6+1)*D6/$E6,0) -> 653.61778 | I6: =IF(F6>0,1,"") | J6: =IF(AND(G6>0,G6<442),1,IF(AND(G6>=442,G6<=642),2,IF(G6>642,3,""))) | K6: =IF(AND(H6>0,H6<442),1,IF(AND(H6>=442,H6<=642),2,IF(H6>642,3,""))) -> 3 | M6: supplément coûts indirects | Q6: =IFERROR(IF(R6>0,R6,Q5/Q4),0) -> 2.8706428 | R6: 2.8706428
A7: 2 | D7: 4052.7705 | E7: 24 | F7: =IFERROR(($Q$6+1)*B7/$E7,0) -> 0 | G7: =IFERROR(($Q$6+1)*C7/$E7,0) -> 0 | H7: =IFERROR(($Q$6+1)*D7/$E7,0) -> 653.61778 | I7: =IF(F7>0,1,"") | J7: =IF(AND(G7>0,G7<442),1,IF(AND(G7>=442,G7<=642),2,IF(G7>642,3,""))) | K7: =IF(AND(H7>0,H7<442),1,IF(AND(H7>=442,H7<=642),2,IF(H7>642,3,""))) -> 3
A8: 3 | D8: 4052.7705 | E8: 24 | F8: =IFERROR(($Q$6+1)*B8/$E8,0) -> 0 | G8: =IFERROR(($Q$6+1)*C8/$E8,0) -> 0 | H8: =IFERROR(($Q$6+1)*D8/$E8,0) -> 653.61778 | I8: =IF(F8>0,1,"") | J8: =IF(AND(G8>0,G8<442),1,IF(AND(G8>=442,G8<=642),2,IF(G8>642,3,""))) | K8: =IF(AND(H8>0,H8<442),1,IF(AND(H8>=442,H8<=642),2,IF(H8>642,3,""))) -> 3 | M8: Coûts totaux/ unités de prestations. | O8: Critères d'attribution cours en bloc
A9: 4 | D9: 3715.0396 | E9: 22 | F9: =IFERROR(($Q$6+1)*B9/$E9,0) -> 0 | G9: =IFERROR(($Q$6+1)*C9/$E9,0) -> 0 | H9: =IFERROR(($Q$6+1)*D9/$E9,0) -> 653.61778 | I9: =IF(F9>0,1,"") | J9: =IF(AND(G9>0,G9<442),1,IF(AND(G9>=442,G9<=642),2,IF(G9>642,3,""))) | K9: =IF(AND(H9>0,H9<442),1,IF(AND(H9>=442,H9<=642),2,IF(H9>642,3,""))) -> 3 | O9: A | P9: B | Q9: C
A10: 5 | D10: 4052.7705 | E10: 24 | F10: =IFERROR(($Q$6+1)*B10/$E10,0) -> 0 | G10: =IFERROR(($Q$6+1)*C10/$E10,0) -> 0 | H10: =IFERROR(($Q$6+1)*D10/$E10,0) -> 653.61778 | I10: =IF(F10>0,1,"") | J10: =IF(AND(G10>0,G10<442),1,IF(AND(G10>=442,G10<=642),2,IF(G10>642,3,""))) | K10: =IF(AND(H10>0,H10<442),1,IF(AND(H10>=442,H10<=642),2,IF(H10>642,3,""))) -> 3 | M10: < 442 | O10: Cat 1 | P10: Cat 1 | Q10: Cat 1
A11: 6 | D11: 4052.7705 | E11: 24 | F11: =IFERROR(($Q$6+1)*B11/$E11,0) -> 0 | G11: =IFERROR(($Q$6+1)*C11/$E11,0) -> 0 | H11: =IFERROR(($Q$6+1)*D11/$E11,0) -> 653.61778 | I11: =IF(F11>0,1,"") | J11: =IF(AND(G11>0,G11<442),1,IF(AND(G11>=442,G11<=642),2,IF(G11>642,3,""))) | K11: =IF(AND(H11>0,H11<442),1,IF(AND(H11>=442,H11<=642),2,IF(H11>642,3,""))) -> 3 | M11: 442 à 642 | O11: Cat 1 | P11: Cat 2 | Q11: Cat 2
A12: 7 | D12: 4052.7705 | E12: 24 | F12: =IFERROR(($Q$6+1)*B12/$E12,0) -> 0 | G12: =IFERROR(($Q$6+1)*C12/$E12,0) -> 0 | H12: =IFERROR(($Q$6+1)*D12/$E12,0) -> 653.61778 | I12: =IF(F12>0,1,"") | J12: =IF(AND(G12>0,G12<442),1,IF(AND(G12>=442,G12<=642),2,IF(G12>642,3,""))) | K12: =IF(AND(H12>0,H12<442),1,IF(AND(H12>=442,H12<=642),2,IF(H12>642,3,""))) -> 3 | M12: > 642 | O12: Cat 1 | P12: Cat 2 | Q12: Cat 3
A13: 8 | D13: 4052.7705 | E13: 24 | F13: =IFERROR(($Q$6+1)*B13/$E13,0) -> 0 | G13: =IFERROR(($Q$6+1)*C13/$E13,0) -> 0 | H13: =IFERROR(($Q$6+1)*D13/$E13,0) -> 653.61778 | I13: =IF(F13>0,1,"") | J13: =IF(AND(G13>0,G13<442),1,IF(AND(G13>=442,G13<=642),2,IF(G13>642,3,""))) | K13: =IF(AND(H13>0,H13<442),1,IF(AND(H13>=442,H13<=642),2,IF(H13>642,3,""))) -> 3
A14: 9 | D14: 4052.7705 | E14: 24 | F14: =IFERROR(($Q$6+1)*B14/$E14,0) -> 0 | G14: =IFERROR(($Q$6+1)*C14/$E14,0) -> 0 | H14: =IFERROR(($Q$6+1)*D14/$E14,0) -> 653.61778 | I14: =IF(F14>0,1,"") | J14: =IF(AND(G14>0,G14<442),1,IF(AND(G14>=442,G14<=642),2,IF(G14>642,3,""))) | K14: =IF(AND(H14>0,H14<442),1,IF(AND(H14>=442,H14<=642),2,IF(H14>642,3,""))) -> 3 | M14: Statistique des cours | P14: A | Q14: B | R14: C
A15: 10 | D15: 3715.0396 | E15: 22 | F15: =IFERROR(($Q$6+1)*B15/$E15,0) -> 0 | G15: =IFERROR(($Q$6+1)*C15/$E15,0) -> 0 | H15: =IFERROR(($Q$6+1)*D15/$E15,0) -> 653.61778 | I15: =IF(F15>0,1,"") | J15: =IF(AND(G15>0,G15<442),1,IF(AND(G15>=442,G15<=642),2,IF(G15>642,3,""))) | K15: =IF(AND(H15>0,H15<442),1,IF(AND(H15>=442,H15<=642),2,IF(H15>642,3,""))) -> 3 | M15: < | O15: 442 | P15: =COUNTIF(F6:F75,">0")-COUNTIF(F6:F75,">442") -> 0 | Q15: =COUNTIF(G6:G75,">0")-COUNTIF(G6:G75,">442") -> 0 | R15: =COUNTIF(H6:H75,">0")-COUNTIF(H6:H75,">442") -> 0
A16: 11 | D16: 4052.7705 | E16: 24 | F16: =IFERROR(($Q$6+1)*B16/$E16,0) -> 0 | G16: =IFERROR(($Q$6+1)*C16/$E16,0) -> 0 | H16: =IFERROR(($Q$6+1)*D16/$E16,0) -> 653.61778 | I16: =IF(F16>0,1,"") | J16: =IF(AND(G16>0,G16<442),1,IF(AND(G16>=442,G16<=642),2,IF(G16>642,3,""))) | K16: =IF(AND(H16>0,H16<442),1,IF(AND(H16>=442,H16<=642),2,IF(H16>642,3,""))) -> 3 | M16: 442 | N16: à | O16: 642 | P16: =COUNTIF(F6:F75,">=442")-COUNTIF(F6:F75,">=642") -> 0 | Q16: =COUNTIF(G6:G75,">=442")-COUNTIF(G6:G75,">=642") -> 0 | R16: =COUNTIF(H6:H75,">=442")-COUNTIF(H6:H75,">=642") -> 0
A17: 12 | D17: 4052.7705 | E17: 24 | F17: =IFERROR(($Q$6+1)*B17/$E17,0) -> 0 | G17: =IFERROR(($Q$6+1)*C17/$E17,0) -> 0 | H17: =IFERROR(($Q$6+1)*D17/$E17,0) -> 653.61778 | I17: =IF(F17>0,1,"") | J17: =IF(AND(G17>0,G17<442),1,IF(AND(G17>=442,G17<=642),2,IF(G17>642,3,""))) | K17: =IF(AND(H17>0,H17<442),1,IF(AND(H17>=442,H17<=642),2,IF(H17>642,3,""))) -> 3 | M17: > | O17: 642 | P17: =COUNTIF(F6:F75,">642") -> 0 | Q17: =COUNTIF(G6:G75,">642") -> 0 | R17: =COUNTIF(H6:H75,">642") -> 29
A18: 13 | D18: 4052.7705 | E18: 24 | F18: =IFERROR(($Q$6+1)*B18/$E18,0) -> 0 | G18: =IFERROR(($Q$6+1)*C18/$E18,0) -> 0 | H18: =IFERROR(($Q$6+1)*D18/$E18,0) -> 653.61778 | I18: =IF(F18>0,1,"") | J18: =IF(AND(G18>0,G18<442),1,IF(AND(G18>=442,G18<=642),2,IF(G18>642,3,""))) | K18: =IF(AND(H18>0,H18<442),1,IF(AND(H18>=442,H18<=642),2,IF(H18>642,3,""))) -> 3
A19: 14 | D19: 4052.7705 | E19: 24 | F19: =IFERROR(($Q$6+1)*B19/$E19,0) -> 0 | G19: =IFERROR(($Q$6+1)*C19/$E19,0) -> 0 | H19: =IFERROR(($Q$6+1)*D19/$E19,0) -> 653.61778 | I19: =IF(F19>0,1,"") | J19: =IF(AND(G19>0,G19<442),1,IF(AND(G19>=442,G19<=642),2,IF(G19>642,3,""))) | K19: =IF(AND(H19>0,H19<442),1,IF(AND(H19>=442,H19<=642),2,IF(H19>642,3,""))) -> 3 | M19: Journées-participants (JP) selon cat. et critères d'attribution.
A20: 15 | D20: 4052.7705 | E20: 24 | F20: =IFERROR(($Q$6+1)*B20/$E20,0) -> 0 | G20: =IFERROR(($Q$6+1)*C20/$E20,0) -> 0 | H20: =IFERROR(($Q$6+1)*D20/$E20,0) -> 653.61778 | I20: =IF(F20>0,1,"") | J20: =IF(AND(G20>0,G20<442),1,IF(AND(G20>=442,G20<=642),2,IF(G20>642,3,""))) | K20: =IF(AND(H20>0,H20<442),1,IF(AND(H20>=442,H20<=642),2,IF(H20>642,3,""))) -> 3 | O20: A | P20: B | Q20: C
A21: 16 | D21: 3715.0396 | E21: 22 | F21: =IFERROR(($Q$6+1)*B21/$E21,0) -> 0 | G21: =IFERROR(($Q$6+1)*C21/$E21,0) -> 0 | H21: =IFERROR(($Q$6+1)*D21/$E21,0) -> 653.61778 | I21: =IF(F21>0,1,"") | J21: =IF(AND(G21>0,G21<442),1,IF(AND(G21>=442,G21<=642),2,IF(G21>642,3,""))) | K21: =IF(AND(H21>0,H21<442),1,IF(AND(H21>=442,H21<=642),2,IF(H21>642,3,""))) -> 3 | M21: Cat1 | O21: =SUMIF(I6:I75,1,$E6:$E75) -> 0 | P21: =SUMIF(J6:J75,1,$E6:$E75) -> 0 | Q21: =SUMIF(K6:K75,1,$E6:$E75) -> 0
A22: 17 | D22: 3715.0396 | E22: 22 | F22: =IFERROR(($Q$6+1)*B22/$E22,0) -> 0 | G22: =IFERROR(($Q$6+1)*C22/$E22,0) -> 0 | H22: =IFERROR(($Q$6+1)*D22/$E22,0) -> 653.61778 | I22: =IF(F22>0,1,"") | J22: =IF(AND(G22>0,G22<442),1,IF(AND(G22>=442,G22<=642),2,IF(G22>642,3,""))) | K22: =IF(AND(H22>0,H22<442),1,IF(AND(H22>=442,H22<=642),2,IF(H22>642,3,""))) -> 3 | M22: Cat2 | O22: - | P22: =SUMIF(J6:J75,2,$E6:$E75) -> 0 | Q22: =SUMIF(K6:K75,2,$E6:$E75) -> 0
A23: 18 | D23: 4052.7705 | E23: 24 | F23: =IFERROR(($Q$6+1)*B23/$E23,0) -> 0 | G23: =IFERROR(($Q$6+1)*C23/$E23,0) -> 0 | H23: =IFERROR(($Q$6+1)*D23/$E23,0) -> 653.61778 | I23: =IF(F23>0,1,"") | J23: =IF(AND(G23>0,G23<442),1,IF(AND(G23>=442,G23<=642),2,IF(G23>642,3,""))) | K23: =IF(AND(H23>0,H23<442),1,IF(AND(H23>=442,H23<=642),2,IF(H23>642,3,""))) -> 3 | M23: Cat3 | O23: - | P23: - | Q23: =SUMIF(K6:K75,3,$E6:$E75) -> 941
A24: 19 | D24: 4052.7705 | E24: 24 | F24: =IFERROR(($Q$6+1)*B24/$E24,0) -> 0 | G24: =IFERROR(($Q$6+1)*C24/$E24,0) -> 0 | H24: =IFERROR(($Q$6+1)*D24/$E24,0) -> 653.61778 | I24: =IF(F24>0,1,"") | J24: =IF(AND(G24>0,G24<442),1,IF(AND(G24>=442,G24<=642),2,IF(G24>642,3,""))) | K24: =IF(AND(H24>0,H24<442),1,IF(AND(H24>=442,H24<=642),2,IF(H24>642,3,""))) -> 3
A25: 20 | D25: 3715.0396 | E25: 22 | F25: =IFERROR(($Q$6+1)*B25/$E25,0) -> 0 | G25: =IFERROR(($Q$6+1)*C25/$E25,0) -> 0 | H25: =IFERROR(($Q$6+1)*D25/$E25,0) -> 653.61778 | I25: =IF(F25>0,1,"") | J25: =IF(AND(G25>0,G25<442),1,IF(AND(G25>=442,G25<=642),2,IF(G25>642,3,""))) | K25: =IF(AND(H25>0,H25<442),1,IF(AND(H25>=442,H25<=642),2,IF(H25>642,3,""))) -> 3 | M25: Coûts totaux (CT) selon catégorie et critères d'imputation | R25: Total
A26: 21 | D26: 4052.7705 | E26: 24 | F26: =IFERROR(($Q$6+1)*B26/$E26,0) -> 0 | G26: =IFERROR(($Q$6+1)*C26/$E26,0) -> 0 | H26: =IFERROR(($Q$6+1)*D26/$E26,0) -> 653.61778 | I26: =IF(F26>0,1,"") | J26: =IF(AND(G26>0,G26<442),1,IF(AND(G26>=442,G26<=642),2,IF(G26>642,3,""))) | K26: =IF(AND(H26>0,H26<442),1,IF(AND(H26>=442,H26<=642),2,IF(H26>642,3,""))) -> 3 | O26: A | P26: B | Q26: C
A27: 22 | D27: 6752.7085 | E27: 36 | F27: =IFERROR(($Q$6+1)*B27/$E27,0) -> 0 | G27: =IFERROR(($Q$6+1)*C27/$E27,0) -> 0 | H27: =IFERROR(($Q$6+1)*D27/$E27,0) -> 726.03672 | I27: =IF(F27>0,1,"") | J27: =IF(AND(G27>0,G27<442),1,IF(AND(G27>=442,G27<=642),2,IF(G27>642,3,""))) | K27: =IF(AND(H27>0,H27<442),1,IF(AND(H27>=442,H27<=642),2,IF(H27>642,3,""))) -> 3 | M27: Cat1 | O27: =SUMIF(I6:I75,1,B6:B75)*(1+$Q$6) -> 0 | P27: =SUMIF(J6:J75,1,C6:C75)*(1+$Q$6) -> 0 | Q27: =SUMIF(K6:K75,1,D6:D75)*(1+$Q$6) -> 0 | R27: =SUM(O27:Q27) -> 0
A28: 23 | D28: 8253.3103 | E28: 44 | F28: =IFERROR(($Q$6+1)*B28/$E28,0) -> 0 | G28: =IFERROR(($Q$6+1)*C28/$E28,0) -> 0 | H28: =IFERROR(($Q$6+1)*D28/$E28,0) -> 726.03672 | I28: =IF(F28>0,1,"") | J28: =IF(AND(G28>0,G28<442),1,IF(AND(G28>=442,G28<=642),2,IF(G28>642,3,""))) | K28: =IF(AND(H28>0,H28<442),1,IF(AND(H28>=442,H28<=642),2,IF(H28>642,3,""))) -> 3 | M28: Cat2 | O28: - | P28: =SUMIF(J6:J75,2,C6:C75)*(1+$Q$6) -> 0 | Q28: =SUMIF(K6:K75,2,D6:D75)*(1+$Q$6) -> 0 | R28: =SUM(O28:Q28) -> 0
A29: 24 | D29: 12379.966 | E29: 66 | F29: =IFERROR(($Q$6+1)*B29/$E29,0) -> 0 | G29: =IFERROR(($Q$6+1)*C29/$E29,0) -> 0 | H29: =IFERROR(($Q$6+1)*D29/$E29,0) -> 726.03672 | I29: =IF(F29>0,1,"") | J29: =IF(AND(G29>0,G29<442),1,IF(AND(G29>=442,G29<=642),2,IF(G29>642,3,""))) | K29: =IF(AND(H29>0,H29<442),1,IF(AND(H29>=442,H29<=642),2,IF(H29>642,3,""))) -> 3 | M29: Cat3 | O29: - | P29: - | Q29: =SUMIF(K6:K75,3,D6:D75)*(1+$Q$6) -> 647425.6 | R29: =SUM(O29:Q29) -> 647425.6
A30: 25 | D30: 15756.32 | E30: 84 | F30: =IFERROR(($Q$6+1)*B30/$E30,0) -> 0 | G30: =IFERROR(($Q$6+1)*C30/$E30,0) -> 0 | H30: =IFERROR(($Q$6+1)*D30/$E30,0) -> 726.03672 | I30: =IF(F30>0,1,"") | J30: =IF(AND(G30>0,G30<442),1,IF(AND(G30>=442,G30<=642),2,IF(G30>642,3,""))) | K30: =IF(AND(H30>0,H30<442),1,IF(AND(H30>=442,H30<=642),2,IF(H30>642,3,""))) -> 3 | R30: =SUM(R27:R29) -> 647425.6
A31: 26 | D31: 6752.7085 | E31: 36 | F31: =IFERROR(($Q$6+1)*B31/$E31,0) -> 0 | G31: =IFERROR(($Q$6+1)*C31/$E31,0) -> 0 | H31: =IFERROR(($Q$6+1)*D31/$E31,0) -> 726.03672 | I31: =IF(F31>0,1,"") | J31: =IF(AND(G31>0,G31<442),1,IF(AND(G31>=442,G31<=642),2,IF(G31>642,3,""))) | K31: =IF(AND(H31>0,H31<442),1,IF(AND(H31>=442,H31<=642),2,IF(H31>642,3,""))) -> 3
A32: 27 | D32: 15006.019 | E32: 80 | F32: =IFERROR(($Q$6+1)*B32/$E32,0) -> 0 | G32: =IFERROR(($Q$6+1)*C32/$E32,0) -> 0 | H32: =IFERROR(($Q$6+1)*D32/$E32,0) -> 726.03672 | I32: =IF(F32>0,1,"") | J32: =IF(AND(G32>0,G32<442),1,IF(AND(G32>=442,G32<=642),2,IF(G32>642,3,""))) | K32: =IF(AND(H32>0,H32<442),1,IF(AND(H32>=442,H32<=642),2,IF(H32>642,3,""))) -> 3 | M32: Données pour le reporting
A33: 28 | D33: 4501.8056 | E33: 24 | F33: =IFERROR(($Q$6+1)*B33/$E33,0) -> 0 | G33: =IFERROR(($Q$6+1)*C33/$E33,0) -> 0 | H33: =IFERROR(($Q$6+1)*D33/$E33,0) -> 726.03672 | I33: =IF(F33>0,1,"") | J33: =IF(AND(G33>0,G33<442),1,IF(AND(G33>=442,G33<=642),2,IF(G33>642,3,""))) | K33: =IF(AND(H33>0,H33<442),1,IF(AND(H33>=442,H33<=642),2,IF(H33>642,3,""))) -> 3 | M33: Catégorie | O33: Nombre de cours | P33: journées participant | Q33: Coûts totaux
A34: 29 | D34: 14443.293 | E34: 77 | F34: =IFERROR(($Q$6+1)*B34/$E34,0) -> 0 | G34: =IFERROR(($Q$6+1)*C34/$E34,0) -> 0 | H34: =IFERROR(($Q$6+1)*D34/$E34,0) -> 726.03672 | I34: =IF(F34>0,1,"") | J34: =IF(AND(G34>0,G34<442),1,IF(AND(G34>=442,G34<=642),2,IF(G34>642,3,""))) | K34: =IF(AND(H34>0,H34<442),1,IF(AND(H34>=442,H34<=642),2,IF(H34>642,3,""))) -> 3 | M34: 1 | O34: =SUM(P15:R15,P16,P17) -> 0 | P34: =SUM(O21:Q21) -> 0 | Q34: =R27 -> 0
A35: 30 | F35: =IFERROR(($Q$6+1)*B35/$E35,0) -> 0 | G35: =IFERROR(($Q$6+1)*C35/$E35,0) -> 0 | H35: =IFERROR(($Q$6+1)*D35/$E35,0) -> 0 | I35: =IF(F35>0,1,"") | J35: =IF(AND(G35>0,G35<442),1,IF(AND(G35>=442,G35<=642),2,IF(G35>642,3,""))) | K35: =IF(AND(H35>0,H35<442),1,IF(AND(H35>=442,H35<=642),2,IF(H35>642,3,""))) | M35: 2 | O35: =SUM(Q16:R16,Q17) -> 0 | P35: =SUM(O22:Q22) -> 0 | Q35: =R28 -> 0
A36: 31 | F36: =IFERROR(($Q$6+1)*B36/$E36,0) -> 0 | G36: =IFERROR(($Q$6+1)*C36/$E36,0) -> 0 | H36: =IFERROR(($Q$6+1)*D36/$E36,0) -> 0 | I36: =IF(F36>0,1,"") | J36: =IF(AND(G36>0,G36<442),1,IF(AND(G36>=442,G36<=642),2,IF(G36>642,3,""))) | K36: =IF(AND(H36>0,H36<442),1,IF(AND(H36>=442,H36<=642),2,IF(H36>642,3,""))) | M36: 3 | O36: =R17 -> 29 | P36: =SUM(O23:Q23) -> 941 | Q36: =R29 -> 647425.6
A37: 32 | F37: =IFERROR(($Q$6+1)*B37/$E37,0) -> 0 | G37: =IFERROR(($Q$6+1)*C37/$E37,0) -> 0 | H37: =IFERROR(($Q$6+1)*D37/$E37,0) -> 0 | I37: =IF(F37>0,1,"") | J37: =IF(AND(G37>0,G37<442),1,IF(AND(G37>=442,G37<=642),2,IF(G37>642,3,""))) | K37: =IF(AND(H37>0,H37<442),1,IF(AND(H37>=442,H37<=642),2,IF(H37>642,3,"")))
A38: 33 | F38: =IFERROR(($Q$6+1)*B38/$E38,0) -> 0 | G38: =IFERROR(($Q$6+1)*C38/$E38,0) -> 0 | H38: =IFERROR(($Q$6+1)*D38/$E38,0) -> 0 | I38: =IF(F38>0,1,"") | J38: =IF(AND(G38>0,G38<442),1,IF(AND(G38>=442,G38<=642),2,IF(G38>642,3,""))) | K38: =IF(AND(H38>0,H38<442),1,IF(AND(H38>=442,H38<=642),2,IF(H38>642,3,"")))
A39: 34 | F39: =IFERROR(($Q$6+1)*B39/$E39,0) -> 0 | G39: =IFERROR(($Q$6+1)*C39/$E39,0) -> 0 | H39: =IFERROR(($Q$6+1)*D39/$E39,0) -> 0 | I39: =IF(F39>0,1,"") | J39: =IF(AND(G39>0,G39<442),1,IF(AND(G39>=442,G39<=642),2,IF(G39>642,3,""))) | K39: =IF(AND(H39>0,H39<442),1,IF(AND(H39>=442,H39<=642),2,IF(H39>642,3,"")))
A40: 35 | F40: =IFERROR(($Q$6+1)*B40/$E40,0) -> 0 | G40: =IFERROR(($Q$6+1)*C40/$E40,0) -> 0 | H40: =IFERROR(($Q$6+1)*D40/$E40,0) -> 0 | I40: =IF(F40>0,1,"") | J40: =IF(AND(G40>0,G40<442),1,IF(AND(G40>=442,G40<=642),2,IF(G40>642,3,""))) | K40: =IF(AND(H40>0,H40<442),1,IF(AND(H40>=442,H40<=642),2,IF(H40>642,3,"")))
A41: 36 | F41: =IFERROR(($Q$6+1)*B41/$E41,0) -> 0 | G41: =IFERROR(($Q$6+1)*C41/$E41,0) -> 0 | H41: =IFERROR(($Q$6+1)*D41/$E41,0) -> 0 | I41: =IF(F41>0,1,"") | J41: =IF(AND(G41>0,G41<442),1,IF(AND(G41>=442,G41<=642),2,IF(G41>642,3,""))) | K41: =IF(AND(H41>0,H41<442),1,IF(AND(H41>=442,H41<=642),2,IF(H41>642,3,"")))
A42: 37 | F42: =IFERROR(($Q$6+1)*B42/$E42,0) -> 0 | G42: =IFERROR(($Q$6+1)*C42/$E42,0) -> 0 | H42: =IFERROR(($Q$6+1)*D42/$E42,0) -> 0 | I42: =IF(F42>0,1,"") | J42: =IF(AND(G42>0,G42<442),1,IF(AND(G42>=442,G42<=642),2,IF(G42>642,3,""))) | K42: =IF(AND(H42>0,H42<442),1,IF(AND(H42>=442,H42<=642),2,IF(H42>642,3,"")))
A43: 38 | F43: =IFERROR(($Q$6+1)*B43/$E43,0) -> 0 | G43: =IFERROR(($Q$6+1)*C43/$E43,0) -> 0 | H43: =IFERROR(($Q$6+1)*D43/$E43,0) -> 0 | I43: =IF(F43>0,1,"") | J43: =IF(AND(G43>0,G43<442),1,IF(AND(G43>=442,G43<=642),2,IF(G43>642,3,""))) | K43: =IF(AND(H43>0,H43<442),1,IF(AND(H43>=442,H43<=642),2,IF(H43>642,3,"")))
A44: 39 | F44: =IFERROR(($Q$6+1)*B44/$E44,0) -> 0 | G44: =IFERROR(($Q$6+1)*C44/$E44,0) -> 0 | H44: =IFERROR(($Q$6+1)*D44/$E44,0) -> 0 | I44: =IF(F44>0,1,"") | J44: =IF(AND(G44>0,G44<442),1,IF(AND(G44>=442,G44<=642),2,IF(G44>642,3,""))) | K44: =IF(AND(H44>0,H44<442),1,IF(AND(H44>=442,H44<=642),2,IF(H44>642,3,"")))
A45: 40 | F45: =IFERROR(($Q$6+1)*B45/$E45,0) -> 0 | G45: =IFERROR(($Q$6+1)*C45/$E45,0) -> 0 | H45: =IFERROR(($Q$6+1)*D45/$E45,0) -> 0 | I45: =IF(F45>0,1,"") | J45: =IF(AND(G45>0,G45<442),1,IF(AND(G45>=442,G45<=642),2,IF(G45>642,3,""))) | K45: =IF(AND(H45>0,H45<442),1,IF(AND(H45>=442,H45<=642),2,IF(H45>642,3,"")))
A46: 41 | F46: =IFERROR(($Q$6+1)*B46/$E46,0) -> 0 | G46: =IFERROR(($Q$6+1)*C46/$E46,0) -> 0 | H46: =IFERROR(($Q$6+1)*D46/$E46,0) -> 0 | I46: =IF(F46>0,1,"") | J46: =IF(AND(G46>0,G46<442),1,IF(AND(G46>=442,G46<=642),2,IF(G46>642,3,""))) | K46: =IF(AND(H46>0,H46<442),1,IF(AND(H46>=442,H46<=642),2,IF(H46>642,3,"")))
A47: 42 | F47: =IFERROR(($Q$6+1)*B47/$E47,0) -> 0 | G47: =IFERROR(($Q$6+1)*C47/$E47,0) -> 0 | H47: =IFERROR(($Q$6+1)*D47/$E47,0) -> 0 | I47: =IF(F47>0,1,"") | J47: =IF(AND(G47>0,G47<442),1,IF(AND(G47>=442,G47<=642),2,IF(G47>642,3,""))) | K47: =IF(AND(H47>0,H47<442),1,IF(AND(H47>=442,H47<=642),2,IF(H47>642,3,"")))
A48: 43 | F48: =IFERROR(($Q$6+1)*B48/$E48,0) -> 0 | G48: =IFERROR(($Q$6+1)*C48/$E48,0) -> 0 | H48: =IFERROR(($Q$6+1)*D48/$E48,0) -> 0 | I48: =IF(F48>0,1,"") | J48: =IF(AND(G48>0,G48<442),1,IF(AND(G48>=442,G48<=642),2,IF(G48>642,3,""))) | K48: =IF(AND(H48>0,H48<442),1,IF(AND(H48>=442,H48<=642),2,IF(H48>642,3,"")))
... A75: 70 | F75: =IFERROR(($Q$6+1)*B75/$E75,0) -> 0 | G75: =IFERROR(($Q$6+1)*C75/$E75,0) -> 0 | H75: =IFERROR(($Q$6+1)*D75/$E75,0) -> 0 | I75: =IF(F75>0,1,"") | J75: =IF(AND(G75>0,G75<442),1,IF(AND(G75>=442,G75<=642),2,IF(G75>642,3,""))) | K75: =IF(AND(H75>0,H75<442),1,IF(AND(H75>=442,H75<=642),2,IF(H75>642,3,"")))

Sheet Auswertungstool Tageskurse
A1: Analyse Cours d'un jour | D1: Le fait de remplir ce tableau est à bien plaire
B2: Coûts totaux/coûts de mise en oeuvre par cours | E2: Nombre journées participant(e)s (ayants droit et non ayants droit) | F2: Coûts totaux par journée-participant | I2: Affectation à une catégorie
M3: Cacul du supplément frais indirects:
B4: Critères d'attribution | F4: Critères d'attribution | I4: Critères d'attribution | M4: Total des coûts de mise en œuvre | Q4: =SUM(B6:D75) -> 28497.15
A5: Cours | B5: A | C5: B | D5: C | F5: A | G5: B | H5: C | I5: A | J5: B | K5: C | M5: Total coûts indirects
A6: 1 | D6: 1499.85 | E6: 11 | F6: =IFERROR(($Q$6+1)*B6/$E6,0) -> 0 | G6: =IFERROR(($Q$6+1)*C6/$E6,0) -> 0 | H6: =IFERROR(($Q$6+1)*D6/$E6,0) -> 503.83338 | I6: =IF(F6>0,1,"") | J6: =IF(AND(G6>0,G6<341),1,IF(AND(G6>=341,G6<=474),2,IF(G6>474,2,""))) | K6: =IF(AND(H6>0,H6<341),1,IF(AND(H6>=341,H6<=474),2,IF(H6>474,3,""))) -> 3 | M6: supplément coûts indirects | Q6: =IFERROR(IF(R6>0,R6,Q5/Q4),0) -> 2.6951477 | R6: 2.6951477
A7: 2 | D7: 1499.85 | E7: 12 | F7: =IFERROR(($Q$6+1)*B7/$E7,0) -> 0 | G7: =IFERROR(($Q$6+1)*C7/$E7,0) -> 0 | H7: =IFERROR(($Q$6+1)*D7/$E7,0) -> 461.84727 | I7: =IF(F7>0,1,"") | J7: =IF(AND(G7>0,G7<341),1,IF(AND(G7>=341,G7<=474),2,IF(G7>474,2,""))) | K7: =IF(AND(H7>0,H7<341),1,IF(AND(H7>=341,H7<=474),2,IF(H7>474,3,""))) -> 2
A8: 3 | D8: 1499.85 | E8: 11 | F8: =IFERROR(($Q$6+1)*B8/$E8,0) -> 0 | G8: =IFERROR(($Q$6+1)*C8/$E8,0) -> 0 | H8: =IFERROR(($Q$6+1)*D8/$E8,0) -> 503.83338 | I8: =IF(F8>0,1,"") | J8: =IF(AND(G8>0,G8<341),1,IF(AND(G8>=341,G8<=474),2,IF(G8>474,2,""))) | K8: =IF(AND(H8>0,H8<341),1,IF(AND(H8>=341,H8<=474),2,IF(H8>474,3,""))) -> 3 | M8: Coûts totaux/ unités de prestations. | O8: Critères d'attribution cours d'un jour
A9: 4 | D9: 1499.85 | E9: 12 | F9: =IFERROR(($Q$6+1)*B9/$E9,0) -> 0 | G9: =IFERROR(($Q$6+1)*C9/$E9,0) -> 0 | H9: =IFERROR(($Q$6+1)*D9/$E9,0) -> 461.84727 | I9: =IF(F9>0,1,"") | J9: =IF(AND(G9>0,G9<341),1,IF(AND(G9>=341,G9<=474),2,IF(G9>474,2,""))) | K9: =IF(AND(H9>0,H9<341),1,IF(AND(H9>=341,H9<=474),2,IF(H9>474,3,""))) -> 2 | O9: A | P9: B | Q9: C
A10: 5 | D10: 1499.85 | E10: 7 | F10: =IFERROR(($Q$6+1)*B10/$E10,0) -> 0 | G10: =IFERROR(($Q$6+1)*C10/$E10,0) -> 0 | H10: =IFERROR(($Q$6+1)*D10/$E10,0) -> 791.73817 | I10: =IF(F10>0,1,"") | J10: =IF(AND(G10>0,G10<341),1,IF(AND(G10>=341,G10<=474),2,IF(G10>474,2,""))) | K10: =IF(AND(H10>0,H10<341),1,IF(AND(H10>=341,H10<=474),2,IF(H10>474,3,""))) -> 3 | M10: < 341 | O10: Cat 1 | P10: Cat 1 | Q10: Cat 1
A11: 6 | D11: 1499.85 | E11: 9 | F11: =IFERROR(($Q$6+1)*B11/$E11,0) -> 0 | G11: =IFERROR(($Q$6+1)*C11/$E11,0) -> 0 | H11: =IFERROR(($Q$6+1)*D11/$E11,0) -> 615.79636 | I11: =IF(F11>0,1,"") | J11: =IF(AND(G11>0,G11<341),1,IF(AND(G11>=341,G11<=474),2,IF(G11>474,2,""))) | K11: =IF(AND(H11>0,H11<341),1,IF(AND(H11>=341,H11<=474),2,IF(H11>474,3,""))) -> 3 | M11: 341 à 474 | O11: Cat 1 | P11: Cat 2 | Q11: Cat 2
A12: 7 | D12: 1499.85 | E12: 10 | F12: =IFERROR(($Q$6+1)*B12/$E12,0) -> 0 | G12: =IFERROR(($Q$6+1)*C12/$E12,0) -> 0 | H12: =IFERROR(($Q$6+1)*D12/$E12,0) -> 554.21672 | I12: =IF(F12>0,1,"") | J12: =IF(AND(G12>0,G12<341),1,IF(AND(G12>=341,G12<=474),2,IF(G12>474,2,""))) | K12: =IF(AND(H12>0,H12<341),1,IF(AND(H12>=341,H12<=474),2,IF(H12>474,3,""))) -> 3 | M12: > 474 | O12: Cat 1 | P12: Cat 2 | Q12: Cat 3
A13: 8 | D13: 1499.85 | E13: 9 | F13: =IFERROR(($Q$6+1)*B13/$E13,0) -> 0 | G13: =IFERROR(($Q$6+1)*C13/$E13,0) -> 0 | H13: =IFERROR(($Q$6+1)*D13/$E13,0) -> 615.79636 | I13: =IF(F13>0,1,"") | J13: =IF(AND(G13>0,G13<341),1,IF(AND(G13>=341,G13<=474),2,IF(G13>474,2,""))) | K13: =IF(AND(H13>0,H13<341),1,IF(AND(H13>=341,H13<=474),2,IF(H13>474,3,""))) -> 3
A14: 9 | D14: 1499.85 | E14: 11 | F14: =IFERROR(($Q$6+1)*B14/$E14,0) -> 0 | G14: =IFERROR(($Q$6+1)*C14/$E14,0) -> 0 | H14: =IFERROR(($Q$6+1)*D14/$E14,0) -> 503.83338 | I14: =IF(F14>0,1,"") | J14: =IF(AND(G14>0,G14<341),1,IF(AND(G14>=341,G14<=474),2,IF(G14>474,2,""))) | K14: =IF(AND(H14>0,H14<341),1,IF(AND(H14>=341,H14<=474),2,IF(H14>474,3,""))) -> 3 | M14: Statistique des cours | P14: A | Q14: B | R14: C
A15: 10 | D15: 1499.85 | E15: 10 | F15: =IFERROR(($Q$6+1)*B15/$E15,0) -> 0 | G15: =IFERROR(($Q$6+1)*C15/$E15,0) -> 0 | H15: =IFERROR(($Q$6+1)*D15/$E15,0) -> 554.21672 | I15: =IF(F15>0,1,"") | J15: =IF(AND(G15>0,G15<341),1,IF(AND(G15>=341,G15<=474),2,IF(G15>474,2,""))) | K15: =IF(AND(H15>0,H15<341),1,IF(AND(H15>=341,H15<=474),2,IF(H15>474,3,""))) -> 3 | M15: < | O15: 341 | P15: =COUNTIF(F6:F75,">0")-COUNTIF(F6:F75,">341") -> 0 | Q15: =COUNTIF(G6:G75,">0")-COUNTIF(G6:G75,">341") -> 0 | R15: =COUNTIF(H6:H75,">0")-COUNTIF(H6:H75,">341") -> 0
A16: 11 | D16: 1499.85 | E16: 10 | F16: =IFERROR(($Q$6+1)*B16/$E16,0) -> 0 | G16: =IFERROR(($Q$6+1)*C16/$E16,0) -> 0 | H16: =IFERROR(($Q$6+1)*D16/$E16,0) -> 554.21672 | I16: =IF(F16>0,1,"") | J16: =IF(AND(G16>0,G16<341),1,IF(AND(G16>=341,G16<=474),2,IF(G16>474,2,""))) | K16: =IF(AND(H16>0,H16<341),1,IF(AND(H16>=341,H16<=474),2,IF(H16>474,3,""))) -> 3 | M16: 341 | N16: à | O16: 474 | P16: =COUNTIF(F6:F75,">=341")-COUNTIF(F6:F75,">=474") -> 0 | Q16: =COUNTIF(G6:G75,">=341")-COUNTIF(G6:G75,">=474") -> 0 | R16: =COUNTIF(H6:H75,">=341")-COUNTIF(H6:H75,">=474") -> 4
A17: 12 | D17: 1499.85 | E17: 10 | F17: =IFERROR(($Q$6+1)*B17/$E17,0) -> 0 | G17: =IFERROR(($Q$6+1)*C17/$E17,0) -> 0 | H17: =IFERROR(($Q$6+1)*D17/$E17,0) -> 554.21672 | I17: =IF(F17>0,1,"") | J17: =IF(AND(G17>0,G17<341),1,IF(AND(G17>=341,G17<=474),2,IF(G17>474,2,""))) | K17: =IF(AND(H17>0,H17<341),1,IF(AND(H17>=341,H17<=474),2,IF(H17>474,3,""))) -> 3 | M17: > | O17: 474 | P17: =COUNTIF(F6:F75,">474") -> 0 | Q17: =COUNTIF(G6:G75,">474") -> 0 | R17: =COUNTIF(H6:H75,">474") -> 15
A18: 13 | D18: 1499.85 | E18: 8 | F18: =IFERROR(($Q$6+1)*B18/$E18,0) -> 0 | G18: =IFERROR(($Q$6+1)*C18/$E18,0) -> 0 | H18: =IFERROR(($Q$6+1)*D18/$E18,0) -> 692.7709 | I18: =IF(F18>0,1,"") | J18: =IF(AND(G18>0,G18<341),1,IF(AND(G18>=341,G18<=474),2,IF(G18>474,2,""))) | K18: =IF(AND(H18>0,H18<341),1,IF(AND(H18>=341,H18<=474),2,IF(H18>474,3,""))) -> 3
A19: 14 | D19: 1499.85 | E19: 10 | F19: =IFERROR(($Q$6+1)*B19/$E19,0) -> 0 | G19: =IFERROR(($Q$6+1)*C19/$E19,0) -> 0 | H19: =IFERROR(($Q$6+1)*D19/$E19,0) -> 554.21672 | I19: =IF(F19>0,1,"") | J19: =IF(AND(G19>0,G19<341),1,IF(AND(G19>=341,G19<=474),2,IF(G19>474,2,""))) | K19: =IF(AND(H19>0,H19<341),1,IF(AND(H19>=341,H19<=474),2,IF(H19>474,3,""))) -> 3 | M19: Journées-participants (JP) selon cat. et critères d'imputation.
A20: 15 | D20: 1499.85 | E20: 13 | F20: =IFERROR(($Q$6+1)*B20/$E20,0) -> 0 | G20: =IFERROR(($Q$6+1)*C20/$E20,0) -> 0 | H20: =IFERROR(($Q$6+1)*D20/$E20,0) -> 426.32056 | I20: =IF(F20>0,1,"") | J20: =IF(AND(G20>0,G20<341),1,IF(AND(G20>=341,G20<=474),2,IF(G20>474,2,""))) | K20: =IF(AND(H20>0,H20<341),1,IF(AND(H20>=341,H20<=474),2,IF(H20>474,3,""))) -> 2 | O20: A | P20: B | Q20: C
A21: 16 | D21: 1499.85 | E21: 12 | F21: =IFERROR(($Q$6+1)*B21/$E21,0) -> 0 | G21: =IFERROR(($Q$6+1)*C21/$E21,0) -> 0 | H21: =IFERROR(($Q$6+1)*D21/$E21,0) -> 461.84727 | I21: =IF(F21>0,1,"") | J21: =IF(AND(G21>0,G21<341),1,IF(AND(G21>=341,G21<=474),2,IF(G21>474,2,""))) | K21: =IF(AND(H21>0,H21<341),1,IF(AND(H21>=341,H21<=474),2,IF(H21>474,3,""))) -> 2 | M21: Cat1 | O21: =SUMIF(I6:I75,1,$E6:$E75) -> 0 | P21: =SUMIF(J6:J75,1,$E6:$E75) -> 0 | Q21: =SUMIF(K6:K75,1,$E6:$E75) -> 0
A22: 17 | D22: 1499.85 | E22: 9 | F22: =IFERROR(($Q$6+1)*B22/$E22,0) -> 0 | G22: =IFERROR(($Q$6+1)*C22/$E22,0) -> 0 | H22: =IFERROR(($Q$6+1)*D22/$E22,0) -> 615.79636 | I22: =IF(F22>0,1,"") | J22: =IF(AND(G22>0,G22<341),1,IF(AND(G22>=341,G22<=474),2,IF(G22>474,2,""))) | K22: =IF(AND(H22>0,H22<341),1,IF(AND(H22>=341,H22<=474),2,IF(H22>474,3,""))) -> 3 | M22: Cat2 | O22: - | P22: =SUMIF(J6:J75,2,$E6:$E75) -> 0 | Q22: =SUMIF(K6:K75,2,$E6:$E75) -> 49
A23: 18 | D23: 1499.85 | E23: 8 | F23: =IFERROR(($Q$6+1)*B23/$E23,0) -> 0 | G23: =IFERROR(($Q$6+1)*C23/$E23,0) -> 0 | H23: =IFERROR(($Q$6+1)*D23/$E23,0) -> 692.7709 | I23: =IF(F23>0,1,"") | J23: =IF(AND(G23>0,G23<341),1,IF(AND(G23>=341,G23<=474),2,IF(G23>474,2,""))) | K23: =IF(AND(H23>0,H23<341),1,IF(AND(H23>=341,H23<=474),2,IF(H23>474,3,""))) -> 3 | M23: Cat3 | O23: - | P23: - | Q23: =SUMIF(K6:K75,3,$E6:$E75) -> 142
A24: 19 | D24: 1499.85 | E24: 9 | F24: =IFERROR(($Q$6+1)*B24/$E24,0) -> 0 | G24: =IFERROR(($Q$6+1)*C24/$E24,0) -> 0 | H24: =IFERROR(($Q$6+1)*D24/$E24,0) -> 615.79636 | I24: =IF(F24>0,1,"") | J24: =IF(AND(G24>0,G24<341),1,IF(AND(G24>=341,G24<=474),2,IF(G24>474,2,""))) | K24: =IF(AND(H24>0,H24<341),1,IF(AND(H24>=341,H24<=474),2,IF(H24>474,3,""))) -> 3
A25: 20 | F25: =IFERROR(($Q$6+1)*B25/$E25,0) -> 0 | G25: =IFERROR(($Q$6+1)*C25/$E25,0) -> 0 | H25: =IFERROR(($Q$6+1)*D25/$E25,0) -> 0 | I25: =IF(F25>0,1,"") | J25: =IF(AND(G25>0,G25<341),1,IF(AND(G25>=341,G25<=474),2,IF(G25>474,2,""))) | K25: =IF(AND(H25>0,H25<341),1,IF(AND(H25>=341,H25<=474),2,IF(H25>474,3,""))) | M25: Coûts totaux (CT) selon catégorie et critères d'imputation | R25: Total
A26: 21 | F26: =IFERROR(($Q$6+1)*B26/$E26,0) -> 0 | G26: =IFERROR(($Q$6+1)*C26/$E26,0) -> 0 | H26: =IFERROR(($Q$6+1)*D26/$E26,0) -> 0 | I26: =IF(F26>0,1,"") | J26: =IF(AND(G26>0,G26<341),1,IF(AND(G26>=341,G26<=474),2,IF(G26>474,2,""))) | K26: =IF(AND(H26>0,H26<341),1,IF(AND(H26>=341,H26<=474),2,IF(H26>474,3,""))) | O26: A | P26: B | Q26: C
A27: 22 | F27: =IFERROR(($Q$6+1)*B27/$E27,0) -> 0 | G27: =IFERROR(($Q$6+1)*C27/$E27,0) -> 0 | H27: =IFERROR(($Q$6+1)*D27/$E27,0) -> 0 | I27: =IF(F27>0,1,"") | J27: =IF(AND(G27>0,G27<341),1,IF(AND(G27>=341,G27<=474),2,IF(G27>474,2,""))) | K27: =IF(AND(H27>0,H27<341),1,IF(AND(H27>=341,H27<=474),2,IF(H27>474,3,""))) | M27: Cat1 | O27: =SUMIF(I6:I75,1,B6:B75)*(1+$Q$6) -> 0 | P27: =SUMIF(J6:J75,1,C6:C75)*(1+$Q$6) -> 0 | Q27: =SUMIF(K6:K75,1,D6:D75)*(1+$Q$6) -> 0 | R27: =SUM(O27:Q27) -> 0
A28: 23 | F28: =IFERROR(($Q$6+1)*B28/$E28,0) -> 0 | G28: =IFERROR(($Q$6+1)*C28/$E28,0) -> 0 | H28: =IFERROR(($Q$6+1)*D28/$E28,0) -> 0 | I28: =IF(F28>0,1,"") | J28: =IF(AND(G28>0,G28<341),1,IF(AND(G28>=341,G28<=474),2,IF(G28>474,2,""))) | K28: =IF(AND(H28>0,H28<341),1,IF(AND(H28>=341,H28<=474),2,IF(H28>474,3,""))) | M28: Cat2 | O28: - | P28: =SUMIF(J6:J75,2,C6:C75)*(1+$Q$6) -> 0 | Q28: =SUMIF(K6:K75,2,D6:D75)*(1+$Q$6) -> 22168.669 | R28: =SUM(O28:Q28) -> 22168.669
A29: 24 | F29: =IFERROR(($Q$6+1)*B29/$E29,0) -> 0 | G29: =IFERROR(($Q$6+1)*C29/$E29,0) -> 0 | H29: =IFERROR(($Q$6+1)*D29/$E29,0) -> 0 | I29: =IF(F29>0,1,"") | J29: =IF(AND(G29>0,G29<341),1,IF(AND(G29>=341,G29<=474),2,IF(G29>474,2,""))) | K29: =IF(AND(H29>0,H29<341),1,IF(AND(H29>=341,H29<=474),2,IF(H29>474,3,""))) | M29: Cat3 | O29: - | P29: - | Q29: =SUMIF(K6:K75,3,D6:D75)*(1+$Q$6) -> 83132.508 | R29: =SUM(O29:Q29) -> 83132.508
A30: 25 | F30: =IFERROR(($Q$6+1)*B30/$E30,0) -> 0 | G30: =IFERROR(($Q$6+1)*C30/$E30,0) -> 0 | H30: =IFERROR(($Q$6+1)*D30/$E30,0) -> 0 | I30: =IF(F30>0,1,"") | J30: =IF(AND(G30>0,G30<341),1,IF(AND(G30>=341,G30<=474),2,IF(G30>474,2,""))) | K30: =IF(AND(H30>0,H30<341),1,IF(AND(H30>=341,H30<=474),2,IF(H30>474,3,""))) | R30: =SUM(R27:R29) -> 105301.18
A31: 26 | F31: =IFERROR(($Q$6+1)*B31/$E31,0) -> 0 | G31: =IFERROR(($Q$6+1)*C31/$E31,0) -> 0 | H31: =IFERROR(($Q$6+1)*D31/$E31,0) -> 0 | I31: =IF(F31>0,1,"") | J31: =IF(AND(G31>0,G31<341),1,IF(AND(G31>=341,G31<=474),2,IF(G31>474,2,""))) | K31: =IF(AND(H31>0,H31<341),1,IF(AND(H31>=341,H31<=474),2,IF(H31>474,3,"")))
A32: 27 | F32: =IFERROR(($Q$6+1)*B32/$E32,0) -> 0 | G32: =IFERROR(($Q$6+1)*C32/$E32,0) -> 0 | H32: =IFERROR(($Q$6+1)*D32/$E32,0) -> 0 | I32: =IF(F32>0,1,"") | J32: =IF(AND(G32>0,G32<341),1,IF(AND(G32>=341,G32<=474),2,IF(G32>474,2,""))) | K32: =IF(AND(H32>0,H32<341),1,IF(AND(H32>=341,H32<=474),2,IF(H32>474,3,""))) | M32: Données pour le reporting
A33: 28 | F33: =IFERROR(($Q$6+1)*B33/$E33,0) -> 0 | G33: =IFERROR(($Q$6+1)*C33/$E33,0) -> 0 | H33: =IFERROR(($Q$6+1)*D33/$E33,0) -> 0 | I33: =IF(F33>0,1,"") | J33: =IF(AND(G33>0,G33<341),1,IF(AND(G33>=341,G33<=474),2,IF(G33>474,2,""))) | K33: =IF(AND(H33>0,H33<341),1,IF(AND(H33>=341,H33<=474),2,IF(H33>474,3,""))) | M33: Catégorie | O33: Nombre de cours | P33: journées participant | Q33: Coûts totaux
A34: 29 | F34: =IFERROR(($Q$6+1)*B34/$E34,0) -> 0 | G34: =IFERROR(($Q$6+1)*C34/$E34,0) -> 0 | H34: =IFERROR(($Q$6+1)*D34/$E34,0) -> 0 | I34: =IF(F34>0,1,"") | J34: =IF(AND(G34>0,G34<341),1,IF(AND(G34>=341,G34<=474),2,IF(G34>474,2,""))) | K34: =IF(AND(H34>0,H34<341),1,IF(AND(H34>=341,H34<=474),2,IF(H34>474,3,""))) | M34: 1 | O34: =SUM(P15:R15,P16,P17) -> 0 | P34: =SUM(O21:Q21) -> 0 | Q34: =R27 -> 0
A35: 30 | F35: =IFERROR(($Q$6+1)*B35/$E35,0) -> 0 | G35: =IFERROR(($Q$6+1)*C35/$E35,0) -> 0 | H35: =IFERROR(($Q$6+1)*D35/$E35,0) -> 0 | I35: =IF(F35>0,1,"") | J35: =IF(AND(G35>0,G35<341),1,IF(AND(G35>=341,G35<=474),2,IF(G35>474,2,""))) | K35: =IF(AND(H35>0,H35<341),1,IF(AND(H35>=341,H35<=474),2,IF(H35>474,3,""))) | M35: 2 | O35: =SUM(Q16:R16,Q17) -> 4 | P35: =SUM(O22:Q22) -> 49 | Q35: =R28 -> 22168.669
A36: 31 | F36: =IFERROR(($Q$6+1)*B36/$E36,0) -> 0 | G36: =IFERROR(($Q$6+1)*C36/$E36,0) -> 0 | H36: =IFERROR(($Q$6+1)*D36/$E36,0) -> 0 | I36: =IF(F36>0,1,"") | J36: =IF(AND(G36>0,G36<341),1,IF(AND(G36>=341,G36<=474),2,IF(G36>474,2,""))) | K36: =IF(AND(H36>0,H36<341),1,IF(AND(H36>=341,H36<=474),2,IF(H36>474,3,""))) | M36: 3 | O36: =R17 -> 15 | P36: =SUM(O23:Q23) -> 142 | Q36: =R29 -> 83132.508
A37: 32 | F37: =IFERROR(($Q$6+1)*B37/$E37,0) -> 0 | G37: =IFERROR(($Q$6+1)*C37/$E37,0) -> 0 | H37: =IFERROR(($Q$6+1)*D37/$E37,0) -> 0 | I37: =IF(F37>0,1,"") | J37: =IF(AND(G37>0,G37<341),1,IF(AND(G37>=341,G37<=474),2,IF(G37>474,2,""))) | K37: =IF(AND(H37>0,H37<341),1,IF(AND(H37>=341,H37<=474),2,IF(H37>474,3,"")))
A38: 33 | F38: =IFERROR(($Q$6+1)*B38/$E38,0) -> 0 | G38: =IFERROR(($Q$6+1)*C38/$E38,0) -> 0 | H38: =IFERROR(($Q$6+1)*D38/$E38,0) -> 0 | I38: =IF(F38>0,1,"") | J38: =IF(AND(G38>0,G38<341),1,IF(AND(G38>=341,G38<=474),2,IF(G38>474,2,""))) | K38: =IF(AND(H38>0,H38<341),1,IF(AND(H38>=341,H38<=474),2,IF(H38>474,3,"")))
A39: 34 | F39: =IFERROR(($Q$6+1)*B39/$E39,0) -> 0 | G39: =IFERROR(($Q$6+1)*C39/$E39,0) -> 0 | H39: =IFERROR(($Q$6+1)*D39/$E39,0) -> 0 | I39: =IF(F39>0,1,"") | J39: =IF(AND(G39>0,G39<341),1,IF(AND(G39>=341,G39<=474),2,IF(G39>474,2,""))) | K39: =IF(AND(H39>0,H39<341),1,IF(AND(H39>=341,H39<=474),2,IF(H39>474,3,"")))
A40: 35 | F40: =IFERROR(($Q$6+1)*B40/$E40,0) -> 0 | G40: =IFERROR(($Q$6+1)*C40/$E40,0) -> 0 | H40: =IFERROR(($Q$6+1)*D40/$E40,0) -> 0 | I40: =IF(F40>0,1,"") | J40: =IF(AND(G40>0,G40<341),1,IF(AND(G40>=341,G40<=474),2,IF(G40>474,2,""))) | K40: =IF(AND(H40>0,H40<341),1,IF(AND(H40>=341,H40<=474),2,IF(H40>474,3,"")))
A41: 36 | F41: =IFERROR(($Q$6+1)*B41/$E41,0) -> 0 | G41: =IFERROR(($Q$6+1)*C41/$E41,0) -> 0 | H41: =IFERROR(($Q$6+1)*D41/$E41,0) -> 0 | I41: =IF(F41>0,1,"") | J41: =IF(AND(G41>0,G41<341),1,IF(AND(G41>=341,G41<=474),2,IF(G41>474,2,""))) | K41: =IF(AND(H41>0,H41<341),1,IF(AND(H41>=341,H41<=474),2,IF(H41>474,3,"")))
A42: 37 | F42: =IFERROR(($Q$6+1)*B42/$E42,0) -> 0 | G42: =IFERROR(($Q$6+1)*C42/$E42,0) -> 0 | H42: =IFERROR(($Q$6+1)*D42/$E42,0) -> 0 | I42: =IF(F42>0,1,"") | J42: =IF(AND(G42>0,G42<341),1,IF(AND(G42>=341,G42<=474),2,IF(G42>474,2,""))) | K42: =IF(AND(H42>0,H42<341),1,IF(AND(H42>=341,H42<=474),2,IF(H42>474,3,"")))
A43: 38 | F43: =IFERROR(($Q$6+1)*B43/$E43,0) -> 0 | G43: =IFERROR(($Q$6+1)*C43/$E43,0) -> 0 | H43: =IFERROR(($Q$6+1)*D43/$E43,0) -> 0 | I43: =IF(F43>0,1,"") | J43: =IF(AND(G43>0,G43<341),1,IF(AND(G43>=341,G43<=474),2,IF(G43>474,2,""))) | K43: =IF(AND(H43>0,H43<341),1,IF(AND(H43>=341,H43<=474),2,IF(H43>474,3,"")))
A44: 39 | F44: =IFERROR(($Q$6+1)*B44/$E44,0) -> 0 | G44: =IFERROR(($Q$6+1)*C44/$E44,0) -> 0 | H44: =IFERROR(($Q$6+1)*D44/$E44,0) -> 0 | I44: =IF(F44>0,1,"") | J44: =IF(AND(G44>0,G44<341),1,IF(AND(G44>=341,G44<=474),2,IF(G44>474,2,""))) | K44: =IF(AND(H44>0,H44<341),1,IF(AND(H44>=341,H44<=474),2,IF(H44>474,3,"")))
A45: 40 | F45: =IFERROR(($Q$6+1)*B45/$E45,0) -> 0 | G45: =IFERROR(($Q$6+1)*C45/$E45,0) -> 0 | H45: =IFERROR(($Q$6+1)*D45/$E45,0) -> 0 | I45: =IF(F45>0,1,"") | J45: =IF(AND(G45>0,G45<341),1,IF(AND(G45>=341,G45<=474),2,IF(G45>474,2,""))) | K45: =IF(AND(H45>0,H45<341),1,IF(AND(H45>=341,H45<=474),2,IF(H45>474,3,"")))
A46: 41 | F46: =IFERROR(($Q$6+1)*B46/$E46,0) -> 0 | G46: =IFERROR(($Q$6+1)*C46/$E46,0) -> 0 | H46: =IFERROR(($Q$6+1)*D46/$E46,0) -> 0 | I46: =IF(F46>0,1,"") | J46: =IF(AND(G46>0,G46<341),1,IF(AND(G46>=341,G46<=474),2,IF(G46>474,2,""))) | K46: =IF(AND(H46>0,H46<341),1,IF(AND(H46>=341,H46<=474),2,IF(H46>474,3,"")))
A47: 42 | F47: =IFERROR(($Q$6+1)*B47/$E47,0) -> 0 | G47: =IFERROR(($Q$6+1)*C47/$E47,0) -> 0 | H47: =IFERROR(($Q$6+1)*D47/$E47,0) -> 0 | I47: =IF(F47>0,1,"") | J47: =IF(AND(G47>0,G47<341),1,IF(AND(G47>=341,G47<=474),2,IF(G47>474,2,""))) | K47: =IF(AND(H47>0,H47<341),1,IF(AND(H47>=341,H47<=474),2,IF(H47>474,3,"")))
A48: 43 | F48: =IFERROR(($Q$6+1)*B48/$E48,0) -> 0 | G48: =IFERROR(($Q$6+1)*C48/$E48,0) -> 0 | H48: =IFERROR(($Q$6+1)*D48/$E48,0) -> 0 | I48: =IF(F48>0,1,"") | J48: =IF(AND(G48>0,G48<341),1,IF(AND(G48>=341,G48<=474),2,IF(G48>474,2,""))) | K48: =IF(AND(H48>0,H48<341),1,IF(AND(H48>=341,H48<=474),2,IF(H48>474,3,"")))
... A75: 70 | F75: =IFERROR(($Q$6+1)*B75/$E75,0) -> 0 | G75: =IFERROR(($Q$6+1)*C75/$E75,0) -> 0 | H75: =IFERROR(($Q$6+1)*D75/$E75,0) -> 0 | I75: =IF(F75>0,1,"") | J75: =IF(AND(G75>0,G75<341),1,IF(AND(G75>=341,G75<=474),2,IF(G75>474,2,""))) | K75: =IF(AND(H75>0,H75<341),1,IF(AND(H75>=341,H75<=474),2,IF(H75>474,3,"")))
