Workbook

Sheet gescon_infosparticip
A1: membre | B1: Dernière mise à jour | C1: Fils de(Père) | D1: Fils de(Mère) | E1: Tuteur | F1: Institution | G1: Adresse urgence | H1: Referent_institut | I1: arpo_gereseul | J1: arpo_avecaidephys | K1: arpo_avecconseil | L1: arpo_negerepas | M1: Mobil_marcheseul | N1: Mobil_marchaide | O1: Mobil_marchauxi | P1: Mobil_fauteuilman | Q1: Mobil_fauteuilelec | R1: Long_dep | S1: Piscine_coment | T1: Piscine_gilet | U1: Publication | V1: habillement | W1: someil | X1: acnuit_atache | Y1: acnuit_drapspec | Z1: acnuit_gilet | AA1: acnuit_barriere | AB1: Expresssion | AC1: Famille | AD1: Fraterie | AE1: Amis | AF1: Passions_Loisirs | AG1: Activités peu appréciées | AH1: autonomierepas | AI1: alim_prefere | AJ1: alim_regime | AK1: alim_decons | AL1: alim_interdit | AM1: bois_condition | AN1: bois_prefere | AO1: bois_regime | AP1: bois_decons | AQ1: bois_interdit | AR1: impot | AS1: Interv_A | AT1: Interv_B | AU1: Interv_C | AV1: Interv_R | AW1: CR_urgence | AX1: CR_surcharge | AY1: CR_loisirs | AZ1: CR_famille | BA1: Medecin 1 | BB1: Medecin 2 | BC1: Medecin 3 | BD1: Caisse maladie | BE1: Accident | BF1: no_assuré | BG1: Type de handicap | BH1: Handicaps Associés | BI1: deg_impot | BJ1: Allergies | BK1: toilette | BL1: incontinence | BM1: escarres | BN1: change_pos | BO1: frequence_change
A2: -2138585887 | B2: 41092 | I2: FALSE | J2: FALSE | K2: FALSE | L2: FALSE | M2: FALSE | N2: FALSE | O2: FALSE | P2: FALSE | Q2: FALSE | R2: ligne1 ligne 2 Ligne 3 | T2: FALSE | U2: FALSE | X2: FALSE | Y2: FALSE | Z2: FALSE | AA2: FALSE | AH2: Incliner légèrement son fauteuil en arrière pour facilier la déglutition. Alimentation normale. Couper fin, très petit, si trop secd rajouter du lait et lui donner à manger. | AM2: II boit à la paille | AN2: café | BG2: IMC profond | BH2: Handicap mental, troubles moteurs | BI2: Elevé | BJ2: protéger Alain du soleil (chapeau, crème). Il a une peau très sensible, faire attention aux coups de soleil dans la nuque! | BK2: Aide complète. Attention a bien mettre son plateau pour évtier les blessures aux genoux. Chaise percée pour douche tous les jours. | BL2: lain a une autonomie moyenne. Par commodité, il est langé à l'extérieur de la maison. Au changement de lange (matin, midi, soir, avant le coucher), lui demander s'il veut aller aux toillettes | BM2: massage des pieds et des fesses
A3: -1974002318 | B3: 42780 | C3: 1241531093 | G3: 2146189445 | I3: FALSE | J3: FALSE | K3: FALSE | L3: FALSE | M3: FALSE | N3: FALSE | O3: FALSE | P3: TRUE | Q3: FALSE | R3: Elle supporte les longs trajets en bus | S3: Elle apprécie l'eau | T3: TRUE | U3: TRUE | V3: Aide totale | X3: FALSE | Y3: FALSE | Z3: FALSE | AA3: FALSE | AB3: Elle n'a pas l'expression verbal. Elle communique par le regard, le toucher, les mimiques. C'est une petite fille très facile qui apprécie tout. Si elle pleure il faut s'inquiéter (il peut y avoir des coliques ou mal positionnement). Donc à observer et la prendre dans les bras car elle a besoin d'être rassurée. | AC3: Elle apprécie beaucoup sa grand-maman. | AD3: Alycia a une petite sœur qui s'appelle Léanne | AF3: Activités en plein air. Elle aime bien écouter de la musiquen et des histoires. Elle apprécie les balades et le vélo. | AH3: Alycia est alimentée par sonde. 150 ml de frébini 300m/h avec la pompe. (peg) matin, midi et soir avec la pompe et le sachet alimentaire. Donner de l'eau 3x/jours 150ml Prend environs 30 min pour le repas trois fois limentation avec les sachet pour la boisson. On peut l'alimenter durant les transports ou en déplacement sur la chaise. | BA3: 226884306 | BD3: 2146189019 | BF3: 00807.17.515.7 | BG3: Polyhandicap | BH3: A mettre lunettes médicales la journée | BK3: Changer les protections matin, midi et soir. Aussi si ell a été à selle. | BN3: oui | BO3: changement de position pendant la journée.
A4: -1949668449 | B4: 37859.411 | C4: 2643 | D4: 2210 | E4: 0 | F4: 0 | G4: 1424 | I4: FALSE | J4: FALSE | K4: FALSE | L4: FALSE | M4: FALSE | N4: FALSE | O4: FALSE | P4: FALSE | Q4: FALSE | S4: Le faire marcher dans l'eau rester tout le temps à ses côtés. | T4: FALSE | U4: TRUE | X4: FALSE | Y4: FALSE | Z4: FALSE | AA4: FALSE | AB4: Expression verbale, mimiques, écholalie, stéréotipie | AC4: Il aime beaucoup la musique: écouter Mylène Farmer, et chanter. Ne pas lui donner trop d'ordres, pas trop d'exigences, juste lui indiquer ce que l'on fait. Si il se fâche, il se donne des claques. | AG4: Elle est destabilisée par la foule. | BA4: 107 | BB4: 0 | BC4: 0 | BE4: 0 | BG4: IMC | BH4: Diplégie spastique, retard mental, comportement autistique, handicap mental
A5: -1887115141 | B5: 42517 | C5: 106817863 | F5: 1424 | H5: Groupe - C4 Beate Friedberger | I5: FALSE | J5: TRUE | K5: TRUE | L5: FALSE | M5: FALSE | N5: FALSE | O5: FALSE | P5: TRUE | Q5: FALSE | R5: Elle supporte les trajets en bus. | S5: Il faut l’accompagner. Si elle ne veut pas, il ne faut pas la forcer | T5: FALSE | U5: TRUE | W5: dort bien mais discute parfois longtemps. Danièla demande pour aller au lit. Le matin, au lever elle boit volontiers un verre d’eau. Protection pour la nuit | X5: FALSE | Y5: FALSE | Z5: FALSE | AA5: TRUE | AB5: s’exprime en allemand et en français à sa manière. Elle mélange les mots allemands avec les mots français. | AC5: Son papa est décédé. | AD5: Elle a 2 sœurs : Claudia et Andrea. | AF5: Danièla possède un cahier avec des photos de sa famille et de son entourage. Danièla s’exprime bien et montre ce qu’elle souhaite. Elle arrive à faire des choix. Elle apprécie les différents styles de musique. Elle aime faire des jeux d’encastrement ex : mettre les pièces dans le jeu du puissance 4. Elle arrive à faire du vélo à 3 roues. | AG5: Toutes les activités avec des bruits, Danièla sursaute beaucoup | AH5: les aliments sont à couper, elle mange seule avec une fourchette dans une assiette creuse ; fait le mouvement de pelle côté droit et elle doit mettre la main gauche à plat sur la table les doigts légèrement écartés. | AM5: elle boit dans un gobelet spécial avec 2 anses. Lors de déplacement elle arrive à boire dans un verre normal. Matin : Tartine au beurre, confiture et café et fruit habituellement. Les autres repas elle mange de tout et sait dire lorsqu’elle ne veut plus. Elle apprécie boire de l’eau, du sirop ou autre minéralesIl faut l'asseoir sur une chaise avec des accoudoirs. | BA5: 107 | BD5: 2146189028 | BE5: 2146189028 | BF5: 3705 | BG5: IMC | BH5: Handicap mental, troubles moteurs, hémiplégie côté gauche | BI5: Elevé | BK5: oui Danièla participe à l’habillage (= pousser les bras, monter les chaussettes) pour le reste elle a besoin d’aide (= se tient debout si elle a une barrière pour se tenir) Elle a des attelles aux jambes. Masser les pieds pour les détendres et ensuite bien mettre le talon au fond de l’attelle. Pour vérifier si le talon est bein au fond regarder le trou sur le talon de l’attelle. Douche : assise sur une chaise, elle se lève pour se faire laver les parties intimes. | BL5: Elle demande si elle a besoin d’uriner. Se déplace dans la salle de bain et se lève avec la barrière. Appelle pour qu’on l’aide à se remettre dans son fauteuil. Le matin, lui proposer d’aller aux WC avant de déjeuner. Protection pour la nuit!
A6: -1756164214 | B6: 41087 | C6: 0 | D6: 0 | E6: 0 | F6: 0 | G6: 0 | I6: FALSE | J6: FALSE | K6: FALSE | L6: FALSE | M6: FALSE | N6: FALSE | O6: FALSE | P6: FALSE | Q6: FALSE | S6: si Laurent n'a pas fond, il a besoin d'aide. | T6: FALSE | U6: TRUE | X6: FALSE | Y6: FALSE | Z6: FALSE | AA6: FALSE | AB6: Parle | AC6: Ses parents sont séparés. Son papa habite dans le canton de Berne et sa maman à Betten près de Naters. Il a deux frères: Jean-Luc (1965) et Yves (1964). Laurent apprécie la piscine, les ballades.Il travaille un après-midi par semaine dans un atelier et le | BA6: 0 | BB6: 0 | BC6: 0 | BD6: 0 | BE6: 0 | BG6: IMC | BH6: Handicap mental | BJ6: Non
A7: -1735727011 | B7: 37861.394 | C7: 0 | D7: 0 | E7: 0 | F7: 0 | G7: 0 | I7: FALSE | J7: FALSE | K7: FALSE | L7: FALSE | M7: FALSE | N7: FALSE | O7: FALSE | P7: FALSE | Q7: FALSE | S7: Il sait nager, il faut être à côté | T7: FALSE | U7: FALSE | X7: FALSE | Y7: FALSE | Z7: FALSE | AA7: FALSE | AB7: oral | BA7: 107 | BB7: 0 | BC7: 0 | BD7: 0 | BE7: 0 | BG7: IMC | BJ7: Rhume des foins
A8: -1690129297 | B8: 37858.563 | C8: 1007640806 | D8: 2210 | E8: 0 | F8: 0 | I8: FALSE | J8: FALSE | K8: FALSE | L8: FALSE | M8: FALSE | N8: FALSE | O8: FALSE | P8: FALSE | Q8: FALSE | S8: Patrice a besoin de l’aide d’un adulte. | T8: FALSE | U8: TRUE | X8: FALSE | Y8: FALSE | Z8: FALSE | AA8: FALSE | AB8: oral, mais avec difficulté. Il faut lui poser des questions pour qu’il participe à la conversation. | AC8: Patrice aime les animaux, la musique, les magazines et regarder la télévision. Il a depuis une année un neveu qu’il aime beaucoup. Sa deuxième sœur dirige une société d’accordéoniste. Son papa est passionné de pétanque. | BA8: 1217 | BB8: 0 | BC8: 0 | BE8: 0 | BG8: Ataxie, syndrome de Marinesco | BH8: troubles moteurs | BJ8: A protéger du Soleil (casquette, crème).
A9: -1579856298 | B9: 38154.441 | C9: 0 | D9: 0 | F9: 0 | G9: 0 | I9: FALSE | J9: FALSE | K9: FALSE | L9: FALSE | M9: FALSE | N9: FALSE | O9: FALSE | P9: FALSE | Q9: FALSE | T9: FALSE | U9: FALSE | X9: FALSE | Y9: FALSE | Z9: FALSE | AA9: FALSE | BA9: 0 | BB9: 0 | BC9: 0 | BD9: 0 | BE9: 0
A10: -1475569285 | B10: 42405 | C10: 2146188951 | F10: 2146189395 | G10: 2146188951 | I10: FALSE | J10: TRUE | K10: FALSE | L10: TRUE | M10: TRUE | N10: FALSE | O10: FALSE | P10: FALSE | Q10: FALSE | R10: Il supporte les longs trajets et se déplace seul. | S10: Il nage seul, sans manchon. Il n'a pas peur de l'eau. | T10: FALSE | U10: TRUE | V10: Il faut l'aider à choisir ses vêtements en fonction du temps. | W10: Il dort beaucoup, de plus en plus. Il n'a pas d'horaires particuliers. | X10: FALSE | Y10: FALSE | Z10: FALSE | AA10: FALSE | AB10: Langage verbal avec des gestes. | AC10: Il n'a plus que sa maman et l'ami de celle-ci. | AD10: décédés | AF10: Avec sa maman et l'ami de celle-ci, ils vont à vélo, au camping, nager, voir des matchs de foot, manger au restaurant, danser, ect. Il a des cousins et cousines mais ne les voit jamais, seul Fritz Karafiat l'amène faire des raquettes parfois l'hiver. Il aime les activités de groupe, est très sociable mains ne parle pas beaucoup. Il aime le cinéma et le foot, les trains à la gare, les avions à l'aéroport, mais surtout voir des gens ! S'il va au ciné, il ne comprend pas le film, c'est juste pour sortir. Attention, quand il voit des jeux de cartes, il les pique pour s'amuser avec. Il aime les avions et les trains. | AG10: Aucune, il est agréable et facile à vivre. | AH10: Il mange seul et se débrouille bien. | BA10: 2146189227 | BB10: 2146189396 | BD10: 2146188987 | BE10: 2146188982 | BF10: 644702 | BG10: Syndrôme de William's | BH10: handicap mental - Malformation cardiaque | BI10: Faible | BJ10: N.B. Il a une bonne santé, rarement malade. Il a un souffle au cœur mais sans conséquences jusqu'à présent. | BK10: N'a pas besoin d'aide. | BL10: Il est sensible aux diarrhées. Il est autonome et va souvent aux toilettes.
A11: -1435346384 | B11: 42886 | I11: FALSE | J11: FALSE | K11: FALSE | L11: FALSE | M11: FALSE | N11: FALSE | O11: FALSE | P11: FALSE | Q11: FALSE | T11: FALSE | U11: FALSE | X11: FALSE | Y11: FALSE | Z11: FALSE | AA11: FALSE
A12: -1354980006 | B12: 42885 | C12: -362773667 | F12: 67 | I12: FALSE | J12: TRUE | K12: TRUE | L12: TRUE | M12: FALSE | N12: FALSE | O12: FALSE | P12: TRUE | Q12: FALSE | R12: Elle supporte les trajets en bus. | S12: Elle aime l'eau, elle y va avec un gilet et une personne en soutenance. | T12: TRUE | U12: TRUE | V12: aide complète, elle aime être propre et être lavée. | W12: Elle dort sur le dos avec un coussin d’allaitement sous les genoux et un coussin sous la tête selon sa position. Elle apprécie avoir un mobile au dessus de sa tête et des nounours autour d’elle. Le soir, elle se couche vers les 20h-21h00. Elle a besoin de temps pour s’endormir et parfois, après avoir mis la sonde, il est nécessaire de la changée. Si non, elle a un bon sommeil. La nuit à vérifier son lange env. 1/ 2heure après l’application de la sonde. | X12: FALSE | Y12: FALSE | Z12: FALSE | AA12: TRUE | AB12: Elle n’a pas une communication verbale mais Cloé communique avec des petits cris. L’intonation varie selon son humeur. (Contente, dérangée, douleur, etc.). Cloé ne peut pas se positionner dans le « oui » ou le « non ». | AD12: Cloé a des frères (Léandre de 2005, Joaquim de 2002). | AF12: Elle aime sortir et faire des balades. Elle apprécie rester dans son lit et jouer avec des mobiles poser au dessus de sa tête. | AH12: médic du matin: dans la seringue et relié à la sonde -> rincer ensuite avec 1-2 seringue d'eau Cloé a besoin d’une aide complète pour les repas. Elle est nourrie essentiellement par le biais de la sonde. Il ne faut pas la forcer. Elle mange de tout et la nourriture est mixée, lisse. Ni trop liquide, ni trop sèche. Elle préfère plutôt salé. Le MATIN : en principe, elle ne mange pas. Il est important de rincer la sonde avec 1 à 2 seringues. MIDI : nourriture mixée lisse en petites quantités. SOIR : nourriture mixée lisse ou des yaourts en petites quantités. Petit sachet pour la nourriture durant la nuit | AJ12: débit EAU : 180 ml/h débit L'ALIMENTATION : 50 ml/h | AM12: alimentation et sonde: s'il fait chaud, on peut donner jusqu'à 1litre d'eau par la sonde. Pour bouillon et eau mettre dans le grand sachet - possibilité de donner à boire en promenade, prendre la pompe et mettre eau dans gd sachet. | AS12: 2146189479 | AT12: 2146189314 | AU12: 2146189314 | BA12: 107 | BD12: 2146188987 | BE12: 2146188987 | BF12: 429923 | BG12: IMC -Polyhandicap, épilepsie (stabilisé) | BH12: Ne doit pas dépasser les 1700m d'altitude. Car elle risque d'avoir des problèmes respiratoires | BI12: Elevé | BJ12: Bien la protéger du soleil car elle a la peau très sensible | BK12: Elle aime être propre. | BL12: En cas de diarrhée, Bioflorin au Perenterol. Elle fait souvent les selles après la prise des médicaments | BM12: Changement de position, il faut lui mettre le harnais quand elle se trouve dans la chaise. | BN12: Sur le dos avec un coussin d'allaitement sous les genoux et un coussin sous la tête selon sa position. Elle est souvent couchle sur le dos. Pas de changement de position la nuit. | BO12: Chaque 4 heures
A13: -1336383801 | B13: 41430 | I13: FALSE | J13: FALSE | K13: FALSE | L13: FALSE | M13: FALSE | N13: FALSE | O13: FALSE | P13: FALSE | Q13: FALSE | T13: FALSE | U13: FALSE | X13: FALSE | Y13: FALSE | Z13: FALSE | AA13: FALSE
A14: -1226171744 | B14: 42941 | I14: FALSE | J14: FALSE | K14: FALSE | L14: FALSE | M14: FALSE | N14: FALSE | O14: FALSE | P14: FALSE | Q14: FALSE | T14: FALSE | U14: FALSE | X14: FALSE | Y14: FALSE | Z14: FALSE | AA14: FALSE
A15: -1213086902 | B15: 41058 | I15: FALSE | J15: FALSE | K15: FALSE | L15: FALSE | M15: FALSE | N15: FALSE | O15: FALSE | P15: FALSE | Q15: FALSE | T15: FALSE | U15: FALSE | X15: FALSE | Y15: FALSE | Z15: FALSE | AA15: FALSE
A16: -1120356771 | B16: 42705 | C16: -1123050406 | F16: 1424 | I16: FALSE | J16: TRUE | K16: FALSE | L16: TRUE | M16: FALSE | N16: FALSE | O16: FALSE | P16: TRUE | Q16: FALSE | R16: Il faut lui mettre les anches droites dès qu'on l'installe dans la chaise. Elle supporte les longs trajets | S16: Elle apprécie beaucoup l'eau, aide complète. | T16: FALSE | U16: TRUE | V16: aide complète | W16: Elle se couche vers les 19h00 et se lève vers 7h30 en général. Durant la nuit changement de position. Elle s’endort sur le dos avec la gouttière. Puis, vers 23h00, la mettre sur le côté gauche, puis sur le côté droit. Si elle est endormie, il n’est pas nécessaire de faire de changement de position. | X16: FALSE | Y16: FALSE | Z16: FALSE | AA16: TRUE | AB16: Non verbal, elle communique avec des cris. | AD16: Elle a un frère Maxime de 1989 et deux sœurs Blanche et Rose de 2002 qui sont jumelles. | AF16: Elle se montre très conviviale lorsqu'elle se retrouve à l'extérieur. Elle apprécie la musique et le rythme. Elle aime tenir des objets dans ses mains et jouer avec, elle apprécie les câlins. | AG16: Rien à signaler. | AH16: Elle mange de tout, plutôt sucré. Pour lui donner à manger elle a une cuillère spéciale, s’assoir en face d’elle et déposer d’abord sur sa lèvre inférieure bien lui faire sentir l’aliment, lui tenir les mains l’une sur l’autre puis elle mange sans problème. Elle mange mixé, sans fil. Si vous avez des difficultés à lui donner à manger, il ne faut pas se faire de soucis. Dans les bagages, Il y aura des boissons (frésubin) qui ont les mêmes calories qu’un repas normal. | AM16: pour boire : Amandine a une sonde reliée directement à l'estomac. Installer le tuyau sur la valve. Ne pas se gener de prendre la valve bien en main pour mettre le tuyau, ça ne lui fait pas mal. Ensuite remplir la seringue dans un verre et placer la seringue dans l'embout du tuyau, puis presser dans le tuyau. Pour terminer, rincer le tout avec de l'eau sans aucun produit (elle boit en général 1 verre d'une quelconque boisson SANS GAZ + 1 verre d'eau) Ne jamais mettre le tuyau au lave vaisselle !! | AN16: le matin et le soir : café ou cacao, presser la seringue plus lentement. A midi : n'importe quelle boisson SANS GAZ. Au goûter : boisson enérgétique (fébrini) | AQ16: Ne pas lui donner de boisson gazeuses. | BA16: 107 | BD16: 2146188984 | BE16: 2146188984 | BF16: 010930279 | BG16: IMC | BH16: Handicap mental, troubles moteurs | BI16: Elevé | BJ16: Aucune | BK16: Si elle a des rougeurs autour du « bouton », sécher au foehn et lui mettre un tampon de ouate démaquillante coupée en Y entre le tampon et la peau. Si elle se mord les doigts lui mettre un sparadrap en cas de saignements. Ne pas lui brosser les dents, elle ne le supporte pas. Pour sa toilette, utiliser de préférence le lit douche, mais elle est peu habituée car elle prend de préférence des bains. | BL16: Elle est langée 24h/24. La changer en général après chaque repas. | BM16: Transferts : Amandine met les bras autour de l'accompagnant, mettre un bras sous sa jambre, l'autre sous son épaule puis la mettre sur le lit. Pour la remettre dans sa chaise, faire pareil. Incliner sa chaise pour la mettre au fond | BN16: Elle apprécie être par terre, la mettre sur le dos sur un tapis.
A17: -1100872493 | B17: 40764.668 | C17: 0 | D17: 0 | E17: 0 | F17: 0 | G17: 0 | I17: FALSE | J17: FALSE | K17: FALSE | L17: FALSE | M17: FALSE | N17: FALSE | O17: FALSE | P17: FALSE | Q17: FALSE | T17: FALSE | U17: FALSE | X17: FALSE | Y17: FALSE | Z17: FALSE | AA17: FALSE | BA17: 0 | BB17: 0 | BC17: 0 | BD17: 0 | BE17: 0
A18: -1029621688 | B18: 41766 | F18: 1434 | G18: 1434 | H18: Loic accompagnement, Linda soin, Lydia infirmière | I18: TRUE | J18: FALSE | K18: FALSE | L18: FALSE | M18: FALSE | N18: FALSE | O18: FALSE | P18: TRUE | Q18: TRUE | R18: Il peut se lever pour un transfert mais il faut le tenir. Il supporte les longs trajets en bus. | S18: René n'aime pas trop, il a besoin d'aide. Pas de gilet mais il faut le soutenir. | T18: FALSE | U18: TRUE | V18: Il est autonome pour l'habillement. Il faut l'aider pour mettre ses chaussettes et ses chaussures. | W18: Urinal à proximité. Il bouge beaucoup. | X18: FALSE | Y18: FALSE | Z18: FALSE | AA18: FALSE | AB18: René parle et il a un appareil auditif. Bien articuler et parler un peu fort bien en face de lui. | AD18: René a deux sœurs, deux nièces et une petite nièce. | AF18: Ordinateur, la ville, les mots croisés, l'astrologie, discuter, les voyages. | AH18: Il faut lui couper la viande | BA18: 2146188983 | BD18: 2146188969 | BE18: 2146188969 | BF18: 267.50.370.119 / 000-02 | BG18: IMC | BH18: Malentendant, il a un appareil. | BI18: Elevé | BJ18: Aucune | BK18: René est autonome. Supervision pour la douche. | BL18: René est autonome. | BN18: Sur sa chaise électrique
A19: -959706217 | B19: 42886 | C19: 1203348545 | F19: 1434 | G19: 1434 | I19: FALSE | J19: TRUE | K19: TRUE | L19: FALSE | M19: FALSE | N19: FALSE | O19: FALSE | P19: TRUE | Q19: FALSE | R19: Se déplace seul à l'intérieur et accompagné à l'extérieur même muni du servomatic.Transfert lit chaise avec cigogne. Antidry sur le dos et les démengeaisons. | S19: Oui avec un grand plaisir. Faire attention à l'eau froide, sait nager seul mais le surveiller. | T19: FALSE | U19: TRUE | V19: S'habille seul le haut et lui donner un coup de main pour le bas. Pour les transfets il a besoin d'avoir ses souliers aux pieds. | W19: Il choisit quand il veut se coucher. Généralement il va au lit tôt. Ne pas oublier de brancher son uriflac sur l'uriflac qu'il a spécialement pour la nuit.Enlever Slip. Mettres des pants si diahrées. | X19: FALSE | Y19: FALSE | Z19: FALSE | AA19: FALSE | AB19: Oral, au premier abord il est qqun de timide mais une fois à l'aise, il se montre très jovial. Il est souvent de bonne humeur, très souriant et galant. Il bagaye. | AF19: Natation, rafroball, puzzles, dessin, peinture, activités manuelles en général et aussi simplement aller boire un verre. Christophe aime parler des sports qu'il pratique et participe volontiers aux discussions et est ouvert à tout. Il aime faire la vaisselle ! | AG19: S'il n'aime pas faire quelque chose il le dit. L'ami de sa maman est décédé et son souvenir lui donne parfois des coups de blues, surtout en janvier. | AH19: Aider à couper les aliments mais mange seul. Pour le temps de midi il reste dans sa chaise | AJ19: lui donner 1 service | AK19: les aliments qui activent son transit intestinal : choux, raisins, poires, pruneaux, fromage car cela lui cause de fortes diahrées. | AM19: il boit seul | AP19: les boissons trop sucrées | BA19: 2146188983 | BD19: 2146189010 | BF19: 8766 | BG19: IMC, retard mental et handicap physique | BH19: Retard mental, malvoyance | BI19: Moyen | BJ19: pas à la connaissance | BL19: Il a une sonde urinaire depuis 2008. Il a toujours sa bouteille avec lui. Il ne dit pas s'il est mouillé car ça le gêne, veiller à lui vider souvent souvent la poche. Le matin et le soir env. 15 min. sur les toilettes pour les selles. | BN19: non | BO19: Mettre en charge la chaise tous les soirs.
A20: -953224796 | B20: 42468 | C20: 2034 | F20: 1434 | G20: 2034 | H20: Quadranti Yann 079/404.86.02 | I20: TRUE | J20: TRUE | K20: TRUE | L20: FALSE | M20: FALSE | N20: FALSE | O20: FALSE | P20: TRUE | Q20: FALSE | R20: Julien supporte les longs trajets sur un siège du bus. Julien a un moteur dans les roues de son fauteil, il faut donc le recharger tous les soirs. | S20: Sortir Julien de sa chaise et le mettre au bord de la piscine. Il faut être à ses côtés lorsqu'il nage. Il nage sur le dos. | T20: FALSE | U20: TRUE | V20: Julien a besoin d'une légère aide pour l'habillement. Toujours mettre les affaires de Julien à sa portée et de manière accessible afin qu'il puisse s'habiller seul. | X20: FALSE | Y20: FALSE | Z20: FALSE | AA20: FALSE | AB20: Il s'exprime bien pour tout ce qui est courant: envies, joies et tristesses. | AD20: Céline | AE20: Thierry, Carole, Sabine, Pierre-Yves, Anne-Françoise, Pierre, Paul | AF20: Il est très attaché à sa famille. Il a des oncles et des tantes à Gèneve, à Zurich et à Neuchâtel. Julien aime la musique, la nature, la fête, les amis et le chant. Il aime aussi son travail aux ateliers du Foyer Valais de Cœur à Sierre. Le karaoké. Il fait partie du Cœur du Cœur. Il vit en appartement protégé. | AH20: Il est autonome pour les repas. | AJ20: Il prend toujours des pruneaux secs au déjeuner | AK20: le Lait | AM20: Verre d'eau chaude au réveil pour faciliter son transit. Un kiwi ou jus d'orange pour déjeuner serait idéal. | AN20: Il aime les bières. Un café après les repas. Un verre de jus d'orange au déjeuner. | AP20: le fromage | BA20: 2146188983 | BD20: 2146188985 | BE20: 2146188985 | BF20: 190 51 144 | BG20: IMC | BH20: Handicap mental | BI20: Faible | BJ20: Protéger Julien du soleil (casquette, crème) | BK20: Besoin d'aide pour l'habillement, surtout pour attaché ses chaussures. Surveiller sa toilette sauf si douche. Il a besoin d'aide pour se laver le dos.. | BL20: Julien est autonome mais il faut vérifier qu'il aille à selle. (si possible chaque deux jours). | BM20: Prévention escarres, douche (avec de l'aide). Pour la douche, si le siège est adapté à hauter du fauteuil roulant. Julien se débrouille bien, il faut surveiller qu'il fasse bien le passage. | BN20: Il fait une sieste après le repas ou en fonction de nos activités.
A21: -587438322 | B21: 42507 | D21: 0 | E21: 0 | F21: 0 | H21: Groupe B2 Claudia Balet - 024 473 51 42 | I21: FALSE | J21: TRUE | K21: TRUE | L21: FALSE | M21: FALSE | N21: FALSE | O21: FALSE | P21: TRUE | Q21: FALSE | R21: Supporte les longs trajets en bus. Dans le fauteuil : bien l'attacher à la taille et au torse | S21: René n'aime pas et ne veut pas aller à la piscine. Présence d'une personne obligatoire pour le tenir. | T21: TRUE | U21: TRUE | V21: Aide totale (complétement dépendant du soignant) | W21: si possible, il fait la sieste après le dîner. Lui mettre un coussin entre les jambes et sous les pieds. Au coucher : mettre un coussin entre ses jambes et sous ses pieds | X21: FALSE | Y21: FALSE | Z21: FALSE | AA21: TRUE | AB21: oral. René comprend tout ce qu’on lui dit en français et en allemand. Il répond aux questions posées par oui ou par non. | AC21: Mère : décédée | AD21: Jean-Claude - décédé | AF21: Il aime participer à toutes sortes d'activités et aime surtout dialoguer et écouter des contes ou histoires. Il aime l’humour et se montre très jovial. | AG21: René n'aime pas trop regarder la télévision. | AH21: couper très, très fin, voir mixer certains aliments sinon fausse route.couper fin, lui donner à manger | AL21: Biscuits secs et gros morceaux | AM21: René boit avec de l’aide. 2 gobelets par repas avec de l’épaississant. | AO21: n'aime pas le lait | BA21: 107 | BB21: 0 | BC21: 0 | BD21: 2146189018 | BE21: 2146189008 | BF21: 158 18 100 | BG21: leucodystrophie à évolution lente | BH21: troubles moteurs | BI21: Elevé | BJ21: Protéger René du soleil (chapeau, crème). | BK21: René est tout à fait dépendant du soignant. Il prend une douche chaque jour ou lui faire une toilette au lit. Il sait cracher dans le haricot après le brossage des dents. Lui masser les jambes avec du lait corporel. Bien lui sécher les mains, les pieds et sous les bras (risque de mycose). Il faut éviter les plis des habits lors de l’installation dans sa chaise et bien le positionner au fond de la chaise et toujours l’attacher (risque de chutes). | BL21: René est langé jour et nuit (le changer 3x par jour, 1x par nuit) | BM21: A prévenir - douche | BN21: Il dort sur le côté, mais il faut le tourner de l’autre côté une fois durant la nuit. Avec un coussin entre les jambes et sous les pieds (éviter les frottements). Après le repos de midi. | BO21: 1Xnuit et après le repos de midi
A22: -568750303 | B22: 42524 | C22: -464138546 | E22: -464138546 | G22: 2146189132 | H22: B3 - 0244735143 | I22: FALSE | J22: FALSE | K22: FALSE | L22: TRUE | M22: FALSE | N22: FALSE | O22: FALSE | P22: TRUE | Q22: TRUE | R22: aucun problème | S22: Aide de l'accompagnement + gillet. N'apprécie pas beaucoup la piscine | T22: FALSE | U22: FALSE | V22: Stéphane aime choisir ses habits la veille.Il a besoin d'une aide complète pour l'habillement et la toilette. | W22: Il a tendance à aller au lit tôt. Il se fatigue vite. Dort sur le ventre | X22: FALSE | Y22: FALSE | Z22: FALSE | AA22: TRUE | AB22: Il utilise un classeur de communication et se montre expressif dans sa gestuelle. Il montre avec la tête quelle option il choisit. Stéphane est quelqu'un de jovial, souvent de bonne humeur. Quand ça n'est pas le cas, il peut pincer ou donner des coups de pieds. | AF22: Il aime l'émission "N'oubliez pas les paroles" sur France2 et le foot. Il apprécie jouer au bowling, regarder les films sentimentaux. Il aime aller au cinéma, au spectacle. Est un très bon spectateur, karaoké | AH22: Il a besoin d'une aide pour lui donner à manger à et boire. Un verre avec une pipette à donner par l'éducateur. IL aime les jus de fruits sans gaz ou sirop. IL préfère le cacao le matin. Il mange avec une cuillère ou fourchette normale. Il sait dire ce qu'il apprécie ou pas. Lui donner qu'un service. Nourriture coupée fine, donnée par l'éducateur | AM22: verre à bec verseur : il mord un peu mais il arrive à boire sans problème avec de l'aide | AN22: jus de fruits sans gaz ou sirop. Préfère le cacao le matin | BA22: 107 | BD22: 2146188969 | BF22: 756.1168.7015.03 | BG22: IMC mixte. Athétosique/spastique | BH22: Handicap mental | BI22: Elevé | BK22: Aide totale : douche, sur chaise percée | BL22: Aide totale : n'est pas langé. Aux toilettes en principe après les repas - avec chaise percée. Urinoir dans son sac derrière la chaise pour les déplacements. | BN22: après le diner | BO22: couché
A23: -486550603 | B23: 42886 | D23: 166 | F23: 1434 | G23: 2146189000 | H23: Danaëlle Savioz 027 451 21 81 (027 451 21 81 infir | I23: TRUE | J23: FALSE | K23: FALSE | L23: FALSE | M23: FALSE | N23: FALSE | O23: FALSE | P23: TRUE | Q23: TRUE | R23: Supporte les longs trajets en bus en principe, oui. Mais voir la route devant. Prend de l’Itinerol pour les trajets sinueux | S23: Faire attention à sa sonde et soutenir Janique selon son besoin. | T23: FALSE | U23: TRUE | V23: Aide totale | W23: à voir avec Janique 1 barrière + lit contre mur. Attention, choisir un lit ou elle tourne le dos au mur pour faire pendre ensuite son uriflak. Attention, elle ne voit pas la nuit. Pas la laisser seule pour les toilettes. | X23: FALSE | Y23: FALSE | Z23: FALSE | AA23: TRUE | AB23: Oral. Janique sait bien se faire comprendre. | AC23: Elle s’exprime elle-même à se sujet. | AD23: Fabian et Nathalie | AF23: Elle croque la vie à pleine dents. Musique française, karaoké, chante à l'ASA-Valais, lecture, shopping | AG23: les jeux de société style « Hâte-toi lentement », les jeux de cartes | AH23: couper. Aider à manger vers la fin du repas. Janique emploie une cuillère spéciale et une assiette + collerette posée sur un sous plat antiglisse. Il faut parfois l’aider, si elle est trop fatiguée.Il faut faire attention à son poids, donc surveiller la quantité. Pour encourager Janique à suivre son régime, servir son repas plutôt dans une assiette à dessert, limiter les féculents et la viande mais pas les légumes. Essayer d’être à table avec des personnes ayant aussi besoin de s’encourager à perdre du poids (accompagnant ou participant).lui mettre des demi.portions. Prend le dessert à 16h. Si tousse lors des repas, la conduire à l'écart, attitude rassurante | AI23: gratin, papé vaudois | AJ23: éviter sucreries en grande quantité et le grignotage et les aliments trop gras. | AK23: limiter les produits laitiers. Elle peut manger un yogourt (à la place d’autre chose) Fenouille, fruits de mer, œuf dur, choux fleurs -> attention à sa toux. | AM23: A la paille / lui donner à la fin du repas 1 dl eau + souhait 1 dl de café | AN23: eau-café noir et 2 assugrines | AO23: éviter les choses sucrées | AP23: sodas / Boissons sucrées ou grasses | BA23: 2146189022 | BD23: 2146189011 | BE23: 2146189011 | BF23: 184 25 597 / 0002 | BG23: IMC | BH23: troubles moteurs, troubles visuels,très vite angoisée | BI23: Elevé | BJ23: protéger Janique du soleil (chapeau, crème) | BK23: Aide totale,Janique à une sonde urinaire elle à tendance à être souvent constipée,si pas de selles pendant 3 jours,il faut lui faire un mycrocliste. Petite toilette Lactacyd | BL23: sonde sous-pubienne. Janique a une sonde sous-pubienne. Elle demande pour aller aux toilettes. Attention à ce qu’elle ne soit pas penchée trop en avant pour éviter de faire une pression sur sonde. Ne pas changer l'uriflac sauf s'il est percé ou s'il est abimé.Pensement cysto Ma et Ve. | BM23: Matin et soir toilette intime minutieuse, bien sécher au foehn car risque important de rougeur. A chaque changement de protection lui faire une peite toilette intime et bien la sécher. | BN23: Elle le fait elle-même avec sa chaise. Lui rappeler de lever ses jambes (surtout au niveau des pieds). Avec aide. Au lit: Coussin "banane" de positionnement autour de la jambe gauche. Bas de soutien le matin
A24: -479406894 | B24: 42969 | C24: 166 | D24: 0 | E24: 0 | F24: 0 | G24: 166 | H24: Vs Coeur - Annick Savioz 027 451 21 84 | I24: FALSE | J24: TRUE | K24: FALSE | L24: FALSE | M24: FALSE | N24: TRUE | O24: FALSE | P24: TRUE | Q24: TRUE | R24: Argent de poche : connaît la valeur de l'argent Supporte les longs trajets en bus | S24: Présence d'une personne obligatoire pour le tenir, de préférence un gilet, Fabian n'aime pas l'eau froide. | T24: TRUE | U24: TRUE | V24: Aide nécessaire complète. Protocole Pansement:siège,pli interfessier:laver avec protosan solution,mettre bépanthène onguent autour-Plis inguinaux:Laver avec bétadine-sécher-talc-compresse- Verge:si rougeur ou lésion,mettre Cavilon,laisser sécher avant de remettre le condom | W24: Il apprécie avoir le lit contre le mur. Il se fatigue vite le soir. Il dort sur le côté avec un grand coussin entre les jambes. Il n'a pas de coussin sous la tête. Comme il devient vite fatigué regarder avec lui quand il veut aller se coucher. | X24: FALSE | Y24: FALSE | Z24: FALSE | AA24: TRUE | AB24: langage oral : parle et comprend tout - a besoin de temps pour répondre - lui parler lentement Apprécie les questions aux réponses oui/non. Il bégaie | AC24: Mère Christiane : y va régulièrement avec sa sœur Janique | AD24: Janique : résidente au foyer Valais de Cœur Nathalie : : mariée - 2 enfants . Maxime (1993) - Marie (1995) | AF24: Passion : cirque et cirque Knie en particulier promenades en ville - restaurants, voir et être en contact avec les gens Travail : 50 % à Valais de Cœur - avec un ordinateur | AG24: Discothèque | AH24: Couper les aliments, lui donner à manger | AI24: Fabian aime le chocolat | AJ24: N'aime pas : poisson, œufs,beurre Lui remplir l'assiette ca il a tendance à peu manger surtout les légumes. | AK24: fatigue en fin de repas ou spasmes durant le repas | AM24: Il boit avec une paille. | AN24: Sirop et coca | AQ24: Boissons alcoolisées | BA24: 2146189022 | BB24: 0 | BC24: 0 | BD24: 2146189011 | BE24: 2146189011 | BF24: 168 58 945 | BG24: IMC | BH24: troubles moteurs | BI24: Elevé | BJ24: Protéger du soleil - Rhume des foins - (voir médicaments) | BK24: Aide complète - crème protectrice sur les fesses et les pieds (matin et soir) - fesses : compresses pour le protéger - Bien sécher les plis de la peau à l'aine, en cas de rougeur (crème Pévary) idem à la hanche droite - talon : mettre la peau de mouton Huile Antidry après la toilette. | BL24: Urine : bouteille à la demande ou lors de longues sorties. Condom chaque matin - poche. Selles : chaise percée 2x/semaine (mercredi et samedi matin) | BM24: Appliquer crème protectrice sur les fesses et les pieds. Sièges : Mopilex border nettoyer au protan si nécessaire bépanthène onguent autour. Verge : si rougeur de lésion, mettre cavillon laisser sécher avant de remettre le condom. | BN24: oui sur demande Transfert avec l'élévateur. Laissez la sangle lorsqu'il est sur les WC. | BO24: la nuit
A25: -414006540 | B25: 42557 | C25: 2092442015 | I25: FALSE | J25: FALSE | K25: FALSE | L25: TRUE | M25: TRUE | N25: FALSE | O25: FALSE | P25: FALSE | Q25: FALSE | R25: Il supporte les trajet en bus. Il porte une atelle à la jambe gauche. ATTENTION aux passages piétons, il traverse toujours sans regarder. | S25: Il adore la piscine. Il faut rester avec lui, il n'a pas de manchons. S'il n'a pas le fond, il coule. | T25: FALSE | U25: TRUE | V25: Il se débrouille bien pour l'habillage et le déshabillage. A besoin d'aide pour finaliser mais demande de l'aide. | W25: Il va au lit vers les 20h00 et dors jusque vers les 7h00. En principe, il ne fait pas la sieste l’après-midi. Le soir, lui raconter une histoire avant de dormir ou une chanson. Il dort avec son doudou. | X25: FALSE | Y25: FALSE | Z25: FALSE | AA25: FALSE | AB25: Il parle distinctement avec un vocabulaire varié. Il ne tient pas toujours un discours très "à propos". Il faut parfois s'armer de patientes questions afin de réellement comprendre le fond de sa pensée. | AC25: Il vit avec sa maman et son compagnon Manu. Son papi s'appelle Alain. Son papa habite à Pont-de-la-Morge avec son amie Laurence. Il a de très bon contact familial : Tonton Jean, Tata Marina, Isa, Pépé Raoul et grand-maman Marie françoise. | AF25: Il aime les trains, les télécabines, les moyens de transport en général. Il aime aussi la musique et gentiment la lecture. Il aime la cuisine grâce à 1 chaîne Youtube. Il aime fabriquer ses propres doudous. | AG25: Il n’apprécie guère la télévision et n’aime pas se salir les mains (ex : peinture à doigt) | AH25: Alexandre mange de tout en bonne quantité. Il faut lui couper ses aliments. | AI25: Bonbons, fruits | AK25: Attention avec le sel sur la table. | AN25: Le thé froid, le sirop | AP25: il ne boit plus de lait | BA25: 2146188990 | BD25: 2146188986 | BE25: 2146188986 | BF25: 00008 375-80-187 | BG25: hydrocéphalie avec hémiparésie à gauche | BH25: trouble de l'attention, du langage, frustration avec crises de larmes et colères. | BJ25: Tendance à avoir le rhume | BK25: Il a besoin d'aide pour sa toilette. Il n'aime pas la douche. Alexandre à un drain qui passe dans son cou, à gauche. En cas de fièvre, cela pourrait indiquer que ce dernier est infecté. Prévenir la Maman de suite. | BL25: Bien veiller à le mettre aux toilettes avant/après une activité avant d'aller au lit.
A26: -362773667 | B26: 41597 | I26: FALSE | J26: FALSE | K26: FALSE | L26: FALSE | M26: TRUE | N26: FALSE | O26: FALSE | P26: TRUE | Q26: FALSE | T26: FALSE | U26: FALSE | X26: FALSE | Y26: FALSE | Z26: FALSE | AA26: FALSE | AS26: -509124961
A27: -22390883 | B27: 42886 | C27: 1201536087 | E27: 1201536087 | F27: 2146189132 | G27: 2146189132 | I27: FALSE | J27: FALSE | K27: FALSE | L27: TRUE | M27: FALSE | N27: FALSE | O27: FALSE | P27: TRUE | Q27: FALSE | R27: Supporte les longs trajets en bus - Changement de position en déplacement : basculer sa chaise. Laisser de l'espace (10cm) entre le dossier et la poignée, incliner la chaise pour éviter que le pose-pieds se coince avec les roues. | S27: Aide totale : ne flotte pas, manchons et autres moyens auxiliaires - Gesticule beaucoup | T27: FALSE | U27: TRUE | V27: Aide totale : bouge beaucoup - lui demander de se calmer | W27: Sur le dos à l'intérieur d'un drap "Zewi" - en haut de pyjama, langé et en slip. Lit avec barrières en bois car il bouge beaucoup ses bras Se fatigue vite et va tôt au lit (22h00) | X27: FALSE | Y27: TRUE | Z27: FALSE | AA27: TRUE | AB27: Pas d'expression verbale : Communication par ipad fixé sur sa table. Bouge la tête à droite pour dire "oui" à gauche pour dire "non" - Agenda pour noter les faits marquants de la journée - Comprend le français et le portugais Quand il tire la langue cela veut dire qu'il a soif | AC27: Maman : Ana Cristina Amaral - Papa : Adelino Gonçalves - séparés. (1 week-end de garde chacun) | AD27: Tania (1994) - Demi-frère Tiago (2006) | AF27: Piscine, musique, mécanique et voitures, télé. | AH27: Aide totale : Se mettre derrière lui et lui tenir le menton avec une main - bouge beaucoup - Manger : cuillère en inox - couper très fin. Couper le pain en petit morceau et mouiller les aliments. Utiliser le Masticateur. | AI27: matin : du pain,confiture (couper le pain en petits morceaux ou faire imbiber les morceaux) | AJ27: Ajouter du liquide avec les aliments c'est plus facile pour Claudio mange mieux | AM27: Claudio boit avec un verre avec un bec verseur et une bavette sous son menton | AN27: matin : café au lait ou cacao. Midi : il boit volontiers des sirops au citron ou orange et le soir des tisanes après avoir mangé ou café. | BD27: 2146188974 | BE27: 2146188974 | BF27: 092322 | BG27: IMC athétosique. Déficience mentale et toubles de vision d'origine centrale | BH27: Problèmes aux poumons il lui reste 1 seul poumon. Rhume des foins | BI27: Elevé | BJ27: Asthme en cas de trop grande excitation ou en période de floraison. Changer tout de suite le pull si celui-ci est mouillé au niveau des poumons. | BK27: Aide totale : Il bouge beaucoup - lui demander de rester calme | BL27: Lange : jour et nuit - Ne va pas sur les WC. Sur demande il arrive à faire "le pont" pour mettre une protection, enfiler ses culottes et ses pantalons | BN27: En déplacement on peut basculer sa chaise. | BO27: env. Chaque 4 heures
A28: 0 | C28: 0 | D28: 0 | E28: 0 | F28: 0 | G28: 0 | I28: FALSE | J28: FALSE | K28: FALSE | L28: FALSE | M28: FALSE | N28: FALSE | O28: FALSE | P28: FALSE | Q28: FALSE | T28: FALSE | U28: TRUE | X28: FALSE | Y28: FALSE | Z28: FALSE | AA28: FALSE | BA28: 0 | BB28: 0 | BC28: 0 | BD28: 0 | BE28: 0
A29: 107 | B29: 40980 | I29: FALSE | J29: FALSE | K29: FALSE | L29: FALSE | M29: FALSE | N29: FALSE | O29: FALSE | P29: FALSE | Q29: FALSE | T29: FALSE | U29: FALSE | X29: FALSE | Y29: FALSE | Z29: FALSE | AA29: FALSE
A30: 111 | B30: 41642 | I30: FALSE | J30: FALSE | K30: FALSE | L30: FALSE | M30: FALSE | N30: FALSE | O30: FALSE | P30: FALSE | Q30: FALSE | T30: FALSE | U30: FALSE | X30: FALSE | Y30: FALSE | Z30: FALSE | AA30: FALSE
A31: 118 | B31: 37833.434 | C31: 352 | D31: 1924 | E31: 0 | F31: 1040296365 | G31: 1040296841 | I31: FALSE | J31: FALSE | K31: FALSE | L31: FALSE | M31: FALSE | N31: FALSE | O31: FALSE | P31: FALSE | Q31: FALSE | S31: Marie-Noëlle ne sait pas nager. Il faut toujours rester près d’elle ; possibilité de faire quelques exercices (planche…). Elle aime beaucoup aller à la piscine et y va régulièrement, mais elle n’aime pas trop l’eau froide. | T31: FALSE | U31: TRUE | X31: FALSE | Y31: FALSE | Z31: FALSE | AA31: FALSE | AB31: Oral. Parle très bien. | AC31: Marie-Noëlle aime aller à la piscine, les jeux de société, la peinture, la musique française (Garou, Goldmann…) et discuter (attention : la stopper tout de suite si elle aborde des sujet tels que sa famille, le sexe et la médisance envers les autres. | AF31: Marie-Noëlle aime aller à la piscine, les jeux de société, la peinture, la musique et discuter (attention : la stopper tout de suite si elle aborde des sujet tels que sa famille, le sexe et la médisance envers les autres. | BA31: 107 | BC31: 0 | BE31: 0 | BG31: IMC | BH31: handicap mental, malvoyant, troubles moteurs | BJ31: Protéger Marie-Noëlle du soleil. | BM31: TROP PETIT??'
A32: 119 | B32: 37833.473 | C32: 138 | D32: 2210 | E32: 0 | I32: FALSE | J32: FALSE | K32: FALSE | L32: FALSE | M32: FALSE | N32: FALSE | O32: FALSE | P32: FALSE | Q32: FALSE | S32: Danielo n’a pas de problèmes pour aller à la piscine. | T32: FALSE | U32: TRUE | X32: FALSE | Y32: FALSE | Z32: FALSE | AA32: FALSE | AB32: langage oral | AC32: Danielo aime bien aller à la piscine, au cinéma et faire des promenades. | BB32: 0 | BC32: 0 | BE32: 0 | BG32: IMC | BJ32: Protéger Danielo du soleil
A33: 129 | B33: 37846.648 | C33: 0 | D33: 0 | E33: 0 | F33: 269 | G33: 269 | I33: FALSE | J33: FALSE | K33: FALSE | L33: FALSE | M33: FALSE | N33: FALSE | O33: FALSE | P33: FALSE | Q33: FALSE | S33: Elle se débrouille, mais une présence à ses côtés est préférable. | T33: FALSE | U33: FALSE | X33: FALSE | Y33: FALSE | Z33: FALSE | AA33: FALSE | AB33: Langage oral | AC33: Anne-Claude apprécie le cinéma, la piscine, etc. Elle se montre intéressée par les différentes activités proposées. | BB33: 0 | BC33: 0 | BE33: 0 | BH33: Dysmorphysme congénital, lambosciatalgie gauche | BJ33: propyphenazare, protéger du soleil, utiliser des pansements hypoallergéniques
A34: 138 | B34: 42858 | C34: -2099377383 | I34: FALSE | J34: FALSE | K34: FALSE | L34: TRUE | M34: TRUE | N34: FALSE | O34: FALSE | P34: TRUE | Q34: FALSE | R34: Il supporte bien les longs trajets. Daniélo marche avec des cannes. Et pour les sorties plus longues il a un fauteil manuel. | S34: Rester attentif et l'aider en cas de besoin | T34: TRUE | U34: FALSE | V34: Il s'habille seul, mais il a besoin de temps | W34: - | X34: FALSE | Y34: FALSE | Z34: FALSE | AA34: FALSE | AB34: Il s'exprime oralement. | AC34: Les parents sont mariés Danièlo est au Foyer St-Hubert à Martigny | AD34: Il a un frère (Fabrice) | AE34: - | AF34: Daniélo aime la piscine, le cinéma et les promenades. | AG34: - | AH34: Daniélo mange seul | AI34: - | AJ34: - | AK34: - | AL34: - | AM34: Il boit seul | AN34: - | AO34: - | AP34: - | AQ34: - | BA34: 2146188992 | BD34: 2146189294 | BE34: 2146189294 | BF34: 482-64-270 | BG34: IMC | BH34: - | BI34: Moyen | BJ34: protéger du soleil (casquette + crème) | BK34: autonome mais a besoin de temps | BL34: il va seul aux toilettes | BM34: - | BN34: pas nécessaire | BO34: 0
A35: 160 | B35: 37847.64 | C35: 2210 | D35: 2210 | E35: 0 | F35: 0 | I35: FALSE | J35: FALSE | K35: FALSE | L35: FALSE | M35: FALSE | N35: FALSE | O35: FALSE | P35: FALSE | Q35: FALSE | S35: Il nage avec un gilet de sauvetage | T35: TRUE | U35: FALSE | X35: FALSE | Y35: FALSE | Z35: FALSE | AA35: FALSE | AB35: Il parle | AC35: Ce qu'il préfère c'est aller au cinéma. | BB35: 0 | BC35: 0 | BD35: 0 | BE35: 0 | BG35: IMC | BH35: troubles moteurs | BJ35: supporte le soleil avec un chapeau
A36: 166 | B36: 41927 | I36: FALSE | J36: FALSE | K36: FALSE | L36: FALSE | M36: FALSE | N36: FALSE | O36: FALSE | P36: FALSE | Q36: FALSE | T36: FALSE | U36: FALSE | X36: FALSE | Y36: FALSE | Z36: FALSE | AA36: FALSE
A37: 167 | B37: 37858.51 | C37: 2210 | D37: 166 | F37: 0 | G37: 269 | I37: FALSE | J37: FALSE | K37: FALSE | L37: FALSE | M37: FALSE | N37: FALSE | O37: FALSE | P37: FALSE | Q37: FALSE | S37: Faire attention à sa sonde et soutenir Janique selon son besoin. | T37: FALSE | U37: TRUE | X37: FALSE | Y37: FALSE | Z37: FALSE | AA37: FALSE | AB37: oral | AC37: Elle s’exprime elle-même à se sujet. | AG37: cartes, jeux de société (Hâte-toi lentement...) | BB37: 0 | BC37: 0 | BE37: 0 | BG37: IMC | BH37: troubles moteurs, troubles visuels. | BJ37: protéger Janique du soleil (chapeau, crème).
A38: 175 | B38: 37858.71 | C38: 0 | D38: 174 | E38: 0 | F38: 269 | G38: 269 | I38: FALSE | J38: FALSE | K38: FALSE | L38: FALSE | M38: FALSE | N38: FALSE | O38: FALSE | P38: FALSE | Q38: FALSE | S38: Christophe a besoin d’une bouée adaptée et d’être soutenu. | T38: FALSE | U38: TRUE | X38: FALSE | Y38: FALSE | Z38: FALSE | AA38: FALSE | AB38: Christophe s’exprime à l’aide d’un tableau « Bliss ». | AC38: Christophe aime bien le football, le hockey et le tennis. Il aime bien discuter avec les acompagnant(e)s. | AG38: Les expositions de peinture etc. | BA38: 107 | BB38: 0 | BC38: 0 | BD38: 0 | BE38: 0 | BG38: IMC | BH38: troubles moteurs | BJ38: protéger Christophe du soleil (chapeau, crème)
A39: 177 | B39: 42888 | D39: 2210 | E39: -1226171744 | F39: 2146189103 | G39: -1226171744 | H39: Steve Quarroz 024 473 52 30 | I39: FALSE | J39: TRUE | K39: FALSE | L39: TRUE | M39: FALSE | N39: FALSE | O39: FALSE | P39: TRUE | Q39: TRUE | R39: Supporte les longs trajets en bus. Se déplace quelquefois à 4 pattes. | S39: Vlada a besoin d'être soutenue. | T39: FALSE | U39: TRUE | V39: Aide totale pour s'habiller - Arrive à se déshabiller | W39: Position: plutôt sur le ventre et sans coussin. ETRE ATTENTIF DURANT LA VEILLE (fait des crises d'épilepsie durant le nuit) | X39: FALSE | Y39: FALSE | Z39: FALSE | AA39: TRUE | AB39: Langage oral | AC39: Parents mariés | AD39: Vlada a une sœur (Malina de 1984 qui est mariée à Davide). 3 neveux (Avril née en 2007, Maorie née en 2010, Siloé né en 2015) | AF39: Elle aime bien écouter de la musique et des histoires d’enfants. Elle aime danser. Elle cherche le contact avec les adultes. Elle aime aussi les poupées, les chiens et les chats (mais de loin). Elle aime aussi les motos. | AH39: A besoin d'aide pour couper fin les aliments. Elle mélange le chaud et le froid; ce qui est froid elle dit chaud. | AI39: Poisson, moules et fruits de mer | AJ39: éviter les aliments trop sucré, proposer des fruits à la place. Etre attentif à son régime alimentaire : beaucoup de salades, de légumes et de fruits. | AK39: N'aime pas les carottes cuites et les petits pois. | AL39: crème, fromage et viande grasse | AM39: Boit normalement sans paille | AO39: Pas de boissons trop sucrées | AP39: le lait entier (de préférence lait maigre) | BA39: 107 | BB39: 2146189422 | BC39: 0 | BD39: 2146188971 | BE39: 2146188971 | BF39: 95278823 | BG39: hémiplégie côté droit IMC | BH39: Handicap mental, épilepsie | BI39: Elevé | BJ39: Vlada doit être protégée du soleil (crème, chapeau) | BK39: Durant week-end toilette au lit 1fois par jour. Durant les camps regarder avec elle pour prendre la douche. Pour chaque soins bien rincer le savon et bien essuyer. | BL39: Elle demande "j'ai mal au ventre" pour aller au WC. Elle s'essuie toute seule pour l'urine mais avec aide pour les selles. Elle va au lever à selles tous les jours. | BM39: faire au minimum 1 changement de position par jour | BN39: soit assise par terre avec les jambes devant, soit dans le lit. En lui tenant les 2 main, elle arrive à marcher sur des courtts trajets (WC-Pour aller au lit) | BO39: min. 1 fois par jour
A40: 179 | B40: 38104.568 | C40: 0 | D40: 0 | E40: 0 | F40: 0 | G40: 0 | I40: FALSE | J40: FALSE | K40: FALSE | L40: FALSE | M40: FALSE | N40: FALSE | O40: FALSE | P40: FALSE | Q40: FALSE | S40: Surveiller Kathia à cause des crises d'épilepsie | T40: FALSE | U40: TRUE | X40: FALSE | Y40: FALSE | Z40: FALSE | AA40: FALSE | AB40: Oral | AC40: Kathia a un frère qui s'appelle Gabriel (1979) et qui a une copine (Chimène). Elle aime bien Roch Voisine. Elle travaille aux ateliers de la FOVHAM à Sion. | BA40: 0 | BB40: 0 | BC40: 0 | BD40: 0 | BE40: 0 | BG40: IMC Légère | BH40: Epilepsie de 1x par semestre à 4x par mois. Facteur déclencheur: boisons sucrée et dessert et émotion forte | BJ40: Rhume des foins
A41: 182 | B41: 42632 | C41: 131 | D41: 0 | E41: 0 | F41: 269 | I41: FALSE | J41: TRUE | K41: TRUE | L41: FALSE | M41: FALSE | N41: TRUE | O41: FALSE | P41: TRUE | Q41: TRUE | R41: Elle ne sait pas calculer le retour de la monnaie. Elle supporte les long trajets. | S41: Elle n'aime pas aller à la piscine. | T41: FALSE | U41: TRUE | V41: Elle a besoin d'aide pour mettre ses chaussettes, ses souliers, son pantalon. | X41: FALSE | Y41: FALSE | Z41: FALSE | AA41: FALSE | AB41: oral, elle a tendance à se faire appeler Catherine. | AG41: La piscine et la bateau | AH41: Elle mange seule, éventuellement lui couper les aliments plus durs. | AK41: Ne mange pas le poulet | AL41: Fraises (allergies !!!!!) | BA41: 107 | BB41: 0 | BC41: 0 | BD41: 2146188975 | BE41: 2146188975 | BF41: 186 62 228 | BG41: Non défini | BH41: troubles moteurs | BJ41: Médicaments autorisés: Panadol, Dafalgan. Autres à bannir. ELLE EST ALLERGIQUE AUX FRAISES !!!!! | BK41: Douche, soins infirmiers | BL41: Gisèle est autonome. Elle a une sonde sus pubienne. | BN41: ----
A42: 184 | B42: 37833.451 | C42: 2210 | D42: 418487882 | F42: 269 | G42: 269 | I42: FALSE | J42: FALSE | K42: FALSE | L42: FALSE | M42: FALSE | N42: FALSE | O42: FALSE | P42: FALSE | Q42: FALSE | S42: présence d’une personne obligatoire pour le tenir, de préférence un gilet, Fabian n’aime pas l’eau froide. | T42: TRUE | U42: TRUE | X42: FALSE | Y42: FALSE | Z42: FALSE | AA42: FALSE | AB42: Fabian parle et comprend tout. Il faut lui parler lentement et il a besoin de temps pour répondre. Il apprécie les questions aux réponses : oui ou non | AC42: Fabian est passionné de cirque et il a de nombreux contact avec le cirque Knie. Il apprécie également se promener en ville, aller au restaurant, voire du monde et être en contact avec des gens. Il va régulièrement chez sa mère avec sa sœur Janique qui est | AD42: Fabian a 2 sœurs: Janique et Nathalie | AF42: Fabian est passionné de cirque et il a de nombreux contact avec le cirque Knie. Il apprécie également se promener en ville, aller au restaurant, voire du monde et être en contact avec des gens. Il va régulièrement chez sa mère avec sa sœur Janique qui est également résidente à Valais de Cœur. | AG42: la discothèque car il y a trop de brui. | BA42: 107 | BB42: 0 | BC42: 0 | BD42: 0 | BG42: IMC | BH42: troubles moteurs | BJ42: A protéger du soleil. Il a parfois le rhume des foins. | BM42: TROP PETIT???
A43: 252 | B43: 42327 | C43: 0 | D43: 0 | E43: 0 | G43: 0 | I43: FALSE | J43: FALSE | K43: FALSE | L43: FALSE | M43: FALSE | N43: FALSE | O43: FALSE | P43: FALSE | Q43: FALSE | T43: FALSE | U43: FALSE | X43: FALSE | Y43: FALSE | Z43: FALSE | AA43: FALSE | BA43: 0 | BB43: 0 | BC43: 0 | BE43: 0
A44: 279 | B44: 37916.59 | C44: 0 | D44: 0 | E44: 0 | F44: 0 | G44: 0 | I44: FALSE | J44: FALSE | K44: FALSE | L44: FALSE | M44: FALSE | N44: FALSE | O44: FALSE | P44: FALSE | Q44: FALSE | S44: Elle aime bien la piscine | T44: FALSE | U44: FALSE | X44: FALSE | Y44: FALSE | Z44: FALSE | AA44: FALSE | AB44: oral | AC44: Vaishali aime jouer du piano. Elle adore bricoler, faire du dessin, jouer à des jeux de société. Elle apprécie la piscine et aller au cinéma. Elle aime aussi faire la vaisselle et aider les autres enfants. Remarques: Vaishali est grande copine avec M | BA44: 0 | BB44: 0 | BC44: 0 | BD44: 0 | BE44: 0 | BG44: Poliomyélite | BH44: --------- | BJ44: ---------
A45: 280 | B45: 37846.615 | C45: 2210 | D45: 1103 | E45: 0 | F45: 0 | G45: 0 | I45: FALSE | J45: FALSE | K45: FALSE | L45: FALSE | M45: FALSE | N45: FALSE | O45: FALSE | P45: FALSE | Q45: FALSE | S45: Fabien nage seul. | T45: FALSE | U45: FALSE | X45: FALSE | Y45: FALSE | Z45: FALSE | AA45: FALSE | AB45: Fabien cherche par tous les moyens de se faire comprendre, mais il n’est pas toujours facile de le comprendre. | AC45: Fabien a un grand frère qui s’appelle Léonard et qui a le même handicap que lui. | BB45: 0 | BC45: 0 | BD45: 1533 | BE45: 1533 | BG45: IMC léger | BH45: handicap mental | BJ45: Protéger Fabien du soleil (chapeau, crème)
A46: 281 | B46: 42482 | C46: 280 | D46: 1103 | E46: 1192527076 | F46: 1465 | G46: 0 | I46: FALSE | J46: TRUE | K46: FALSE | L46: FALSE | M46: TRUE | N46: FALSE | O46: FALSE | P46: FALSE | Q46: FALSE | S46: Léonard nage seul. | T46: FALSE | U46: TRUE | X46: FALSE | Y46: FALSE | Z46: FALSE | AA46: FALSE | AB46: Léonard cherche par tous les moyens à se faire comprendre. Il n'est pas toujours facile de la comprendre. | AC46: Léonard a un petit frère qui s'appelle fabien et qui a le même handicap que lui. | AH46: Éviter de mettre Léonard en face de son frère (Fabien) durant les repas, ils ont tendance à se provoquer. Faire attention à ce qu'il ne mange pas trop et trop vite. | AJ46: Attention à ce qu'il ne mange pas trop. | AN46: Le coca | AO46: Favoriser l'eau plate (Henniez) | BA46: 2146188980 | BB46: 0 | BC46: 0 | BD46: 2146188981 | BE46: 2146188982 | BF46: 1223-4288-7 | BG46: IMC léger | BH46: graves difficultés d’élocution, handicap mental, troubles moteurs. | BI46: Elevé | BJ46: protéger Léonard du soleil (chapeau, crème). | BK46: Rasage + brossage des dents | BL46: Léonard est autonome.
A47: 283 | B47: 37847.463 | C47: 0 | D47: 0 | E47: 0 | F47: 0 | G47: 0 | I47: FALSE | J47: FALSE | K47: FALSE | L47: FALSE | M47: FALSE | N47: FALSE | O47: FALSE | P47: FALSE | Q47: FALSE | S47: Avec des manchons et une surveillance total. Il aime beaucoup l'eau. | T47: FALSE | U47: TRUE | X47: FALSE | Y47: FALSE | Z47: FALSE | AA47: FALSE | AB47: Philippe ne parle pas, mais essaye de se faire comprendre par exemple en prenant la main | AC47: Il aime jouer aux Duplo: démonter des constructions. Il apprécie tous les jeux de la 1ère enfance, du 1er âge. Il aime écouter de la musique prendre la douche et aller à la piscine. | AG47: il n'aime pas la foule. | BA47: 2151 | BB47: 107 | BC47: 0 | BE47: 0 | BG47: Trisomie 13 | BH47: handicap mental, malvoyant (lui indiquer les reliefs), troubles de l'ouïe (perçoit mieux les sons graves). | BJ47: Chronique
A48: 286 | B48: 37847.417 | C48: 145 | D48: 2210 | E48: 0 | F48: 0 | I48: FALSE | J48: FALSE | K48: FALSE | L48: FALSE | M48: FALSE | N48: FALSE | O48: FALSE | P48: FALSE | Q48: FALSE | S48: Lionel a besoin d’aide pour rentrer dans la piscine. | T48: FALSE | U48: TRUE | X48: FALSE | Y48: FALSE | Z48: FALSE | AA48: FALSE | AB48: Oral | AC48: Lionel aime bien participer aux activités de Sport-Handicap, regarder des match de football et aller au cinéma. Il a un petit frère que s'appelle Jonas. | BA48: 107 | BC48: 0 | BE48: 0 | BG48: maladie neuromusculaire | BH48: troubles moteurs | BJ48: protéger Lionel du soleil (chapeau, crème).
A49: 287 | B49: 42886 | C49: 144 | D49: 0 | E49: 0 | F49: 1424 | G49: 2146189446 | H49: B4 Maria 024 473 51 48 | I49: FALSE | J49: TRUE | K49: TRUE | L49: FALSE | M49: FALSE | N49: FALSE | O49: FALSE | P49: TRUE | Q49: FALSE | R49: Alain supporte difficilement les longs trajets en bus. De préférence, le placer à l'avant du véhicule. | S49: avec de manchons et une bouée fournie par ses parents. Alain n'apprécie plus beaucoup la piscine. | T49: FALSE | U49: TRUE | V49: aide totale | W49: horaire normal | X49: FALSE | Y49: FALSE | Z49: FALSE | AA49: TRUE | AB49: Alain s’exprime à l’aide d’un tableau. | AC49: Alain a deux sœurs Nathalie qui est mariée à Olivier et qui ont cinq filles (Clémence, Mathilde, Véronique, Delphine et Rachel) et Christelle qui est mariée à Thierry et ont trois enfants (Benjamin, Mathias et Sarah). | AF49: le football, les sorties au restaurant, le cinéma et les concerts. Savoir le programme du jour. | AG49: Carnaval | AH49: Incliner légèrement son fauteuil en arrière pour faciliter la déglutition.Couper fin et très petit et si trop sec rajouter du lait ou de la mayonnaise. Alimentation normale. Couper fin et lui donner à manger. Rajouter sauce, lait ou autre. | AI49: Raclette, poisson | AM49: Il boit à la paille. | AN49: Tout | AP49: Alcool | BA49: 2146189786 | BB49: 0 | BC49: 0 | BD49: 2146189004 | BE49: 2146189004 | BF49: 036628 | BG49: IMC profond | BH49: handicap mental, troubles moteurs. | BI49: Elevé | BJ49: protéger Alain du soleil (chapeau, crème).Il a une peau très sensible, faire attention aux coups de soleil. | BK49: aide complète. Attention a bien mettre son plateau pour éviter les blessures aux genoux. Chaise percée pour douche tous les jours | BL49: Alain a une autonomie moyenne. Par commodité, il est langé à l'extérieur de la maison. Au changement de lange (matin, midi, soir, avant le coucher), lui demander s'il veut aller aux toilettes. | BM49: massage des pieds et des fesses. Surveillance de sa peau (frottements) | BN49: Légèrement incliné pour faciliter la déglutition. | BO49: chaque 5 heures
A50: 290 | B50: 37847.565 | C50: 150 | D50: 0 | E50: 0 | I50: FALSE | J50: FALSE | K50: FALSE | L50: FALSE | M50: FALSE | N50: FALSE | O50: FALSE | P50: FALSE | Q50: FALSE | S50: Elle sait nager sur le dos, sans manchons. Mais il faut quand même être près d’elle pour lui indiquer la direction. | T50: FALSE | U50: TRUE | X50: FALSE | Y50: FALSE | Z50: FALSE | AA50: FALSE | AB50: Oral | AC50: Tatjana aime bien faire du bricolage, écouter de la musique et être avec des amis. Elle aime aussi les animaux (zoo, ferme), aller à cheval et lire. | AG50: Les bruits forts, vite effrayée: pétards, tambours | BA50: 2134 | BB50: 0 | BC50: 0 | BE50: 0 | BG50: IMC | BH50: aucun | BJ50: Si elle est malade, il faut lui donner des médicaments à base de plantes.
A51: 292 | B51: 42920 | D51: 188 | E51: 0 | F51: 1424 | G51: 188 | H51: Groupe C2 - Rossi Marisa - 024 473 51 52 | I51: FALSE | J51: FALSE | K51: FALSE | L51: TRUE | M51: FALSE | N51: FALSE | O51: FALSE | P51: TRUE | Q51: FALSE | R51: fauteuil manuel : il doit être assis bien droit, il doit être assis bien droit, mettre toujours les sangles (il faut le faire à sa place) - +boissoin rafraîchissante | S51: Il flotte très naturellement. | T51: TRUE | U51: TRUE | V51: Aide totale. A la mise en place des chaussures veiller à rentrer correctement les orteils à plat car il risque des lésions. | W51: Lui donner sa musiquette et des peluches(de préférence, sinon il part gentiment de son matelas) | X51: FALSE | Y51: FALSE | Z51: FALSE | AA51: TRUE | AB51: Avec son regard.Lionel est sourd. Faire attention à ce qu’il y a sur la table, il prend tout dans la main. | AC51: Aime Coralie sa nièce de 11 ans. | AD51: 1 frère 1 nièce | AF51: Lionel aime bien les câlins, les promenades. Aime la télévision, spectacle | AG51: se mouvoir pour se déplacer. | AH51: Lionel mange de tout, il vaut mieux lui donner une sauce avec les aliments. Il a besoin que ses aliments soient mixés très fin. Lui donner deux gobelets en cas de chaleur car il se déshydrate facilement et est vite constipé. Pour un pic-nic une tranche de mousse de canard est par exemple facile à lui donner. Yaour, compote, semoule. Lui donner une sauce avec les aliments - Mixé très fin Si pic-nic donner une tranche de mousse de canard Mettre une cuillère dans la bouche et lui présenter un une boisson dans un gobelet | AI51: Jus de fruits et frappés - Mange de tout. Cacao - café.Jus d'orange le matin. | AJ51: Mixé très fin | AM51: Avec épaissisant (texture similaire au yoghourt), et lui donner avec une cuillère. | AN51: Il aime particulièrement café, chocolat. Il boit de tout.Boissons froides et jus d'orange | AP51: boissons gazeuses. Les boissons ne doivent pas être bouillantes (tièdes) | BA51: 2146189786 | BB51: 2146189787 | BC51: 0 | BD51: 1948 | BE51: 1948 | BG51: IMC profond | BH51: Handicap mental | BI51: Elevé | BJ51: Soleil (le mettre à l'ombre et l'enduire d'une protection haute effiacité. | BK51: douche à l’aide d’un lit-douche (il apprécie beaucoup les bains relaxants). En cas de grande chaleur, il peut avoir la diarrhée. Il a une peau qui se dessèche vite (appliquer une crème hydratante) surtout sur la figure et les mains. | BL51: Lionel a besoin qu’on lui mette des couches et qu’on lui les change (matin, midi, soir). | BM51: Etre attentif à son siège, bas du dos.Il faut bien le fixer à l’aide du matériel qui compose son fauteuil. | BN51: Oui. Changement de position: l'assoir dans un hamac ou foteuil relax | BO51: 2 fois par jour minimum
A52: 296 | B52: 37859.535 | C52: 0 | D52: 0 | E52: 0 | F52: 0 | I52: FALSE | J52: FALSE | K52: FALSE | L52: FALSE | M52: FALSE | N52: FALSE | O52: FALSE | P52: FALSE | Q52: FALSE | S52: Il sait nager, il apprécie la piscine | T52: FALSE | U52: FALSE | X52: FALSE | Y52: FALSE | Z52: FALSE | AA52: FALSE | AB52: oral | BA52: 0 | BB52: 0 | BC52: 0 | BE52: 0 | BG52: myopathie | BJ52: il est allergique à la Pennicelyne (à la place prendre de la cloroxine ou un dérivé)
A53: 297 | B53: 42972 | C53: 1137414434 | D53: 163 | E53: 0 | F53: 1424 | G53: 1424 | H53: A3 024/473.51.23 ou la reception 024/473.51.41 | I53: FALSE | J53: TRUE | K53: TRUE | L53: TRUE | M53: FALSE | N53: FALSE | O53: FALSE | P53: FALSE | Q53: TRUE | R53: Supporte les longs trajets en bus - Inclinaison dans le fauteuil si une longue période assise. | S53: Ne peut pas nager, le soutenir en permanence de préférence avec un gilet. | T53: TRUE | U53: TRUE | V53: Aide totale pour l’habillement et le déshabillement. Habillage du haut : d’abord bras gauche, tête, bras droit, et le contraire pour déshabiller. Steeve peut nous aider pour se tourner sur le côté, se soulever le bassin, etc. | W53: Steeve a besoin de repos, il s’endort sur le dos sans oreiller mais en levant légèrement le dossier du lit. Coussin de sable sur le côté gauche et peau de mouton sous les pieds. Vu qu’il est long, il faut être attentif que ses pieds ne frottent pas le fond du lit. La nuit, il n’y a pas de changement de position à faire. | X53: FALSE | Y53: FALSE | Z53: FALSE | AA53: TRUE | AB53: langage oral Steeve est une personne très sociale qui sait très bien s’exprimer s’il désire quelque chose. Il est INDISPENSABLE d’avoir un homme comme accompagnant car il a tendance à vite tomber amoureux et il se construit des scénarios qui ne correspondent pas à la réalité. Il est important d’être clair dans les consignes et bien fixer les limites. Possibilité de déplacement : fauteuil électrique, sa batterie ne doit pas être déchargée complètement. La charger tous les soirs. Pour incliner la chaise, appuyer 2x bouton "mode" avec joystick, allumer 2 boutons rouges : siège/dossier, puis on peut basculer la chaise. C’est un moyen pour changer de position en cas de déplacement. | AC53: Les parents sont divorcés mais c’est la maman et le papa qui assurent le suivi de Steeve. | AD53: Aurélia / nièce : Alya Benjamin | AE53: camarade de chambre à la Castalie : Thierry | AF53: Steeve aime la musique en général, chanter, le foot à la télé, les promenades en ville, le cinéma, les spectacles, etc. Il apprécie son travail à l’atelier tricotin chez Véronika et il cherche tout ce qui renforce le côté masculin afin de s’identifier. Il a besoin d’être reconnu et valorisé dans les activités qu’il entreprend. | AG53: Il n'aime pas être seul. | AH53: Lui couper la nourriture. Dans son gobelet avec la paille, sa cuillère et son assiette spéciale, Steeve mange seul et parfois avec un peu d’aide. | AI53: petit déjeuner : plutôt salé | AJ53: Steve a repris du poids. Actuellement, être attentif à ses apports caloriques. Travailler sur les quantités, priviléger légumes/salades. | AK53: Les choux, la charcuterie, les concombres et les endives cuites, les fenouils entre autre, car il n'apprécie pas les légumes. | AM53: lui donner dans un verre avec une paille ou en lui donnant. | AN53: café, coca-cola | AP53: Attention : pas de trop grandes quantités de boissons sucrées | AQ53: - | BA53: 107 | BB53: 0 | BC53: 0 | BD53: 2146189004 | BE53: 2146189004 | BF53: 756.9638.5935.42 | BG53: IMC | BH53: retard mental, troubles moteurs, malvoyant, malformation à la hanche droite et hypertension en cas d’émotion. | BI53: Elevé | BJ53: A protéger du soleil (casquette, crème, lunettes). | BK53: Steeve a besoin d’une aide complète. En principe une douche chaque 2 jours. Etre attentif à bien le sécher après la toilette. Steeve a également le pied gauche qui est marqué par plusieurs petits accidents. Ce ne sont pas des escarres.Il suffit de masser le pied afin de faire circuler le sang. A être attentif aux rougeurs au niveau des fesses et des pieds et aux mycoses entre les orteils et sous les aisselles. | BL53: Steeve est langé jour et nuit. A changer les protections le matin, midi, soir et en cas de besoin. Le matin et le soir lui mettre la bouteille. | BM53: pas de risque majeur | BN53: oui | BO53: après-dîner et après souper env. 30 min
A54: 301 | B54: 42327 | C54: 0 | D54: 155 | E54: 0 | F54: 0 | I54: FALSE | J54: FALSE | K54: FALSE | L54: FALSE | M54: TRUE | N54: FALSE | O54: FALSE | P54: FALSE | Q54: FALSE | S54: Il nage tout seul | T54: FALSE | U54: TRUE | X54: FALSE | Y54: FALSE | Z54: FALSE | AA54: FALSE | AB54: oral Il travail a la Coop à Sion. | AC54: Patrick aime le football, le tennis, le ski, le vélo. Il aime bien aller visiter des musées, faire des ballades en bateau, sortir en disco. | BA54: 2146189002 | BC54: 0 | BE54: 0 | BG54: PSO (psycho-syndrome organique) | BH54: Handicap mental, retard mental, Hyperactif, troubles du comportement, problème de cœur | BJ54: rhume des foins, allergique à la penicilline | BL54: Autonome
A55: 302 | B55: 42852 | C55: 1298966339 | D55: 173 | E55: 1298966339 | F55: 1424 | G55: 2146189128 | H55: C1 - Léonardo Pamelli - 024 473 51 51 | I55: FALSE | J55: TRUE | K55: FALSE | L55: TRUE | M55: FALSE | N55: FALSE | O55: FALSE | P55: TRUE | Q55: FALSE | R55: Supporte les longs trajets en bus. Position dans le fauteuil : bien au fond, bien droite (remarque générale) | S55: Aide et dépendance totale | T55: TRUE | U55: TRUE | V55: Aide totale | W55: Dort sur le dos ou en latéral gauche avec barrières des deux côtés | X55: FALSE | Y55: FALSE | Z55: FALSE | AA55: TRUE | AB55: Langage oral : petits cris répétitifs : signes de mauvaise humeur. Se secoue et se balance dans sa sa chaise. Rigole bien quand on est seul avec elle | AC55: Mère : Gabrielle - fait des veilles donc n'est pas toujours disponible la journée Père : Jean-Luc - divorcé | AF55: Musique (Pierre Bachelet, Céline Dion, Joe Dassin) Ecouter de la muique et danser, se promener, faire la fête, feuilleter son livre | AG55: Activités avec trop de bruits subits (ex. pétard) | AH55: Aide totale : Support en bois avec un trou pour l'assiette pour qu'elle puisse manger seule. Mettre les médicaments dans la première cuillère et lui donner - Manger : couper fin - mange seule + rebord d'assiette. Tartine: humidifier avec du lait les tartines! Essaier de lui mettre le verre et la cuillère dans la main droite pour qu'elle mange seule. Elle mange plus le matin et le soir qu'à midi. Après le repas, lui donner son petit classeur. La faire manger à l'écart du groupe. La prise d'aliment sera ainsi facilité. | AI55: Aime manger - kellogg's pour le déjeuner | AK55: N'aime pas le poisson! | AM55: Elle boit avec un goblet toute seule, la forcer un peu car n'aime pas boire. Rester à côté d'elle car elle renverse son verre lorsqu'elle a fini. | AN55: Café sucré. Un verre de thé avant le cacao sinon elle ne boit pas. | BB55: 0 | BC55: 0 | BD55: 2146189010 | BE55: 2146189010 | BF55: 0342936 | BG55: IMC avec tétraplégie, spastique et retard mental important | BH55: Handicap mental, - retard mental important épilepsie, malvoyante, troubles moteurs | BI55: Elevé | BJ55: Soleil | BK55: Aide totale : Important de bien laver et sécher en tamponnant les parties intimes (grandes lèvres) car risque important d'inflammations. Lors de la sieste elle dort sur le dos et le soir contre le mur. | BL55: Aide totale : langée jour et nuit | BM55: A une tige le long de la colonne vertébrale. La solliciter et lui expliquer ce que l'on fait. Elle dort contre le mur + coussin entre les jambes | BN55: couchée sur le dos | BO55: à la demi-journée
A56: 303 | B56: 42502 | C56: 176 | I56: FALSE | J56: TRUE | K56: TRUE | L56: TRUE | M56: FALSE | N56: FALSE | O56: FALSE | P56: TRUE | Q56: FALSE | R56: Oui mais changement de position après 2 heures de route. | S56: ne sait pas nager, il a besoin d’une bouée et d’une personne pour le soutenir. Il déteste avoir la tête sous l’eau. Après 20 min, il en a marre. Faire attention qu'il ne boive pas la tasse. | T56: FALSE | U56: TRUE | V56: Oui, aide totale. | W56: En principe, elle se couche vers 20h45 (à voir avec son comportement). Elle se lève vers 8h00. Elle dort sur le coté ou à plat ventre. Lui donner un petit bout de gaze dans le coin de la bouche pour s’endormir. Le soir, lui mettre un lange et mettre deux alaises pour éviter qu'elle mouille son lit. Il lui arrive, parfois, de faire des crises d’épilepsie durant son sommeil. Samuel se couche environ 1h, 1h30 pour détendre son dos après diner. | X56: FALSE | Y56: FALSE | Z56: FALSE | AA56: TRUE | AB56: Il communique à l’aide de cris et de sourires lorsqu’il est content. Il crie et pleure quand il ne l’est pas. Lorsqu'il n'aime pas quelque chose, il fait des grimaces. | AC56: Nicolas a 3 frères; un s'appelle Gabriel et travaille à la bijouterie.Il a 2 enfants et la fille a aussi 2 enfants. Un autre de ses frères s'appelle Emannuel et a le magasin d'optique à Sion. Il a 3 filles. le 3ème frère haite au Tessin | AF56: les promenades et la musique plus tôt douce. Lorsqu'il est à l'extérieur bien freiner sa chaise pour pas qu'il ne parte. | AG56: Il n’a pas d’activité peu appréciée. Il n'aime pas trop être touché et toucher les objets de lui-même car il a une hypersensibilité au niveau des mains | AH56: Samuel aime tout. Lui donner à manger. Couper très fin, écraser les patates et les légumes et hacher la viande car Samuel ne mâche pas. Soulever le menton pour donner à manger ou à boire. Samuel mange volontiers des fruits pour le goûter. Ne pas lui donner les aliments en bouillie. | AJ56: Samuel doit surveiller son poids, 1 assiette à soupe + ¼ lui suffise. En principe, il ne mange pas entre les repas. | AM56: lui donner. Lui faire tenir son verre avec la main droite mais la soutenir quand même sinon il le lâche. Vu son insuffisance rénale doit boire souvent. | AP56: Samuel n’aime pas les boissons gazeuses et froides. | BA56: 107 | BD56: 2146189005 | BE56: 2146189005 | BF56: 756.30.84.5679.59 | BG56: IMC | BI56: Elevé | BJ56: Parfois les yeux rouges et le nez qui coule dû au pollen. Rincer les narines 3x par jour avec le Fluimare. | BK56: Samuel bave. Lui mettre une bavette sur la veste ou le pull lors des sorties. Pour la toiliette: aide totale. Lors du brossage des dents, Samuel avale le dentifrice et l’eau de rinçage qui doit être chaude. Après la douche, bien sécher au foehn les plis des cuisses, entre les orteils et les doigts et mettre la crème au visage. Au coucher, bien nettoyer le visage et ne pas lui mettre de crème. Pas besoin de raser Samuel. | BL56: Samuel est langé jour et nuit. Changement de lange 3x par jour. Le mettre si possible au toilette sur un rehausseur 15 min après les repas. | BO56: chaque 2 heures
A57: 429 | B57: 42248 | I57: FALSE | J57: FALSE | K57: FALSE | L57: FALSE | M57: FALSE | N57: FALSE | O57: FALSE | P57: FALSE | Q57: FALSE | T57: FALSE | U57: FALSE | X57: FALSE | Y57: FALSE | Z57: FALSE | AA57: FALSE
A58: 450 | B58: 37860.686 | C58: 0 | D58: 0 | E58: 0 | F58: 0 | G58: 0 | I58: FALSE | J58: FALSE | K58: FALSE | L58: FALSE | M58: FALSE | N58: FALSE | O58: FALSE | P58: FALSE | Q58: FALSE | T58: FALSE | U58: FALSE | X58: FALSE | Y58: FALSE | Z58: FALSE | AA58: FALSE | BA58: 0 | BB58: 0 | BC58: 0 | BE58: 0
A59: 455 | B59: 40933 | I59: FALSE | J59: FALSE | K59: FALSE | L59: FALSE | M59: FALSE | N59: FALSE | O59: FALSE | P59: FALSE | Q59: FALSE | T59: FALSE | U59: FALSE | X59: FALSE | Y59: FALSE | Z59: FALSE | AA59: FALSE
A60: 857 | B60: 40933 | I60: FALSE | J60: FALSE | K60: FALSE | L60: FALSE | M60: FALSE | N60: FALSE | O60: FALSE | P60: FALSE | Q60: FALSE | T60: FALSE | U60: FALSE | X60: FALSE | Y60: FALSE | Z60: FALSE | AA60: FALSE
A61: 1414 | B61: 42289 | I61: FALSE | J61: FALSE | K61: FALSE | L61: FALSE | M61: FALSE | N61: FALSE | O61: FALSE | P61: FALSE | Q61: FALSE | T61: FALSE | U61: FALSE | X61: FALSE | Y61: FALSE | Z61: FALSE | AA61: FALSE
A62: 1447 | B62: 42145 | C62: -1771355288 | D62: 1231699724 | E62: 0 | F62: 1424 | I62: FALSE | J62: FALSE | K62: TRUE | L62: FALSE | M62: TRUE | N62: FALSE | O62: FALSE | P62: FALSE | Q62: FALSE | R62: supporte les longs trajets | S62: Elle peut aller dans la piscine mais toujours avec une aide. Elle ne nage pas. | T62: FALSE | U62: TRUE | V62: se débroille seul | X62: FALSE | Y62: FALSE | Z62: FALSE | AA62: FALSE | AB62: verbale | AC62: Elle aime jouer avec les jeux de société, écouter de la musique, dessiner et aime être assise. éviter la surprotection. Elle a de la difficulté à être dans un rythme | AG62: Elle n'aime pas se mouvoir, elle aime être passive | AS62: 1429891015 | AT62: 1231232923 | AU62: 1290764579 | BA62: 107 | BB62: 0 | BC62: 0 | BD62: 1533 | BE62: 1533 | BG62: Spidia-bifida | BH62: Handicap mental, troubles moteurs et sphincters | BJ62: non
A63: 1452 | B63: 37858.369 | C63: 132 | D63: -936114117 | E63: 0 | F63: 269 | G63: 269 | I63: FALSE | J63: FALSE | K63: FALSE | L63: FALSE | M63: FALSE | N63: FALSE | O63: FALSE | P63: FALSE | Q63: FALSE | S63: Sandrine a besoin de l’aide d’une personne. | T63: FALSE | U63: FALSE | X63: FALSE | Y63: FALSE | Z63: FALSE | AA63: FALSE | AB63: oral | AC63: Sandrine parle de tout. Elle aime sortir, rencontrer des gens. | BA63: 107 | BB63: 0 | BC63: 0 | BD63: 1533 | BE63: 1533 | BG63: Spina Bifida | BH63: handicap mental (léger), troubles moteurs. | BJ63: protéger Sandrine du soleil (chapeau, crème)
A64: 1507 | B64: 37847.367 | C64: 125 | D64: 0 | E64: 0 | F64: 0 | I64: FALSE | J64: FALSE | K64: FALSE | L64: FALSE | M64: FALSE | N64: FALSE | O64: FALSE | P64: FALSE | Q64: FALSE | S64: Sapna sait nager. Elle apprécie la piscine. | T64: FALSE | U64: TRUE | X64: FALSE | Y64: FALSE | Z64: FALSE | AA64: FALSE | AB64: oral | AC64: Sapna aime bien faire les magasins, écouter de la musique et aller en discothèque. | AG64: Sapna n'aime pas les promenades. | BA64: 1431399595 | BB64: 0 | BC64: 0 | BD64: 1948 | BE64: 1948 | BG64: éctomélie (membres petits) | BH64: aucun | BJ64: Elle est alergique aux piqûres d’insectes (abeilles, moustiques…).
A65: 1508 | B65: 37847.384 | C65: 125 | D65: 0 | E65: 0 | F65: 0 | I65: FALSE | J65: FALSE | K65: FALSE | L65: FALSE | M65: FALSE | N65: FALSE | O65: FALSE | P65: FALSE | Q65: FALSE | S65: Prince ne sait pas nager et il n'aime pas aller à la piscine. | T65: TRUE | U65: TRUE | X65: FALSE | Y65: FALSE | Z65: FALSE | AA65: FALSE | AB65: oral | AC65: Prince aime bien le sport, le foot, le rafroball, aller boire une verre et la bonne ambiance. Il est ouvert à tous les sujets de discussion. | AG65: la piscine, la natation, la plage. | BA65: 1431399595 | BB65: 0 | BC65: 0 | BD65: 1948 | BE65: 1948 | BG65: phocomélie (Prince n’a pas de jambes) | BH65: aucun | BJ65: protéger Prince du soleil (casquette, crème)
A66: 1511 | B66: 42131 | C66: 2210 | D66: 2210 | E66: 0 | F66: 0 | I66: FALSE | J66: FALSE | K66: FALSE | L66: FALSE | M66: FALSE | N66: FALSE | O66: FALSE | P66: FALSE | Q66: FALSE | S66: Maud sait nager et se débrouille seule. | T66: FALSE | U66: TRUE | X66: FALSE | Y66: FALSE | Z66: FALSE | AA66: FALSE | AB66: expression orale | AC66: Le sport en général, le tennis. | BB66: 0 | BC66: 0 | BE66: 0 | BG66: IMC
A67: 1512 | B67: 42852 | C67: 2146189236 | D67: 1542885674 | G67: 1542885674 | I67: FALSE | J67: FALSE | K67: FALSE | L67: TRUE | M67: FALSE | N67: TRUE | O67: FALSE | P67: FALSE | Q67: FALSE | R67: Supporte les longs trajets en bus il les apprécient beaucoup. Samuel marche avec de l’aide pour le guider. Il nous tiens par l'épaule pour marcher, ne pas le laisser trop s’appuyer sur soi. | S67: Samuel apprécie l’eau et les « bulles et massages d’eau » dans les bains thermaux. Une personne doit le tenir continuellement car, il ne nage pas. Il apprécie les jeux dans l’eau : sauter, se faire tirer ou pousser dans l’eau. Il n’aime pas les piscines avec de l’eau « froide ». | T67: FALSE | U67: TRUE | V67: Samuel, avec une stimulation verbale, arrive à ôter ses habits (en phases d’apprentissage). Pour l’habillement, il a besoin de l’aide. | W67: Au coucher, il n’a pas d’habitudes particulières. Il apprécie les massages et les petites histoires, les vacances et les week-ends pas d’horaires. Contrôler env. toutes les 2h sa poche et vider les gaz si nécessaire. • Maintenant il apprécie une sieste si on se couche avec lui, surtout si la journée et les soirées sont bien chargées. Seul, lui passer de la musique. | X67: FALSE | Y67: FALSE | Z67: FALSE | AA67: FALSE | AB67: Il parle et commence à s’affirmer avec le oui et le non. Il a besoin qu’on lui verbalise les activités que l’on fait sur le moment. Cela le rassure et l’aide à se situer. | AC67: Ses grands-parents maternels Benjamin et Eliane. Sa marraine Karine. | AD67: 1 sœur : Catherine de 1989 et 1 frère : Florent de 1986.Il est tonton de Melvin et Gabriel (fils de Catherine et Simon) né en 2011, Théo (fils de Florent et Adriana) né en 2014 et Océane né en 2015 | AF67: Samuel aime les balades à cheval, les bains thermaux, les balades à vélo, les balades et le karaoké (chanter et danser). Il apprécie le contact physique et être contenu dans les bras. | AH67: A mettre une bavette avant le repas. Mixer et couper les aliments fins ou écraser à la fourchette car il ne mâche pas. Samuel arrive à les mettre en bouche avec une cuillère en utilisant un bol ou une assiette à soupe. Lui faire boire au moins 2 littres par jour. | AI67: Il mange de tout, fondue avec patates écrasées (les céréales qui fondent bien eau-lait tiède) | AJ67: sans lactose ni gluten | AK67: les légumes aux vinaigres | AM67: Il doit beaucoup boire, (thé, eau, chocolat chaud, etc.). Le faire boire au verre si on arrive pas lui donner avec la cuillère mais favoriser le verre. Paille-gobelet bec | AN67: Il aime le thé, l'eau et le chocolat chaud sans lactose, sirop, jus de fruits. | AP67: les eaux gazeuses | AS67: 2146189591 | AT67: 2146189770 | AU67: 2146189781 | BA67: 2146189745 | BC67: 0 | BD67: 2146189004 | BE67: 2146189004 | BG67: Micro-céphalie | BH67: non-voyant, stéréotypies, crises d’angoisse avec des cris, retard mental. | BI67: Elevé | BJ67: Le protéger du soleil avec une casquettes. Lunettes de soleil sur l'eau et la neige | BK67: Samuel a besoin d’une aide complète pour sa toilette (laver le visage, les dents, coiffer, etc.). Cependant, il commence à participer à certaines tâches ex. se brosse les dents. Le matin et le soir bien lui laver les parties intimes. Lui changer le lange quand nécessaire. Il porte une sonde sus-pubienne (sans uriflac). Il faut la vider chaque 3-4 heures (pas la nuit). | BL67: Samuel a une culotte en papier (pans) + sonde sus-pubienne. Iliostomie (poche) | BM67: mains sèches
A68: 1513 | B68: 37847.452 | C68: 0 | D68: 0 | E68: 0 | F68: 0 | G68: 0 | I68: FALSE | J68: FALSE | K68: FALSE | L68: FALSE | M68: FALSE | N68: FALSE | O68: FALSE | P68: FALSE | Q68: FALSE | S68: Il aime les piscines avec l'esu chaude. Il faut le soutenir (manchons ou bouée), bien lui soutenir la tête. | T68: FALSE | U68: FALSE | X68: FALSE | Y68: FALSE | Z68: FALSE | AA68: FALSE | AB68: Langage oral. | AC68: Andreï aime écouter de la musique. Il est interéssé par tout ce qui est technique. Il apprécie de discuter et d'être entouré. | BA68: 107 | BB68: 0 | BC68: 0 | BD68: 0 | BE68: 0 | BG68: IMC | BH68: aucun | BJ68: aucune
A69: 1578 | B69: 41092 | C69: 2621 | D69: 1456 | E69: 2621 | F69: 1058535655 | G69: 2621 | I69: FALSE | J69: FALSE | K69: FALSE | L69: FALSE | M69: FALSE | N69: FALSE | O69: FALSE | P69: FALSE | Q69: FALSE | S69: incontinance à gérer + manipulations spéciales | T69: TRUE | U69: TRUE | X69: FALSE | Y69: FALSE | Z69: FALSE | AA69: FALSE | AB69: Normal | AC69: Parents divorcés. La Maman est remariée avec le frêre du père avec lequel elle a eu 2 enfants. Excellents contacts avec les grands-parents de Neuchâtel (Papy et Mamy). | AD69: Un frêre directe, Mathieu (1986) Deux 1/2 frêres Yann (et Jérémie | AE69: Excellents contacts avec son Parrain et sa Maraine (Stéphane et Véronique Délétroz). Entretien des relations avec plusieurs amis | AF69: Voyages en train Il aime la pêche et faire des gâteaux, un peu de cuisine. | AG69: Piscine | AT69: -707996126 | AU69: 1174489966 | BA69: 107 | BB69: 1714 | BE69: 2210 | BH69: essai de formulation pour test | BI69: Moyen | BJ69: RAS | BK69: Le doucher, le savonner et le sécher. | BL69: Il est langé la nuit et lors d'événements particuliers. Il peut être mouillé seulement par accident ou en cas de crise d'épilepsie. Préconise de le laisser langer la journée. | BM69: RAS | BN69: Si il est fatigué faire une sieste | BO69: Selon fatigue
A70: 1630 | B70: 37809.761 | C70: 2210 | D70: 2034 | G70: 2677 | I70: FALSE | J70: FALSE | K70: FALSE | L70: FALSE | M70: FALSE | N70: FALSE | O70: FALSE | P70: FALSE | Q70: FALSE | S70: Sortir Julien de sa chaise et le mettre au bord de la piscine. Il faut être à ses côtés lorsqu’il nage. Il nage sur le dos. | T70: TRUE | U70: TRUE | X70: FALSE | Y70: FALSE | Z70: FALSE | AA70: FALSE | AB70: Oral: Julien s’exprime bien pour tout ce qui concerne le courant (ses besoins, ses envies, ses joies, ses tristesses). | AC70: Julien est très attaché à sa famille. Il a une sœur qui s’appelle Céline, ainsi que des oncles et des tantes à Genève, à Zürich et à Neuchâtel. Il a une grand-maman qui s’appelle Ida et qui est dans un home. Julien aime la musique, la nature, la fête, les | BA70: 107 | BB70: 394 | BC70: 0 | BD70: 1533 | BE70: 1533 | BG70: IMC | BH70: Handicap mental | BJ70: protéger Julien du soleil (casquette, crème).
A71: 1691 | B71: 42299.457 | G71: 2542 | H71: Roxanne Monnet (éducatrice) | I71: FALSE | J71: TRUE | K71: TRUE | L71: FALSE | M71: FALSE | N71: TRUE | O71: FALSE | P71: FALSE | Q71: FALSE | R71: En fauteuil roulant. Mais sur de courte distance, James marche avec ses deux cannes anglaises. | T71: FALSE | U71: FALSE | V71: Les cheveux mi-longs , habillement style rock. | W71: Stimuler James à aller au Wc 1 * pendant la nuit , car il y a risque d'énuresie. | X71: FALSE | Y71: FALSE | Z71: FALSE | AA71: FALSE | AB71: James s'exprime bien. Il dis parfois qu'il entend des voix ,mais elle sont gentilles. | AF71: La guitare, la musique rock. Il aime bien parler de son voyage en Inde et de ses expériences de vie.Il aime écouter de la musique et lire des revues sur la musique.
A72: 1828 | B72: 42556.556 | C72: 2146189922 | G72: 2146189922 | I72: FALSE | J72: FALSE | K72: FALSE | L72: TRUE | M72: TRUE | N72: FALSE | O72: FALSE | P72: FALSE | Q72: FALSE | S72: Ne sait pas nager sans flotteurs | T72: TRUE | U72: FALSE | V72: aide complet pour l'habillement | W72: Pour qu'il s'endorme, il doit toujours dormir avec quelqu'un à ses côtés | X72: FALSE | Y72: FALSE | Z72: FALSE | AA72: TRUE | AB72: Ne s'exprime pas verbalement, avec des gestes. | AC72: ses parents, ses grands-parents maternel et paternel | AD72: son grand-frère Antoine, né en 2011. sa petite sœur Myriam, née en 2014 | AE72: ses camarades de la crèche | AF72: balades, trampoline, jeux au parc, bob, pâte à modeler | AG72: apprécie moins les activités à l'intérieur. | AH72: repas + goûter | AI72: pâtes, saucisses | AK72: bonbons, chocolats | AM72: 3x le matin et 3x l'après-midi | AN72: jus de pomme, jus de raisin (avec un peu d'eau) | AP72: boissons gazeuses sucrées | BA72: 2146189548 | BB72: 2146189867 | BG72: trouble du spectre autistique | BH72: difficultés d'autonomie | BI72: Faible | BK72: apprend gentillement à aller aux toilettes mais doit être accompagné. | BL72: Langer jour et nuit
A73: 2045 | B73: 37847.571 | C73: 0 | D73: 0 | E73: 0 | F73: 67 | I73: FALSE | J73: FALSE | K73: FALSE | L73: FALSE | M73: FALSE | N73: FALSE | O73: FALSE | P73: FALSE | Q73: FALSE | S73: Il sait nager, mais se mettre à deux pour l'aider car il vient d'avoir une longue période d'arrêt. | T73: FALSE | U73: TRUE | X73: FALSE | Y73: FALSE | Z73: FALSE | AA73: FALSE | AB73: Langage oral | AC73: Laza aime beaucoup le basket, le cinéma. Il aime jouer aux échecs, écouter de la musique mais surtout aller voir des concerts. | BA73: 107 | BB73: 0 | BC73: 0 | BE73: 0
A74: 2204 | B74: 37833.375 | C74: 0 | D74: 2210 | E74: 0 | F74: 1040296841 | G74: 1040296841 | I74: FALSE | J74: FALSE | K74: FALSE | L74: FALSE | M74: FALSE | N74: FALSE | O74: FALSE | P74: FALSE | Q74: FALSE | S74: Ne peux pas nager, 2 personnes la soutiennent | T74: FALSE | U74: TRUE | X74: FALSE | Y74: FALSE | Z74: FALSE | AA74: FALSE | AB74: Elle parle doucement, elle bégaie un peu, parfois c’est difficile à la comprendre. | AC74: Sophie aime la musique, les promenades en ville, l’ambiance de fête et elle aime bien que l’on s’occupe d’elle. Elle ne fume plus. | AF74: Sophie aime la musique, les promenades en ville, l’ambiance de fête et elle aime bien que l’on s’occupe d’elle. De tant en tant, elle fume une cigarette. | AG74: La piscine | BA74: 107 | BB74: 0 | BC74: 0 | BE74: 0 | BG74: Tétraplégie spastique post-traumatique | BH74: handicap mental, troubles moteurs | BJ74: A protéger du soleil. En cas de canicule:surélever les jambes et augmenter les changement de position. | BM74: TROP PETIT??
A75: 2210 | B75: 42475 | C75: 1038843490 | D75: -1919064405 | E75: 1042036191 | F75: 1424 | G75: 0 | H75: Hendrix Kouamé 024 473 51 42 | I75: FALSE | J75: TRUE | K75: FALSE | L75: FALSE | M75: FALSE | N75: FALSE | O75: FALSE | P75: TRUE | Q75: FALSE | R75: Supporte les longs trajets. | T75: TRUE | U75: TRUE | V75: Aide nécessaire pour l'habillement. | W75: Sieste après dîner si possible. | X75: FALSE | Y75: FALSE | Z75: FALSE | AA75: TRUE | AB75: verbale mais faible. Il articule difficilement les mots : adieu, maman, allo, encore, content, nen=manger, kéké=télé, non=signe de la tête, oui=un baiser, malade | AC75: Il a sa maman, son frère Olivier, sa belle-sœur Tess, son oncle Abel, sa nièce Julie, Hélène une amie de sa maman. Il aime la musique, la téié, faire de la peinture, se promener, mager | AF75: Sa maman, son papa (décédé), son frère Olivier, sa belle-sœur Tess, son oncle Abel, Hélène une amie de la maman, sa nièce Julie. Il aime la musique, la télé, faire de la peinture, se promener, nager. | AG75: Stéphane angoisse facilement, il est nécessaire de bien lui expliqer à l'avance nos gestes et les différentes situations pour qu'il puisse s'y préparer et ne pas angoisser. | AH75: On doit lui donner à manger, la nourriture doit être mixée. | AJ75: Mixé et coupé très fin. | AL75: Pas de biscuits secs, d'aliments durs, de bonbons etc. | AM75: Il boit avec une paille. | BA75: 107 | BB75: 0 | BC75: 0 | BD75: 2146188985 | BE75: 2146188985 | BF75: 161.47.813 | BG75: IMC | BH75: Handicap mental, épilepsie, troubles moteurs, autres… | BI75: Elevé | BJ75: Ruhme des foins…yeux très sensibles (mettre les lunettes de soleil SVP) | BK75: Aide nécessaire. | BL75: Doit être langé Selle : suppositoires: lundi et vendredi | BM75: Surveiller les points d'appui,surtout les pieds(hydrater par effleurage si jamais). | BN75: Position dans le lit : Avec un oreiller. Sur le dos au couché. Sur le côté gauche au changement de position de la nuit. Sur le côté droit au changement de position l'après-midi.
A76: 2215 | B76: 42858 | C76: 1176210416 | E76: 1176210416 | F76: 0 | I76: FALSE | J76: FALSE | K76: FALSE | L76: TRUE | M76: FALSE | N76: TRUE | O76: TRUE | P76: TRUE | Q76: FALSE | R76: Supporte les longs trajets en bus. Maniement autonome de sa chaise - aide pour descendre du fauteuil et cale entre les jambes. Marche : avec attelle aux pieds - déambulateur et porte une attelle complète jambe gauche | S76: Aide totale : la tenir et mettre les manchons et une culotte plastique sous le caleçon de bain. Flotte sur le dos sans manchon | T76: FALSE | U76: TRUE | V76: Aide complète pour être lavée et la toilette (laver les dents, coiffer, etc) | W76: Coucher : peluche "Guggus" et prière en allemand | X76: FALSE | Y76: FALSE | Z76: FALSE | AA76: FALSE | AB76: Langage oral | AC76: Jean-Louis, son grand-père, vient lui dire bonjour tous les deux jours 2 matins Cousins: Loïc, Axel, Noa, Camille, Emilie, Anais et Maël Apprécie ses cousin-es : Loïc, Axel, Noa, Camille, Emilie, Anais et Maël | AD76: Fabrice (1989) | AF76: Discussions préférées : informations sur la famille, leurs métiers, leurs passions Activités préférées : regarder des livers avec des petites histoires, musique, chant, jeux (manque vite d'attention) | AG76: Besoin d'être stimulée face à la nouveauté | AH76: Autonome -- petite quantité, dans une assiette creuse. Manger : l'aider à piquer la viande et couper fin, donner plus de légumes que de féculents | AJ76: Limiter les aliments caloriques | AK76: Tendance à la constipation | AM76: Aurélie boit au verre ou avec sa gourde Demande parfois un fond de verre d'eau avant de se coucher. | AN76: Sirop light, café le matin, thé froid light | BA76: 2146189292 | BB76: 107 | BC76: 0 | BD76: 2146188969 | BE76: 2146188969 | BF76: 756.4842.5132.87 | BG76: Holoprosencéphalie, classé dans les IMC | BH76: Retard de développement et trouble de concentration Petites absences et tremblements liés aux médicaments. Tendance à être constipée | BI76: Elevé | BJ76: Léger rhume des foins | BK76: Aide totale | BL76: Langée jour et nuit : Ne pas la mettre à selles la nuit sauf en cas de changement de protection. Elle demande parfois pour aller aux toillettes; il est préférable de ne pas accepter sauf si elle a la protection est pleines de selles.(les demandes pr aller aux toilettes sont de plus en plus juste). Le matin, la mettre 5min.sur les toilettes avec une personne à côté d'elle. | BM76: Voir chagement de position | BN76: après le dîner | BO76: 20 minutes à 1/2 heures
A77: 2219 | B77: 37859.541 | C77: 0 | D77: 0 | E77: 0 | G77: 0 | I77: FALSE | J77: FALSE | K77: FALSE | L77: FALSE | M77: FALSE | N77: FALSE | O77: FALSE | P77: FALSE | Q77: FALSE | S77: elle aime beaucoup la piscine. Il faut toujours être avec elle. | T77: FALSE | U77: FALSE | X77: FALSE | Y77: FALSE | Z77: FALSE | AA77: FALSE | AB77: Elle a un cahier de communication | AC77: Elle grimpe partout, sort de partout. Il faut mettre des limites dès le début. Elle aime les balançoires, les toboggans. Elle aime le chant et la musique. Elle peut marcher environ 15 minutes. | BA77: 0 | BB77: 0 | BC77: 0 | BD77: 0 | BE77: 0 | BG77: microcéphalie | BH77: handicap mental, troubles moteurs | BJ77: avec le chlore elle a tendance à vomir
A78: 2291 | B78: 42489 | C78: 2146189403 | D78: 2290 | E78: 2146189403 | F78: 1559 | G78: 2146189403 | H78: M. Gilles Aymon | I78: FALSE | J78: TRUE | K78: TRUE | L78: TRUE | M78: TRUE | N78: FALSE | O78: FALSE | P78: FALSE | Q78: FALSE | R78: oui, il apprécie énormément, il préfère être à l’avant | S78: Bernard apprécie l’eau, mais ne sait pas nager. Vu sa longue taille, il a facilement le fond. Cependant la présence d’une personne est obligatoire pour le surveiller. | T78: FALSE | U78: TRUE | V78: Aide nécessaire : l’encourager à s’habiller et se déshabiller seul, il ne sait pas boutonner et déboutonner, ni attacher les souliers | W78: Il dort env. 9h par nuit. Il n’a pas besoin de rituel particulier, mais il s’endort avec une peluche et une gourde pour boire durant la nuit (avec de l’eau). Faire attention que le dos ne soit pas découvert. | X78: FALSE | Y78: FALSE | Z78: FALSE | AA78: FALSE | AB78: orale, il utilise plutôt des mots qui résument une phrase. Il a une gestuelle très expressive. A surveiller constamment, car Bernard n’a pas encore acquis la notion du danger. Il sait mettre en marche des véhicules et les défreiner. Essayer de la recadrer, de la ramener dans la réalité quand il parle tout seul. L'appeler par son vrai prénom : Bernard et non Bernie ! | AC78: Il apprecie Claudy l'ami de maman. | AD78: Il a une grande sœur qui s’appelle Valérie de 1984. Le mari de Valérie est Yoan. Ils sont à Cousset | AF78: Bernard apprécie la musique de fanfare, faire de la musique (le tambour), manipuler une bouteille de pet, faire du cheval, participer à des concerts et spectacles, regarder les vidéos réalistes (Fifi brin d’acier, Maison dans la prairie, Mr. Bean.Il aime tout ce qui concerne les machines, la mécanique les véhicules (attention de ne pas laisser les clefs sur un véhicule et bien tirer le frein à main). Faire des Puzzles(niveau 5-6 ans) | AG78: visiter des musées | AH78: Ne pas le faire manger s’il n’a pas faim (risque de vomissements nocturnes). Bernard mange de manière autonome, mais il faut l’aider à couper les aliments | AI78: Le matin, il apprécie le pain et la confiture, les yoghourts, les flans, la tart aux pommes, le laisser choisir. | AJ78: n'aime pas le beurre, les bonbons et le chocolat | AK78: lait, crème, mayonnaise (risque de diarrhée) | AM78: Il aime boire abondamment, d’ailleurs il a souvent une bouteille en pet avec lui | AN78: le matin : café, tisane de camomille | AQ78: Eviter le Coca et le thé froid la soirée | BB78: -895323539 | BC78: 0 | BD78: 2146189193 | BE78: 2146189193 | BF78: 80756002900021968361 | BG78: retard général (48 chromosomes au lieu de 46). | BH78: Handicap mental | BI78: Moyen | BJ78: Il est en traitement pour des verrues à 1 main. (Selon évolution) rhume des foins, à donner le Similasan no 2 | BK78: lui brosser les dents, le coiffer, l’aider à se laver la figure, les mains, le doucher, le raser.
A79: 2309 | B79: 37846.623 | C79: 2210 | D79: 219 | E79: 0 | F79: 1040296365 | I79: FALSE | J79: FALSE | K79: FALSE | L79: FALSE | M79: FALSE | N79: FALSE | O79: FALSE | P79: FALSE | Q79: FALSE | S79: Gil a besoin d’un gilet pour aller à la piscine. | T79: TRUE | U79: TRUE | X79: FALSE | Y79: FALSE | Z79: FALSE | AA79: FALSE | AB79: Oui et non et avec le regard et avec son panneau de pictos. | AC79: Gil a deux oncle Roger et Jean-Bernard et leurs enfants. Lorsque Gil parle de ses oncles, il dit « meuh » car ils ont des vaches. Il aime bien feuilleter des catalogues. | AG79: Rien faire. | BA79: 0 | BB79: 0 | BC79: 0 | BE79: 0 | BG79: IMC | BH79: Troubles moteurs | BJ79: Protéger Gil du soleil
A80: 2347 | B80: 42888 | C80: 1049183490 | D80: 1428 | E80: 1428 | F80: 2146189103 | G80: 1428 | H80: Steve Quarroz - 027 473 52 31 | I80: FALSE | J80: FALSE | K80: FALSE | L80: TRUE | M80: TRUE | N80: TRUE | O80: FALSE | P80: FALSE | Q80: FALSE | R80: Salima peut marcher en donnant la main. Eviter au maximum de la laisser s’appuyer sur soi. Sur des chemins plats et larges Salima peut marcher seule avec une stimulation verbale. Il faut l’encourager à marcher seule quand c’est possible | S80: Salima adore l'eau, aime flotter sur le dos avec l'accompagnant à proximité et aime aussi les « bulles et massages d’eau » doux dans les bains thermaux. Une personne doit l’accompagner car, elle ne nage pas. La mettre sur les WC avant d'aller dans l'eau. | T80: FALSE | U80: TRUE | V80: Salima, avec une stimulation verbale, arrive, selon les jours, à mettre ses habits (chausettes, pulls, pantalons,…) en partie et à les ôter. Ils doivent lui être présentés dans le bon sens. | X80: FALSE | Y80: TRUE | Z80: FALSE | AA80: FALSE | AB80: Salima ne parle pas, mais elle a des moyens pour demander : montrer, tourner la tête, tirer par le bras… Elle utilise le non-verbal, elle arrive à choisir des aliments lorsqu’on les lui présente. | AF80: écouter de la musique, aime qu’on lui chante ; danser ; les jeux d’encastrement, de tri ; les jeux avec un contact avec les autres : roulade, massages.Elle apprécie sa sœur Sara et ses frères Julien et Matthieu. Elle apprécie les sources de chaleur, les balades au soleil, le vent, la marche et le vélo. | AG80: apprécie moins: pâte à modeler, peinture, lieux trop bruyants ou foule excitée...cris | AH80: mettre une bavette avant le repas. Salima retient parfois ses selles, il est préférable d’avoir une alimentation variée avec des fibres. Elle doit aussi bcp boire (thé, eau, etc.). Lui donner un fruit ou jus de fruits avant le déjeuner pour prévenir la constipation. Elle boit seule mais la présence de l’adulte est nécessaire pour éviter les inondations. La rassure pour les repas. | AJ80: Couper fin les aliments (pas mixer) car mastique mal | AK80: Elle n'aime pas le melon | AN80: Boit de l'eau. Elle aime un cacao de temps en temps froid ou tiède. Un léger café au lait parfois | AP80: les eaux gazeuses et trop sucrées. EVITER le coca qui devient une idée FIXE ! Sauf vers la fin d'une fête | AS80: 2146189417 | AT80: 2146189030 | AU80: 1831959862 | BA80: 2146189305 | BB80: 1935972411 | BC80: 2146189306 | BD80: 2146188984 | BE80: 2146188984 | BF80: 011399476 | BG80: Handicap mental et malvoyante | BH80: stéréotypies, crises d’angoisse. Elle a une vision périphérique. Les forts contrastes lumineux peuvent provoquer des angoisses. N'est pas propre. Ne parle pas mais comprend ce qui est simplement expliqué. | BI80: Elevé | BJ80: Yeux à protéger du soleil, éviter si possible qu'elle fixe soleil ou sources lumineuses intenses (reflets de l'eau, neige). Si épanchements externe de l'oreille (otite), ne JAMAIS nettoyer avec des Q-Tips. Avertir les parents | BK80: Aide complète pour sa toilette. Bien essuyer ses oreilles et entre les orteilles. Séchage complet des cheveux après la piscine. Le matin et le soir laver le siège avec lavette et savon et BIEN sécher. Aime le bain et la douche et lui donner de temps en temps le pommeau pour se rincer ou l’aider en la guidant. | BL80: Salima est langée jour et nuit. WC et la changer 4-5 fois/jour. La laisser sur les WC env. 10 min. avant ou après les repas en surveillant de tps en tps. Urine presque chaque matin sur les wc et souvent dans la journée. Parfois signale qu'elle doit aller au WC en criait. | BN80: La journée, elle ne fait pas de sieste
A81: 2425 | B81: 37860.556 | C81: 0 | D81: 0 | E81: 0 | F81: 0 | G81: 0 | I81: FALSE | J81: FALSE | K81: FALSE | L81: FALSE | M81: FALSE | N81: FALSE | O81: FALSE | P81: FALSE | Q81: FALSE | T81: FALSE | U81: FALSE | X81: FALSE | Y81: FALSE | Z81: FALSE | AA81: FALSE | BA81: 0 | BB81: 0 | BE81: 0
A82: 2541 | B82: 42888 | C82: 1586575665 | G82: 1586575665 | H82: Habite dans son appartement dixence 47C à Sion | I82: FALSE | J82: TRUE | K82: TRUE | L82: FALSE | M82: FALSE | N82: FALSE | O82: FALSE | P82: TRUE | Q82: FALSE | R82: Lavette humide sur la visage et le corps pour la rafraîchir. Sensible aux changements de température (chaud ET froid). Si elle a froid, la couvrir avec une couverture. La chaise de Caroline s'incline pour un meilleur confort lors des longs trajets. | S82: Caroline a besoin d’une personne en permanence. La tenir dans les bras. Rentrer doucement dans l'eau. Elle n'aime pas avoir froid. | T82: FALSE | U82: TRUE | V82: Elle a besoin d'aide. Lorsqu'on lui enfile un pull, il est mieux de commencer par le bras gauche. | W82: Caroline dort généralement sur le dos avec un coussin banane sous les jambes avec un peu de lecture et une petite prière avant le couché. Elle a un peu de peine à s'endormir mais après elle dort facilement 8 à 9 heures. Surveiller la température de ses pieds est une bonne indication pour vérifier son confort. Si elle a froid, mettre des chaussettes, voire une bouillotte. | X82: FALSE | Y82: FALSE | Z82: FALSE | AA82: TRUE | AB82: Fais des "bulles" avec la bouche quand elle est satisfaite. Mouvement de bisous avec la bouche. Par ses attitudes, la communication facilitée, le pointage du oui ou du non en soutenant la main, le regard vers ce qu'elle veut. Caroline a dans son sac un classeur bleu destiné à ses accompagnants. Prenez le temps de le lire. | AC82: Était très attachée à son grand-père Albert (qui est décédé) et à sa grand-mère Yvette (qui vit au home) | AD82: petite sœur : Rebecca (1994) | AF82: Caroline aime bien regarder la télévision, écouter de la musique et aller au cinéma. Elle aime écouter Yannick Noah, Linda Lemay, Yussuf, Julien Clerc, Grand Corp Malade et Stress. Elle apprécie la musique douce le soir pour s'endormir: Grégory Lemarchal et pleins d'autres. Elle aime le contact et les discussions. | AG82: Elle crie ou sert les dents quand elle n'aime pas une activité. | AH82: cf. feuille des aliments, | AJ82: mixé, ajouter bouillon ou liquide pour la faire boire -> aime la soupe | AM82: Dans une bouteille cycliste ou un verre échancré, boit bien à le seringue et à la cuillère Caroline peine à boire. Pensez à l'encourager et à bien verbaliser | AN82: Jus (sans acidité) pêche, mangue, poire. Tisane. Eau, Café+crème, Lait de soja | AP82: Alcool (boit occasionnellement un peu d'alcool 1dl) | AQ82: Boissons gazeuse et très sucrées | AS82: 1127805523 | AT82: 1319632834 | AU82: 2146189152 | BA82: 1599 | BB82: 0 | BC82: 0 | BD82: 2146189010 | BE82: 2146189010 | BG82: IMC polyhandicap | BH82: épilepsie et des crises spastiques, Caroline prend régulièrement des traitements homéopathiques ou spagiriques :Suivre les instructions avant l'activité. | BI82: Elevé | BJ82: produits alimentaires, Caroline est facilement éblouie, lui mettre des lunettes ou une casquette. N'aime pas le vent. | BK82: Elle a besoin d'aide. Lotion de soin sur le visage. En cas de problèmes de digestion, la prendre dans les bras contre soi et lui faire des légers massages de l'estomac. Les médicaments sous forme de pastilles ou comprimés, se donne dans une cuillère avec un peu de liquide ou d'aliment. | BL82: Caroline est langée jour et nuit. Il faut lui changer les langes après le déjeuner, puis vers 10h, après le dîner, vers 16h et avant le coucher. Pour aller à selles, la laisser faire dans les langes. Si après 2-3 jours, elle est constipée, il faut lui faire un lavement. (Systématiquement) | BM82: ! : au coccyx qui a tendence à devenir rouge
A83: 2542 | B83: 41962 | I83: FALSE | J83: FALSE | K83: FALSE | L83: FALSE | M83: FALSE | N83: FALSE | O83: FALSE | P83: FALSE | Q83: FALSE | T83: FALSE | U83: FALSE | X83: FALSE | Y83: FALSE | Z83: FALSE | AA83: FALSE | BA83: 2146189119
A84: 2548 | B84: 43070 | C84: 252 | E84: 0 | F84: 2146189160 | G84: 252 | H84: B2 - 024 473 51 42 Sophia Eddadoui | I84: FALSE | J84: FALSE | K84: FALSE | L84: TRUE | M84: FALSE | N84: TRUE | O84: TRUE | P84: FALSE | Q84: FALSE | R84: Supporte les longs trajets en bus. Elle peut aussi marcher avec le Rollator. | S84: Elle apprécie beaucoup la piscine. Pas besoin de manchon mais la tenir. Aime les bulles, marcher dans l'eau. | T84: FALSE | U84: TRUE | V84: Aide totale L’habillement lui demander pour le choix des vêtements et l’aider avec guidance | W84: Elle dort très bien et avec un coussin, chaussetes aux mains pour la nuit. Lui mettre le pyjama avec la fermeture dasn le dos. Ne rien laisser à sa portée car elle prend tout à la bouche et déchire. La mettre au wc avant d’aller au lit et la langer. A l’habitude d'une prière le soir. Le matin si elle dort, la réveiller au plus tard à 9h30. Lui donner ses médics à 8h00 | X84: FALSE | Y84: FALSE | Z84: FALSE | AA84: FALSE | AB84: Langage non-verbal, elle arrive à se faire comprendre par l’expression du visage et la direction de ses yeux. Elle tend les bras en direction de ce qu’elle veut.marche avec aide. Bien la faire marcher et ne pas trop la soutenir, il faut bien lacer ses chaussures pour tenir ses chevilles et qu’elle se tienne bien droite. Elle marche pour fortifier ses muscles, jamais la lâcher, toujours la tenir par la main ou le poignet | AD84: Elle a un frère Raphaël de 1975 qui souffre d’un retard mental | AF84: Vélo, spectacles, contes, bricolage, chants Promenade, musique, elle aime les animaux : chiens, chevaux. | AG84: Elle met tout en bouche ne pas la laisser faire. Concentration limitée dans le temps. Ne pas la laisser sans surveillance. Faire les choses avec elle et non pour elle. Tjs lui expliquer ce que l’on fait et pourquoi. Faire très attention avec les ballons gonflables, Emilie les suce et les avale! Elle s’angoisse et ça peut provoquer des crises. Il est important de bcp lui parler. A la messe dominicale, Emilie communie tjs. | AH84: Aider à couper et à mettre en bouche, couper en petits morceaux, Emilie a bon appétit et mange de tout, elle ne mange pas chaud mais tiède. Avec guidance avec Emilie, lui faire tenir la cuillère.Cela se peut qu’elle refuse de manger. Cela dépend de son humeur, essayer et insister un peu et une fois qu’elle a goûté elle mange, si non, lui proposer un peu plus tard. Faire les choses avec elle, pour les repas, toujours en guidance.Ne pas lui donner. | AM84: pour boire tenir le verre et attendre qu’elle prenne et en guidance avec elle. Mettre la bavette. | AN84: Elle boit de tout | AQ84: Alcool | AS84: 2146189576 | AT84: 2146189572 | AU84: 2146189983 | AV84: 2146189091 | BB84: 0 | BC84: 0 | BD84: 2146189020 | BE84: 2146189020 | BF84: 95.05178 | BG84: Handicap mental avec troubles moteurs | BH84: épilepsie, absence, troubles moteurs. | BI84: Elevé | BK84: Lui faire la toilette.Les soins usuels, bien lui brosser les dents. | BL84: La mettre assise régulièrement sur les toilettes entre 5 et 7 minutes. Elle peut retenir plusieurs jours ses selles. Emilie est langée la nuit. La laisser plus longtemps sur les toilettes lorsqu’on voit qu’elle a la chaire de poule car en générale c’est un signe qui nous dis qu’elle fait ses selles. La journée la laisser sans lange, la mettre souvent au WC, chaque 2 ou 3 heures. Le soir avant le coucher la mettre au WC, de même que le matin au réveil. | BN84: Bien la faire marcher. Emilie peut marcher durant 1h et plus
A85: 2554 | B85: 42909 | C85: 2012547768 | E85: 0 | H85: Urgence: Rosendo Marta 078 802 46 57-027 398 16 26 | I85: FALSE | J85: TRUE | K85: FALSE | L85: TRUE | M85: FALSE | N85: FALSE | O85: FALSE | P85: TRUE | Q85: FALSE | R85: Supporte les longs trajets en bus : mettre le harnais de sécurité | S85: Gilet et manchons, il a besoin d'une aide constante | T85: TRUE | U85: TRUE | V85: Aide complète | W85: Dort 10 à 11h/nuit - sur le dos ou sur le côté - à la demande de Juan-Luis, le changer de position durant la nuit | X85: FALSE | Y85: FALSE | Z85: FALSE | AA85: TRUE | AB85: Propre langage oral. Il se fait comprendre surtout avec le oui et le non. Il comprend le français et l’espagnol. Voir feuille annexe (langage de Juan-Luis). | AC85: Vit avec ses parents. | AD85: Frères : Guillermo et Rosendo (appelés "aka" par JL) Neveu : David fils de Rosendo et Marta et Yana | AF85: Promenades - discussions - musique - piscine Attention! Soyez attentif aux bras de Jean-Louis. Lorsqu'il se promène, lorsqu'il est près d'un mur, d'une voiture ou autre, il a tendance à lancer le bras contre ceux-ci. | AG85: Il n'aime pas rester seul | AH85: Manger : couper fin et l'aider à les mettre en bouche ou dans une assiette à soupe avec un rebord il arrive à prendre une fourchette dans sa main gauche. Aide pour mettre les aliments dans sa fourchette puis il mange seul | AI85: Aime : café sans caféine, corn flakes, cacao tiède, tartines | AJ85: N'aime pas les sucreries, mie de pain | AK85: Jus de fruit (risque de diarrhée) | AL85: Diabétique | AM85: Boire : avec de l'aide + verre | BA85: 2146189584 | BB85: 2146189584 | BC85: 2146189014 | BD85: 2146188985 | BE85: 2146188985 | BF85: 00008206-54-173 | BG85: IMC | BH85: Handicap mental, épilepsie, malvoyant, troubles moteurs. Il a parfois des spasmes principalement au réveil | BI85: Elevé | BJ85: A protéger du soleil (chapeau, crème). Eviter de lui donner de l'aspirine (provoque urticaire) | BK85: Aide complète - Après avoir été à selles sur la chaise percée on peut lui donner la douche sur la chaise percée. Lors qu'il se lave les dents, lui enlever le dentifrice avec un cotton tige. | BL85: Chaise percée matin, midi et soir. Mettre talc sous la protection. | BM85: Ne pas oublier le coussin de la chaise roulante. | BN85: l'allonger sur le lit (il dit "afou afou" pour s'allonger) | BO85: après le dîner - durant la nuit s'il demande
A86: 2578 | B86: 37858.705 | C86: 2520 | D86: 0 | E86: 0 | F86: 0 | I86: FALSE | J86: FALSE | K86: FALSE | L86: FALSE | M86: FALSE | N86: FALSE | O86: FALSE | P86: FALSE | Q86: FALSE | S86: Avec un accompagnant. Les manchons ne sont pas nécessaire. | T86: FALSE | U86: TRUE | X86: FALSE | Y86: FALSE | Z86: FALSE | AA86: FALSE | AB86: oral | AC86: Raphaël aime la play station et le sport. Il s’intéresse au football (FC Sion, FC Marseille), au hockey (HC Sierre). Il aime les animaux, les poneys, les chats, les chiens, les rongeurs. Il a deux sœurs : Sylvie (1984) et Martine (1986). | BB86: 0 | BC86: 0 | BE86: 0 | BG86: IMC paraplégie
A87: 2584 | B87: 42517 | C87: -1984616081 | D87: 194 | E87: 0 | F87: 2580 | G87: 0 | I87: FALSE | J87: TRUE | K87: TRUE | L87: FALSE | M87: FALSE | N87: FALSE | O87: FALSE | P87: FALSE | Q87: TRUE | R87: Peut se mettre debout pour un transfert. | S87: Il aime la piscine mais il faut être à côté | T87: FALSE | U87: TRUE | X87: FALSE | Y87: FALSE | Z87: FALSE | AA87: FALSE | AB87: oral | AH87: Faire attentio naux sucreries. Lui couper les aliments. | AL87: noix, châtaignes, abricots séchés. | BA87: 2146189009 | BB87: 0 | BC87: 0 | BD87: 2146189008 | BE87: 2146189008 | BG87: IMC | BJ87: rhume des foins (médicament: Hismanal), allergie aux blancs d' œufs, possibilité de crises d'asthme causées par les maroniers (médicament: Tavegyl) | BL87: Avec un condom urinaire
A88: 2589 | B88: 41816 | I88: FALSE | J88: FALSE | K88: FALSE | L88: FALSE | M88: FALSE | N88: FALSE | O88: FALSE | P88: FALSE | Q88: FALSE | T88: FALSE | U88: FALSE | X88: FALSE | Y88: FALSE | Z88: FALSE | AA88: FALSE
A89: 2604 | B89: 42866 | C89: -1336383801 | D89: 2603 | E89: -1336383801 | F89: 1424 | G89: -562642022 | H89: Groupe - B3 | I89: FALSE | J89: TRUE | K89: FALSE | L89: TRUE | M89: FALSE | N89: FALSE | O89: TRUE | P89: TRUE | Q89: FALSE | R89: Il supporte les longs trajets en bus. | S89: présence d’une personne obligatoire pour le tenir, de préférence un gilet. | T89: TRUE | U89: TRUE | V89: Aide complète pour l'habillement et le déshabillement. Il peut donner un coup de main pour ôter les habits. | W89: Il dort env. 10h à 11h par nuit. Il n’a pas besoin de rituel particulier. Depuis son opération, il dort sur le dos avec le coussin pour les jambes. | X89: FALSE | Y89: FALSE | Z89: FALSE | AA89: TRUE | AB89: Ludovic parle lentement et il a besoin de temps pour répondre. | AC89: Ludovic est souvent avec sa cousine Myriam qui a env. 54 ans | AF89: Il aime les animaux de la ferme, jouer aux puzzles, regarder les livres, la natation, la gym, le vélo rollefit, le foot et les courses de F1, en particulier les Ferrari. Ludovic aime le contact et se montre sociable. | AH89: Il faut couper fin les aliments et les lui donner en bouche. Ludovic arrive à mâcher. Quand ont lui donne les médicaments les mélanger avec les aliments. Si Ludovic gesticule et fait des petits cris c’est qu’il a une gélule collé au palais. Il ne faut pas hésiter à mettre le doigt ou une petite cuillère pour la décoller. | AJ89: Il n’aime pas la salade verte, les lasagnes, la viande hachée | AL89: les gros morceaux. | AM89: Ludovic boit avec une paille. | AU89: 2146189314 | BA89: 107 | BB89: 2146189293 | BC89: 0 | BD89: 2146188985 | BE89: 2146189011 | BF89: 262 85 739 0002 | BG89: IMC, maladie de Leigh | BH89: épilepsie | BI89: Elevé | BJ89: A protéger du soleil, mettre une casquette. | BK89: Aide complète pour la toilette et la douche. | BL89: Ludovic est propre. Il demande pour aller aux toilettes (bouteille pour uriner en cas d'exception) et chaque 3 à 4 jours il demande pour aller à selles (le mettre sur les toilettes). Il demande parfois (avant un départ en activité ou avant d'aller dormir) de lui mettre une protection, au cas où | BM89: Prévention des escarres : Important de contrôler le dos, surtout le bas. | BN89: de temps en temps le sortir de la chaise | BO89: Après le dîner et avant le souper
A90: 2611 | B90: 42888 | C90: 2146189795 | E90: 2146189796 | F90: 1424 | G90: 2146189796 | H90: Groupe - C2 - Marina Silva - 024 473 51 52 | I90: FALSE | J90: FALSE | K90: FALSE | L90: TRUE | M90: FALSE | N90: FALSE | O90: FALSE | P90: TRUE | Q90: FALSE | R90: Il supporte les longs trajets en bus. | S90: Il apprécie beaucoup la piscine. L'institution demande le port d'un gilet pour toutes les personnes éliptiques. | T90: TRUE | U90: TRUE | W90: Il dort bien. Il écoute du Pierre Bachelet avant de s'endormir.(un Cd se trouve dans son sac) | X90: FALSE | Y90: FALSE | Z90: FALSE | AA90: TRUE | AB90: non verbale. Il montre son contentement en riant, en envoyant des baisers et en "disant" bonjour. Il montre son mécontentement en criant et en tapant de la main sur la table. Il exagère parfois surtout avec des nouvelles personnes. Dans ce cas il faut s'isoler un moment avec lui et lui expliquer que son comportement n'est pas adéquat. | AF90: Il aime surtout les promenades, les sorties en ville ou dans les magasins, boire un café sur une terrasse. Il apprécie les activités en rapport avec l'eau et la cuisine. Il aime regarder un film, mais seulement sur grand écran. Il apprécie la musique (Henri Dès, Pierre Bachelet) | AG90: Ne montre pas d'intérêt pour la télévision et les activités de bricolage. Ne joue pas avec des objets sauf s'ils sont en mousse ou en éponge. | AH90: Ne pas lui donner plus de 300 g. par repas. : Il mange seul avec cerceau sur son assiette et cuillère personnelle. Il boit seul avec un gobelet en plastique. | AJ90: Alimentation mixée lisse car risque de fausse route | AM90: Il boit seul avec un gobelet en plastique | AN90: café au lait, boissons sucrées (thé,sirop,jus de pomme) | AP90: Boissons gazeuses | AQ90: alcool | BA90: 2146189786 | BB90: 2146189787 | BD90: 2146189020 | BE90: 2146189020 | BF90: 01060 07-59736-8 | BG90: Tétraplégie spastique | BH90: handicap mental, épilepsie (très bien stabilisée, si nécessaire : 10 mg de Midazolam | BI90: Elevé | BK90: Si il semble avoir des douleurs abdominales : lui donner 1suppo. spasmo Cibalgine Bien lui laver et sécher les mains car a tendance à avoir des dermatoses. Appliquer une crème grasse type Neutrogena | BL90: Il est langé jour et nuit. Il ne va pas à selles spontanément. Il faut lui faire un Clyssie (petit lavement) chaque 3ème jour et le mettre sur la chaise percée. Ainsi il va la selle dans le ¼ d'heure. | BN90: Il a l'habitude de faire une sieste après le dîner.
A91: 2619 | B91: 42503 | I91: FALSE | J91: FALSE | K91: FALSE | L91: FALSE | M91: FALSE | N91: FALSE | O91: FALSE | P91: FALSE | Q91: FALSE | T91: FALSE | U91: FALSE | X91: FALSE | Y91: FALSE | Z91: FALSE | AA91: FALSE
A92: 2625 | B92: 43039 | C92: 252 | D92: 0 | E92: 0 | F92: 2677 | G92: 252 | I92: FALSE | J92: FALSE | K92: TRUE | L92: TRUE | M92: TRUE | N92: FALSE | O92: FALSE | P92: FALSE | Q92: FALSE | R92: Supporte les longs trajets en bus | S92: Raphaël nage un peu dans eau peu profonde, pas de manchon, avec surveillance. | T92: FALSE | U92: TRUE | V92: lui préparer les habits | X92: FALSE | Y92: FALSE | Z92: FALSE | AA92: FALSE | AB92: Raphaël articule mal, faire répéter lentement Le faire participer le plus possible à la vie de groupe, car il a tendance à être solitaire. Lorsque vous participez à la messe dominicale, Raphaël communie toujours. | AD92: Une sœur : Emilie | AF92: Apprécie beaucoup la météo, les nuages et leurs noms. Il aime tout, il suffit de le motiver. Aimes les heures, montres et jours de la semaine | AH92: Raphaël se débrouille seul | AI92: Il mange de tout et a bon appétit | AM92: Raphaël se débrouille seul | AQ92: alcool | BA92: 2146189598 | BC92: 0 | BD92: 2146189020 | BE92: 2146189020 | BF92: 95.05177 | BG92: Handicap mental avec des troubles autistiques | BH92: Problème avec le cœur. Eviter le stress et les montées, les grandes marches Il doit marcher doucement car risque de chute de tension et peut devenir pâle. Il doit s'assoir si trop fatigué pour éviter les chutes. | BI92: Moyen | BJ92: aucune | BK92: Lui répéter de bien se brosser les dents. Ne pas laisser se rendre trop souvent aux toilettes ou dans sa chambre. L'aider pour les cheveux. Régler la douche et éviter qu'il mette trop chaud, bien surveiller. | BL92: Raphaël se débrouille seul après les selles le laver à l'eau tiède, bien sécher mettre un peu de poudre Pévaryl | BN92: Durant la journée, il doit prendre du temps pour se reposer. Pour éviter de fatiguer son cœur
A93: 2642 | B93: 41039 | I93: FALSE | J93: FALSE | K93: FALSE | L93: FALSE | M93: FALSE | N93: FALSE | O93: FALSE | P93: FALSE | Q93: FALSE | T93: FALSE | U93: FALSE | X93: FALSE | Y93: FALSE | Z93: FALSE | AA93: FALSE
A94: 2643 | B94: 40996 | I94: FALSE | J94: FALSE | K94: FALSE | L94: FALSE | M94: FALSE | N94: FALSE | O94: FALSE | P94: FALSE | Q94: FALSE | T94: FALSE | U94: FALSE | X94: FALSE | Y94: FALSE | Z94: FALSE | AA94: FALSE
A95: 2653 | B95: 42972 | C95: 81 | D95: 0 | E95: 0 | F95: 2146189483 | G95: 2146189103 | H95: B4 . Maude Lang | I95: FALSE | J95: FALSE | K95: FALSE | L95: TRUE | M95: FALSE | N95: FALSE | O95: FALSE | P95: TRUE | Q95: TRUE | R95: Supporte les longs trajets en bus Attention si Nicole est excitée ou si il y a beaucoup de monde autour d’elle, ne pas la laisser conduire, | S95: Présence obligatoire d’une personne pour la tenir, de préférence, un gilet | T95: FALSE | U95: TRUE | V95: Aide totale | W95: Pour dormir, la mettre sur le coté droit jusqu'à la première veille avec un cousin entre les genoux. A gauche 1 ère position - A droite position dès 2h le matin ( idem pour la sieste) la mettre ensuite sur le dos lors de la première veille avec un coussin banane sous les genoux et un petit coussin vertical pour séparer les genoux. Elle fait la sieste environ 1 heure après le repas de midi. | X95: FALSE | Y95: FALSE | Z95: FALSE | AA95: TRUE | AB95: oral (elle dit oui et non), mimiques et gestes Remarques générales : Lorsqu’elle s’excite, elle se met en appui sur ses pose-pieds, ceci lui provoque des blessures aux genoux et aux pieds. Lui dire des mots Calme ou Doucement. Ces mots aideront à la stabiliser et à reprendre sa position normale sur son fauteuil. | AF95: Nicole aime sortir, faire la fête, les concerts et voyager en voiture. Elle s’intéresse à tous les sujets. | AG95: aucune, elle est toujours partante | AH95: Couper les aliments. Nicole emploie des ustensiles spéciaux (cuillère coudée, rebord d'assiette, verre, paille, disque antidérapant). Elle mange avec la main gauche. | AJ95: 1 service - faire attention à la quantité. | AK95: N'aime pas trop les légumes et le poisson. | AM95: Boit dans un verre normal,dans le plot en bois avec une paille normal | BA95: 2146189786 | BB95: 0 | BC95: 0 | BD95: 2146189021 | BE95: 2146189021 | BF95: 008814 | BG95: IMC | BH95: handicap mental, troubles moteurs, côté droit moins mobile Epilepsie | BI95: Elevé | BJ95: protéger du soleil (crème, chapeau) | BK95: Il faut lui faire la douche dans la chaise percée. Aide complète ou une petite toilette au lit. | BL95: Mettre Nicole régulièrement aux toilettes (matin-midi-soir). Elle emploie une chaise percée. Elle a de la peine à aller à selles. 2x par semaine, elle a un suppositoire.Mardi et Vendredi Lors de sortie qui dure toute la journée, langer Nicole, elle est plus rassurée ainsi et ça évite des surprises. Mettre une protection si rien le matin et pas de possibilité de la mettre à midi. | BN95: Au lit, sur le dos avec un coussin sous genoux L’asseoir bien au fond de sa chaise, doit tenir sa poignée. Elle sait se mettre au fond en ayant les pieds sanglés | BO95: Ne plus lui mettre la sangle au pied gauche car cela lui provoque un cor au petit orteil
A96: 2654 | B96: 42405 | I96: FALSE | J96: FALSE | K96: FALSE | L96: FALSE | M96: FALSE | N96: FALSE | O96: FALSE | P96: FALSE | Q96: FALSE | T96: FALSE | U96: FALSE | X96: FALSE | Y96: FALSE | Z96: FALSE | AA96: FALSE
A97: 2655 | B97: 42426 | C97: -367246467 | D97: 2027 | E97: 0 | F97: 1424 | G97: 1424 | I97: FALSE | J97: FALSE | K97: FALSE | L97: TRUE | M97: FALSE | N97: TRUE | O97: FALSE | P97: TRUE | Q97: FALSE | R97: Marche avec de l'aide et des chausettes anti-glisse | S97: La ceinture ou une bouée, le surveiller et le tenir. | T97: FALSE | U97: TRUE | W97: La nuit, il a toujours la chemisette, le cycliste en plus du pyjama et une combinaison par-dessus. Il a la ceinture de sécurité pour la sieste et la nuit. Il va se coucher vers 20h et se lève vers 8h. Il dort facilement le matin. Sommeil très léger et fragile. Il ne faut pas faire du bruit quand il est juste au lit. Samuel dort sur le ventre. | X97: FALSE | Y97: FALSE | Z97: FALSE | AA97: TRUE | AB97: Il ne communique pas de manière verbale. Il s'exprime par des cris, rire, grognements. Il pleure quand il est mal ou malade. | AC97: Il a quatre frères et sœur : Stéphane (1974), Christiane (1977), Patricia (1981) Frédéric (1986). | AF97: Il aime bien serrer les autres. Il aime tout ce qui est en plastique, la musique et principalement la musique de fanfare, les promenades et la piscine. | AG97: Il n'aime pas être peigner, laver les dents, se laver le visage ainsi que l'eau froide. ATTENTION : Ne pas le laisser jouer avec des sacs en plastique car il attrape des boutons au visage et de l'herpès. Il peut en plus les avaler. Ne rien le laisser mettre en bouche pour cause d'inflammation. | AH97: Samuel aime manger les aliments tièdes et pas trop sec. Il peut manger les gâteaux mou et pas trop sec. Lui donner avec une cuillère à soupe et lui faire garder les mains sous la table.Mixer et donner à manger | AJ97: Aliments mixés | AM97: Lui rappeler qu'il doit boire. Il boit avec un gobelet en plastique et une paille solide | AP97: boissons gazeuses et les boisson à base de lait | BA97: 107 | BB97: -749136963 | BC97: 0 | BD97: 2146188969 | BE97: 2146188974 | BF97: 057904 | BG97: IMC hémiplégie côté droit | BH97: épilepsie stabilisée (foyer épileptique sur la droite du cerveau). | BJ97: protéger Samuel du soleil à cause des risques d’épilepsie. Il prend facilement des coups de soleil (car il a été greffé aux ja,bes et aux pieds). Il est allergique au plastique car il a facilement de l'herpes et risque d'avaler. | BK97: Aide complète. Il apprécie qu’on verbalise ce que l’on fait. Lui laver les dents. Samuel n’aime pas les coups de peigne. Il porte toujours sur lui un cycliste une chemisette et une ceinture (fermée dans le dos pour éviter qu'il l'enlève) à son pantalon la journée. | BL97: Samuel est langé jour et nuit. Il faut lui changer les langes en principe le matin, à midi et le soir. S’il fait des selles, le changer tout de suite car il n’aime pas ça et cherche de déchirer la protection. Il reste sur les toilettes bien surveiller car il peut manger ses selles et il faut éloigner tout autour de lui.
A98: 2657 | B98: 37833.49 | C98: 700 | D98: 0 | E98: 0 | F98: -199496155 | G98: -199496155 | I98: FALSE | J98: FALSE | K98: FALSE | L98: FALSE | M98: FALSE | N98: FALSE | O98: FALSE | P98: FALSE | Q98: FALSE | S98: présence d’une personne obligatoire pour le tenir, de préférence un gilet. | T98: TRUE | U98: TRUE | X98: FALSE | Y98: FALSE | Z98: FALSE | AA98: FALSE | AB98: Jean-Claude parle et comprend le français et l’allemand. Il faut lui parler lentement. Il a besoin de temps pour répondre. Il apprécie les questions aux réponses : oui ou non. | AC98: Son papa habite la Souste et sa maman est décédée en 2002. Jean-Claude en parle régulièrement. Il a deux frères : Réné également à la Castalie B2 et Hubert qui est marié avec 2 enfants Malik et Cyril. Il est fier d’être tonton. Jean-Claude apprécie écout | AD98: Il a deux frères : Réné également à la Castalie B2 et Hubert qui est marié avec 2 enfants Malik et Cyril. Il est fier d’être tonton. | AF98: Jean-Claude apprécie écouter de la musique folklorique et la radio, jouer au jeu du moulin et être en contact avec les autres. Il travail à l’atelier bois chez Victor. | BA98: 107 | BB98: 0 | BC98: 0 | BE98: 0 | BG98: Leucodistrophie dégénérative | BH98: handicap mental, troubles moteurs | BJ98: A protéger du soleil, en cas de douleur ne supporte que le Dafalgan, il est allergique à l’Aspirin. | BM98: TROP PETIT???
A99: 2659 | B99: 37847.488 | C99: 1018357734 | D99: 2210 | E99: 0 | I99: FALSE | J99: FALSE | K99: FALSE | L99: FALSE | M99: FALSE | N99: FALSE | O99: FALSE | P99: FALSE | Q99: FALSE | S99: Alexandre sait nager. | T99: FALSE | U99: FALSE | X99: FALSE | Y99: FALSE | Z99: FALSE | AA99: FALSE | AB99: Langage oral | AC99: Alexandre aime la natation, le vélo. Il regarde volontiers à la télé des films. Il aime les jeux électroniques et les jeux de socété. Il a un caractère bien trempé, boude volontiers. | BA99: 2154 | BB99: 534 | BC99: 0 | BE99: 0 | BG99: Polio | BJ99: risque d'otites l'hiver
A100: 2734 | B100: 37847.634 | C100: 2210 | D100: 1429 | E100: 0 | F100: 0 | G100: 0 | I100: FALSE | J100: FALSE | K100: FALSE | L100: FALSE | M100: FALSE | N100: FALSE | O100: FALSE | P100: FALSE | Q100: FALSE | S100: Kim sait nager. | T100: FALSE | U100: TRUE | X100: FALSE | Y100: FALSE | Z100: FALSE | AA100: FALSE | AB100: : Kim s’exprime à l’aide d’un classeur de communication et d’un ordinateur de communication. | AC100: Kim a un frère aîné qui est né en 1986 et qui fait du basket ainsi qu’un petit frère qui est né en 1991 et qui fait du golf et du badminton. Sa famille maternelle habite en Belgique. | BA100: 1379 | BB100: 0 | BC100: 0 | BD100: 1533 | BE100: 1533 | BG100: IMC | BJ100: protéger Kim du soleil (casquette, crème).
...

Sheet migInfoMédical
A1: medId | B1: medConId | C1: medAlimCommentair | D1: medAlimPrefere | E1: medAlimRegime | F1: medAlimDecons | G1: medAlimInterdit | H1: medBoisCondition | I1: medBoisPrefere | J1: medBoisRegime | K1: medBoisDecons | L1: medBoisInterdit | M1: medMedecin1 | N1: medMedecin2 | O1: medMedecin3 | P1: medCaisseMaladie | Q1: medAccident | R1: medNoAssure | S1: medTypeHandicap | T1: medHandicapsAsso | U1: medDegre | V1: medAllergies | W1: medToilette | X1: medEncontinence | Y1: medEscarres | Z1: medOfasType | AA1: medOfasPluri | AB1: medOfasReconnu | AC1: medMaj
B2: =gescon_infosparticip!A1 -> membre | C2: =gescon_infosparticip!AH1 -> autonomierepas | D2: =gescon_infosparticip!AI1 -> alim_prefere | E2: =gescon_infosparticip!AJ1 -> alim_regime | F2: =gescon_infosparticip!AK1 -> alim_decons | G2: =gescon_infosparticip!AL1 -> alim_interdit | H2: =gescon_infosparticip!AM1 -> bois_condition | I2: =gescon_infosparticip!AN1 -> bois_prefere | J2: =gescon_infosparticip!AO1 -> bois_regime | ... L2: =gescon_infosparticip!AQ1 -> bois_interdit | M2: =gescon_infosparticip!BA1 -> Medecin 1 | N2: =gescon_infosparticip!BB1 -> Medecin 2 | O2: =gescon_infosparticip!BC1 -> Medecin 3 | P2: =gescon_infosparticip!BD1 -> Caisse maladie | Q2: =gescon_infosparticip!BE1 -> Accident | R2: =gescon_infosparticip!BF1 -> no_assuré | S2: =gescon_infosparticip!BG1 -> Type de handicap | T2: =gescon_infosparticip!BH1 -> Handicaps Associés | ... Y2: =gescon_infosparticip!BM1 -> escarres
B3: =gescon_infosparticip!A2 -> -2138585887 | C3: =gescon_infosparticip!AH2 -> Incliner légèrement son fauteuil en arrière pour facilier la déglutition. Alimentation normale. Couper fin, très petit, si trop secd rajouter du lait et lui donner à manger. | D3: =gescon_infosparticip!AI2 | E3: =gescon_infosparticip!AJ2 | F3: =gescon_infosparticip!AK2 | G3: =gescon_infosparticip!AL2 | H3: =gescon_infosparticip!AM2 -> II boit à la paille | I3: =gescon_infosparticip!AN2 -> café | J3: =gescon_infosparticip!AO2 | ... L3: =gescon_infosparticip!AQ2 | M3: =gescon_infosparticip!BA2 -> 0 | N3: =gescon_infosparticip!BB2 -> 0 | O3: =gescon_infosparticip!BC2 -> 0 | P3: =gescon_infosparticip!BD2 -> 0 | Q3: =gescon_infosparticip!BE2 -> 0 | R3: =gescon_infosparticip!BF2 | S3: =gescon_infosparticip!BG2 -> IMC profond | T3: =gescon_infosparticip!BH2 -> Handicap mental, troubles moteurs | ... Y3: =gescon_infosparticip!BM2 -> massage des pieds et des fesses
B4: =gescon_infosparticip!A3 -> -1974002318 | C4: =gescon_infosparticip!AH3 -> Alycia est alimentée par sonde. 150 ml de frébini 300m/h avec la pompe. (peg) matin, midi et soir avec la pompe et le sachet alimentaire. Donner de l'eau 3x/jours 150ml Prend environs 30 min pour le repas trois fois limentation avec les sachet pour la boisson. On peut l'alimenter durant les transports ou en déplacement sur la chaise. | D4: =gescon_infosparticip!AI3 | E4: =gescon_infosparticip!AJ3 | F4: =gescon_infosparticip!AK3 | G4: =gescon_infosparticip!AL3 | H4: =gescon_infosparticip!AM3 | I4: =gescon_infosparticip!AN3 | J4: =gescon_infosparticip!AO3 | ... L4: =gescon_infosparticip!AQ3 | M4: =gescon_infosparticip!BA3 -> 226884306 | N4: =gescon_infosparticip!BB3 -> 0 | O4: =gescon_infosparticip!BC3 -> 0 | P4: =gescon_infosparticip!BD3 -> 2146189019 | Q4: =gescon_infosparticip!BE3 -> 0 | R4: =gescon_infosparticip!BF3 -> 00807.17.515.7 | S4: =gescon_infosparticip!BG3 -> Polyhandicap | T4: =gescon_infosparticip!BH3 -> A mettre lunettes médicales la journée | ... Y4: =gescon_infosparticip!BM3
B5: =gescon_infosparticip!A4 -> -1949668449 | C5: =gescon_infosparticip!AH4 | D5: =gescon_infosparticip!AI4 | E5: =gescon_infosparticip!AJ4 | F5: =gescon_infosparticip!AK4 | G5: =gescon_infosparticip!AL4 | H5: =gescon_infosparticip!AM4 | I5: =gescon_infosparticip!AN4 | J5: =gescon_infosparticip!AO4 | ... L5: =gescon_infosparticip!AQ4 | M5: =gescon_infosparticip!BA4 -> 107 | N5: =gescon_infosparticip!BB4 -> 0 | O5: =gescon_infosparticip!BC4 -> 0 | P5: =gescon_infosparticip!BD4 -> 0 | Q5: =gescon_infosparticip!BE4 -> 0 | R5: =gescon_infosparticip!BF4 | S5: =gescon_infosparticip!BG4 -> IMC | T5: =gescon_infosparticip!BH4 -> Diplégie spastique, retard mental, comportement autistique, handicap mental | ... Y5: =gescon_infosparticip!BM4
B6: =gescon_infosparticip!A5 -> -1887115141 | C6: =gescon_infosparticip!AH5 -> les aliments sont à couper, elle mange seule avec une fourchette dans une assiette creuse ; fait le mouvement de pelle côté droit et elle doit mettre la main gauche à plat sur la table les doigts légèrement écartés. | D6: =gescon_infosparticip!AI5 | E6: =gescon_infosparticip!AJ5 | F6: =gescon_infosparticip!AK5 | G6: =gescon_infosparticip!AL5 | H6: =gescon_infosparticip!AM5 -> elle boit dans un gobelet spécial avec 2 anses. Lors de déplacement elle arrive à boire dans un verre normal. Matin : Tartine au beurre, confiture et café et fruit habituellement. Les autres repas elle mange de tout et sait dire lorsqu’elle ne veut plus. Elle apprécie boire de l’eau, du sirop ou autre minéralesIl faut l'asseoir sur une chaise avec des accoudoirs. | I6: =gescon_infosparticip!AN5 | J6: =gescon_infosparticip!AO5 | ... L6: =gescon_infosparticip!AQ5 | M6: =gescon_infosparticip!BA5 -> 107 | N6: =gescon_infosparticip!BB5 -> 0 | O6: =gescon_infosparticip!BC5 -> 0 | P6: =gescon_infosparticip!BD5 -> 2146189028 | Q6: =gescon_infosparticip!BE5 -> 2146189028 | R6: =gescon_infosparticip!BF5 -> 3705 | S6: =gescon_infosparticip!BG5 -> IMC | T6: =gescon_infosparticip!BH5 -> Handicap mental, troubles moteurs, hémiplégie côté gauche | ... Y6: =gescon_infosparticip!BM5
B7: =gescon_infosparticip!A6 -> -1756164214 | C7: =gescon_infosparticip!AH6 | D7: =gescon_infosparticip!AI6 | E7: =gescon_infosparticip!AJ6 | F7: =gescon_infosparticip!AK6 | G7: =gescon_infosparticip!AL6 | H7: =gescon_infosparticip!AM6 | I7: =gescon_infosparticip!AN6 | J7: =gescon_infosparticip!AO6 | ... L7: =gescon_infosparticip!AQ6 | M7: =gescon_infosparticip!BA6 -> 0 | N7: =gescon_infosparticip!BB6 -> 0 | O7: =gescon_infosparticip!BC6 -> 0 | P7: =gescon_infosparticip!BD6 -> 0 | Q7: =gescon_infosparticip!BE6 -> 0 | R7: =gescon_infosparticip!BF6 | S7: =gescon_infosparticip!BG6 -> IMC | T7: =gescon_infosparticip!BH6 -> Handicap mental | ... Y7: =gescon_infosparticip!BM6
B8: =gescon_infosparticip!A7 -> -1735727011 | C8: =gescon_infosparticip!AH7 | D8: =gescon_infosparticip!AI7 | E8: =gescon_infosparticip!AJ7 | F8: =gescon_infosparticip!AK7 | G8: =gescon_infosparticip!AL7 | H8: =gescon_infosparticip!AM7 | I8: =gescon_infosparticip!AN7 | J8: =gescon_infosparticip!AO7 | ... L8: =gescon_infosparticip!AQ7 | M8: =gescon_infosparticip!BA7 -> 107 | N8: =gescon_infosparticip!BB7 -> 0 | O8: =gescon_infosparticip!BC7 -> 0 | P8: =gescon_infosparticip!BD7 -> 0 | Q8: =gescon_infosparticip!BE7 -> 0 | R8: =gescon_infosparticip!BF7 | S8: =gescon_infosparticip!BG7 -> IMC | T8: =gescon_infosparticip!BH7 | ... Y8: =gescon_infosparticip!BM7
B9: =gescon_infosparticip!A8 -> -1690129297 | C9: =gescon_infosparticip!AH8 | D9: =gescon_infosparticip!AI8 | E9: =gescon_infosparticip!AJ8 | F9: =gescon_infosparticip!AK8 | G9: =gescon_infosparticip!AL8 | H9: =gescon_infosparticip!AM8 | I9: =gescon_infosparticip!AN8 | J9: =gescon_infosparticip!AO8 | ... L9: =gescon_infosparticip!AQ8 | M9: =gescon_infosparticip!BA8 -> 1217 | N9: =gescon_infosparticip!BB8 -> 0 | O9: =gescon_infosparticip!BC8 -> 0 | P9: =gescon_infosparticip!BD8 -> 0 | Q9: =gescon_infosparticip!BE8 -> 0 | R9: =gescon_infosparticip!BF8 | S9: =gescon_infosparticip!BG8 -> Ataxie, syndrome de Marinesco | T9: =gescon_infosparticip!BH8 -> troubles moteurs | ... Y9: =gescon_infosparticip!BM8
B10: =gescon_infosparticip!A9 -> -1579856298 | C10: =gescon_infosparticip!AH9 | D10: =gescon_infosparticip!AI9 | E10: =gescon_infosparticip!AJ9 | F10: =gescon_infosparticip!AK9 | G10: =gescon_infosparticip!AL9 | H10: =gescon_infosparticip!AM9 | I10: =gescon_infosparticip!AN9 | J10: =gescon_infosparticip!AO9 | ... L10: =gescon_infosparticip!AQ9 | M10: =gescon_infosparticip!BA9 -> 0 | N10: =gescon_infosparticip!BB9 -> 0 | O10: =gescon_infosparticip!BC9 -> 0 | P10: =gescon_infosparticip!BD9 -> 0 | Q10: =gescon_infosparticip!BE9 -> 0 | R10: =gescon_infosparticip!BF9 | S10: =gescon_infosparticip!BG9 | T10: =gescon_infosparticip!BH9 | ... Y10: =gescon_infosparticip!BM9
B11: =gescon_infosparticip!A10 -> -1475569285 | C11: =gescon_infosparticip!AH10 -> Il mange seul et se débrouille bien. | D11: =gescon_infosparticip!AI10 | E11: =gescon_infosparticip!AJ10 | F11: =gescon_infosparticip!AK10 | G11: =gescon_infosparticip!AL10 | H11: =gescon_infosparticip!AM10 | I11: =gescon_infosparticip!AN10 | J11: =gescon_infosparticip!AO10 | ... L11: =gescon_infosparticip!AQ10 | M11: =gescon_infosparticip!BA10 -> 2146189227 | N11: =gescon_infosparticip!BB10 -> 2146189396 | O11: =gescon_infosparticip!BC10 -> 0 | P11: =gescon_infosparticip!BD10 -> 2146188987 | Q11: =gescon_infosparticip!BE10 -> 2146188982 | R11: =gescon_infosparticip!BF10 -> 644702 | S11: =gescon_infosparticip!BG10 -> Syndrôme de William's | T11: =gescon_infosparticip!BH10 -> handicap mental - Malformation cardiaque | ... Y11: =gescon_infosparticip!BM10
B12: =gescon_infosparticip!A11 -> -1435346384 | C12: =gescon_infosparticip!AH11 | D12: =gescon_infosparticip!AI11 | E12: =gescon_infosparticip!AJ11 | F12: =gescon_infosparticip!AK11 | G12: =gescon_infosparticip!AL11 | H12: =gescon_infosparticip!AM11 | I12: =gescon_infosparticip!AN11 | J12: =gescon_infosparticip!AO11 | ... L12: =gescon_infosparticip!AQ11 | M12: =gescon_infosparticip!BA11 -> 0 | N12: =gescon_infosparticip!BB11 -> 0 | O12: =gescon_infosparticip!BC11 -> 0 | P12: =gescon_infosparticip!BD11 -> 0 | Q12: =gescon_infosparticip!BE11 -> 0 | R12: =gescon_infosparticip!BF11 | S12: =gescon_infosparticip!BG11 | T12: =gescon_infosparticip!BH11 | ... Y12: =gescon_infosparticip!BM11
B13: =gescon_infosparticip!A12 -> -1354980006 | C13: =gescon_infosparticip!AH12 -> médic du matin: dans la seringue et relié à la sonde -> rincer ensuite avec 1-2 seringue d'eau Cloé a besoin d’une aide complète pour les repas. Elle est nourrie essentiellement par le biais de la sonde. Il ne faut pas la forcer. Elle mange de tout et la nourriture est mixée, lisse. Ni trop liquide, ni trop sèche. Elle préfère plutôt salé. Le MATIN : en principe, elle ne mange pas. Il est important de rincer la sonde avec 1 à 2 seringues. MIDI : nourriture mixée lisse en petites quantités. SOIR : nourriture mixée lisse ou des yaourts en petites quantités. Petit sachet pour la nourriture durant la nuit | D13: =gescon_infosparticip!AI12 | E13: =gescon_infosparticip!AJ12 -> débit EAU : 180 ml/h débit L'ALIMENTATION : 50 ml/h | F13: =gescon_infosparticip!AK12 | G13: =gescon_infosparticip!AL12 | H13: =gescon_infosparticip!AM12 -> alimentation et sonde: s'il fait chaud, on peut donner jusqu'à 1litre d'eau par la sonde. Pour bouillon et eau mettre dans le grand sachet - possibilité de donner à boire en promenade, prendre la pompe et mettre eau dans gd sachet. | I13: =gescon_infosparticip!AN12 | J13: =gescon_infosparticip!AO12 | ... L13: =gescon_infosparticip!AQ12 | M13: =gescon_infosparticip!BA12 -> 107 | N13: =gescon_infosparticip!BB12 -> 0 | O13: =gescon_infosparticip!BC12 -> 0 | P13: =gescon_infosparticip!BD12 -> 2146188987 | Q13: =gescon_infosparticip!BE12 -> 2146188987 | R13: =gescon_infosparticip!BF12 -> 429923 | S13: =gescon_infosparticip!BG12 -> IMC -Polyhandicap, épilepsie (stabilisé) | T13: =gescon_infosparticip!BH12 -> Ne doit pas dépasser les 1700m d'altitude. Car elle risque d'avoir des problèmes respiratoires | ... Y13: =gescon_infosparticip!BM12 -> Changement de position, il faut lui mettre le harnais quand elle se trouve dans la chaise.
... B336: =gescon_infosparticip!A335 -> 2146190077 | C336: =gescon_infosparticip!AH335 | D336: =gescon_infosparticip!AI335 | E336: =gescon_infosparticip!AJ335 | F336: =gescon_infosparticip!AK335 | G336: =gescon_infosparticip!AL335 | H336: =gescon_infosparticip!AM335 | I336: =gescon_infosparticip!AN335 | J336: =gescon_infosparticip!AO335 | ... L336: =gescon_infosparticip!AQ335 | M336: =gescon_infosparticip!BA335 -> 0 | N336: =gescon_infosparticip!BB335 -> 0 | O336: =gescon_infosparticip!BC335 -> 0 | P336: =gescon_infosparticip!BD335 -> 0 | Q336: =gescon_infosparticip!BE335 -> 0 | R336: =gescon_infosparticip!BF335 | S336: =gescon_infosparticip!BG335 | T336: =gescon_infosparticip!BH335 | ... Y336: =gescon_infosparticip!BM335

Sheet migAloIntervenant
A1: aloIntId | B1: aloIntBeneficiare | C1: aloIntA | D1: aloIntB | E1: aloIntC | F1: aloIntD
B2: =gescon_infosparticip!A1 -> membre | C2: =gescon_infosparticip!AS1 -> Interv_A | D2: =gescon_infosparticip!AT1 -> Interv_B | E2: =gescon_infosparticip!AU1 -> Interv_C | F2: =gescon_infosparticip!AV1 -> Interv_R
B3: =gescon_infosparticip!A2 -> -2138585887 | C3: =gescon_infosparticip!AS2 -> 0 | D3: =gescon_infosparticip!AT2 -> 0 | E3: =gescon_infosparticip!AU2 -> 0 | F3: =gescon_infosparticip!AV2 -> 0
B4: =gescon_infosparticip!A3 -> -1974002318 | C4: =gescon_infosparticip!AS3 -> 0 | D4: =gescon_infosparticip!AT3 -> 0 | E4: =gescon_infosparticip!AU3 -> 0 | F4: =gescon_infosparticip!AV3 -> 0
B5: =gescon_infosparticip!A4 -> -1949668449 | C5: =gescon_infosparticip!AS4 -> 0 | D5: =gescon_infosparticip!AT4 -> 0 | E5: =gescon_infosparticip!AU4 -> 0 | F5: =gescon_infosparticip!AV4 -> 0
B6: =gescon_infosparticip!A5 -> -1887115141 | C6: =gescon_infosparticip!AS5 -> 0 | D6: =gescon_infosparticip!AT5 -> 0 | E6: =gescon_infosparticip!AU5 -> 0 | F6: =gescon_infosparticip!AV5 -> 0
B7: =gescon_infosparticip!A6 -> -1756164214 | C7: =gescon_infosparticip!AS6 -> 0 | D7: =gescon_infosparticip!AT6 -> 0 | E7: =gescon_infosparticip!AU6 -> 0 | F7: =gescon_infosparticip!AV6 -> 0
B8: =gescon_infosparticip!A7 -> -1735727011 | C8: =gescon_infosparticip!AS7 -> 0 | D8: =gescon_infosparticip!AT7 -> 0 | E8: =gescon_infosparticip!AU7 -> 0 | F8: =gescon_infosparticip!AV7 -> 0
B9: =gescon_infosparticip!A8 -> -1690129297 | C9: =gescon_infosparticip!AS8 -> 0 | D9: =gescon_infosparticip!AT8 -> 0 | E9: =gescon_infosparticip!AU8 -> 0 | F9: =gescon_infosparticip!AV8 -> 0
B10: =gescon_infosparticip!A9 -> -1579856298 | C10: =gescon_infosparticip!AS9 -> 0 | D10: =gescon_infosparticip!AT9 -> 0 | E10: =gescon_infosparticip!AU9 -> 0 | F10: =gescon_infosparticip!AV9 -> 0
B11: =gescon_infosparticip!A10 -> -1475569285 | C11: =gescon_infosparticip!AS10 -> 0 | D11: =gescon_infosparticip!AT10 -> 0 | E11: =gescon_infosparticip!AU10 -> 0 | F11: =gescon_infosparticip!AV10 -> 0
B12: =gescon_infosparticip!A11 -> -1435346384 | C12: =gescon_infosparticip!AS11 -> 0 | D12: =gescon_infosparticip!AT11 -> 0 | E12: =gescon_infosparticip!AU11 -> 0 | F12: =gescon_infosparticip!AV11 -> 0
B13: =gescon_infosparticip!A12 -> -1354980006 | C13: =gescon_infosparticip!AS12 -> 2146189479 | D13: =gescon_infosparticip!AT12 -> 2146189314 | E13: =gescon_infosparticip!AU12 -> 2146189314 | F13: =gescon_infosparticip!AV12 -> 0
... B336: =gescon_infosparticip!A335 -> 2146190077 | C336: =gescon_infosparticip!AS335 -> 0 | D336: =gescon_infosparticip!AT335 -> 0 | E336: =gescon_infosparticip!AU335 -> 0 | F336: =gescon_infosparticip!AV335 -> 0

Sheet migInfoSocial
A1: socId | B1: socConId | C1: socMaj | D1: socPere | E1: socMere | F1: socTuteur | G1: socInstitution | H1: socUrgence | I1: socReferentInstitut | J1: socGereseul | K1: socAvecaidephys | L1: socAvecconseil | M1: socNegerepas | N1: socMarcheseul | O1: socMarchaide | P1: socMarchauxi | Q1: socFauteuilMan | R1: socFauteuilElec | S1: socDeplacement | T1: socHabillement | U1: socPiscine | V1: socPublication | W1: socPiscineGilet | X1: socSomeil | Y1: socatache | Z1: socdrapspec | AA1: socgilet | AB1: socbarriere | AC1: socExpresssion | AD1: socFamille | AE1: socFraterie | AF1: socAmis | AG1: socPassions | AH1: socAimePas | AI1: socPossitionJour | AJ1: socFrequenceJour
B2: =gescon_infosparticip!A1 -> membre | C2: =gescon_infosparticip!B1 -> Dernière mise à jour | D2: =gescon_infosparticip!C1 -> Fils de(Père) | E2: =gescon_infosparticip!D1 -> Fils de(Mère) | F2: =gescon_infosparticip!E1 -> Tuteur | G2: =gescon_infosparticip!F1 -> Institution | H2: =gescon_infosparticip!G1 -> Adresse urgence | I2: =gescon_infosparticip!H1 -> Referent_institut | J2: =IF(gescon_infosparticip!I1=FALSE,0,1) -> 1 | K2: =gescon_infosparticip!J1 -> arpo_avecaidephys | L2: =gescon_infosparticip!K1 -> arpo_avecconseil | M2: =gescon_infosparticip!L1 -> arpo_negerepas | N2: =gescon_infosparticip!M1 -> Mobil_marcheseul | O2: =gescon_infosparticip!N1 -> Mobil_marchaide | P2: =gescon_infosparticip!O1 -> Mobil_marchauxi | Q2: =gescon_infosparticip!P1 -> Mobil_fauteuilman | R2: =gescon_infosparticip!Q1 -> Mobil_fauteuilelec | S2: =gescon_infosparticip!R1 -> Long_dep | T2: =gescon_infosparticip!V1 -> habillement | U2: =gescon_infosparticip!S1 -> Piscine_coment | V2: =gescon_infosparticip!U1 -> Publication | W2: =gescon_infosparticip!T1 -> Piscine_gilet | X2: =gescon_infosparticip!W1 -> someil | Y2: =gescon_infosparticip!X1 -> acnuit_atache | Z2: =gescon_infosparticip!Y1 -> acnuit_drapspec | AA2: =gescon_infosparticip!Z1 -> acnuit_gilet | AB2: =gescon_infosparticip!AA1 -> acnuit_barriere | AC2: =gescon_infosparticip!AB1 -> Expresssion | AD2: =gescon_infosparticip!AC1 -> Famille | AE2: =gescon_infosparticip!AD1 -> Fraterie | ... AH2: =gescon_infosparticip!AG1 -> Activités peu appréciées | AI2: =gescon_infosparticip!BN1 -> change_pos | AJ2: =gescon_infosparticip!BO1 -> frequence_change
B3: =gescon_infosparticip!A2 -> -2138585887 | C3: =gescon_infosparticip!B2 -> 41092 | D3: =gescon_infosparticip!C2 -> 0 | E3: =gescon_infosparticip!D2 -> 0 | F3: =gescon_infosparticip!E2 -> 0 | G3: =gescon_infosparticip!F2 -> 0 | H3: =gescon_infosparticip!G2 -> 0 | I3: =gescon_infosparticip!H2 | J3: =IF(gescon_infosparticip!I2=FALSE,0,1) -> 0 | K3: =IF(gescon_infosparticip!J2=FALSE,0,1) -> 0 | L3: =IF(gescon_infosparticip!K2=FALSE,0,1) -> 0 | M3: =IF(gescon_infosparticip!L2=FALSE,0,1) -> 0 | N3: =IF(gescon_infosparticip!M2=FALSE,0,1) -> 0 | O3: =IF(gescon_infosparticip!N2=FALSE,0,1) -> 0 | P3: =IF(gescon_infosparticip!O2=FALSE,0,1) -> 0 | Q3: =IF(gescon_infosparticip!P2=FALSE,0,1) -> 0 | R3: =IF(gescon_infosparticip!Q2=FALSE,0,1) -> 0 | S3: =gescon_infosparticip!R2 -> ligne1 ligne 2 Ligne 3 | T3: =gescon_infosparticip!V2 | U3: =gescon_infosparticip!S2 | V3: =IF(gescon_infosparticip!U2=FALSE,0,1) -> 0 | W3: =IF(gescon_infosparticip!T2=FALSE,0,1) -> 0 | X3: =gescon_infosparticip!W2 | Y3: =IF(gescon_infosparticip!X2=FALSE,0,1) -> 0 | Z3: =IF(gescon_infosparticip!Y2=FALSE,0,1) -> 0 | AA3: =IF(gescon_infosparticip!Z2=FALSE,0,1) -> 0 | AB3: =IF(gescon_infosparticip!AA2=FALSE,0,1) -> 0 | AC3: =gescon_infosparticip!AB2 | AD3: =gescon_infosparticip!AC2 | AE3: =gescon_infosparticip!AD2 | AF3: =gescon_infosparticip!AE2 | AG3: =gescon_infosparticip!AF2 | AH3: =gescon_infosparticip!AG2 | AI3: =gescon_infosparticip!BN2 | AJ3: =gescon_infosparticip!BO2
B4: =gescon_infosparticip!A3 -> -1974002318 | C4: =gescon_infosparticip!B3 -> 42780 | D4: =gescon_infosparticip!C3 -> 1241531093 | E4: =gescon_infosparticip!D3 -> 0 | F4: =gescon_infosparticip!E3 -> 0 | G4: =gescon_infosparticip!F3 -> 0 | H4: =gescon_infosparticip!G3 -> 2146189445 | I4: =gescon_infosparticip!H3 | J4: =IF(gescon_infosparticip!I3=FALSE,0,1) -> 0 | K4: =IF(gescon_infosparticip!J3=FALSE,0,1) -> 0 | L4: =IF(gescon_infosparticip!K3=FALSE,0,1) -> 0 | M4: =IF(gescon_infosparticip!L3=FALSE,0,1) -> 0 | N4: =IF(gescon_infosparticip!M3=FALSE,0,1) -> 0 | O4: =IF(gescon_infosparticip!N3=FALSE,0,1) -> 0 | P4: =IF(gescon_infosparticip!O3=FALSE,0,1) -> 0 | Q4: =IF(gescon_infosparticip!P3=FALSE,0,1) -> 1 | R4: =IF(gescon_infosparticip!Q3=FALSE,0,1) -> 0 | S4: =gescon_infosparticip!R3 -> Elle supporte les longs trajets en bus | T4: =gescon_infosparticip!V3 -> Aide totale | U4: =gescon_infosparticip!S3 -> Elle apprécie l'eau | V4: =IF(gescon_infosparticip!U3=FALSE,0,1) -> 1 | W4: =IF(gescon_infosparticip!T3=FALSE,0,1) -> 1 | X4: =gescon_infosparticip!W3 | Y4: =IF(gescon_infosparticip!X3=FALSE,0,1) -> 0 | Z4: =IF(gescon_infosparticip!Y3=FALSE,0,1) -> 0 | AA4: =IF(gescon_infosparticip!Z3=FALSE,0,1) -> 0 | AB4: =IF(gescon_infosparticip!AA3=FALSE,0,1) -> 0 | AC4: =gescon_infosparticip!AB3 -> Elle n'a pas l'expression verbal. Elle communique par le regard, le toucher, les mimiques. C'est une petite fille très facile qui apprécie tout. Si elle pleure il faut s'inquiéter (il peut y avoir des coliques ou mal positionnement). Donc à observer et la prendre dans les bras car elle a besoin d'être rassurée. | AD4: =gescon_infosparticip!AC3 -> Elle apprécie beaucoup sa grand-maman. | AE4: =gescon_infosparticip!AD3 -> Alycia a une petite sœur qui s'appelle Léanne | AF4: =gescon_infosparticip!AE3 | AG4: =gescon_infosparticip!AF3 -> Activités en plein air. Elle aime bien écouter de la musiquen et des histoires. Elle apprécie les balades et le vélo. | AH4: =gescon_infosparticip!AG3 | AI4: =gescon_infosparticip!BN3 -> oui | AJ4: =gescon_infosparticip!BO3 -> changement de position pendant la journée.
B5: =gescon_infosparticip!A4 -> -1949668449 | C5: =gescon_infosparticip!B4 -> 37859.411 | D5: =gescon_infosparticip!C4 -> 2643 | E5: =gescon_infosparticip!D4 -> 2210 | F5: =gescon_infosparticip!E4 -> 0 | G5: =gescon_infosparticip!F4 -> 0 | H5: =gescon_infosparticip!G4 -> 1424 | I5: =gescon_infosparticip!H4 | J5: =IF(gescon_infosparticip!I4=FALSE,0,1) -> 0 | K5: =IF(gescon_infosparticip!J4=FALSE,0,1) -> 0 | L5: =IF(gescon_infosparticip!K4=FALSE,0,1) -> 0 | M5: =IF(gescon_infosparticip!L4=FALSE,0,1) -> 0 | N5: =IF(gescon_infosparticip!M4=FALSE,0,1) -> 0 | O5: =IF(gescon_infosparticip!N4=FALSE,0,1) -> 0 | P5: =IF(gescon_infosparticip!O4=FALSE,0,1) -> 0 | Q5: =IF(gescon_infosparticip!P4=FALSE,0,1) -> 0 | R5: =IF(gescon_infosparticip!Q4=FALSE,0,1) -> 0 | S5: =gescon_infosparticip!R4 | T5: =gescon_infosparticip!V4 | U5: =gescon_infosparticip!S4 -> Le faire marcher dans l'eau rester tout le temps à ses côtés. | V5: =IF(gescon_infosparticip!U4=FALSE,0,1) -> 1 | W5: =IF(gescon_infosparticip!T4=FALSE,0,1) -> 0 | X5: =gescon_infosparticip!W4 | Y5: =IF(gescon_infosparticip!X4=FALSE,0,1) -> 0 | Z5: =IF(gescon_infosparticip!Y4=FALSE,0,1) -> 0 | AA5: =IF(gescon_infosparticip!Z4=FALSE,0,1) -> 0 | AB5: =IF(gescon_infosparticip!AA4=FALSE,0,1) -> 0 | AC5: =gescon_infosparticip!AB4 -> Expression verbale, mimiques, écholalie, stéréotipie | AD5: =gescon_infosparticip!AC4 -> Il aime beaucoup la musique: écouter Mylène Farmer, et chanter. Ne pas lui donner trop d'ordres, pas trop d'exigences, juste lui indiquer ce que l'on fait. Si il se fâche, il se donne des claques. | AE5: =gescon_infosparticip!AD4 | AF5: =gescon_infosparticip!AE4 | AG5: =gescon_infosparticip!AF4 | AH5: =gescon_infosparticip!AG4 -> Elle est destabilisée par la foule. | AI5: =gescon_infosparticip!BN4 | AJ5: =gescon_infosparticip!BO4
B6: =gescon_infosparticip!A5 -> -1887115141 | C6: =gescon_infosparticip!B5 -> 42517 | D6: =gescon_infosparticip!C5 -> 106817863 | E6: =gescon_infosparticip!D5 -> 0 | F6: =gescon_infosparticip!E5 -> 0 | G6: =gescon_infosparticip!F5 -> 1424 | H6: =gescon_infosparticip!G5 -> 0 | I6: =gescon_infosparticip!H5 -> Groupe - C4 Beate Friedberger | J6: =IF(gescon_infosparticip!I5=FALSE,0,1) -> 0 | K6: =IF(gescon_infosparticip!J5=FALSE,0,1) -> 1 | L6: =IF(gescon_infosparticip!K5=FALSE,0,1) -> 1 | M6: =IF(gescon_infosparticip!L5=FALSE,0,1) -> 0 | N6: =IF(gescon_infosparticip!M5=FALSE,0,1) -> 0 | O6: =IF(gescon_infosparticip!N5=FALSE,0,1) -> 0 | P6: =IF(gescon_infosparticip!O5=FALSE,0,1) -> 0 | Q6: =IF(gescon_infosparticip!P5=FALSE,0,1) -> 1 | R6: =IF(gescon_infosparticip!Q5=FALSE,0,1) -> 0 | S6: =gescon_infosparticip!R5 -> Elle supporte les trajets en bus. | T6: =gescon_infosparticip!V5 | U6: =gescon_infosparticip!S5 -> Il faut l’accompagner. Si elle ne veut pas, il ne faut pas la forcer | V6: =IF(gescon_infosparticip!U5=FALSE,0,1) -> 1 | W6: =IF(gescon_infosparticip!T5=FALSE,0,1) -> 0 | X6: =gescon_infosparticip!W5 -> dort bien mais discute parfois longtemps. Danièla demande pour aller au lit. Le matin, au lever elle boit volontiers un verre d’eau. Protection pour la nuit | Y6: =IF(gescon_infosparticip!X5=FALSE,0,1) -> 0 | Z6: =IF(gescon_infosparticip!Y5=FALSE,0,1) -> 0 | AA6: =IF(gescon_infosparticip!Z5=FALSE,0,1) -> 0 | AB6: =IF(gescon_infosparticip!AA5=FALSE,0,1) -> 1 | AC6: =gescon_infosparticip!AB5 -> s’exprime en allemand et en français à sa manière. Elle mélange les mots allemands avec les mots français. | AD6: =gescon_infosparticip!AC5 -> Son papa est décédé. | AE6: =gescon_infosparticip!AD5 -> Elle a 2 sœurs : Claudia et Andrea. | AF6: =gescon_infosparticip!AE5 | AG6: =gescon_infosparticip!AF5 -> Danièla possède un cahier avec des photos de sa famille et de son entourage. Danièla s’exprime bien et montre ce qu’elle souhaite. Elle arrive à faire des choix. Elle apprécie les différents styles de musique. Elle aime faire des jeux d’encastrement ex : mettre les pièces dans le jeu du puissance 4. Elle arrive à faire du vélo à 3 roues. | AH6: =gescon_infosparticip!AG5 -> Toutes les activités avec des bruits, Danièla sursaute beaucoup | AI6: =gescon_infosparticip!BN5 | AJ6: =gescon_infosparticip!BO5
B7: =gescon_infosparticip!A6 -> -1756164214 | C7: =gescon_infosparticip!B6 -> 41087 | D7: =gescon_infosparticip!C6 -> 0 | E7: =gescon_infosparticip!D6 -> 0 | F7: =gescon_infosparticip!E6 -> 0 | G7: =gescon_infosparticip!F6 -> 0 | H7: =gescon_infosparticip!G6 -> 0 | I7: =gescon_infosparticip!H6 | J7: =IF(gescon_infosparticip!I6=FALSE,0,1) -> 0 | K7: =IF(gescon_infosparticip!J6=FALSE,0,1) -> 0 | L7: =IF(gescon_infosparticip!K6=FALSE,0,1) -> 0 | M7: =IF(gescon_infosparticip!L6=FALSE,0,1) -> 0 | N7: =IF(gescon_infosparticip!M6=FALSE,0,1) -> 0 | O7: =IF(gescon_infosparticip!N6=FALSE,0,1) -> 0 | P7: =IF(gescon_infosparticip!O6=FALSE,0,1) -> 0 | Q7: =IF(gescon_infosparticip!P6=FALSE,0,1) -> 0 | R7: =IF(gescon_infosparticip!Q6=FALSE,0,1) -> 0 | S7: =gescon_infosparticip!R6 | T7: =gescon_infosparticip!V6 | U7: =gescon_infosparticip!S6 -> si Laurent n'a pas fond, il a besoin d'aide. | V7: =IF(gescon_infosparticip!U6=FALSE,0,1) -> 1 | W7: =IF(gescon_infosparticip!T6=FALSE,0,1) -> 0 | X7: =gescon_infosparticip!W6 | Y7: =IF(gescon_infosparticip!X6=FALSE,0,1) -> 0 | Z7: =IF(gescon_infosparticip!Y6=FALSE,0,1) -> 0 | AA7: =IF(gescon_infosparticip!Z6=FALSE,0,1) -> 0 | AB7: =IF(gescon_infosparticip!AA6=FALSE,0,1) -> 0 | AC7: =gescon_infosparticip!AB6 -> Parle | AD7: =gescon_infosparticip!AC6 -> Ses parents sont séparés. Son papa habite dans le canton de Berne et sa maman à Betten près de Naters. Il a deux frères: Jean-Luc (1965) et Yves (1964). Laurent apprécie la piscine, les ballades.Il travaille un après-midi par semaine dans un atelier et le | AE7: =gescon_infosparticip!AD6 | AF7: =gescon_infosparticip!AE6 | AG7: =gescon_infosparticip!AF6 | AH7: =gescon_infosparticip!AG6 | AI7: =gescon_infosparticip!BN6 | AJ7: =gescon_infosparticip!BO6
B8: =gescon_infosparticip!A7 -> -1735727011 | C8: =gescon_infosparticip!B7 -> 37861.394 | D8: =gescon_infosparticip!C7 -> 0 | E8: =gescon_infosparticip!D7 -> 0 | F8: =gescon_infosparticip!E7 -> 0 | G8: =gescon_infosparticip!F7 -> 0 | H8: =gescon_infosparticip!G7 -> 0 | I8: =gescon_infosparticip!H7 | J8: =IF(gescon_infosparticip!I7=FALSE,0,1) -> 0 | K8: =IF(gescon_infosparticip!J7=FALSE,0,1) -> 0 | L8: =IF(gescon_infosparticip!K7=FALSE,0,1) -> 0 | M8: =IF(gescon_infosparticip!L7=FALSE,0,1) -> 0 | N8: =IF(gescon_infosparticip!M7=FALSE,0,1) -> 0 | O8: =IF(gescon_infosparticip!N7=FALSE,0,1) -> 0 | P8: =IF(gescon_infosparticip!O7=FALSE,0,1) -> 0 | Q8: =IF(gescon_infosparticip!P7=FALSE,0,1) -> 0 | R8: =IF(gescon_infosparticip!Q7=FALSE,0,1) -> 0 | S8: =gescon_infosparticip!R7 | T8: =gescon_infosparticip!V7 | U8: =gescon_infosparticip!S7 -> Il sait nager, il faut être à côté | V8: =IF(gescon_infosparticip!U7=FALSE,0,1) -> 0 | W8: =IF(gescon_infosparticip!T7=FALSE,0,1) -> 0 | X8: =gescon_infosparticip!W7 | Y8: =IF(gescon_infosparticip!X7=FALSE,0,1) -> 0 | Z8: =IF(gescon_infosparticip!Y7=FALSE,0,1) -> 0 | AA8: =IF(gescon_infosparticip!Z7=FALSE,0,1) -> 0 | AB8: =IF(gescon_infosparticip!AA7=FALSE,0,1) -> 0 | AC8: =gescon_infosparticip!AB7 -> oral | AD8: =gescon_infosparticip!AC7 | AE8: =gescon_infosparticip!AD7 | AF8: =gescon_infosparticip!AE7 | AG8: =gescon_infosparticip!AF7 | AH8: =gescon_infosparticip!AG7 | AI8: =gescon_infosparticip!BN7 | AJ8: =gescon_infosparticip!BO7
B9: =gescon_infosparticip!A8 -> -1690129297 | C9: =gescon_infosparticip!B8 -> 37858.563 | D9: =gescon_infosparticip!C8 -> 1007640806 | E9: =gescon_infosparticip!D8 -> 2210 | F9: =gescon_infosparticip!E8 -> 0 | G9: =gescon_infosparticip!F8 -> 0 | H9: =gescon_infosparticip!G8 -> 0 | I9: =gescon_infosparticip!H8 | J9: =IF(gescon_infosparticip!I8=FALSE,0,1) -> 0 | K9: =IF(gescon_infosparticip!J8=FALSE,0,1) -> 0 | L9: =IF(gescon_infosparticip!K8=FALSE,0,1) -> 0 | M9: =IF(gescon_infosparticip!L8=FALSE,0,1) -> 0 | N9: =IF(gescon_infosparticip!M8=FALSE,0,1) -> 0 | O9: =IF(gescon_infosparticip!N8=FALSE,0,1) -> 0 | P9: =IF(gescon_infosparticip!O8=FALSE,0,1) -> 0 | Q9: =IF(gescon_infosparticip!P8=FALSE,0,1) -> 0 | R9: =IF(gescon_infosparticip!Q8=FALSE,0,1) -> 0 | S9: =gescon_infosparticip!R8 | T9: =gescon_infosparticip!V8 | U9: =gescon_infosparticip!S8 -> Patrice a besoin de l’aide d’un adulte. | V9: =IF(gescon_infosparticip!U8=FALSE,0,1) -> 1 | W9: =IF(gescon_infosparticip!T8=FALSE,0,1) -> 0 | X9: =gescon_infosparticip!W8 | Y9: =IF(gescon_infosparticip!X8=FALSE,0,1) -> 0 | Z9: =IF(gescon_infosparticip!Y8=FALSE,0,1) -> 0 | AA9: =IF(gescon_infosparticip!Z8=FALSE,0,1) -> 0 | AB9: =IF(gescon_infosparticip!AA8=FALSE,0,1) -> 0 | AC9: =gescon_infosparticip!AB8 -> oral, mais avec difficulté. Il faut lui poser des questions pour qu’il participe à la conversation. | AD9: =gescon_infosparticip!AC8 -> Patrice aime les animaux, la musique, les magazines et regarder la télévision. Il a depuis une année un neveu qu’il aime beaucoup. Sa deuxième sœur dirige une société d’accordéoniste. Son papa est passionné de pétanque. | AE9: =gescon_infosparticip!AD8 | AF9: =gescon_infosparticip!AE8 | AG9: =gescon_infosparticip!AF8 | AH9: =gescon_infosparticip!AG8 | AI9: =gescon_infosparticip!BN8 | AJ9: =gescon_infosparticip!BO8
B10: =gescon_infosparticip!A9 -> -1579856298 | C10: =gescon_infosparticip!B9 -> 38154.441 | D10: =gescon_infosparticip!C9 -> 0 | E10: =gescon_infosparticip!D9 -> 0 | F10: =gescon_infosparticip!E9 -> 0 | G10: =gescon_infosparticip!F9 -> 0 | H10: =gescon_infosparticip!G9 -> 0 | I10: =gescon_infosparticip!H9 | J10: =IF(gescon_infosparticip!I9=FALSE,0,1) -> 0 | K10: =IF(gescon_infosparticip!J9=FALSE,0,1) -> 0 | L10: =IF(gescon_infosparticip!K9=FALSE,0,1) -> 0 | M10: =IF(gescon_infosparticip!L9=FALSE,0,1) -> 0 | N10: =IF(gescon_infosparticip!M9=FALSE,0,1) -> 0 | O10: =IF(gescon_infosparticip!N9=FALSE,0,1) -> 0 | P10: =IF(gescon_infosparticip!O9=FALSE,0,1) -> 0 | Q10: =IF(gescon_infosparticip!P9=FALSE,0,1) -> 0 | R10: =IF(gescon_infosparticip!Q9=FALSE,0,1) -> 0 | S10: =gescon_infosparticip!R9 | T10: =gescon_infosparticip!V9 | U10: =gescon_infosparticip!S9 | V10: =IF(gescon_infosparticip!U9=FALSE,0,1) -> 0 | W10: =IF(gescon_infosparticip!T9=FALSE,0,1) -> 0 | X10: =gescon_infosparticip!W9 | Y10: =IF(gescon_infosparticip!X9=FALSE,0,1) -> 0 | Z10: =IF(gescon_infosparticip!Y9=FALSE,0,1) -> 0 | AA10: =IF(gescon_infosparticip!Z9=FALSE,0,1) -> 0 | AB10: =IF(gescon_infosparticip!AA9=FALSE,0,1) -> 0 | AC10: =gescon_infosparticip!AB9 | AD10: =gescon_infosparticip!AC9 | AE10: =gescon_infosparticip!AD9 | AF10: =gescon_infosparticip!AE9 | AG10: =gescon_infosparticip!AF9 | AH10: =gescon_infosparticip!AG9 | AI10: =gescon_infosparticip!BN9 | AJ10: =gescon_infosparticip!BO9
B11: =gescon_infosparticip!A10 -> -1475569285 | C11: =gescon_infosparticip!B10 -> 42405 | D11: =gescon_infosparticip!C10 -> 2146188951 | E11: =gescon_infosparticip!D10 -> 0 | F11: =gescon_infosparticip!E10 -> 0 | G11: =gescon_infosparticip!F10 -> 2146189395 | H11: =gescon_infosparticip!G10 -> 2146188951 | I11: =gescon_infosparticip!H10 | J11: =IF(gescon_infosparticip!I10=FALSE,0,1) -> 0 | K11: =IF(gescon_infosparticip!J10=FALSE,0,1) -> 1 | L11: =IF(gescon_infosparticip!K10=FALSE,0,1) -> 0 | M11: =IF(gescon_infosparticip!L10=FALSE,0,1) -> 1 | N11: =IF(gescon_infosparticip!M10=FALSE,0,1) -> 1 | O11: =IF(gescon_infosparticip!N10=FALSE,0,1) -> 0 | P11: =IF(gescon_infosparticip!O10=FALSE,0,1) -> 0 | Q11: =IF(gescon_infosparticip!P10=FALSE,0,1) -> 0 | R11: =IF(gescon_infosparticip!Q10=FALSE,0,1) -> 0 | S11: =gescon_infosparticip!R10 -> Il supporte les longs trajets et se déplace seul. | T11: =gescon_infosparticip!V10 -> Il faut l'aider à choisir ses vêtements en fonction du temps. | U11: =gescon_infosparticip!S10 -> Il nage seul, sans manchon. Il n'a pas peur de l'eau. | V11: =IF(gescon_infosparticip!U10=FALSE,0,1) -> 1 | W11: =IF(gescon_infosparticip!T10=FALSE,0,1) -> 0 | X11: =gescon_infosparticip!W10 -> Il dort beaucoup, de plus en plus. Il n'a pas d'horaires particuliers. | Y11: =IF(gescon_infosparticip!X10=FALSE,0,1) -> 0 | Z11: =IF(gescon_infosparticip!Y10=FALSE,0,1) -> 0 | AA11: =IF(gescon_infosparticip!Z10=FALSE,0,1) -> 0 | AB11: =IF(gescon_infosparticip!AA10=FALSE,0,1) -> 0 | AC11: =gescon_infosparticip!AB10 -> Langage verbal avec des gestes. | AD11: =gescon_infosparticip!AC10 -> Il n'a plus que sa maman et l'ami de celle-ci. | AE11: =gescon_infosparticip!AD10 -> décédés | AF11: =gescon_infosparticip!AE10 | AG11: =gescon_infosparticip!AF10 -> Avec sa maman et l'ami de celle-ci, ils vont à vélo, au camping, nager, voir des matchs de foot, manger au restaurant, danser, ect. Il a des cousins et cousines mais ne les voit jamais, seul Fritz Karafiat l'amène faire des raquettes parfois l'hiver. Il aime les activités de groupe, est très sociable mains ne parle pas beaucoup. Il aime le cinéma et le foot, les trains à la gare, les avions à l'aéroport, mais surtout voir des gens ! S'il va au ciné, il ne comprend pas le film, c'est juste pour sortir. Attention, quand il voit des jeux de cartes, il les pique pour s'amuser avec. Il aime les avions et les trains. | AH11: =gescon_infosparticip!AG10 -> Aucune, il est agréable et facile à vivre. | AI11: =gescon_infosparticip!BN10 | AJ11: =gescon_infosparticip!BO10
B12: =gescon_infosparticip!A11 -> -1435346384 | C12: =gescon_infosparticip!B11 -> 42886 | D12: =gescon_infosparticip!C11 -> 0 | E12: =gescon_infosparticip!D11 -> 0 | F12: =gescon_infosparticip!E11 -> 0 | G12: =gescon_infosparticip!F11 -> 0 | H12: =gescon_infosparticip!G11 -> 0 | I12: =gescon_infosparticip!H11 | J12: =IF(gescon_infosparticip!I11=FALSE,0,1) -> 0 | K12: =IF(gescon_infosparticip!J11=FALSE,0,1) -> 0 | L12: =IF(gescon_infosparticip!K11=FALSE,0,1) -> 0 | M12: =IF(gescon_infosparticip!L11=FALSE,0,1) -> 0 | N12: =IF(gescon_infosparticip!M11=FALSE,0,1) -> 0 | O12: =IF(gescon_infosparticip!N11=FALSE,0,1) -> 0 | P12: =IF(gescon_infosparticip!O11=FALSE,0,1) -> 0 | Q12: =IF(gescon_infosparticip!P11=FALSE,0,1) -> 0 | R12: =IF(gescon_infosparticip!Q11=FALSE,0,1) -> 0 | S12: =gescon_infosparticip!R11 | T12: =gescon_infosparticip!V11 | U12: =gescon_infosparticip!S11 | V12: =IF(gescon_infosparticip!U11=FALSE,0,1) -> 0 | W12: =IF(gescon_infosparticip!T11=FALSE,0,1) -> 0 | X12: =gescon_infosparticip!W11 | Y12: =IF(gescon_infosparticip!X11=FALSE,0,1) -> 0 | Z12: =IF(gescon_infosparticip!Y11=FALSE,0,1) -> 0 | AA12: =IF(gescon_infosparticip!Z11=FALSE,0,1) -> 0 | AB12: =IF(gescon_infosparticip!AA11=FALSE,0,1) -> 0 | AC12: =gescon_infosparticip!AB11 | AD12: =gescon_infosparticip!AC11 | AE12: =gescon_infosparticip!AD11 | AF12: =gescon_infosparticip!AE11 | AG12: =gescon_infosparticip!AF11 | AH12: =gescon_infosparticip!AG11 | AI12: =gescon_infosparticip!BN11 | AJ12: =gescon_infosparticip!BO11
B13: =gescon_infosparticip!A12 -> -1354980006 | C13: =gescon_infosparticip!B12 -> 42885 | D13: =gescon_infosparticip!C12 -> -362773667 | E13: =gescon_infosparticip!D12 -> 0 | F13: =gescon_infosparticip!E12 -> 0 | G13: =gescon_infosparticip!F12 -> 67 | H13: =gescon_infosparticip!G12 -> 0 | I13: =gescon_infosparticip!H12 | J13: =IF(gescon_infosparticip!I12=FALSE,0,1) -> 0 | K13: =IF(gescon_infosparticip!J12=FALSE,0,1) -> 1 | L13: =IF(gescon_infosparticip!K12=FALSE,0,1) -> 1 | M13: =IF(gescon_infosparticip!L12=FALSE,0,1) -> 1 | N13: =IF(gescon_infosparticip!M12=FALSE,0,1) -> 0 | O13: =IF(gescon_infosparticip!N12=FALSE,0,1) -> 0 | P13: =IF(gescon_infosparticip!O12=FALSE,0,1) -> 0 | Q13: =IF(gescon_infosparticip!P12=FALSE,0,1) -> 1 | R13: =IF(gescon_infosparticip!Q12=FALSE,0,1) -> 0 | S13: =gescon_infosparticip!R12 -> Elle supporte les trajets en bus. | T13: =gescon_infosparticip!V12 -> aide complète, elle aime être propre et être lavée. | U13: =gescon_infosparticip!S12 -> Elle aime l'eau, elle y va avec un gilet et une personne en soutenance. | V13: =IF(gescon_infosparticip!U12=FALSE,0,1) -> 1 | W13: =IF(gescon_infosparticip!T12=FALSE,0,1) -> 1 | X13: =gescon_infosparticip!W12 -> Elle dort sur le dos avec un coussin d’allaitement sous les genoux et un coussin sous la tête selon sa position. Elle apprécie avoir un mobile au dessus de sa tête et des nounours autour d’elle. Le soir, elle se couche vers les 20h-21h00. Elle a besoin de temps pour s’endormir et parfois, après avoir mis la sonde, il est nécessaire de la changée. Si non, elle a un bon sommeil. La nuit à vérifier son lange env. 1/ 2heure après l’application de la sonde. | Y13: =IF(gescon_infosparticip!X12=FALSE,0,1) -> 0 | Z13: =IF(gescon_infosparticip!Y12=FALSE,0,1) -> 0 | AA13: =IF(gescon_infosparticip!Z12=FALSE,0,1) -> 0 | AB13: =IF(gescon_infosparticip!AA12=FALSE,0,1) -> 1 | AC13: =gescon_infosparticip!AB12 -> Elle n’a pas une communication verbale mais Cloé communique avec des petits cris. L’intonation varie selon son humeur. (Contente, dérangée, douleur, etc.). Cloé ne peut pas se positionner dans le « oui » ou le « non ». | AD13: =gescon_infosparticip!AC12 | AE13: =gescon_infosparticip!AD12 -> Cloé a des frères (Léandre de 2005, Joaquim de 2002). | AF13: =gescon_infosparticip!AE12 | AG13: =gescon_infosparticip!AF12 -> Elle aime sortir et faire des balades. Elle apprécie rester dans son lit et jouer avec des mobiles poser au dessus de sa tête. | AH13: =gescon_infosparticip!AG12 | AI13: =gescon_infosparticip!BN12 -> Sur le dos avec un coussin d'allaitement sous les genoux et un coussin sous la tête selon sa position. Elle est souvent couchle sur le dos. Pas de changement de position la nuit. | AJ13: =gescon_infosparticip!BO12 -> Chaque 4 heures
B14: =gescon_infosparticip!A13 -> -1336383801 | C14: =gescon_infosparticip!B13 -> 41430 | D14: =gescon_infosparticip!C13 -> 0 | E14: =gescon_infosparticip!D13 -> 0 | F14: =gescon_infosparticip!E13 -> 0 | G14: =gescon_infosparticip!F13 -> 0 | H14: =gescon_infosparticip!G13 -> 0 | I14: =gescon_infosparticip!H13 | J14: =IF(gescon_infosparticip!I13=FALSE,0,1) -> 0 | K14: =IF(gescon_infosparticip!J13=FALSE,0,1) -> 0 | L14: =IF(gescon_infosparticip!K13=FALSE,0,1) -> 0 | M14: =IF(gescon_infosparticip!L13=FALSE,0,1) -> 0 | N14: =IF(gescon_infosparticip!M13=FALSE,0,1) -> 0 | O14: =IF(gescon_infosparticip!N13=FALSE,0,1) -> 0 | P14: =IF(gescon_infosparticip!O13=FALSE,0,1) -> 0 | Q14: =IF(gescon_infosparticip!P13=FALSE,0,1) -> 0 | R14: =IF(gescon_infosparticip!Q13=FALSE,0,1) -> 0 | S14: =gescon_infosparticip!R13 | T14: =gescon_infosparticip!V13 | U14: =gescon_infosparticip!S13 | V14: =IF(gescon_infosparticip!U13=FALSE,0,1) -> 0 | W14: =IF(gescon_infosparticip!T13=FALSE,0,1) -> 0 | X14: =gescon_infosparticip!W13 | Y14: =IF(gescon_infosparticip!X13=FALSE,0,1) -> 0 | Z14: =IF(gescon_infosparticip!Y13=FALSE,0,1) -> 0 | AA14: =IF(gescon_infosparticip!Z13=FALSE,0,1) -> 0 | AB14: =IF(gescon_infosparticip!AA13=FALSE,0,1) -> 0 | AC14: =gescon_infosparticip!AB13 | AD14: =gescon_infosparticip!AC13 | AE14: =gescon_infosparticip!AD13 | AF14: =gescon_infosparticip!AE13 | AG14: =gescon_infosparticip!AF13 | AH14: =gescon_infosparticip!AG13 | AI14: =gescon_infosparticip!BN13 | AJ14: =gescon_infosparticip!BO13
... B336: =gescon_infosparticip!A335 -> 2146190077 | C336: =gescon_infosparticip!B335 -> 43083.423 | D336: =gescon_infosparticip!C335 -> 2146190035 | E336: =gescon_infosparticip!D335 -> 0 | F336: =gescon_infosparticip!E335 -> 0 | G336: =gescon_infosparticip!F335 -> 0 | H336: =gescon_infosparticip!G335 -> 0 | I336: =gescon_infosparticip!H335 | J336: =IF(gescon_infosparticip!I335=FALSE,0,1) -> 0 | K336: =IF(gescon_infosparticip!J335=FALSE,0,1) -> 0 | L336: =IF(gescon_infosparticip!K335=FALSE,0,1) -> 0 | M336: =IF(gescon_infosparticip!L335=FALSE,0,1) -> 0 | N336: =IF(gescon_infosparticip!M335=FALSE,0,1) -> 0 | O336: =IF(gescon_infosparticip!N335=FALSE,0,1) -> 0 | P336: =IF(gescon_infosparticip!O335=FALSE,0,1) -> 0 | Q336: =IF(gescon_infosparticip!P335=FALSE,0,1) -> 0 | R336: =IF(gescon_infosparticip!Q335=FALSE,0,1) -> 0 | S336: =gescon_infosparticip!R335 | T336: =gescon_infosparticip!V335 | U336: =gescon_infosparticip!S335 | V336: =IF(gescon_infosparticip!U335=FALSE,0,1) -> 0 | W336: =IF(gescon_infosparticip!T335=FALSE,0,1) -> 0 | X336: =gescon_infosparticip!W335 | Y336: =IF(gescon_infosparticip!X335=FALSE,0,1) -> 0 | Z336: =IF(gescon_infosparticip!Y335=FALSE,0,1) -> 0 | AA336: =IF(gescon_infosparticip!Z335=FALSE,0,1) -> 0 | AB336: =IF(gescon_infosparticip!AA335=FALSE,0,1) -> 0 | AC336: =gescon_infosparticip!AB335 | AD336: =gescon_infosparticip!AC335 | AE336: =gescon_infosparticip!AD335 | AF336: =gescon_infosparticip!AE335 | AG336: =gescon_infosparticip!AF335 | AH336: =gescon_infosparticip!AG335 | AI336: =gescon_infosparticip!BN335 | AJ336: =gescon_infosparticip!BO335
